Workbook

Sheet ReadMe
B1: DECISION MAKING USING FINANCIAL STATEMENTS - Group project: Excel workings
B2: Industry: Indian listed logistics & freight-transport services | 10 companies | 7 financial years, FY2020-FY2026
B4: 1. Purpose
B5: Ratio analysis (liquidity, leverage, activity, profitability and valuation), DuPont analysis, industry comparison and statistical analysis of 10 listed Indian logistics companies over FY2020-FY2026. The 10 firms are treated as the whole industry, so every industry benchmark in this workbook is computed from these 10 firms only.
B7: 2. Sheet map (click a sheet name to open it)
B8: Setup | C8: Settings used by the formulas (days in the year) and the textbook benchmark norms.
B9: Sources | C9: Links to the annual reports / financial statements of every company.
B10: Firm_Profiles | C10: The 10 firms, their segments and business models, and the evidence that they form one industry.
B11: Scorecard | C11: Key ratios as 7-year averages (FY2020-FY2026) for every firm vs the industry aggregate and the 10-firm median, with a composite ranking.
B12: Industry_Compare | C12: Every ratio for every firm and year, with industry aggregate, mean, median, standard deviation, minimum, maximum, assessment against the median and rank.
B13: Statistics | C13: Descriptive statistics, correlation matrix (with caution notes), paired t-tests FY2020 vs FY2026, growth and stability.
B14: Panel | C14: 70 firm-year observations of the key variables (linked to the company sheets); the data used by Statistics.
B15: Industry | C15: The 10 firms added together line by line, with the same ratio formulas (size-weighted industry ratios).
B16: Tiger ... MahindraLog | C16: One sheet per company: P&L, balance sheet, cash flow statement, market data, working figures, all ratios and the DuPont analysis.
B18: 3. Conventions
B19: Blue figures on a light-blue background are inputs taken from the annual reports; black cells are formulas; green cells are links to another sheet; a yellow background marks an adjusted input, explained in the cell comment on the row label.
B20: Liquidity and capital-structure (leverage) ratios are shown in ratio form, e.g. 1.65:1. Coverage, turnover and valuation ratios are shown as plain numbers, days as whole numbers, and margins / returns as percentages.
B21: N/M = not meaningful. It is used only where a ratio cannot be interpreted: the denominator is nil or negative (negative net worth, no inventory held, no dividend declared, loss-making EPS for P/E, a net cash inflow from investing for the capital expenditure ratio). N/C = not comparable (Allcargo valuation ratios, see section 6). n.a. = not applicable (per-share data for the industry aggregate).
B22: All amounts are in Rs crore; per-share data in Rs. FY2026 = April 2025 - March 2026. Percentages are stored as fractions.
B24: 4. Data and sources
B25: Consolidated statement of profit and loss, balance sheet and cash flow statement for FY2020-FY2026, and the year-end share price, for each company, taken from the companies' annual reports. The links are on the Sources sheet and in row 3 of each company sheet. The figures were collected with the Screener.in Excel export (ALL_10_Companies.xlsx), which condenses each statement into a standard set of line items. No FY2019 figures are used anywhere in the workbook.
B27: 5. Basis of calculation
B28: - Closing balances: every ratio that uses a balance-sheet figure uses the closing (31 March) balance of the same year. No opening or average balances are used, so the analysis needs no FY2019 data.
B29: - EBIT = operating profit = Operating EBITDA - depreciation, i.e. before other income and exceptional items. This EBIT is used for the operating profit margin, interest coverage, earning power, ROCE and the five-step DuPont, so that treasury income and one-off gains or losses do not distort operating performance. PBT = EBIT + other income - finance costs, which agrees with the reported PBT for every firm-year.
B30: - Current assets and current liabilities: the condensed statements show "other assets" (all assets other than fixed assets, CWIP and investments) and "other liabilities" (all liabilities other than borrowings and equity), which are used as proxies. Trade payables are not shown separately, so creditor days and the cash conversion cycle are indicative only.
B31: - Debt = total borrowings including lease liabilities (long-term and short-term borrowings are not separated in the data).
... B48: 9. Review of N/M results (live counts)
B49: Sheet | C49: N/M cells | D49: N/C cells | E49: Where N/M remains and why
B50: Tiger | C50: =COUNTIF(Tiger!$D$94:$J$177,"N/M") -> 23 | D50: =COUNTIF(Tiger!$D$94:$J$177,"N/C") -> 0 | E50: Inventory turnover - no inventory held (all years); inventory days shown as 0; dividend coverage - no dividend declared (FY20-21, FY23-26); capital expenditure ratio - net cash inflow from investing (FY20, FY23, FY25-26); debt/EBITDA and EV/EBITDA - negative operating EBITDA (FY20-21); P/E - loss year (FY20-21).
B51: Allcargo | C51: =COUNTIF(Allcargo!$D$94:$J$177,"N/M") -> 6 | D51: =COUNTIF(Allcargo!$D$94:$J$177,"N/C") -> 30 | E51: Inventory turnover - no inventory held (FY25-26); inventory days shown as 0; dividend coverage - no dividend declared (FY26); capital expenditure ratio - net cash inflow from investing (FY21, FY25-26); N/C: P/E, P/B, EV/EBITDA, earnings and dividend yield (FY20-25) - demerger-adjusted prices.
B52: BlueDart | C52: =COUNTIF(BlueDart!$D$94:$J$177,"N/M") -> 4 | D52: =COUNTIF(BlueDart!$D$94:$J$177,"N/C") -> 0 | E52: Dividend coverage - no dividend declared (FY20); capital expenditure ratio - net cash inflow from investing (FY22); P/E - loss year (FY20); working capital turnover - negative net working capital (FY20).
B53: CONCOR | C53: =COUNTIF(CONCOR!$D$94:$J$177,"N/M") -> 1 | D53: =COUNTIF(CONCOR!$D$94:$J$177,"N/C") -> 0 | E53: Capital expenditure ratio - net cash inflow from investing (FY21).
B54: JetFreight | C54: =COUNTIF(JetFreight!$D$94:$J$177,"N/M") -> 17 | D54: =COUNTIF(JetFreight!$D$94:$J$177,"N/C") -> 0 | E54: Inventory turnover - no inventory held (all years); inventory days shown as 0; dividend coverage - no dividend declared (FY20-21, FY23-26); capital expenditure ratio - net cash inflow from investing (FY26); debt/EBITDA and EV/EBITDA - negative operating EBITDA (FY20); P/E - loss year (FY20).
B55: Patel | C55: =COUNTIF(Patel!$D$94:$J$177,"N/M") -> 12 | D55: =COUNTIF(Patel!$D$94:$J$177,"N/C") -> 0 | E55: Inventory turnover - no inventory held (all years); inventory days shown as 0; capital expenditure ratio - net cash inflow from investing (FY20-21, FY23-25).
B56: Sical | C56: =COUNTIF(Sical!$D$94:$J$177,"N/M") -> 57 | D56: =COUNTIF(Sical!$D$94:$J$177,"N/C") -> 0 | E56: Debt-equity, gearing, ROE, P/B and equity multiplier - negative net worth (FY21-22, FY25); dividend coverage - no dividend declared (all years); capital expenditure ratio - net cash inflow from investing (FY23, FY26); debt/EBITDA and EV/EBITDA - negative operating EBITDA (FY20-22); P/E - loss year (FY20-25); working capital turnover - negative net working capital (FY20-25).
B57: TCI | C57: =COUNTIF(TCI!$D$94:$J$177,"N/M") -> 0 | D57: =COUNTIF(TCI!$D$94:$J$177,"N/C") -> 0 | E57: None.
B58: Shreeji | C58: =COUNTIF(Shreeji!$D$94:$J$177,"N/M") -> 7 | D58: =COUNTIF(Shreeji!$D$94:$J$177,"N/C") -> 0 | E58: Dividend coverage - no dividend declared (FY25-26); capital expenditure ratio - net cash inflow from investing (FY24, FY26); P/E - loss year (FY21); payout and retention - dividend paid in a loss year (FY21).
B59: MahindraLog | C59: =COUNTIF(MahindraLog!$D$94:$J$177,"N/M") -> 12 | D59: =COUNTIF(MahindraLog!$D$94:$J$177,"N/C") -> 0 | E59: Inventory turnover - no inventory held (FY20-21, FY24-26); inventory days shown as 0; capital expenditure ratio - net cash inflow from investing (FY20); P/E - loss year (FY24-25); payout and retention - dividend paid in a loss year (FY24-25).
B60: Industry | C60: =COUNTIF(Industry!$D$95:$J$178,"N/M") -> 3 | D60: =COUNTIF(Industry!$D$95:$J$178,"N/C") -> 0 | E60: P/E - loss year (FY21); payout and retention - dividend paid in a loss year (FY21).
B62: Counts cover the ratio and DuPont sections (FY2020-FY2026 columns). All earlier N/M cells were reviewed: N/M now appears only where the ratio is genuinely not meaningful; where a value can be calculated it is shown (e.g. inventory days of 0 when no inventory is held, and a 0% payout ratio when no dividend is paid).
B64: 10. Use of AI tools
B65: The workbook was prepared with the help of Claude (Anthropic), an AI assistant, which helped set up the formulas and layout from the group's data and the course formula list. All inputs come from the annual reports listed on the Sources sheet, every ratio is a live formula, and the results were cross-checked against an independent calculation. The interpretation and conclusions are the group's own.

Sheet Setup
A1: Setup - model settings and benchmark norms
A2: Settings referenced by the formulas, and the textbook norms quoted in the "Norm / unit" column of the company sheets.
B4: 1. GENERAL SETTINGS
B5: Industry | C5: Indian listed logistics & freight-transport services
B6: Currency & scale | C6: Rs crore (per-share data in Rs)
B7: Financial statements | C7: Consolidated where published (standalone otherwise)
B8: Days in a financial year | C8: 365
B9: Analysis period | C9: FY2020-FY2026 (7 years; FY = April to March)
B10: Balance-sheet basis for ratios | C10: Closing balance of the same year (no averages, no FY2019 figures)
B11: Maximum corporate tax rate (cap on t) | C11: 0.34944
B13: 2. TEXTBOOK BENCHMARK NORMS (reference only)
B14: Ratio | C14: Norm | D14: Shown as | E14: Rationale
B15: Current ratio | C15: 2 : 1 | D15: ratio | E15: Current assets twice current liabilities give creditors a 100% margin of safety.
B16: Quick (acid-test) ratio | C16: 1 : 1 | D16: ratio | E16: Stricter test that leaves out inventory and prepaid expenses.
B17: Cash ratio | C17: 0.5 : 1 | D17: ratio | E17: Ability to meet current obligations from cash and near-cash assets alone.
B18: Debt to capital employed | C18: max 0.5 : 1 | D18: ratio | E18: Debt should not exceed half of permanent capital.
B19: Debt to total assets | C19: max 0.5 : 1 | D19: ratio | E19: Total debt should not exceed half of the asset base.
B20: Proprietary ratio | C20: min 0.5 : 1 | D20: ratio | E20: Owners' funds should finance at least half of total assets.
B21: Interest coverage | C21: above 3 | D21: number | E21: Adequate cushion for finance costs out of operating profit.
B22: Debt-service coverage ratio | C22: above 1.25 | D22: number | E22: Below 1 means earnings do not cover interest plus principal.
B23: Capital expenditure ratio | C23: above 1 | D23: number | E23: Operating cash flow fully funds net capital expenditure.
B25: Liquidity and capital-structure ratios are shown in ratio form (e.g. 1.65:1). Coverage, turnover and valuation ratios are shown as plain numbers; margins and returns as percentages.

Sheet Sources
A1: Sources - annual reports and financial statements
A2: Primary sources for every company sheet. Figures are the consolidated statements in these reports, compiled into one data sheet per company through the Screener.in Excel export (ALL_10_Companies.xlsx); the export was used only to collect the numbers.
A4: # | B4: Company | C4: BSE code | D4: Document | E4: Period | F4: Link
A5: 1 | B5: Tiger Logistics (India) Ltd | C5: 536264 | D5: Annual reports - company investor page | E5: FY2020-FY2026 | F5: https://www.tigerlogistics.in/Annual_Report.php
A6: 2 | B6: Tiger Logistics (India) Ltd | C6: 536264 | D6: Annual reports - BSE corporate filings | E6: FY2020-FY2026 | F6: https://www.bseindia.com/stock-share-price/tiger-logistics-india-ltd/tigerlogs/536264/financials-annual-reports/
A7: 3 | B7: Allcargo Logistics Ltd | C7: 532749 | D7: Annual reports - company investor page | E7: FY2020-FY2026 | F7: https://www.allcargologistics.com/investor/logistics-annual-reports
A8: 4 | B8: Allcargo Logistics Ltd | C8: 532749 | D8: Annual reports - BSE corporate filings | E8: FY2020-FY2026 | F8: https://www.bseindia.com/stock-share-price/allcargo-logistics-ltd/allcargo/532749/financials-annual-reports/
A9: 5 | B9: Allcargo Logistics Ltd | C9: 532749 | D9: Annual Report 2022-23 | E9: FY2023 | F9: https://www.allcargologistics.com/cms/annual-reports/February2025/8QxMvclnT0owjBnY34Zk.pdf
A10: 6 | B10: Allcargo Logistics Ltd | C10: 532749 | D10: Annual Report 2023-24 | E10: FY2024 | F10: https://www.allcargologistics.com/cms/annual-reports/February2025/Bsl5vDz8atYU5wg09BlM.pdf
A11: 7 | B11: Blue Dart Express Ltd | C11: 526612 | D11: Annual reports - company investor page | E11: FY2020-FY2026 | F11: https://www.bluedart.com/financials
A12: 8 | B12: Blue Dart Express Ltd | C12: 526612 | D12: Annual reports - BSE corporate filings | E12: FY2020-FY2026 | F12: https://www.bseindia.com/stock-share-price/blue-dart-express-ltd/bluedart/526612/financials-annual-reports/
A13: 9 | B13: Blue Dart Express Ltd | C13: 526612 | D13: Annual Report 2019-20 | E13: FY2020 | F13: https://api.bluedart.com/documents/20182/0/Blue+Dart+Annual+Report-2019-2020.pdf/995ddbb8-b493-399f-2cc7-b5444cacf917
A14: 10 | B14: Blue Dart Express Ltd | C14: 526612 | D14: Annual Report 2024-25 | E14: FY2025 | F14: https://www.bluedart.com/documents/d/guest/annual-report-2024-25
A15: 11 | B15: Container Corporation of India Ltd | C15: 531344 | D15: Annual reports - company investor page | E15: FY2020-FY2026 | F15: https://www.concorindia.co.in/annual_report.aspx
A16: 12 | B16: Container Corporation of India Ltd | C16: 531344 | D16: Annual reports - BSE corporate filings | E16: FY2020-FY2026 | F16: https://www.bseindia.com/stock-share-price/container-corporation-of-india-ltd/concor/531344/financials-annual-reports/
... A46: 42 | B46: Mahindra Logistics Ltd | C46: 540768 | D46: Audited financial results FY2024-25 | E46: FY2025 | F46: https://mahindralogistics.com/tabs/cms/files/Annual-Financial-Results-FY-2025.pdf
B48: Notes
B49: - Where a single-year PDF is not listed, that year's report is available from the company's annual-report page and from the BSE annual-report page given for the company.
B50: - Share prices are the closing prices on the last trading day of March (BSE/NSE), adjusted for splits and bonus issues.
B51: - Company-specific adjustments to the data are explained in cell comments on the company sheets (yellow cells) and in the ReadMe.

Sheet Firm_Profiles
A1: Firm selection - the 10 listed Indian logistics companies and evidence that they form one industry
A2: Columns H-Q are linked to the company sheets. A cost structure dominated by direct operating (freight / handling) costs, negligible inventory and receivable-led working capital show a common operating model; asset intensity separates the asset-light forwarders / 3PLs from the asset-heavy network operators.
A4: # | B4: Company | C4: NSE symbol | D4: BSE code | E4: Segment / value proposition | F4: Business model | G4: Asset group (vs median net block / TA) | H4: Sales FY2026 (Rs cr) | I4: Total assets FY2026 (Rs cr) | J4: Market cap FY2026 (Rs cr) | K4: Sales CAGR FY20-26 | L4: Direct operating cost % sales (7-yr avg) | M4: Employee cost % sales (7-yr avg) | N4: Inventory % total assets (FY20-26) | O4: Receivables % total assets (FY20-26) | P4: Net block % total assets (FY20-26) | Q4: Operating EBITDA margin (7-yr avg)
A5: 1 | B5: Tiger Logistics (India) Ltd | C5: TIGERLOGS | D5: 536264 | E5: International freight forwarding (sea & air), customs brokerage, project cargo | F5: Asset-light forwarder | G5: =IF(P5>=MEDIAN($P$5:$P$14),"Asset-heavy","Asset-light") -> Asset-light | H5: =Tiger!J7 -> 572.82 | I5: =Tiger!J49 -> 262.62 | J5: =Tiger!J82 -> 252.623 | K5: =(Tiger!J7/Tiger!D7)^(1/6)-1 -> 0.11290974 | L5: =Tiger!K135 -> 0.90008469 | M5: =Tiger!K137 -> 0.042590791 | N5: =SUM(Tiger!D51:J51)/SUM(Tiger!D49:J49) -> 0 | O5: =SUM(Tiger!D50:J50)/SUM(Tiger!D49:J49) -> 0.54298621 | P5: =SUM(Tiger!D45:J45)/SUM(Tiger!D49:J49) -> 0.059499229 | Q5: =Tiger!K130 -> 0.029629489
A6: 2 | B6: Allcargo Logistics Ltd | C6: ALLCARGO | D6: 532749 | E6: LCL consolidation/NVOCC (international business demerged to Allcargo Global w.e.f. 1-Nov-2025); domestic express & contract logistics | F6: Asset-light network operator | G6: =IF(P6>=MEDIAN($P$5:$P$14),"Asset-heavy","Asset-light") -> Asset-heavy | H6: =Allcargo!J7 -> 2058 | I6: =Allcargo!J49 -> 1736 | J6: =Allcargo!J82 -> 1075.4204 | K6: =(Allcargo!J7/Allcargo!D7)^(1/6)-1 -> -0.19109651 | L6: =Allcargo!K135 -> 0.76369076 | M6: =Allcargo!K137 -> 0.11942794 | N6: =SUM(Allcargo!D51:J51)/SUM(Allcargo!D49:J49) -> 0.00078673889 | O6: =SUM(Allcargo!D50:J50)/SUM(Allcargo!D49:J49) -> 0.28615394 | P6: =SUM(Allcargo!D45:J45)/SUM(Allcargo!D49:J49) -> 0.37746854 | Q6: =Allcargo!K130 -> 0.073607981
A7: 3 | B7: Blue Dart Express Ltd | C7: BLUEDART | D7: 526612 | E7: Express air & ground courier and integrated transport (DHL Group); dedicated freighter fleet | F7: Asset-heavy express network | G7: =IF(P7>=MEDIAN($P$5:$P$14),"Asset-heavy","Asset-light") -> Asset-heavy | H7: =BlueDart!J7 -> 6140.88 | I7: =BlueDart!J49 -> 4126.85 | J7: =BlueDart!J82 -> 11250.39 | K7: =(BlueDart!J7/BlueDart!D7)^(1/6)-1 -> 0.11620728 | L7: =BlueDart!K135 -> 0.57413445 | M7: =BlueDart!K137 -> 0.18587756 | N7: =SUM(BlueDart!D51:J51)/SUM(BlueDart!D49:J49) -> 0.012802242 | O7: =SUM(BlueDart!D50:J50)/SUM(BlueDart!D49:J49) -> 0.20304214 | P7: =SUM(BlueDart!D45:J45)/SUM(BlueDart!D49:J49) -> 0.51634353 | Q7: =BlueDart!K130 -> 0.17658992
A8: 4 | B8: Container Corporation of India Ltd | C8: CONCOR | D8: 531344 | E8: Rail-based EXIM & domestic container logistics, ICDs/CFSs (Navratna CPSE, Ministry of Railways) | F8: Asset-heavy multimodal | G8: =IF(P8>=MEDIAN($P$5:$P$14),"Asset-heavy","Asset-light") -> Asset-heavy | H8: =CONCOR!J7 -> 9078.97 | I8: =CONCOR!J49 -> 15175.78 | J8: =CONCOR!J82 -> 32390.848 | K8: =(CONCOR!J7/CONCOR!D7)^(1/6)-1 -> 0.056454767 | L8: =CONCOR!K135 -> 0.65386661 | M8: =CONCOR!K137 -> 0.05554146 | N8: =SUM(CONCOR!D51:J51)/SUM(CONCOR!D49:J49) -> 0.0028825407 | O8: =SUM(CONCOR!D50:J50)/SUM(CONCOR!D49:J49) -> 0.020580932 | P8: =SUM(CONCOR!D45:J45)/SUM(CONCOR!D49:J49) -> 0.44638229 | Q8: =CONCOR!K130 -> 0.21971019
A9: 5 | B9: Jet Freight Logistics Ltd | C9: JETFREIGHT | D9: 543420 | E9: International air & ocean freight forwarding (incl. perishables), customs clearance | F9: Asset-light forwarder | G9: =IF(P9>=MEDIAN($P$5:$P$14),"Asset-heavy","Asset-light") -> Asset-light | H9: =JetFreight!J7 -> 444.08 | I9: =JetFreight!J49 -> 194.09 | J9: =JetFreight!J82 -> 79.1584 | K9: =(JetFreight!J7/JetFreight!D7)^(1/6)-1 -> 0.067684882 | L9: =JetFreight!K135 -> 0.924891 | M9: =JetFreight!K137 -> 0.040392871 | N9: =SUM(JetFreight!D51:J51)/SUM(JetFreight!D49:J49) -> 0 | O9: =SUM(JetFreight!D50:J50)/SUM(JetFreight!D49:J49) -> 0.42369073 | P9: =SUM(JetFreight!D45:J45)/SUM(JetFreight!D49:J49) -> 0.183062 | Q9: =JetFreight!K130 -> 0.020453399
A10: 6 | B10: Patel Integrated Logistics Ltd | C10: PATINTLOG | D10: 526381 | E10: Surface transport (Patel Roadways), domestic & international air-freight consolidation | F10: Asset-light carrier/consolidator | G10: =IF(P10>=MEDIAN($P$5:$P$14),"Asset-heavy","Asset-light") -> Asset-light | H10: =Patel!J7 -> 357.14 | I10: =Patel!J49 -> 163.32 | J10: =Patel!J82 -> 57.4896 | K10: =(Patel!J7/Patel!D7)^(1/6)-1 -> 0.0046143172 | L10: =Patel!K135 -> 0.90083674 | M10: =Patel!K137 -> 0.046566838 | N10: =SUM(Patel!D51:J51)/SUM(Patel!D49:J49) -> 0 | O10: =SUM(Patel!D50:J50)/SUM(Patel!D49:J49) -> 0.41704385 | P10: =SUM(Patel!D45:J45)/SUM(Patel!D49:J49) -> 0.28157151 | Q10: =Patel!K130 -> 0.0290875
A11: 7 | B11: Sical Logistics Ltd | C11: SICALLOG | D11: 520086 | E11: Bulk/mining logistics (coal), port & rail-road handling; IBC resolution plan of Pristine Malwa Logistics Park approved by NCLT Chennai (8-Dec-2022) | F11: Asset-heavy bulk logistics | G11: =IF(P11>=MEDIAN($P$5:$P$14),"Asset-heavy","Asset-light") -> Asset-heavy | H11: =Sical!J7 -> 385.68 | I11: =Sical!J49 -> 906.73 | J11: =Sical!J82 -> 502.69378 | K11: =(Sical!J7/Sical!D7)^(1/6)-1 -> -0.14765313 | L11: =Sical!K135 -> 0.77007687 | M11: =Sical!K137 -> 0.094975198 | N11: =SUM(Sical!D51:J51)/SUM(Sical!D49:J49) -> 0.0049394181 | O11: =SUM(Sical!D50:J50)/SUM(Sical!D49:J49) -> 0.091790321 | P11: =SUM(Sical!D45:J45)/SUM(Sical!D49:J49) -> 0.51796157 | Q11: =Sical!K130 -> 0.041720612
A12: 8 | B12: Transport Corporation of India Ltd | C12: TCI | D12: 532349 | E12: Integrated multimodal: road freight, supply-chain solutions/warehousing, coastal seaways, rail (JV with CONCOR) | F12: Hybrid multimodal | G12: =IF(P12>=MEDIAN($P$5:$P$14),"Asset-heavy","Asset-light") -> Asset-heavy | H12: =TCI!J7 -> 4916.77 | I12: =TCI!J49 -> 3481.86 | J12: =TCI!J82 -> 7079.41 | K12: =(TCI!J7/TCI!D7)^(1/6)-1 -> 0.10384815 | L12: =TCI!K135 -> 0.8143326 | M12: =TCI!K137 -> 0.054711809 | N12: =SUM(TCI!D51:J51)/SUM(TCI!D49:J49) -> 0.0036293535 | O12: =SUM(TCI!D50:J50)/SUM(TCI!D49:J49) -> 0.25858037 | P12: =SUM(TCI!D45:J45)/SUM(TCI!D49:J49) -> 0.38034014 | Q12: =TCI!K130 -> 0.10460636
A13: 9 | B13: Shreeji Translogistics Ltd | C13: — (BSE only) | D13: 540738 | E13: Road freight transport (full & part truck-load) and allied logistics | F13: Asset-light road carrier | G13: =IF(P13>=MEDIAN($P$5:$P$14),"Asset-heavy","Asset-light") -> Asset-light | H13: =Shreeji!J7 -> 234.29 | I13: =Shreeji!J49 -> 119.52 | J13: =Shreeji!J82 -> 41.1012 | K13: =(Shreeji!J7/Shreeji!D7)^(1/6)-1 -> 0.13429716 | L13: =Shreeji!K135 -> 0.80428674 | M13: =Shreeji!K137 -> 0.059367831 | N13: =SUM(Shreeji!D51:J51)/SUM(Shreeji!D49:J49) -> 0.021844079 | O13: =SUM(Shreeji!D50:J50)/SUM(Shreeji!D49:J49) -> 0.51219581 | P13: =SUM(Shreeji!D45:J45)/SUM(Shreeji!D49:J49) -> 0.25174176 | Q13: =Shreeji!K130 -> 0.072103023
A14: 10 | B14: Mahindra Logistics Ltd | C14: MAHLOG | D14: 540768 | E14: Integrated 3PL: contract logistics & warehousing, B2B express, freight forwarding, last-mile, enterprise mobility | F14: Asset-light 3PL (leased) | G14: =IF(P14>=MEDIAN($P$5:$P$14),"Asset-heavy","Asset-light") -> Asset-light | H14: =MahindraLog!J7 -> 6999.3 | I14: =MahindraLog!J49 -> 3105.01 | J14: =MahindraLog!J82 -> 3301.376 | K14: =(MahindraLog!J7/MahindraLog!D7)^(1/6)-1 -> 0.12399336 | L14: =MahindraLog!K135 -> 0.85615338 | M14: =MahindraLog!K137 -> 0.07499944 | N14: =SUM(MahindraLog!D51:J51)/SUM(MahindraLog!D49:J49) -> 0.00011646926 | O14: =SUM(MahindraLog!D50:J50)/SUM(MahindraLog!D49:J49) -> 0.26453777 | P14: =SUM(MahindraLog!D45:J45)/SUM(MahindraLog!D49:J49) -> 0.3060559 | Q14: =MahindraLog!K130 -> 0.046407247
B15: Median | H15: =MEDIAN(H5:H14) -> 1315.41 | I15: =MEDIAN(I5:I14) -> 1321.365 | J15: =MEDIAN(J5:J14) -> 789.05709 | K15: =MEDIAN(K5:K14) -> 0.085766516 | L15: =MEDIAN(L5:L14) -> 0.80930967 | M15: =MEDIAN(M5:M14) -> 0.057454646 | N15: =MEDIAN(N5:N14) -> 0.0018346398 | O15: =MEDIAN(O5:O14) -> 0.27534586 | ... Q15: =MEDIAN(Q5:Q14) -> 0.059255135
B16: Mean | H16: =AVERAGE(H5:H14) -> 3118.793 | I16: =AVERAGE(I5:I14) -> 2927.178 | J16: =AVERAGE(J5:J14) -> 5603.051 | K16: =AVERAGE(K5:K14) -> 0.038126002 | L16: =AVERAGE(L5:L14) -> 0.79623538 | M16: =AVERAGE(M5:M14) -> 0.077445173 | N16: =AVERAGE(N5:N14) -> 0.0047000842 | O16: =AVERAGE(O5:O14) -> 0.30206021 | ... Q16: =AVERAGE(Q5:Q14) -> 0.081391573
B17: Minimum | H17: =MIN(H5:H14) -> 234.29 | I17: =MIN(I5:I14) -> 119.52 | J17: =MIN(J5:J14) -> 41.1012 | K17: =MIN(K5:K14) -> -0.19109651 | L17: =MIN(L5:L14) -> 0.57413445 | M17: =MIN(M5:M14) -> 0.040392871 | N17: =MIN(N5:N14) -> 0 | O17: =MIN(O5:O14) -> 0.020580932 | ... Q17: =MIN(Q5:Q14) -> 0.020453399
B18: Maximum | H18: =MAX(H5:H14) -> 9078.97 | I18: =MAX(I5:I14) -> 15175.78 | J18: =MAX(J5:J14) -> 32390.848 | K18: =MAX(K5:K14) -> 0.13429716 | L18: =MAX(L5:L14) -> 0.924891 | M18: =MAX(M5:M14) -> 0.18587756 | N18: =MAX(N5:N14) -> 0.021844079 | O18: =MAX(O5:O14) -> 0.54298621 | ... Q18: =MAX(Q5:Q14) -> 0.21971019
B19: Coeff. of variation (SD / mean) | H19: =IF(ABS(AVERAGE(H5:H14))>0,STDEV(H5:H14)/ABS(AVERAGE(H5:H14)),"N/M") -> 1.0747906 | I19: =IF(ABS(AVERAGE(I5:I14))>0,STDEV(I5:I14)/ABS(AVERAGE(I5:I14)),"N/M") -> 1.5588836 | J19: =IF(ABS(AVERAGE(J5:J14))>0,STDEV(J5:J14)/ABS(AVERAGE(J5:J14)),"N/M") -> 1.8086734 | K19: =IF(ABS(AVERAGE(K5:K14))>0,STDEV(K5:K14)/ABS(AVERAGE(K5:K14)),"N/M") -> 3.0540321 | L19: =IF(ABS(AVERAGE(L5:L14))>0,STDEV(L5:L14)/ABS(AVERAGE(L5:L14)),"N/M") -> 0.14110106 | M19: =IF(ABS(AVERAGE(M5:M14))>0,STDEV(M5:M14)/ABS(AVERAGE(M5:M14)),"N/M") -> 0.58854746 | N19: =IF(ABS(AVERAGE(N5:N14))>0,STDEV(N5:N14)/ABS(AVERAGE(N5:N14)),"N/M") -> 1.5320597 | O19: =IF(ABS(AVERAGE(O5:O14))>0,STDEV(O5:O14)/ABS(AVERAGE(O5:O14)),"N/M") -> 0.57023666 | ... Q19: =IF(ABS(AVERAGE(Q5:Q14))>0,STDEV(Q5:Q14)/ABS(AVERAGE(Q5:Q14)),"N/M") -> 0.82730417
B21: Reading: direct operating (freight / handling) costs are the largest cost for every firm and inventory is negligible for all ten (about 2% of total assets at most), which supports treating the 10 firms as one industry; the wide spread of net block / total assets reflects different value propositions (asset-light vs asset-heavy). Allcargo's CAGR is negative because FY2026 is after the demerger of its international business.

Sheet Scorecard
A1: Scorecard - key ratios, 7-year average FY2020-FY2026
A2: Each figure is the average of the seven yearly ratios (FY2020-FY2026) from the company sheets. Green = better than the 10-firm median, red = weaker (direction shown in column B). Valuation ratios have no normative direction and are not coloured.
A4: A. Key ratios - 7-year average (FY2020-FY2026)
A5: Ratio | B5: Category / direction | C5: Tiger | D5: Allcargo | E5: Blue Dart | F5: CONCOR | G5: Jet Freight | H5: Patel | I5: Sical | J5: TCI | K5: Shreeji | L5: Mahindra Log. | M5: Industry (agg.) | N5: Median (10 firms)
A6: Current ratio | B6: Liquidity (↑) | C6: =Tiger!K95 -> 4.8832317 | D6: =Allcargo!K95 -> 1.6559883 | E6: =BlueDart!K95 -> 1.2083102 | F6: =CONCOR!K95 -> 3.9096987 | G6: =JetFreight!K95 -> 2.7399296 | H6: =Patel!K95 -> 5.5817034 | I6: =Sical!K95 -> 0.7195622 | J6: =TCI!K95 -> 2.8768546 | K6: =Shreeji!K95 -> 5.0975533 | L6: =MahindraLog!K95 -> 1.4129884 | M6: =Industry!K96 -> 1.9742087 | N6: =IF(COUNT(C6:L6)=0,"N/M",MEDIAN(C6:L6)) -> 2.8083921
A7: Quick (acid-test) ratio | B7: Liquidity (↑) | C7: =Tiger!K96 -> 4.1690597 | D7: =Allcargo!K96 -> 1.0636674 | E7: =BlueDart!K96 -> 0.82047016 | F7: =CONCOR!K96 -> 2.3952545 | G7: =JetFreight!K96 -> 1.620697 | H7: =Patel!K96 -> 4.3914109 | I7: =Sical!K96 -> 0.46681949 | J7: =TCI!K96 -> 1.9838517 | K7: =Shreeji!K96 -> 3.8810091 | L7: =MahindraLog!K96 -> 0.69863375 | M7: =Industry!K97 -> 1.2448907 | N7: =IF(COUNT(C7:L7)=0,"N/M",MEDIAN(C7:L7)) -> 1.8022743
A8: Cash flow from operations ratio | B8: Liquidity (↑) | C8: =Tiger!K99 -> 0.12295018 | D8: =Allcargo!K99 -> 0.33150185 | E8: =BlueDart!K99 -> 0.72776984 | F8: =CONCOR!K99 -> 1.2513667 | G8: =JetFreight!K99 -> -0.11414869 | H8: =Patel!K99 -> 0.10835287 | I8: =Sical!K99 -> 0.12059511 | J8: =TCI!K99 -> 0.99039578 | K8: =Shreeji!K99 -> 0.43081607 | L8: =MahindraLog!K99 -> 0.20161113 | M8: =Industry!K100 -> 0.55763214 | N8: =IF(COUNT(C8:L8)=0,"N/M",MEDIAN(C8:L8)) -> 0.26655649
A9: Debt-equity ratio | B9: Leverage (↓) | C9: =Tiger!K101 -> 0.24661787 | D9: =Allcargo!K101 -> 0.87612163 | E9: =BlueDart!K101 -> 1.1280755 | F9: =CONCOR!K101 -> 0.062736366 | G9: =JetFreight!K101 -> 1.3550845 | H9: =Patel!K101 -> 0.29634174 | I9: =Sical!K101 -> 8.2478837 | J9: =TCI!K101 -> 0.15977623 | K9: =Shreeji!K101 -> 1.2179689 | L9: =MahindraLog!K101 -> 1.0148062 | M9: =Industry!K102 -> 0.30963722 | N9: =IF(COUNT(C9:L9)=0,"N/M",MEDIAN(C9:L9)) -> 0.94546393
A10: Proprietary ratio | B10: Leverage (↑) | C10: =Tiger!K105 -> 0.64580193 | D10: =Allcargo!K105 -> 0.34869893 | E10: =BlueDart!K105 -> 0.33080972 | F10: =CONCOR!K105 -> 0.84060615 | G10: =JetFreight!K105 -> 0.30649204 | H10: =Patel!K105 -> 0.66174853 | I10: =Sical!K105 -> -0.079794883 | J10: =TCI!K105 -> 0.73518162 | K10: =Shreeji!K105 -> 0.4032542 | L10: =MahindraLog!K105 -> 0.28048555 | M10: =Industry!K106 -> 0.58700064 | N10: =IF(COUNT(C10:L10)=0,"N/M",MEDIAN(C10:L10)) -> 0.37597656
A11: Debt to EBITDA | B11: Leverage (↓) | C11: =Tiger!K107 -> 0.75113098 | D11: =Allcargo!K107 -> 2.8434977 | E11: =BlueDart!K107 -> 1.3147804 | F11: =CONCOR!K107 -> 0.42697979 | G11: =JetFreight!K107 -> 5.6555538 | H11: =Patel!K107 -> 4.7785377 | I11: =Sical!K107 -> 20.639178 | J11: =TCI!K107 -> 0.70349827 | K11: =Shreeji!K107 -> 4.1414082 | L11: =MahindraLog!K107 -> 2.3755368 | M11: =Industry!K108 -> 1.3775514 | N11: =IF(COUNT(C11:L11)=0,"N/M",MEDIAN(C11:L11)) -> 2.6095173
A12: Interest coverage ratio | B12: Coverage (↑) | C12: =Tiger!K109 -> 10.730958 | D12: =Allcargo!K109 -> 4.0494231 | E12: =BlueDart!K109 -> 4.777735 | F12: =CONCOR!K109 -> 18.439328 | G12: =JetFreight!K109 -> 1.1858265 | H12: =Patel!K109 -> 4.7808037 | I12: =Sical!K109 -> -1.4105085 | J12: =TCI!K109 -> 17.263744 | K12: =Shreeji!K109 -> 2.045678 | L12: =MahindraLog!K109 -> 1.7499748 | M12: =Industry!K110 -> 6.1443735 | N12: =IF(COUNT(C12:L12)=0,"N/M",MEDIAN(C12:L12)) -> 4.4135791
A13: Debt-service coverage ratio (DSCR) | B13: Coverage (↑) | C13: =Tiger!K114 -> 10.758914 | D13: =Allcargo!K114 -> 4.5920994 | E13: =BlueDart!K114 -> 2.3667539 | F13: =CONCOR!K114 -> 10.604068 | G13: =JetFreight!K114 -> 1.3424754 | H13: =Patel!K114 -> 3.3119867 | I13: =Sical!K114 -> -5.6077461 | J13: =TCI!K114 -> 16.090305 | K13: =Shreeji!K114 -> 3.0023597 | L13: =MahindraLog!K114 -> 2.7067417 | M13: =Industry!K115 -> 3.0150827 | N13: =IF(COUNT(C13:L13)=0,"N/M",MEDIAN(C13:L13)) -> 3.1571732
A14: Average collection period (days) | B14: Activity (↓) | C14: =Tiger!K119 -> 76.281334 | D14: =Allcargo!K119 -> 63.069257 | E14: =BlueDart!K119 -> 51.762184 | F14: =CONCOR!K119 -> 12.380379 | G14: =JetFreight!K119 -> 55.3619 | H14: =Patel!K119 -> 96.313471 | I14: =Sical!K119 -> 103.2761 | J14: =TCI!K119 -> 59.542759 | K14: =Shreeji!K119 -> 104.60979 | L14: =MahindraLog!K119 -> 45.718712 | M14: =Industry!K120 -> 46.139843 | N14: =IF(COUNT(C14:L14)=0,"N/M",MEDIAN(C14:L14)) -> 61.306008
A15: Fixed assets turnover (times) | B15: Activity (↑) | C15: =Tiger!K123 -> 47.430962 | D15: =Allcargo!K123 -> 4.3948625 | E15: =BlueDart!K123 -> 2.8163152 | F15: =CONCOR!K123 -> 1.3145974 | G15: =JetFreight!K123 -> 15.771494 | H15: =Patel!K123 -> 5.859202 | I15: =Sical!K123 -> 0.60484321 | J15: =TCI!K123 -> 4.1864023 | K15: =Shreeji!K123 -> 7.1944463 | L15: =MahindraLog!K123 -> 8.2546136 | M15: =Industry!K124 -> 2.7208254 | N15: =IF(COUNT(C15:L15)=0,"N/M",MEDIAN(C15:L15)) -> 5.1270322
A16: Total assets turnover (times) | B16: Activity (↑) | C16: =Tiger!K124 -> 2.8806467 | D16: =Allcargo!K124 -> 1.6321028 | E16: =BlueDart!K124 -> 1.4389931 | F16: =CONCOR!K124 -> 0.58508733 | G16: =JetFreight!K124 -> 2.9659525 | H16: =Patel!K124 -> 1.6385818 | I16: =Sical!K124 -> 0.33477339 | J16: =TCI!K124 -> 1.6231699 | K16: =Shreeji!K124 -> 1.7530154 | L16: =MahindraLog!K124 -> 2.1892969 | M16: =Industry!K125 -> 1.1428556 | N16: =IF(COUNT(C16:L16)=0,"N/M",MEDIAN(C16:L16)) -> 1.6353423
A17: Gross profit margin | B17: Profitability (↑) | C17: =Tiger!K129 -> 0.099915313 | D17: =Allcargo!K129 -> 0.23630924 | E17: =BlueDart!K129 -> 0.42586555 | F17: =CONCOR!K129 -> 0.34613339 | G17: =JetFreight!K129 -> 0.075109 | H17: =Patel!K129 -> 0.099163264 | I17: =Sical!K129 -> 0.22992313 | J17: =TCI!K129 -> 0.1856674 | K17: =Shreeji!K129 -> 0.19571326 | L17: =MahindraLog!K129 -> 0.14384662 | M17: =Industry!K130 -> 0.25888543 | N17: =IF(COUNT(C17:L17)=0,"N/M",MEDIAN(C17:L17)) -> 0.19069033
A18: Operating EBITDA margin | B18: Profitability (↑) | C18: =Tiger!K130 -> 0.029629489 | D18: =Allcargo!K130 -> 0.073607981 | E18: =BlueDart!K130 -> 0.17658992 | F18: =CONCOR!K130 -> 0.21971019 | G18: =JetFreight!K130 -> 0.020453399 | H18: =Patel!K130 -> 0.0290875 | I18: =Sical!K130 -> 0.041720612 | J18: =TCI!K130 -> 0.10460636 | K18: =Shreeji!K130 -> 0.072103023 | L18: =MahindraLog!K130 -> 0.046407247 | M18: =Industry!K131 -> 0.11740644 | N18: =IF(COUNT(C18:L18)=0,"N/M",MEDIAN(C18:L18)) -> 0.059255135
A19: Operating profit (EBIT) margin | B19: Profitability (↑) | C19: =Tiger!K131 -> 0.027035179 | D19: =Allcargo!K131 -> 0.02913258 | E19: =BlueDart!K131 -> 0.082258617 | F19: =CONCOR!K131 -> 0.14575848 | G19: =JetFreight!K131 -> 0.015028909 | H19: =Patel!K131 -> 0.019310825 | I19: =Sical!K131 -> -0.11299976 | J19: =TCI!K131 -> 0.073993461 | K19: =Shreeji!K131 -> 0.046968483 | L19: =MahindraLog!K131 -> 0.012903028 | M19: =Industry!K132 -> 0.067261761 | N19: =IF(COUNT(C19:L19)=0,"N/M",MEDIAN(C19:L19)) -> 0.02808388
A20: Net profit margin | B20: Profitability (↑) | C20: =Tiger!K133 -> 0.019312592 | D20: =Allcargo!K133 -> 0.025549208 | E20: =BlueDart!K133 -> 0.045375983 | F20: =CONCOR!K133 -> 0.12136961 | G20: =JetFreight!K133 -> 0.0013562643 | H20: =Patel!K133 -> 0.018081543 | I20: =Sical!K133 -> -0.77125135 | J20: =TCI!K133 -> 0.078488617 | K20: =Shreeji!K133 -> 0.027812603 | L20: =MahindraLog!K133 -> 0.0027070853 | M20: =Industry!K134 -> 0.044064558 | N20: =IF(COUNT(C20:L20)=0,"N/M",MEDIAN(C20:L20)) -> 0.0224309
A21: Operating ratio | B21: Expenses (↓) | C21: =Tiger!K140 -> 0.97037051 | D21: =Allcargo!K140 -> 0.92639202 | E21: =BlueDart!K140 -> 0.82341008 | F21: =CONCOR!K140 -> 0.78028981 | G21: =JetFreight!K140 -> 0.9795466 | H21: =Patel!K140 -> 0.9709125 | I21: =Sical!K140 -> 0.95827939 | J21: =TCI!K140 -> 0.89539364 | K21: =Shreeji!K140 -> 0.92789698 | L21: =MahindraLog!K140 -> 0.95359275 | M21: =Industry!K141 -> 0.88259356 | N21: =IF(COUNT(C21:L21)=0,"N/M",MEDIAN(C21:L21)) -> 0.94074487
A22: Return on assets (ROA) | B22: Returns (↑) | C22: =Tiger!K142 -> 0.073754177 | D22: =Allcargo!K142 -> 0.044572826 | E22: =BlueDart!K142 -> 0.069314504 | F22: =CONCOR!K142 -> 0.0720001 | G22: =JetFreight!K142 -> 0.0015715268 | H22: =Patel!K142 -> 0.032361336 | I22: =Sical!K142 -> -0.27701266 | J22: =TCI!K142 -> 0.12722538 | K22: =Shreeji!K142 -> 0.053066207 | L22: =MahindraLog!K142 -> 0.0057816857 | M22: =Industry!K143 -> 0.051867676 | N22: =IF(COUNT(C22:L22)=0,"N/M",MEDIAN(C22:L22)) -> 0.048819516
A23: Return on capital employed (post-tax) | B23: Returns (↑) | C23: =Tiger!K146 -> 0.094712109 | D23: =Allcargo!K146 -> 0.067070152 | E23: =BlueDart!K146 -> 0.13833211 | F23: =CONCOR!K146 -> 0.072251715 | G23: =JetFreight!K146 -> 0.036616476 | H23: =Patel!K146 -> 0.036368505 | I23: =Sical!K146 -> -0.061079075 | J23: =TCI!K146 -> 0.12781958 | K23: =Shreeji!K146 -> 0.07357899 | L23: =MahindraLog!K146 -> 0.040818271 | M23: =Industry!K147 -> 0.07527092 | N23: =IF(COUNT(C23:L23)=0,"N/M",MEDIAN(C23:L23)) -> 0.069660933
A24: Return on total shareholders' equity (ROE) | B24: Returns (↑) | C24: =Tiger!K147 -> 0.086615744 | D24: =Allcargo!K147 -> 0.12644432 | E24: =BlueDart!K147 -> 0.19434874 | F24: =CONCOR!K147 -> 0.085598326 | G24: =JetFreight!K147 -> -0.015603736 | H24: =Patel!K147 -> 0.048323836 | I24: =Sical!K147 -> -4.102302 | J24: =TCI!K147 -> 0.17114783 | K24: =Shreeji!K147 -> 0.12804549 | L24: =MahindraLog!K147 -> 0.0059799242 | M24: =Industry!K148 -> 0.086582652 | N24: =IF(COUNT(C24:L24)=0,"N/M",MEDIAN(C24:L24)) -> 0.086107035
A25: Price-earnings (P/E) ratio | B25: Valuation (-) | C25: =Tiger!K158 -> 18.205493 | D25: =Allcargo!K158 -> 134.42755 | E25: =BlueDart!K158 -> 60.639355 | F25: =CONCOR!K158 -> 41.785842 | G25: =JetFreight!K158 -> 203.63814 | H25: =Patel!K158 -> 207.37891 | I25: =Sical!K158 -> 10.200767 | J25: =TCI!K158 -> 15.551279 | K25: =Shreeji!K158 -> 24.35755 | L25: =MahindraLog!K158 -> 406.63754 | M25: =Industry!K159 -> 44.890973 | N25: =IF(COUNT(C25:L25)=0,"N/M",MEDIAN(C25:L25)) -> 51.212598
A26: Price-to-book (P/B) ratio | B26: Valuation (-) | C26: =Tiger!K159 -> 2.5994839 | D26: =Allcargo!K159 -> 1.8735547 | E26: =BlueDart!K159 -> 12.921371 | F26: =CONCOR!K159 -> 3.2852064 | G26: =JetFreight!K159 -> 1.7591522 | H26: =Patel!K159 -> 0.66414011 | I26: =Sical!K159 -> 9.5263998 | J26: =TCI!K159 -> 2.7172077 | K26: =Shreeji!K159 -> 3.4046469 | L26: =MahindraLog!K159 -> 6.0935807 | M26: =Industry!K160 -> 4.0055146 | N26: =IF(COUNT(C26:L26)=0,"N/M",MEDIAN(C26:L26)) -> 3.001207
A27: Dividend yield | B27: Valuation (-) | C27: =Tiger!K157 -> 0.00067832672 | D27: =Allcargo!K157 -> 0 | E27: =BlueDart!K157 -> 0.0042458934 | F27: =CONCOR!K157 -> 0.014493263 | G27: =JetFreight!K157 -> 0.00012704887 | H27: =Patel!K157 -> 0.010418909 | I27: =Sical!K157 -> 0 | J27: =TCI!K157 -> 0.0092816836 | K27: =Shreeji!K157 -> 0.0073395875 | L27: =MahindraLog!K157 -> 0.0053561347 | M27: =Industry!K158 -> 0.011025959 | N27: =IF(COUNT(C27:L27)=0,"N/M",MEDIAN(C27:L27)) -> 0.004801014
A28: EV / EBITDA | B28: Valuation (-) | C28: =Tiger!K160 -> 14.504126 | D28: =Allcargo!K160 -> 6.9677464 | E28: =BlueDart!K160 -> 16.489895 | F28: =CONCOR!K160 -> 20.793214 | G28: =JetFreight!K160 -> 11.526534 | H28: =Patel!K160 -> 11.464136 | I28: =Sical!K160 -> 38.516551 | J28: =TCI!K160 -> 12.403091 | K28: =Shreeji!K160 -> 12.750233 | L28: =MahindraLog!K160 -> 19.108693 | M28: =Industry!K161 -> 18.590864 | N28: =IF(COUNT(C28:L28)=0,"N/M",MEDIAN(C28:L28)) -> 13.627179
A31: B. Composite ranking on the 7-year averages (rank 1 = best among the 10 firms; ties share the better rank)
A32: Ratio | B32: Direction | C32: Tiger | D32: Allcargo | E32: Blue Dart | F32: CONCOR | G32: Jet Freight | H32: Patel | I32: Sical | J32: TCI | K32: Shreeji | L32: Mahindra Log.
A33: Current ratio | B33: higher is better | C33: =IF(ISNUMBER(C6),RANK(C6,$C$6:$L$6,0),"-") -> 3 | D33: =IF(ISNUMBER(D6),RANK(D6,$C$6:$L$6,0),"-") -> 7 | E33: =IF(ISNUMBER(E6),RANK(E6,$C$6:$L$6,0),"-") -> 9 | F33: =IF(ISNUMBER(F6),RANK(F6,$C$6:$L$6,0),"-") -> 4 | G33: =IF(ISNUMBER(G6),RANK(G6,$C$6:$L$6,0),"-") -> 6 | H33: =IF(ISNUMBER(H6),RANK(H6,$C$6:$L$6,0),"-") -> 1 | I33: =IF(ISNUMBER(I6),RANK(I6,$C$6:$L$6,0),"-") -> 10 | J33: =IF(ISNUMBER(J6),RANK(J6,$C$6:$L$6,0),"-") -> 5 | ... L33: =IF(ISNUMBER(L6),RANK(L6,$C$6:$L$6,0),"-") -> 8
A34: Cash flow from operations ratio | B34: higher is better | C34: =IF(ISNUMBER(C8),RANK(C8,$C$8:$L$8,0),"-") -> 7 | D34: =IF(ISNUMBER(D8),RANK(D8,$C$8:$L$8,0),"-") -> 5 | E34: =IF(ISNUMBER(E8),RANK(E8,$C$8:$L$8,0),"-") -> 3 | F34: =IF(ISNUMBER(F8),RANK(F8,$C$8:$L$8,0),"-") -> 1 | G34: =IF(ISNUMBER(G8),RANK(G8,$C$8:$L$8,0),"-") -> 10 | H34: =IF(ISNUMBER(H8),RANK(H8,$C$8:$L$8,0),"-") -> 9 | I34: =IF(ISNUMBER(I8),RANK(I8,$C$8:$L$8,0),"-") -> 8 | J34: =IF(ISNUMBER(J8),RANK(J8,$C$8:$L$8,0),"-") -> 2 | ... L34: =IF(ISNUMBER(L8),RANK(L8,$C$8:$L$8,0),"-") -> 6
A35: Debt-equity ratio | B35: lower is better | C35: =IF(ISNUMBER(C9),RANK(C9,$C$9:$L$9,1),"-") -> 3 | D35: =IF(ISNUMBER(D9),RANK(D9,$C$9:$L$9,1),"-") -> 5 | E35: =IF(ISNUMBER(E9),RANK(E9,$C$9:$L$9,1),"-") -> 7 | F35: =IF(ISNUMBER(F9),RANK(F9,$C$9:$L$9,1),"-") -> 1 | G35: =IF(ISNUMBER(G9),RANK(G9,$C$9:$L$9,1),"-") -> 9 | H35: =IF(ISNUMBER(H9),RANK(H9,$C$9:$L$9,1),"-") -> 4 | I35: =IF(ISNUMBER(I9),RANK(I9,$C$9:$L$9,1),"-") -> 10 | J35: =IF(ISNUMBER(J9),RANK(J9,$C$9:$L$9,1),"-") -> 2 | ... L35: =IF(ISNUMBER(L9),RANK(L9,$C$9:$L$9,1),"-") -> 6
A36: Interest coverage ratio | B36: higher is better | C36: =IF(ISNUMBER(C12),RANK(C12,$C$12:$L$12,0),"-") -> 3 | D36: =IF(ISNUMBER(D12),RANK(D12,$C$12:$L$12,0),"-") -> 6 | E36: =IF(ISNUMBER(E12),RANK(E12,$C$12:$L$12,0),"-") -> 5 | F36: =IF(ISNUMBER(F12),RANK(F12,$C$12:$L$12,0),"-") -> 1 | G36: =IF(ISNUMBER(G12),RANK(G12,$C$12:$L$12,0),"-") -> 9 | H36: =IF(ISNUMBER(H12),RANK(H12,$C$12:$L$12,0),"-") -> 4 | I36: =IF(ISNUMBER(I12),RANK(I12,$C$12:$L$12,0),"-") -> 10 | J36: =IF(ISNUMBER(J12),RANK(J12,$C$12:$L$12,0),"-") -> 2 | ... L36: =IF(ISNUMBER(L12),RANK(L12,$C$12:$L$12,0),"-") -> 8
A37: Average collection period (days) | B37: lower is better | C37: =IF(ISNUMBER(C14),RANK(C14,$C$14:$L$14,1),"-") -> 7 | D37: =IF(ISNUMBER(D14),RANK(D14,$C$14:$L$14,1),"-") -> 6 | E37: =IF(ISNUMBER(E14),RANK(E14,$C$14:$L$14,1),"-") -> 3 | F37: =IF(ISNUMBER(F14),RANK(F14,$C$14:$L$14,1),"-") -> 1 | G37: =IF(ISNUMBER(G14),RANK(G14,$C$14:$L$14,1),"-") -> 4 | H37: =IF(ISNUMBER(H14),RANK(H14,$C$14:$L$14,1),"-") -> 8 | I37: =IF(ISNUMBER(I14),RANK(I14,$C$14:$L$14,1),"-") -> 9 | J37: =IF(ISNUMBER(J14),RANK(J14,$C$14:$L$14,1),"-") -> 5 | ... L37: =IF(ISNUMBER(L14),RANK(L14,$C$14:$L$14,1),"-") -> 2
A38: Total assets turnover (times) | B38: higher is better | C38: =IF(ISNUMBER(C16),RANK(C16,$C$16:$L$16,0),"-") -> 2 | D38: =IF(ISNUMBER(D16),RANK(D16,$C$16:$L$16,0),"-") -> 6 | E38: =IF(ISNUMBER(E16),RANK(E16,$C$16:$L$16,0),"-") -> 8 | F38: =IF(ISNUMBER(F16),RANK(F16,$C$16:$L$16,0),"-") -> 9 | G38: =IF(ISNUMBER(G16),RANK(G16,$C$16:$L$16,0),"-") -> 1 | H38: =IF(ISNUMBER(H16),RANK(H16,$C$16:$L$16,0),"-") -> 5 | I38: =IF(ISNUMBER(I16),RANK(I16,$C$16:$L$16,0),"-") -> 10 | J38: =IF(ISNUMBER(J16),RANK(J16,$C$16:$L$16,0),"-") -> 7 | ... L38: =IF(ISNUMBER(L16),RANK(L16,$C$16:$L$16,0),"-") -> 3
A39: Operating EBITDA margin | B39: higher is better | C39: =IF(ISNUMBER(C18),RANK(C18,$C$18:$L$18,0),"-") -> 8 | D39: =IF(ISNUMBER(D18),RANK(D18,$C$18:$L$18,0),"-") -> 4 | E39: =IF(ISNUMBER(E18),RANK(E18,$C$18:$L$18,0),"-") -> 2 | F39: =IF(ISNUMBER(F18),RANK(F18,$C$18:$L$18,0),"-") -> 1 | G39: =IF(ISNUMBER(G18),RANK(G18,$C$18:$L$18,0),"-") -> 10 | H39: =IF(ISNUMBER(H18),RANK(H18,$C$18:$L$18,0),"-") -> 9 | I39: =IF(ISNUMBER(I18),RANK(I18,$C$18:$L$18,0),"-") -> 7 | J39: =IF(ISNUMBER(J18),RANK(J18,$C$18:$L$18,0),"-") -> 3 | ... L39: =IF(ISNUMBER(L18),RANK(L18,$C$18:$L$18,0),"-") -> 6
A40: Operating profit (EBIT) margin | B40: higher is better | C40: =IF(ISNUMBER(C19),RANK(C19,$C$19:$L$19,0),"-") -> 6 | D40: =IF(ISNUMBER(D19),RANK(D19,$C$19:$L$19,0),"-") -> 5 | E40: =IF(ISNUMBER(E19),RANK(E19,$C$19:$L$19,0),"-") -> 2 | F40: =IF(ISNUMBER(F19),RANK(F19,$C$19:$L$19,0),"-") -> 1 | G40: =IF(ISNUMBER(G19),RANK(G19,$C$19:$L$19,0),"-") -> 8 | H40: =IF(ISNUMBER(H19),RANK(H19,$C$19:$L$19,0),"-") -> 7 | I40: =IF(ISNUMBER(I19),RANK(I19,$C$19:$L$19,0),"-") -> 10 | J40: =IF(ISNUMBER(J19),RANK(J19,$C$19:$L$19,0),"-") -> 3 | ... L40: =IF(ISNUMBER(L19),RANK(L19,$C$19:$L$19,0),"-") -> 9
A41: Return on capital employed (post-tax) | B41: higher is better | C41: =IF(ISNUMBER(C23),RANK(C23,$C$23:$L$23,0),"-") -> 3 | D41: =IF(ISNUMBER(D23),RANK(D23,$C$23:$L$23,0),"-") -> 6 | E41: =IF(ISNUMBER(E23),RANK(E23,$C$23:$L$23,0),"-") -> 1 | F41: =IF(ISNUMBER(F23),RANK(F23,$C$23:$L$23,0),"-") -> 5 | G41: =IF(ISNUMBER(G23),RANK(G23,$C$23:$L$23,0),"-") -> 8 | H41: =IF(ISNUMBER(H23),RANK(H23,$C$23:$L$23,0),"-") -> 9 | I41: =IF(ISNUMBER(I23),RANK(I23,$C$23:$L$23,0),"-") -> 10 | J41: =IF(ISNUMBER(J23),RANK(J23,$C$23:$L$23,0),"-") -> 2 | ... L41: =IF(ISNUMBER(L23),RANK(L23,$C$23:$L$23,0),"-") -> 7
A42: Return on total shareholders' equity (ROE) | B42: higher is better | C42: =IF(ISNUMBER(C24),RANK(C24,$C$24:$L$24,0),"-") -> 5 | D42: =IF(ISNUMBER(D24),RANK(D24,$C$24:$L$24,0),"-") -> 4 | E42: =IF(ISNUMBER(E24),RANK(E24,$C$24:$L$24,0),"-") -> 1 | F42: =IF(ISNUMBER(F24),RANK(F24,$C$24:$L$24,0),"-") -> 6 | G42: =IF(ISNUMBER(G24),RANK(G24,$C$24:$L$24,0),"-") -> 9 | H42: =IF(ISNUMBER(H24),RANK(H24,$C$24:$L$24,0),"-") -> 7 | I42: =IF(ISNUMBER(I24),RANK(I24,$C$24:$L$24,0),"-") -> 10 | J42: =IF(ISNUMBER(J24),RANK(J24,$C$24:$L$24,0),"-") -> 2 | ... L42: =IF(ISNUMBER(L24),RANK(L24,$C$24:$L$24,0),"-") -> 8
A43: Composite score (average rank) | B43: lower is better | C43: =AVERAGE(C33:C42) -> 4.7 | D43: =AVERAGE(D33:D42) -> 5.4 | E43: =AVERAGE(E33:E42) -> 4.1 | F43: =AVERAGE(F33:F42) -> 3 | G43: =AVERAGE(G33:G42) -> 7.4 | H43: =AVERAGE(H33:H42) -> 6.3 | I43: =AVERAGE(I33:I42) -> 9.4 | J43: =AVERAGE(J33:J42) -> 3.3 | ... L43: =AVERAGE(L33:L42) -> 6.3
A44: Overall position (1 = strongest) | C44: =RANK(C43,$C$43:$L$43,1) -> 4 | D44: =RANK(D43,$C$43:$L$43,1) -> 6 | E44: =RANK(E43,$C$43:$L$43,1) -> 3 | F44: =RANK(F43,$C$43:$L$43,1) -> 1 | G44: =RANK(G43,$C$43:$L$43,1) -> 9 | H44: =RANK(H43,$C$43:$L$43,1) -> 7 | I44: =RANK(I43,$C$43:$L$43,1) -> 10 | J44: =RANK(J43,$C$43:$L$43,1) -> 2 | ... L44: =RANK(L43,$C$43:$L$43,1) -> 7
A46: Note: a 7-year average uses only the years in which the ratio is meaningful (N/M years are skipped). For Allcargo, valuation averages cover FY2026 only (earlier years N/C). Sical's leverage averages exclude its negative net-worth years.

Sheet Industry_Compare
A1: Industry comparison - every ratio, every firm, FY2020-FY2026
A2: Industry (aggregate) = ratio on the summed financials of the 10 firms (size-weighted). Mean / median / SD / min / max = simple statistics of the 10 firm ratios (N/M and N/C values are ignored). Assessment and rank compare each firm's 7-year average with the 10-firm median (the typical-firm benchmark).
A4: Firm / statistic | B4: FY2020 | C4: FY2021 | D4: FY2022 | E4: FY2023 | F4: FY2024 | G4: FY2025 | H4: FY2026 | I4: 7-Yr Average | J4: 7-yr avg vs median | K4: Assessment | L4: Rank (1 = best)
A6: 1.1 Net working capital [Current assets - Current liabilities] - Liquidity; no normative direction
A7: Tiger | B7: =Tiger!D94 -> 79.44 | C7: =Tiger!E94 -> 48.16 | D7: =Tiger!F94 -> 61.36 | E7: =Tiger!G94 -> 84.64 | F7: =Tiger!H94 -> 102.6 | G7: =Tiger!I94 -> 151.77 | H7: =Tiger!J94 -> 187.87 | I7: =Tiger!K94 -> 102.26286 | J7: =IF(AND(ISNUMBER(I7),ISNUMBER(I$19)),IF(I7>I$19,"Above",IF(I7<I$19,"Below","At median")),"-") -> Below | K7: - | L7: -
A8: Allcargo | B8: =Allcargo!D94 -> 1002.04 | C8: =Allcargo!E94 -> 857.7 | D8: =Allcargo!F94 -> 1417.79 | E8: =Allcargo!G94 -> 1265.14 | F8: =Allcargo!H94 -> 1242.73 | G8: =Allcargo!I94 -> 578 | H8: =Allcargo!J94 -> 481 | I8: =Allcargo!K94 -> 977.77143 | J8: =IF(AND(ISNUMBER(I8),ISNUMBER(I$19)),IF(I8>I$19,"Above",IF(I8<I$19,"Below","At median")),"-") -> Above | K8: - | L8: -
A9: Blue Dart | B9: =BlueDart!D94 -> -662.18 | C9: =BlueDart!E94 -> 374.18 | D9: =BlueDart!F94 -> 224.54 | E9: =BlueDart!G94 -> 252.87 | F9: =BlueDart!H94 -> 236.54 | G9: =BlueDart!I94 -> 289.72 | H9: =BlueDart!J94 -> 443.88 | I9: =BlueDart!K94 -> 165.65 | J9: =IF(AND(ISNUMBER(I9),ISNUMBER(I$19)),IF(I9>I$19,"Above",IF(I9<I$19,"Below","At median")),"-") -> Above | K9: - | L9: -
A10: CONCOR | B10: =CONCOR!D94 -> 2626.3 | C10: =CONCOR!E94 -> 3063.63 | D10: =CONCOR!F94 -> 3805.64 | E10: =CONCOR!G94 -> 4333.98 | F10: =CONCOR!H94 -> 4747.44 | G10: =CONCOR!I94 -> 4689.41 | H10: =CONCOR!J94 -> 4759.67 | I10: =CONCOR!K94 -> 4003.7243 | J10: =IF(AND(ISNUMBER(I10),ISNUMBER(I$19)),IF(I10>I$19,"Above",IF(I10<I$19,"Below","At median")),"-") -> Above | K10: - | L10: -
A11: Jet Freight | B11: =JetFreight!D94 -> 39.16 | C11: =JetFreight!E94 -> 23.78 | D11: =JetFreight!F94 -> 42.17 | E11: =JetFreight!G94 -> 92.29 | F11: =JetFreight!H94 -> 90.86 | G11: =JetFreight!I94 -> 103.78 | H11: =JetFreight!J94 -> 122.24 | I11: =JetFreight!K94 -> 73.468571 | J11: =IF(AND(ISNUMBER(I11),ISNUMBER(I$19)),IF(I11>I$19,"Above",IF(I11<I$19,"Below","At median")),"-") -> Below | K11: - | L11: -
A12: Patel | B12: =Patel!D94 -> 115.87 | C12: =Patel!E94 -> 115.04 | D12: =Patel!F94 -> 102.28 | E12: =Patel!G94 -> 88.52 | F12: =Patel!H94 -> 90.18 | G12: =Patel!I94 -> 83.19 | H12: =Patel!J94 -> 79.32 | I12: =Patel!K94 -> 96.342857 | J12: =IF(AND(ISNUMBER(I12),ISNUMBER(I$19)),IF(I12>I$19,"Above",IF(I12<I$19,"Below","At median")),"-") -> Below | K12: - | L12: -
A13: Sical | B13: =Sical!D94 -> -459.35 | C13: =Sical!E94 -> -646.28 | D13: =Sical!F94 -> -337.55 | E13: =Sical!G94 -> -68.93 | F13: =Sical!H94 -> -32.09 | G13: =Sical!I94 -> -51.8 | H13: =Sical!J94 -> 40.73 | I13: =Sical!K94 -> -222.18143 | J13: =IF(AND(ISNUMBER(I13),ISNUMBER(I$19)),IF(I13>I$19,"Above",IF(I13<I$19,"Below","At median")),"-") -> Below | K13: - | L13: -
A14: TCI | B14: =TCI!D94 -> 517.29 | C14: =TCI!E94 -> 507.36 | D14: =TCI!F94 -> 525.15 | E14: =TCI!G94 -> 690.52 | F14: =TCI!H94 -> 684.09 | G14: =TCI!I94 -> 766.74 | H14: =TCI!J94 -> 855.89 | I14: =TCI!K94 -> 649.57714 | J14: =IF(AND(ISNUMBER(I14),ISNUMBER(I$19)),IF(I14>I$19,"Above",IF(I14<I$19,"Below","At median")),"-") -> Above | K14: - | L14: -
A15: Shreeji | B15: =Shreeji!D94 -> 43.83 | C15: =Shreeji!E94 -> 46.23 | D15: =Shreeji!F94 -> 56.35 | E15: =Shreeji!G94 -> 56.1 | F15: =Shreeji!H94 -> 66.91 | G15: =Shreeji!I94 -> 65.55 | H15: =Shreeji!J94 -> 72.95 | I15: =Shreeji!K94 -> 58.274286 | J15: =IF(AND(ISNUMBER(I15),ISNUMBER(I$19)),IF(I15>I$19,"Above",IF(I15<I$19,"Below","At median")),"-") -> Below | K15: - | L15: -
A16: Mahindra Log. | B16: =MahindraLog!D94 -> 496.81 | C16: =MahindraLog!E94 -> 418.69 | D16: =MahindraLog!F94 -> 316.78 | E16: =MahindraLog!G94 -> 462.39 | F16: =MahindraLog!H94 -> 373.47 | G16: =MahindraLog!I94 -> 308.71 | H16: =MahindraLog!J94 -> 527.87 | I16: =MahindraLog!K94 -> 414.96 | J16: =IF(AND(ISNUMBER(I16),ISNUMBER(I$19)),IF(I16>I$19,"Above",IF(I16<I$19,"Below","At median")),"-") -> Above | K16: - | L16: -
A17: Industry (aggregate) | B17: =Industry!D95 -> 3799.21 | C17: =Industry!E95 -> 4808.49 | D17: =Industry!F95 -> 6214.51 | E17: =Industry!G95 -> 7257.52 | F17: =Industry!H95 -> 7602.73 | G17: =Industry!I95 -> 6985.07 | H17: =Industry!J95 -> 7571.42 | I17: =Industry!K95 -> 6319.85
A18: Mean (10 firms) | B18: =IF(COUNT(B7:B16)=0,"N/M",AVERAGE(B7:B16)) -> 379.921 | C18: =IF(COUNT(C7:C16)=0,"N/M",AVERAGE(C7:C16)) -> 480.849 | D18: =IF(COUNT(D7:D16)=0,"N/M",AVERAGE(D7:D16)) -> 621.451 | E18: =IF(COUNT(E7:E16)=0,"N/M",AVERAGE(E7:E16)) -> 725.752 | F18: =IF(COUNT(F7:F16)=0,"N/M",AVERAGE(F7:F16)) -> 760.273 | G18: =IF(COUNT(G7:G16)=0,"N/M",AVERAGE(G7:G16)) -> 698.507 | H18: =IF(COUNT(H7:H16)=0,"N/M",AVERAGE(H7:H16)) -> 757.142 | I18: =IF(COUNT(I7:I16)=0,"N/M",AVERAGE(I7:I16)) -> 631.985
A19: Median (10 firms) | B19: =IF(COUNT(B7:B16)=0,"N/M",MEDIAN(B7:B16)) -> 97.655 | C19: =IF(COUNT(C7:C16)=0,"N/M",MEDIAN(C7:C16)) -> 244.61 | D19: =IF(COUNT(D7:D16)=0,"N/M",MEDIAN(D7:D16)) -> 163.41 | E19: =IF(COUNT(E7:E16)=0,"N/M",MEDIAN(E7:E16)) -> 172.58 | F19: =IF(COUNT(F7:F16)=0,"N/M",MEDIAN(F7:F16)) -> 169.57 | G19: =IF(COUNT(G7:G16)=0,"N/M",MEDIAN(G7:G16)) -> 220.745 | H19: =IF(COUNT(H7:H16)=0,"N/M",MEDIAN(H7:H16)) -> 315.875 | I19: =IF(COUNT(I7:I16)=0,"N/M",MEDIAN(I7:I16)) -> 133.95643
A20: Standard deviation | B20: =IF(COUNT(B7:B16)<2,"N/M",STDEV(B7:B16)) -> 921.66644 | C20: =IF(COUNT(C7:C16)<2,"N/M",STDEV(C7:C16)) -> 989.83617 | D20: =IF(COUNT(D7:D16)<2,"N/M",STDEV(D7:D16)) -> 1210.6326 | E20: =IF(COUNT(E7:E16)<2,"N/M",STDEV(E7:E16)) -> 1329.2765 | F20: =IF(COUNT(F7:F16)<2,"N/M",STDEV(F7:F16)) -> 1452.8992 | G20: =IF(COUNT(G7:G16)<2,"N/M",STDEV(G7:G16)) -> 1424.4049 | H20: =IF(COUNT(H7:H16)<2,"N/M",STDEV(H7:H16)) -> 1430.8084 | I20: =IF(COUNT(I7:I16)<2,"N/M",STDEV(I7:I16)) -> 1233.3907
A21: Minimum | B21: =IF(COUNT(B7:B16)=0,"N/M",MIN(B7:B16)) -> -662.18 | C21: =IF(COUNT(C7:C16)=0,"N/M",MIN(C7:C16)) -> -646.28 | D21: =IF(COUNT(D7:D16)=0,"N/M",MIN(D7:D16)) -> -337.55 | E21: =IF(COUNT(E7:E16)=0,"N/M",MIN(E7:E16)) -> -68.93 | F21: =IF(COUNT(F7:F16)=0,"N/M",MIN(F7:F16)) -> -32.09 | G21: =IF(COUNT(G7:G16)=0,"N/M",MIN(G7:G16)) -> -51.8 | H21: =IF(COUNT(H7:H16)=0,"N/M",MIN(H7:H16)) -> 40.73 | I21: =IF(COUNT(I7:I16)=0,"N/M",MIN(I7:I16)) -> -222.18143
A22: Maximum | B22: =IF(COUNT(B7:B16)=0,"N/M",MAX(B7:B16)) -> 2626.3 | C22: =IF(COUNT(C7:C16)=0,"N/M",MAX(C7:C16)) -> 3063.63 | D22: =IF(COUNT(D7:D16)=0,"N/M",MAX(D7:D16)) -> 3805.64 | E22: =IF(COUNT(E7:E16)=0,"N/M",MAX(E7:E16)) -> 4333.98 | F22: =IF(COUNT(F7:F16)=0,"N/M",MAX(F7:F16)) -> 4747.44 | G22: =IF(COUNT(G7:G16)=0,"N/M",MAX(G7:G16)) -> 4689.41 | H22: =IF(COUNT(H7:H16)=0,"N/M",MAX(H7:H16)) -> 4759.67 | I22: =IF(COUNT(I7:I16)=0,"N/M",MAX(I7:I16)) -> 4003.7243
A24: 1.2 Current ratio [Current assets / Current liabilities] - Liquidity; higher is better
A25: Tiger | B25: =Tiger!D95 -> 6.047014 | C25: =Tiger!E95 -> 2.7896693 | D25: =Tiger!F95 -> 2.310551 | E25: =Tiger!G95 -> 4.8683729 | F25: =Tiger!H95 -> 5.9541284 | G25: =Tiger!I95 -> 7.5958279 | H25: =Tiger!J95 -> 4.6170581 | I25: =Tiger!K95 -> 4.8832317 | J25: =IF(AND(ISNUMBER(I25),ISNUMBER(I$37)),IF(I25>I$37,"Above",IF(I25<I$37,"Below","At median")),"-") -> Above | K25: =IF(J25="Above","Better",IF(J25="Below","Weaker",IF(J25="At median","In line","-"))) -> Better | L25: =IF(ISNUMBER(I25),RANK(I25,I$25:I$34,0),"-") -> 3
A26: Allcargo | B26: =Allcargo!D95 -> 1.6456859 | C26: =Allcargo!E95 -> 1.2893373 | D26: =Allcargo!F95 -> 1.3437125 | E26: =Allcargo!G95 -> 1.3908215 | F26: =Allcargo!H95 -> 1.4445132 | G26: =Allcargo!I95 -> 2.4522613 | H26: =Allcargo!J95 -> 2.0255864 | I26: =Allcargo!K95 -> 1.6559883 | J26: =IF(AND(ISNUMBER(I26),ISNUMBER(I$37)),IF(I26>I$37,"Above",IF(I26<I$37,"Below","At median")),"-") -> Below | K26: =IF(J26="Above","Better",IF(J26="Below","Weaker",IF(J26="At median","In line","-"))) -> Weaker | L26: =IF(ISNUMBER(I26),RANK(I26,I$25:I$34,0),"-") -> 7
A27: Blue Dart | B27: =BlueDart!D95 -> 0.59123682 | C27: =BlueDart!E95 -> 1.4776847 | D27: =BlueDart!F95 -> 1.2520571 | E27: =BlueDart!G95 -> 1.2738644 | F27: =BlueDart!H95 -> 1.2317475 | G27: =BlueDart!I95 -> 1.2641671 | H27: =BlueDart!J95 -> 1.3674138 | I27: =BlueDart!K95 -> 1.2083102 | J27: =IF(AND(ISNUMBER(I27),ISNUMBER(I$37)),IF(I27>I$37,"Above",IF(I27<I$37,"Below","At median")),"-") -> Below | K27: =IF(J27="Above","Better",IF(J27="Below","Weaker",IF(J27="At median","In line","-"))) -> Weaker | L27: =IF(ISNUMBER(I27),RANK(I27,I$25:I$34,0),"-") -> 9
A28: CONCOR | B28: =CONCOR!D95 -> 2.5701338 | C28: =CONCOR!E95 -> 3.042066 | D28: =CONCOR!F95 -> 3.5179069 | E28: =CONCOR!G95 -> 3.9676867 | F28: =CONCOR!H95 -> 4.7198355 | G28: =CONCOR!I95 -> 4.7991234 | H28: =CONCOR!J95 -> 4.7511388 | I28: =CONCOR!K95 -> 3.9096987 | J28: =IF(AND(ISNUMBER(I28),ISNUMBER(I$37)),IF(I28>I$37,"Above",IF(I28<I$37,"Below","At median")),"-") -> Above | K28: =IF(J28="Above","Better",IF(J28="Below","Weaker",IF(J28="At median","In line","-"))) -> Better | L28: =IF(ISNUMBER(I28),RANK(I28,I$25:I$34,0),"-") -> 4
A29: Jet Freight | B29: =JetFreight!D95 -> 2.1770364 | C29: =JetFreight!E95 -> 1.5218345 | D29: =JetFreight!F95 -> 2.1581983 | E29: =JetFreight!G95 -> 4.0013008 | F29: =JetFreight!H95 -> 2.7379495 | G29: =JetFreight!I95 -> 2.9950019 | H29: =JetFreight!J95 -> 3.5881855 | I29: =JetFreight!K95 -> 2.7399296 | J29: =IF(AND(ISNUMBER(I29),ISNUMBER(I$37)),IF(I29>I$37,"Above",IF(I29<I$37,"Below","At median")),"-") -> Below | K29: =IF(J29="Above","Better",IF(J29="Below","Weaker",IF(J29="At median","In line","-"))) -> Weaker | L29: =IF(ISNUMBER(I29),RANK(I29,I$25:I$34,0),"-") -> 6
A30: Patel | B30: =Patel!D95 -> 5.5191108 | C30: =Patel!E95 -> 10.618729 | D30: =Patel!F95 -> 8.4062274 | E30: =Patel!G95 -> 4.8155172 | F30: =Patel!H95 -> 2.8559374 | G30: =Patel!I95 -> 3.4914645 | H30: =Patel!J95 -> 3.3649374 | I30: =Patel!K95 -> 5.5817034 | J30: =IF(AND(ISNUMBER(I30),ISNUMBER(I$37)),IF(I30>I$37,"Above",IF(I30<I$37,"Below","At median")),"-") -> Above | K30: =IF(J30="Above","Better",IF(J30="Below","Weaker",IF(J30="At median","In line","-"))) -> Better | L30: =IF(ISNUMBER(I30),RANK(I30,I$25:I$34,0),"-") -> 1
A31: Sical | B31: =Sical!D95 -> 0.53880059 | C31: =Sical!E95 -> 0.43040965 | D31: =Sical!F95 -> 0.53771673 | E31: =Sical!G95 -> 0.73076322 | F31: =Sical!H95 -> 0.86142419 | G31: =Sical!I95 -> 0.79756136 | H31: =Sical!J95 -> 1.1402597 | I31: =Sical!K95 -> 0.7195622 | J31: =IF(AND(ISNUMBER(I31),ISNUMBER(I$37)),IF(I31>I$37,"Above",IF(I31<I$37,"Below","At median")),"-") -> Below | K31: =IF(J31="Above","Better",IF(J31="Below","Weaker",IF(J31="At median","In line","-"))) -> Weaker | L31: =IF(ISNUMBER(I31),RANK(I31,I$25:I$34,0),"-") -> 10
A32: TCI | B32: =TCI!D95 -> 3.1791642 | C32: =TCI!E95 -> 2.8679037 | D32: =TCI!F95 -> 2.7474711 | E32: =TCI!G95 -> 3.2474207 | F32: =TCI!H95 -> 3.2510365 | G32: =TCI!I95 -> 2.4267054 | H32: =TCI!J95 -> 2.4182809 | I32: =TCI!K95 -> 2.8768546 | J32: =IF(AND(ISNUMBER(I32),ISNUMBER(I$37)),IF(I32>I$37,"Above",IF(I32<I$37,"Below","At median")),"-") -> Above | K32: =IF(J32="Above","Better",IF(J32="Below","Weaker",IF(J32="At median","In line","-"))) -> Better | L32: =IF(ISNUMBER(I32),RANK(I32,I$25:I$34,0),"-") -> 5
A33: Shreeji | B33: =Shreeji!D95 -> 6.1143524 | C33: =Shreeji!E95 -> 5.4709865 | D33: =Shreeji!F95 -> 5.4686757 | E33: =Shreeji!G95 -> 4.1375839 | F33: =Shreeji!H95 -> 4.7823629 | G33: =Shreeji!I95 -> 4.9369369 | H33: =Shreeji!J95 -> 4.7719752 | I33: =Shreeji!K95 -> 5.0975533 | J33: =IF(AND(ISNUMBER(I33),ISNUMBER(I$37)),IF(I33>I$37,"Above",IF(I33<I$37,"Below","At median")),"-") -> Above | K33: =IF(J33="Above","Better",IF(J33="Below","Weaker",IF(J33="At median","In line","-"))) -> Better | L33: =IF(ISNUMBER(I33),RANK(I33,I$25:I$34,0),"-") -> 2
A34: Mahindra Log. | B34: =MahindraLog!D95 -> 1.7350456 | C34: =MahindraLog!E95 -> 1.4929302 | D34: =MahindraLog!F95 -> 1.30859 | E34: =MahindraLog!G95 -> 1.3995697 | F34: =MahindraLog!H95 -> 1.2998699 | G34: =MahindraLog!I95 -> 1.2426698 | H34: =MahindraLog!J95 -> 1.4122438 | I34: =MahindraLog!K95 -> 1.4129884 | J34: =IF(AND(ISNUMBER(I34),ISNUMBER(I$37)),IF(I34>I$37,"Above",IF(I34<I$37,"Below","At median")),"-") -> Below | K34: =IF(J34="Above","Better",IF(J34="Below","Weaker",IF(J34="At median","In line","-"))) -> Weaker | L34: =IF(ISNUMBER(I34),RANK(I34,I$25:I$34,0),"-") -> 8
A35: Industry (aggregate) | B35: =Industry!D96 -> 1.5556838 | C35: =Industry!E96 -> 1.6328318 | D35: =Industry!F96 -> 1.7147979 | E35: =Industry!G96 -> 1.9761212 | F35: =Industry!H96 -> 2.0841188 | G35: =Industry!I96 -> 2.4198509 | H35: =Industry!J96 -> 2.4360563 | I35: =Industry!K96 -> 1.9742087
A36: Mean (10 firms) | B36: =IF(COUNT(B25:B34)=0,"N/M",AVERAGE(B25:B34)) -> 3.011758 | C36: =IF(COUNT(C25:C34)=0,"N/M",AVERAGE(C25:C34)) -> 3.1001551 | D36: =IF(COUNT(D25:D34)=0,"N/M",AVERAGE(D25:D34)) -> 2.9051107 | E36: =IF(COUNT(E25:E34)=0,"N/M",AVERAGE(E25:E34)) -> 2.9832901 | F36: =IF(COUNT(F25:F34)=0,"N/M",AVERAGE(F25:F34)) -> 2.9138805 | G36: =IF(COUNT(G25:G34)=0,"N/M",AVERAGE(G25:G34)) -> 3.200172 | H36: =IF(COUNT(H25:H34)=0,"N/M",AVERAGE(H25:H34)) -> 2.945708 | I36: =IF(COUNT(I25:I34)=0,"N/M",AVERAGE(I25:I34)) -> 3.0085821
A37: Median (10 firms) | B37: =IF(COUNT(B25:B34)=0,"N/M",MEDIAN(B25:B34)) -> 2.3735851 | C37: =IF(COUNT(C25:C34)=0,"N/M",MEDIAN(C25:C34)) -> 2.1557519 | D37: =IF(COUNT(D25:D34)=0,"N/M",MEDIAN(D25:D34)) -> 2.2343747 | E37: =IF(COUNT(E25:E34)=0,"N/M",MEDIAN(E25:E34)) -> 3.6075537 | F37: =IF(COUNT(F25:F34)=0,"N/M",MEDIAN(F25:F34)) -> 2.7969435 | G37: =IF(COUNT(G25:G34)=0,"N/M",MEDIAN(G25:G34)) -> 2.7236316 | H37: =IF(COUNT(H25:H34)=0,"N/M",MEDIAN(H25:H34)) -> 2.8916092 | I37: =IF(COUNT(I25:I34)=0,"N/M",MEDIAN(I25:I34)) -> 2.8083921
A38: Standard deviation | B38: =IF(COUNT(B25:B34)<2,"N/M",STDEV(B25:B34)) -> 2.1477661 | C38: =IF(COUNT(C25:C34)<2,"N/M",STDEV(C25:C34)) -> 2.9891803 | D38: =IF(COUNT(D25:D34)<2,"N/M",STDEV(D25:D34)) -> 2.3914171 | E38: =IF(COUNT(E25:E34)<2,"N/M",STDEV(E25:E34)) -> 1.6110133 | F38: =IF(COUNT(F25:F34)<2,"N/M",STDEV(F25:F34)) -> 1.762259 | G38: =IF(COUNT(G25:G34)<2,"N/M",STDEV(G25:G34)) -> 2.0958113 | H38: =IF(COUNT(H25:H34)<2,"N/M",STDEV(H25:H34)) -> 1.460736 | I38: =IF(COUNT(I25:I34)<2,"N/M",STDEV(I25:I34)) -> 1.7718986
A39: Minimum | B39: =IF(COUNT(B25:B34)=0,"N/M",MIN(B25:B34)) -> 0.53880059 | C39: =IF(COUNT(C25:C34)=0,"N/M",MIN(C25:C34)) -> 0.43040965 | D39: =IF(COUNT(D25:D34)=0,"N/M",MIN(D25:D34)) -> 0.53771673 | E39: =IF(COUNT(E25:E34)=0,"N/M",MIN(E25:E34)) -> 0.73076322 | F39: =IF(COUNT(F25:F34)=0,"N/M",MIN(F25:F34)) -> 0.86142419 | G39: =IF(COUNT(G25:G34)=0,"N/M",MIN(G25:G34)) -> 0.79756136 | H39: =IF(COUNT(H25:H34)=0,"N/M",MIN(H25:H34)) -> 1.1402597 | I39: =IF(COUNT(I25:I34)=0,"N/M",MIN(I25:I34)) -> 0.7195622
A40: Maximum | B40: =IF(COUNT(B25:B34)=0,"N/M",MAX(B25:B34)) -> 6.1143524 | C40: =IF(COUNT(C25:C34)=0,"N/M",MAX(C25:C34)) -> 10.618729 | D40: =IF(COUNT(D25:D34)=0,"N/M",MAX(D25:D34)) -> 8.4062274 | E40: =IF(COUNT(E25:E34)=0,"N/M",MAX(E25:E34)) -> 4.8683729 | F40: =IF(COUNT(F25:F34)=0,"N/M",MAX(F25:F34)) -> 5.9541284 | G40: =IF(COUNT(G25:G34)=0,"N/M",MAX(G25:G34)) -> 7.5958279 | H40: =IF(COUNT(H25:H34)=0,"N/M",MAX(H25:H34)) -> 4.7719752 | I40: =IF(COUNT(I25:I34)=0,"N/M",MAX(I25:I34)) -> 5.5817034
A42: 1.3 Quick (acid-test) ratio [Quick assets / Current liabilities] - Liquidity; higher is better
A43: Tiger | B43: =Tiger!D96 -> 4.5463787 | C43: =Tiger!E96 -> 1.8784838 | D43: =Tiger!F96 -> 2.1405382 | E43: =Tiger!G96 -> 4.6480804 | F43: =Tiger!H96 -> 5.385804 | G43: =Tiger!I96 -> 6.6857888 | H43: =Tiger!J96 -> 3.8983442 | I43: =Tiger!K96 -> 4.1690597 | J43: =IF(AND(ISNUMBER(I43),ISNUMBER(I$55)),IF(I43>I$55,"Above",IF(I43<I$55,"Below","At median")),"-") -> Above | K43: =IF(J43="Above","Better",IF(J43="Below","Weaker",IF(J43="At median","In line","-"))) -> Better | L43: =IF(ISNUMBER(I43),RANK(I43,I$43:I$52,0),"-") -> 2
A44: Allcargo | B44: =Allcargo!D96 -> 1.1198466 | C44: =Allcargo!E96 -> 0.86255381 | D44: =Allcargo!F96 -> 0.90198137 | E44: =Allcargo!G96 -> 1.0338819 | F44: =Allcargo!H96 -> 0.99669494 | G44: =Allcargo!I96 -> 1.3366834 | H44: =Allcargo!J96 -> 1.1940299 | I44: =Allcargo!K96 -> 1.0636674 | J44: =IF(AND(ISNUMBER(I44),ISNUMBER(I$55)),IF(I44>I$55,"Above",IF(I44<I$55,"Below","At median")),"-") -> Below | K44: =IF(J44="Above","Better",IF(J44="Below","Weaker",IF(J44="At median","In line","-"))) -> Weaker | L44: =IF(ISNUMBER(I44),RANK(I44,I$43:I$52,0),"-") -> 7
A45: Blue Dart | B45: =BlueDart!D96 -> 0.38780587 | C45: =BlueDart!E96 -> 1.057601 | D45: =BlueDart!F96 -> 0.85800882 | E45: =BlueDart!G96 -> 0.792969 | F45: =BlueDart!H96 -> 0.81971823 | G45: =BlueDart!I96 -> 0.8693115 | H45: =BlueDart!J96 -> 0.9578767 | I45: =BlueDart!K96 -> 0.82047016 | J45: =IF(AND(ISNUMBER(I45),ISNUMBER(I$55)),IF(I45>I$55,"Above",IF(I45<I$55,"Below","At median")),"-") -> Below | K45: =IF(J45="Above","Better",IF(J45="Below","Weaker",IF(J45="At median","In line","-"))) -> Weaker | L45: =IF(ISNUMBER(I45),RANK(I45,I$43:I$52,0),"-") -> 8
A46: CONCOR | B46: =CONCOR!D96 -> 1.4086844 | C46: =CONCOR!E96 -> 1.7689134 | D46: =CONCOR!F96 -> 2.0507466 | E46: =CONCOR!G96 -> 2.272078 | F46: =CONCOR!H96 -> 2.8440509 | G46: =CONCOR!I96 -> 3.2917024 | H46: =CONCOR!J96 -> 3.1306054 | I46: =CONCOR!K96 -> 2.3952545 | J46: =IF(AND(ISNUMBER(I46),ISNUMBER(I$55)),IF(I46>I$55,"Above",IF(I46<I$55,"Below","At median")),"-") -> Above | K46: =IF(J46="Above","Better",IF(J46="Below","Weaker",IF(J46="At median","In line","-"))) -> Better | L46: =IF(ISNUMBER(I46),RANK(I46,I$43:I$52,0),"-") -> 4
A47: Jet Freight | B47: =JetFreight!D96 -> 1.6537421 | C47: =JetFreight!E96 -> 0.93877551 | D47: =JetFreight!F96 -> 1.331777 | E47: =JetFreight!G96 -> 1.739187 | F47: =JetFreight!H96 -> 1.5774675 | G47: =JetFreight!I96 -> 1.739331 | H47: =JetFreight!J96 -> 2.3645988 | I47: =JetFreight!K96 -> 1.620697 | J47: =IF(AND(ISNUMBER(I47),ISNUMBER(I$55)),IF(I47>I$55,"Above",IF(I47<I$55,"Below","At median")),"-") -> Below | K47: =IF(J47="Above","Better",IF(J47="Below","Weaker",IF(J47="At median","In line","-"))) -> Weaker | L47: =IF(ISNUMBER(I47),RANK(I47,I$43:I$52,0),"-") -> 6
A48: Patel | B48: =Patel!D96 -> 3.9637285 | C48: =Patel!E96 -> 7.9423077 | D48: =Patel!F96 -> 6.2280956 | E48: =Patel!G96 -> 4.225 | F48: =Patel!H96 -> 2.5336489 | G48: =Patel!I96 -> 2.8772087 | H48: =Patel!J96 -> 2.9698867 | I48: =Patel!K96 -> 4.3914109 | J48: =IF(AND(ISNUMBER(I48),ISNUMBER(I$55)),IF(I48>I$55,"Above",IF(I48<I$55,"Below","At median")),"-") -> Above | K48: =IF(J48="Above","Better",IF(J48="Below","Weaker",IF(J48="At median","In line","-"))) -> Better | L48: =IF(ISNUMBER(I48),RANK(I48,I$43:I$52,0),"-") -> 1
A49: Sical | B49: =Sical!D96 -> 0.29196076 | C49: =Sical!E96 -> 0.24450927 | D49: =Sical!F96 -> 0.31262155 | E49: =Sical!G96 -> 0.53558316 | F49: =Sical!H96 -> 0.70548862 | G49: =Sical!I96 -> 0.61997811 | H49: =Sical!J96 -> 0.55759496 | I49: =Sical!K96 -> 0.46681949 | J49: =IF(AND(ISNUMBER(I49),ISNUMBER(I$55)),IF(I49>I$55,"Above",IF(I49<I$55,"Below","At median")),"-") -> Below | K49: =IF(J49="Above","Better",IF(J49="Below","Weaker",IF(J49="At median","In line","-"))) -> Weaker | L49: =IF(ISNUMBER(I49),RANK(I49,I$43:I$52,0),"-") -> 10
A50: TCI | B50: =TCI!D96 -> 2.1620187 | C50: =TCI!E96 -> 2.0269126 | D50: =TCI!F96 -> 1.9389724 | E50: =TCI!G96 -> 2.4263303 | F50: =TCI!H96 -> 2.2909839 | G50: =TCI!I96 -> 1.5013025 | H50: =TCI!J96 -> 1.5404411 | I50: =TCI!K96 -> 1.9838517 | J50: =IF(AND(ISNUMBER(I50),ISNUMBER(I$55)),IF(I50>I$55,"Above",IF(I50<I$55,"Below","At median")),"-") -> Above | K50: =IF(J50="Above","Better",IF(J50="Below","Weaker",IF(J50="At median","In line","-"))) -> Better | L50: =IF(ISNUMBER(I50),RANK(I50,I$43:I$52,0),"-") -> 5
A51: Shreeji | B51: =Shreeji!D96 -> 3.5227538 | C51: =Shreeji!E96 -> 4.0522244 | D51: =Shreeji!F96 -> 3.8818398 | E51: =Shreeji!G96 -> 3.4765101 | F51: =Shreeji!H96 -> 3.924251 | G51: =Shreeji!I96 -> 4.1321321 | H51: =Shreeji!J96 -> 4.1773526 | I51: =Shreeji!K96 -> 3.8810091 | J51: =IF(AND(ISNUMBER(I51),ISNUMBER(I$55)),IF(I51>I$55,"Above",IF(I51<I$55,"Below","At median")),"-") -> Above | K51: =IF(J51="Above","Better",IF(J51="Below","Weaker",IF(J51="At median","In line","-"))) -> Better | L51: =IF(ISNUMBER(I51),RANK(I51,I$43:I$52,0),"-") -> 3
A52: Mahindra Log. | B52: =MahindraLog!D96 -> 0.93973871 | C52: =MahindraLog!E96 -> 0.80454208 | D52: =MahindraLog!F96 -> 0.60711711 | E52: =MahindraLog!G96 -> 0.67292304 | F52: =MahindraLog!H96 -> 0.6206401 | G52: =MahindraLog!I96 -> 0.55109501 | H52: =MahindraLog!J96 -> 0.69438023 | I52: =MahindraLog!K96 -> 0.69863375 | J52: =IF(AND(ISNUMBER(I52),ISNUMBER(I$55)),IF(I52>I$55,"Above",IF(I52<I$55,"Below","At median")),"-") -> Below | K52: =IF(J52="Above","Better",IF(J52="Below","Weaker",IF(J52="At median","In line","-"))) -> Weaker | L52: =IF(ISNUMBER(I52),RANK(I52,I$43:I$52,0),"-") -> 9
A53: Industry (aggregate) | B53: =Industry!D97 -> 0.93899956 | C53: =Industry!E97 -> 1.0240038 | D53: =Industry!F97 -> 1.0699672 | E53: =Industry!G97 -> 1.2607565 | F53: =Industry!H97 -> 1.3221457 | G53: =Industry!I97 -> 1.5497685 | H53: =Industry!J97 -> 1.5485939 | I53: =Industry!K97 -> 1.2448907
A54: Mean (10 firms) | B54: =IF(COUNT(B43:B52)=0,"N/M",AVERAGE(B43:B52)) -> 1.9996658 | C54: =IF(COUNT(C43:C52)=0,"N/M",AVERAGE(C43:C52)) -> 2.1576824 | D54: =IF(COUNT(D43:D52)=0,"N/M",AVERAGE(D43:D52)) -> 2.0251699 | E54: =IF(COUNT(E43:E52)=0,"N/M",AVERAGE(E43:E52)) -> 2.1822543 | F54: =IF(COUNT(F43:F52)=0,"N/M",AVERAGE(F43:F52)) -> 2.1698748 | G54: =IF(COUNT(G43:G52)=0,"N/M",AVERAGE(G43:G52)) -> 2.3604534 | H54: =IF(COUNT(H43:H52)=0,"N/M",AVERAGE(H43:H52)) -> 2.1485111 | I54: =IF(COUNT(I43:I52)=0,"N/M",AVERAGE(I43:I52)) -> 2.1490874
A55: Median (10 firms) | B55: =IF(COUNT(B43:B52)=0,"N/M",MEDIAN(B43:B52)) -> 1.5312132 | C55: =IF(COUNT(C43:C52)=0,"N/M",MEDIAN(C43:C52)) -> 1.4132572 | D55: =IF(COUNT(D43:D52)=0,"N/M",MEDIAN(D43:D52)) -> 1.6353747 | E55: =IF(COUNT(E43:E52)=0,"N/M",MEDIAN(E43:E52)) -> 2.0056325 | F55: =IF(COUNT(F43:F52)=0,"N/M",MEDIAN(F43:F52)) -> 1.9342257 | G55: =IF(COUNT(G43:G52)=0,"N/M",MEDIAN(G43:G52)) -> 1.6203168 | H55: =IF(COUNT(H43:H52)=0,"N/M",MEDIAN(H43:H52)) -> 1.9525199 | I55: =IF(COUNT(I43:I52)=0,"N/M",MEDIAN(I43:I52)) -> 1.8022743
A56: Standard deviation | B56: =IF(COUNT(B43:B52)<2,"N/M",STDEV(B43:B52)) -> 1.5118143 | C56: =IF(COUNT(C43:C52)<2,"N/M",STDEV(C43:C52)) -> 2.2891499 | D56: =IF(COUNT(D43:D52)<2,"N/M",STDEV(D43:D52)) -> 1.8006637 | E56: =IF(COUNT(E43:E52)<2,"N/M",STDEV(E43:E52)) -> 1.5066754 | F56: =IF(COUNT(F43:F52)<2,"N/M",STDEV(F43:F52)) -> 1.5675999 | G56: =IF(COUNT(G43:G52)<2,"N/M",STDEV(G43:G52)) -> 1.9344884 | H56: =IF(COUNT(H43:H52)<2,"N/M",STDEV(H43:H52)) -> 1.341967 | I56: =IF(COUNT(I43:I52)<2,"N/M",STDEV(I43:I52)) -> 1.5037787
A57: Minimum | B57: =IF(COUNT(B43:B52)=0,"N/M",MIN(B43:B52)) -> 0.29196076 | C57: =IF(COUNT(C43:C52)=0,"N/M",MIN(C43:C52)) -> 0.24450927 | D57: =IF(COUNT(D43:D52)=0,"N/M",MIN(D43:D52)) -> 0.31262155 | E57: =IF(COUNT(E43:E52)=0,"N/M",MIN(E43:E52)) -> 0.53558316 | F57: =IF(COUNT(F43:F52)=0,"N/M",MIN(F43:F52)) -> 0.6206401 | G57: =IF(COUNT(G43:G52)=0,"N/M",MIN(G43:G52)) -> 0.55109501 | H57: =IF(COUNT(H43:H52)=0,"N/M",MIN(H43:H52)) -> 0.55759496 | I57: =IF(COUNT(I43:I52)=0,"N/M",MIN(I43:I52)) -> 0.46681949
A58: Maximum | B58: =IF(COUNT(B43:B52)=0,"N/M",MAX(B43:B52)) -> 4.5463787 | C58: =IF(COUNT(C43:C52)=0,"N/M",MAX(C43:C52)) -> 7.9423077 | D58: =IF(COUNT(D43:D52)=0,"N/M",MAX(D43:D52)) -> 6.2280956 | E58: =IF(COUNT(E43:E52)=0,"N/M",MAX(E43:E52)) -> 4.6480804 | F58: =IF(COUNT(F43:F52)=0,"N/M",MAX(F43:F52)) -> 5.385804 | G58: =IF(COUNT(G43:G52)=0,"N/M",MAX(G43:G52)) -> 6.6857888 | H58: =IF(COUNT(H43:H52)=0,"N/M",MAX(H43:H52)) -> 4.1773526 | I58: =IF(COUNT(I43:I52)=0,"N/M",MAX(I43:I52)) -> 4.3914109
A60: 1.4 Cash ratio [Cash & bank / Current liabilities] - Liquidity; higher is better
A61: Tiger | B61: =Tiger!D97 -> 0.38373571 | C61: =Tiger!E97 -> 0.27424749 | D61: =Tiger!F97 -> 0.67407091 | E61: =Tiger!G97 -> 2.3948812 | F61: =Tiger!H97 -> 2.0159343 | G61: =Tiger!I97 -> 2.2233811 | H61: =Tiger!J97 -> 0.7980362 | I61: =Tiger!K97 -> 1.252041 | J61: =IF(AND(ISNUMBER(I61),ISNUMBER(I$73)),IF(I61>I$73,"Above",IF(I61<I$73,"Below","At median")),"-") -> Above | K61: =IF(J61="Above","Better",IF(J61="Below","Weaker",IF(J61="At median","In line","-"))) -> Better | L61: =IF(ISNUMBER(I61),RANK(I61,I$61:I$70,0),"-") -> 2
A62: Allcargo | B62: =Allcargo!D97 -> 0.37876152 | C62: =Allcargo!E97 -> 0.12860111 | D62: =Allcargo!F97 -> 0.15620871 | E62: =Allcargo!G97 -> 0.4042964 | F62: =Allcargo!H97 -> 0.19987409 | G62: =Allcargo!I97 -> 0.39447236 | H62: =Allcargo!J97 -> 0.2793177 | I62: =Allcargo!K97 -> 0.2773617 | J62: =IF(AND(ISNUMBER(I62),ISNUMBER(I$73)),IF(I62>I$73,"Above",IF(I62<I$73,"Below","At median")),"-") -> Above | K62: =IF(J62="Above","Better",IF(J62="Below","Weaker",IF(J62="At median","In line","-"))) -> Better | L62: =IF(ISNUMBER(I62),RANK(I62,I$61:I$70,0),"-") -> 5
A63: Blue Dart | B63: =BlueDart!D97 -> 0.061729919 | C63: =BlueDart!E97 -> 0.39641526 | D63: =BlueDart!F97 -> 0.20691939 | E63: =BlueDart!G97 -> 0.10345052 | F63: =BlueDart!H97 -> 0.16287181 | G63: =BlueDart!I97 -> 0.1525535 | H63: =BlueDart!J97 -> 0.19781148 | I63: =BlueDart!K97 -> 0.18310741 | J63: =IF(AND(ISNUMBER(I63),ISNUMBER(I$73)),IF(I63>I$73,"Above",IF(I63<I$73,"Below","At median")),"-") -> Below | K63: =IF(J63="Above","Better",IF(J63="Below","Weaker",IF(J63="At median","In line","-"))) -> Weaker | L63: =IF(ISNUMBER(I63),RANK(I63,I$61:I$70,0),"-") -> 9
A64: CONCOR | B64: =CONCOR!D97 -> 1.3102603 | C64: =CONCOR!E97 -> 1.6615787 | D64: =CONCOR!F97 -> 1.9305161 | E64: =CONCOR!G97 -> 2.1241723 | F64: =CONCOR!H97 -> 2.5826366 | G64: =CONCOR!I97 -> 2.9676588 | H64: =CONCOR!J97 -> 2.7483883 | I64: =CONCOR!K97 -> 2.1893159 | J64: =IF(AND(ISNUMBER(I64),ISNUMBER(I$73)),IF(I64>I$73,"Above",IF(I64<I$73,"Below","At median")),"-") -> Above | K64: =IF(J64="Above","Better",IF(J64="Below","Weaker",IF(J64="At median","In line","-"))) -> Better | L64: =IF(ISNUMBER(I64),RANK(I64,I$61:I$70,0),"-") -> 1
A65: Jet Freight | B65: =JetFreight!D97 -> 0.10339645 | C65: =JetFreight!E97 -> 0.070002194 | D65: =JetFreight!F97 -> 0.18099423 | E65: =JetFreight!G97 -> 0.27609756 | F65: =JetFreight!H97 -> 0.25439939 | G65: =JetFreight!I97 -> 0.23894656 | H65: =JetFreight!J97 -> 0.30849037 | I65: =JetFreight!K97 -> 0.20461811 | J65: =IF(AND(ISNUMBER(I65),ISNUMBER(I$73)),IF(I65>I$73,"Above",IF(I65<I$73,"Below","At median")),"-") -> Below | K65: =IF(J65="Above","Better",IF(J65="Below","Weaker",IF(J65="At median","In line","-"))) -> Weaker | L65: =IF(ISNUMBER(I65),RANK(I65,I$61:I$70,0),"-") -> 8
A66: Patel | B66: =Patel!D97 -> 0.50195008 | C66: =Patel!E97 -> 1.9297659 | D66: =Patel!F97 -> 1.5691528 | E66: =Patel!G97 -> 1.0413793 | F66: =Patel!H97 -> 0.66577485 | G66: =Patel!I97 -> 0.85594489 | H66: =Patel!J97 -> 0.80292188 | I66: =Patel!K97 -> 1.0524128 | J66: =IF(AND(ISNUMBER(I66),ISNUMBER(I$73)),IF(I66>I$73,"Above",IF(I66<I$73,"Below","At median")),"-") -> Above | K66: =IF(J66="Above","Better",IF(J66="Below","Weaker",IF(J66="At median","In line","-"))) -> Better | L66: =IF(ISNUMBER(I66),RANK(I66,I$61:I$70,0),"-") -> 3
A67: Sical | B67: =Sical!D97 -> 0.050462354 | C67: =Sical!E97 -> 0.056951985 | D67: =Sical!F97 -> 0.11849133 | E67: =Sical!G97 -> 0.32208421 | F67: =Sical!H97 -> 0.51522218 | G67: =Sical!I97 -> 0.33808817 | H67: =Sical!J97 -> 0.22717724 | I67: =Sical!K97 -> 0.23263964 | J67: =IF(AND(ISNUMBER(I67),ISNUMBER(I$73)),IF(I67>I$73,"Above",IF(I67<I$73,"Below","At median")),"-") -> Below | K67: =IF(J67="Above","Better",IF(J67="Below","Weaker",IF(J67="At median","In line","-"))) -> Weaker | L67: =IF(ISNUMBER(I67),RANK(I67,I$61:I$70,0),"-") -> 7
A68: TCI | B68: =TCI!D97 -> 0.10919201 | C68: =TCI!E97 -> 0.14546057 | D68: =TCI!F97 -> 0.24773726 | E68: =TCI!G97 -> 0.60074858 | F68: =TCI!H97 -> 0.31457716 | G68: =TCI!I97 -> 0.157977 | H68: =TCI!J97 -> 0.18766467 | I68: =TCI!K97 -> 0.25190818 | J68: =IF(AND(ISNUMBER(I68),ISNUMBER(I$73)),IF(I68>I$73,"Above",IF(I68<I$73,"Below","At median")),"-") -> Below | K68: =IF(J68="Above","Better",IF(J68="Below","Weaker",IF(J68="At median","In line","-"))) -> Weaker | L68: =IF(ISNUMBER(I68),RANK(I68,I$61:I$70,0),"-") -> 6
A69: Shreeji | B69: =Shreeji!D97 -> 0.37456243 | C69: =Shreeji!E97 -> 0.5270793 | D69: =Shreeji!F97 -> 0.34020619 | E69: =Shreeji!G97 -> 0.37639821 | F69: =Shreeji!H97 -> 0.25664217 | G69: =Shreeji!I97 -> 0.46186186 | H69: =Shreeji!J97 -> 0.33040331 | I69: =Shreeji!K97 -> 0.38102192 | J69: =IF(AND(ISNUMBER(I69),ISNUMBER(I$73)),IF(I69>I$73,"Above",IF(I69<I$73,"Below","At median")),"-") -> Above | K69: =IF(J69="Above","Better",IF(J69="Below","Weaker",IF(J69="At median","In line","-"))) -> Better | L69: =IF(ISNUMBER(I69),RANK(I69,I$61:I$70,0),"-") -> 4
A70: Mahindra Log. | B70: =MahindraLog!D97 -> 0.14725769 | C70: =MahindraLog!E97 -> 0.23283768 | D70: =MahindraLog!F97 -> 0.13085705 | E70: =MahindraLog!G97 -> 0.10908038 | F70: =MahindraLog!H97 -> 0.05706417 | G70: =MahindraLog!I97 -> 0.05971827 | H70: =MahindraLog!J97 -> 0.15584 | I70: =MahindraLog!K97 -> 0.12752218 | J70: =IF(AND(ISNUMBER(I70),ISNUMBER(I$73)),IF(I70>I$73,"Above",IF(I70<I$73,"Below","At median")),"-") -> Below | K70: =IF(J70="Above","Better",IF(J70="Below","Weaker",IF(J70="At median","In line","-"))) -> Weaker | L70: =IF(ISNUMBER(I70),RANK(I70,I$61:I$70,0),"-") -> 10
A71: Industry (aggregate) | B71: =Industry!D98 -> 0.4505909 | C71: =Industry!E98 -> 0.46398635 | D71: =Industry!F98 -> 0.47226734 | E71: =Industry!G98 -> 0.67133957 | F71: =Industry!H98 -> 0.62728546 | G71: =Industry!I98 -> 0.88110164 | H71: =Industry!J98 -> 0.82039197 | I71: =Industry!K98 -> 0.62670903
A72: Mean (10 firms) | B72: =IF(COUNT(B61:B70)=0,"N/M",AVERAGE(B61:B70)) -> 0.34213085 | C72: =IF(COUNT(C61:C70)=0,"N/M",AVERAGE(C61:C70)) -> 0.54229401 | D72: =IF(COUNT(D61:D70)=0,"N/M",AVERAGE(D61:D70)) -> 0.5555154 | E72: =IF(COUNT(E61:E70)=0,"N/M",AVERAGE(E61:E70)) -> 0.77525886 | F72: =IF(COUNT(F61:F70)=0,"N/M",AVERAGE(F61:F70)) -> 0.70249968 | G72: =IF(COUNT(G61:G70)=0,"N/M",AVERAGE(G61:G70)) -> 0.78506026 | H72: =IF(COUNT(H61:H70)=0,"N/M",AVERAGE(H61:H70)) -> 0.60360512 | I72: =IF(COUNT(I61:I70)=0,"N/M",AVERAGE(I61:I70)) -> 0.61519488
A73: Median (10 firms) | B73: =IF(COUNT(B61:B70)=0,"N/M",MEDIAN(B61:B70)) -> 0.26091006 | C73: =IF(COUNT(C61:C70)=0,"N/M",MEDIAN(C61:C70)) -> 0.25354259 | D73: =IF(COUNT(D61:D70)=0,"N/M",MEDIAN(D61:D70)) -> 0.22732832 | E73: =IF(COUNT(E61:E70)=0,"N/M",MEDIAN(E61:E70)) -> 0.3903473 | F73: =IF(COUNT(F61:F70)=0,"N/M",MEDIAN(F61:F70)) -> 0.28560967 | G73: =IF(COUNT(G61:G70)=0,"N/M",MEDIAN(G61:G70)) -> 0.36628026 | H73: =IF(COUNT(H61:H70)=0,"N/M",MEDIAN(H61:H70)) -> 0.29390403 | I73: =IF(COUNT(I61:I70)=0,"N/M",MEDIAN(I61:I70)) -> 0.26463494
A74: Standard deviation | B74: =IF(COUNT(B61:B70)<2,"N/M",STDEV(B61:B70)) -> 0.37710399 | C74: =IF(COUNT(C61:C70)<2,"N/M",STDEV(C61:C70)) -> 0.67939807 | D74: =IF(COUNT(D61:D70)<2,"N/M",STDEV(D61:D70)) -> 0.65538661 | E74: =IF(COUNT(E61:E70)<2,"N/M",STDEV(E61:E70)) -> 0.82934849 | F74: =IF(COUNT(F61:F70)<2,"N/M",STDEV(F61:F70)) -> 0.86966989 | G74: =IF(COUNT(G61:G70)<2,"N/M",STDEV(G61:G70)) -> 0.99509841 | H74: =IF(COUNT(H61:H70)<2,"N/M",STDEV(H61:H70)) -> 0.79052629 | I74: =IF(COUNT(I61:I70)<2,"N/M",STDEV(I61:I70)) -> 0.67618053
A75: Minimum | B75: =IF(COUNT(B61:B70)=0,"N/M",MIN(B61:B70)) -> 0.050462354 | C75: =IF(COUNT(C61:C70)=0,"N/M",MIN(C61:C70)) -> 0.056951985 | D75: =IF(COUNT(D61:D70)=0,"N/M",MIN(D61:D70)) -> 0.11849133 | E75: =IF(COUNT(E61:E70)=0,"N/M",MIN(E61:E70)) -> 0.10345052 | F75: =IF(COUNT(F61:F70)=0,"N/M",MIN(F61:F70)) -> 0.05706417 | G75: =IF(COUNT(G61:G70)=0,"N/M",MIN(G61:G70)) -> 0.05971827 | H75: =IF(COUNT(H61:H70)=0,"N/M",MIN(H61:H70)) -> 0.15584 | I75: =IF(COUNT(I61:I70)=0,"N/M",MIN(I61:I70)) -> 0.12752218
A76: Maximum | B76: =IF(COUNT(B61:B70)=0,"N/M",MAX(B61:B70)) -> 1.3102603 | C76: =IF(COUNT(C61:C70)=0,"N/M",MAX(C61:C70)) -> 1.9297659 | D76: =IF(COUNT(D61:D70)=0,"N/M",MAX(D61:D70)) -> 1.9305161 | E76: =IF(COUNT(E61:E70)=0,"N/M",MAX(E61:E70)) -> 2.3948812 | F76: =IF(COUNT(F61:F70)=0,"N/M",MAX(F61:F70)) -> 2.5826366 | G76: =IF(COUNT(G61:G70)=0,"N/M",MAX(G61:G70)) -> 2.9676588 | H76: =IF(COUNT(H61:H70)=0,"N/M",MAX(H61:H70)) -> 2.7483883 | I76: =IF(COUNT(I61:I70)=0,"N/M",MAX(I61:I70)) -> 2.1893159
A78: 1.5 Defensive-interval ratio (days) [Quick assets / (Total operating expenses / 365)] - Liquidity; higher is better
A79: Tiger | B79: =Tiger!D98 -> 84.291477 | C79: =Tiger!E98 -> 104.02994 | D79: =Tiger!F98 -> 63.341414 | E79: =Tiger!G98 -> 91.225332 | F79: =Tiger!H98 -> 181.01507 | G79: =Tiger!I98 -> 111.21551 | H79: =Tiger!J98 -> 135.40463 | I79: =Tiger!K98 -> 110.07477 | J79: =IF(AND(ISNUMBER(I79),ISNUMBER(I$91)),IF(I79>I$91,"Above",IF(I79<I$91,"Below","At median")),"-") -> Above | K79: =IF(J79="Above","Better",IF(J79="Below","Weaker",IF(J79="At median","In line","-"))) -> Better | L79: =IF(ISNUMBER(I79),RANK(I79,I$79:I$88,0),"-") -> 5
A80: Allcargo | B80: =Allcargo!D98 -> 92.859244 | C80: =Allcargo!E98 -> 94.700645 | D80: =Allcargo!F98 -> 76.37579 | E80: =Allcargo!G98 -> 72.237994 | F80: =Allcargo!H98 -> 81.378075 | G80: =Allcargo!I98 -> 110.39227 | H80: =Allcargo!J98 -> 112.12287 | I80: =Allcargo!K98 -> 91.438127 | J80: =IF(AND(ISNUMBER(I80),ISNUMBER(I$91)),IF(I80>I$91,"Above",IF(I80<I$91,"Below","At median")),"-") -> Below | K80: =IF(J80="Above","Better",IF(J80="Below","Weaker",IF(J80="At median","In line","-"))) -> Weaker | L80: =IF(ISNUMBER(I80),RANK(I80,I$79:I$88,0),"-") -> 6
A81: Blue Dart | B81: =BlueDart!D98 -> 84.911036 | C81: =BlueDart!E98 -> 116.21798 | D81: =BlueDart!F98 -> 81.802004 | E81: =BlueDart!G98 -> 63.109873 | F81: =BlueDart!H98 -> 69.172437 | G81: =BlueDart!I98 -> 71.840782 | H81: =BlueDart!J98 -> 81.381704 | I81: =BlueDart!K98 -> 81.205117 | J81: =IF(AND(ISNUMBER(I81),ISNUMBER(I$91)),IF(I81>I$91,"Above",IF(I81<I$91,"Below","At median")),"-") -> Below | K81: =IF(J81="Above","Better",IF(J81="Below","Weaker",IF(J81="At median","In line","-"))) -> Weaker | L81: =IF(ISNUMBER(I81),RANK(I81,I$79:I$88,0),"-") -> 7
A82: CONCOR | B82: =CONCOR!D98 -> 177.83754 | C82: =CONCOR!E98 -> 180.05646 | D82: =CONCOR!F98 -> 191.61409 | E82: =CONCOR!G98 -> 192.20002 | F82: =CONCOR!H98 -> 197.89413 | G82: =CONCOR!I98 -> 213.16977 | H82: =CONCOR!J98 -> 203.41761 | I82: =CONCOR!K98 -> 193.74137 | J82: =IF(AND(ISNUMBER(I82),ISNUMBER(I$91)),IF(I82>I$91,"Above",IF(I82<I$91,"Below","At median")),"-") -> Above | K82: =IF(J82="Above","Better",IF(J82="Below","Weaker",IF(J82="At median","In line","-"))) -> Better | L82: =IF(ISNUMBER(I82),RANK(I82,I$79:I$88,0),"-") -> 2
A83: Jet Freight | B83: =JetFreight!D98 -> 66.214844 | C83: =JetFreight!E98 -> 46.26852 | D83: =JetFreight!F98 -> 39.6853 | E83: =JetFreight!G98 -> 47.762852 | F83: =JetFreight!H98 -> 78.828759 | G83: =JetFreight!I98 -> 78.192064 | H83: =JetFreight!J98 -> 95.350284 | I83: =JetFreight!K98 -> 64.61466 | J83: =IF(AND(ISNUMBER(I83),ISNUMBER(I$91)),IF(I83>I$91,"Above",IF(I83<I$91,"Below","At median")),"-") -> Below | K83: =IF(J83="Above","Better",IF(J83="Below","Weaker",IF(J83="At median","In line","-"))) -> Weaker | L83: =IF(ISNUMBER(I83),RANK(I83,I$79:I$88,0),"-") -> 9
A84: Patel | B84: =Patel!D98 -> 109.32144 | C84: =Patel!E98 -> 167.42974 | D84: =Patel!F98 -> 138.52381 | E84: =Patel!G98 -> 133.51732 | F84: =Patel!H98 -> 159.65589 | G84: =Patel!I98 -> 105.02441 | H84: =Patel!J98 -> 104.84658 | I84: =Patel!K98 -> 131.18845 | J84: =IF(AND(ISNUMBER(I84),ISNUMBER(I$91)),IF(I84>I$91,"Above",IF(I84<I$91,"Below","At median")),"-") -> Above | K84: =IF(J84="Above","Better",IF(J84="Below","Weaker",IF(J84="At median","In line","-"))) -> Better | L84: =IF(ISNUMBER(I84),RANK(I84,I$79:I$88,0),"-") -> 3
A85: Sical | B85: =Sical!D98 -> 103.2163 | C85: =Sical!E98 -> 197.36094 | D85: =Sical!F98 -> 214.72193 | E85: =Sical!G98 -> 137.30056 | F85: =Sical!H98 -> 291.60375 | G85: =Sical!I98 -> 289.04108 | H85: =Sical!J98 -> 192.28527 | I85: =Sical!K98 -> 203.64712 | J85: =IF(AND(ISNUMBER(I85),ISNUMBER(I$91)),IF(I85>I$91,"Above",IF(I85<I$91,"Below","At median")),"-") -> Above | K85: =IF(J85="Above","Better",IF(J85="Below","Weaker",IF(J85="At median","In line","-"))) -> Better | L85: =IF(ISNUMBER(I85),RANK(I85,I$79:I$88,0),"-") -> 1
A86: TCI | B86: =TCI!D98 -> 75.644201 | C86: =TCI!E98 -> 79.134096 | D86: =TCI!F98 -> 74.705653 | E86: =TCI!G98 -> 81.050831 | F86: =TCI!H98 -> 70.335411 | G86: =TCI!I98 -> 73.08932 | H86: =TCI!J98 -> 77.154478 | I86: =TCI!K98 -> 75.873427 | J86: =IF(AND(ISNUMBER(I86),ISNUMBER(I$91)),IF(I86>I$91,"Above",IF(I86<I$91,"Below","At median")),"-") -> Below | K86: =IF(J86="Above","Better",IF(J86="Below","Weaker",IF(J86="At median","In line","-"))) -> Weaker | L86: =IF(ISNUMBER(I86),RANK(I86,I$79:I$88,0),"-") -> 8
A87: Shreeji | B87: =Shreeji!D98 -> 109.15651 | C87: =Shreeji!E98 -> 151.2411 | D87: =Shreeji!F98 -> 121.51772 | E87: =Shreeji!G98 -> 136.01343 | F87: =Shreeji!H98 -> 109.39599 | G87: =Shreeji!I98 -> 118.92404 | H87: =Shreeji!J98 -> 130.1684 | I87: =Shreeji!K98 -> 125.20246 | J87: =IF(AND(ISNUMBER(I87),ISNUMBER(I$91)),IF(I87>I$91,"Above",IF(I87<I$91,"Below","At median")),"-") -> Above | K87: =IF(J87="Above","Better",IF(J87="Below","Weaker",IF(J87="At median","In line","-"))) -> Better | L87: =IF(ISNUMBER(I87),RANK(I87,I$79:I$88,0),"-") -> 4
A88: Mahindra Log. | B88: =MahindraLog!D98 -> 69.984061 | C88: =MahindraLog!E98 -> 79.714561 | D88: =MahindraLog!F98 -> 57.496449 | E88: =MahindraLog!G98 -> 58.384765 | F88: =MahindraLog!H98 -> 53.487866 | G88: =MahindraLog!I98 -> 43.964125 | H88: =MahindraLog!J98 -> 49.019878 | I88: =MahindraLog!K98 -> 58.864529 | J88: =IF(AND(ISNUMBER(I88),ISNUMBER(I$91)),IF(I88>I$91,"Above",IF(I88<I$91,"Below","At median")),"-") -> Below | K88: =IF(J88="Above","Better",IF(J88="Below","Weaker",IF(J88="At median","In line","-"))) -> Weaker | L88: =IF(ISNUMBER(I88),RANK(I88,I$79:I$88,0),"-") -> 10
A89: Industry (aggregate) | B89: =Industry!D99 -> 105.37052 | C89: =Industry!E99 -> 114.32589 | D89: =Industry!F99 -> 95.150745 | E89: =Industry!G99 -> 91.759859 | F89: =Industry!H99 -> 100.06819 | G89: =Industry!I99 -> 110.94862 | H89: =Industry!J99 -> 110.32181 | I89: =Industry!K99 -> 103.99223
A90: Mean (10 firms) | B90: =IF(COUNT(B79:B88)=0,"N/M",AVERAGE(B79:B88)) -> 97.343665 | C90: =IF(COUNT(C79:C88)=0,"N/M",AVERAGE(C79:C88)) -> 121.6154 | D90: =IF(COUNT(D79:D88)=0,"N/M",AVERAGE(D79:D88)) -> 105.97842 | E90: =IF(COUNT(E79:E88)=0,"N/M",AVERAGE(E79:E88)) -> 101.2803 | F90: =IF(COUNT(F79:F88)=0,"N/M",AVERAGE(F79:F88)) -> 129.27674 | G90: =IF(COUNT(G79:G88)=0,"N/M",AVERAGE(G79:G88)) -> 121.48534 | H90: =IF(COUNT(H79:H88)=0,"N/M",AVERAGE(H79:H88)) -> 118.11517 | I90: =IF(COUNT(I79:I88)=0,"N/M",AVERAGE(I79:I88)) -> 113.585
A91: Median (10 firms) | B91: =IF(COUNT(B79:B88)=0,"N/M",MEDIAN(B79:B88)) -> 88.88514 | C91: =IF(COUNT(C79:C88)=0,"N/M",MEDIAN(C79:C88)) -> 110.12396 | D91: =IF(COUNT(D79:D88)=0,"N/M",MEDIAN(D79:D88)) -> 79.088897 | E91: =IF(COUNT(E79:E88)=0,"N/M",MEDIAN(E79:E88)) -> 86.138082 | F91: =IF(COUNT(F79:F88)=0,"N/M",MEDIAN(F79:F88)) -> 95.387034 | G91: =IF(COUNT(G79:G88)=0,"N/M",MEDIAN(G79:G88)) -> 107.70834 | H91: =IF(COUNT(H79:H88)=0,"N/M",MEDIAN(H79:H88)) -> 108.48473 | I91: =IF(COUNT(I79:I88)=0,"N/M",MEDIAN(I79:I88)) -> 100.75645
A92: Standard deviation | B92: =IF(COUNT(B79:B88)<2,"N/M",STDEV(B79:B88)) -> 32.197689 | C92: =IF(COUNT(C79:C88)<2,"N/M",STDEV(C79:C88)) -> 49.921781 | D92: =IF(COUNT(D79:D88)<2,"N/M",STDEV(D79:D88)) -> 59.124431 | E92: =IF(COUNT(E79:E88)<2,"N/M",STDEV(E79:E88)) -> 46.337391 | F92: =IF(COUNT(F79:F88)<2,"N/M",STDEV(F79:F88)) -> 76.538471 | G92: =IF(COUNT(G79:G88)<2,"N/M",STDEV(G79:G88)) -> 74.294917 | H92: =IF(COUNT(H79:H88)<2,"N/M",STDEV(H79:H88)) -> 49.16345 | I92: =IF(COUNT(I79:I88)<2,"N/M",STDEV(I79:I88)) -> 50.932336
A93: Minimum | B93: =IF(COUNT(B79:B88)=0,"N/M",MIN(B79:B88)) -> 66.214844 | C93: =IF(COUNT(C79:C88)=0,"N/M",MIN(C79:C88)) -> 46.26852 | D93: =IF(COUNT(D79:D88)=0,"N/M",MIN(D79:D88)) -> 39.6853 | E93: =IF(COUNT(E79:E88)=0,"N/M",MIN(E79:E88)) -> 47.762852 | F93: =IF(COUNT(F79:F88)=0,"N/M",MIN(F79:F88)) -> 53.487866 | G93: =IF(COUNT(G79:G88)=0,"N/M",MIN(G79:G88)) -> 43.964125 | H93: =IF(COUNT(H79:H88)=0,"N/M",MIN(H79:H88)) -> 49.019878 | I93: =IF(COUNT(I79:I88)=0,"N/M",MIN(I79:I88)) -> 58.864529
A94: Maximum | B94: =IF(COUNT(B79:B88)=0,"N/M",MAX(B79:B88)) -> 177.83754 | C94: =IF(COUNT(C79:C88)=0,"N/M",MAX(C79:C88)) -> 197.36094 | D94: =IF(COUNT(D79:D88)=0,"N/M",MAX(D79:D88)) -> 214.72193 | E94: =IF(COUNT(E79:E88)=0,"N/M",MAX(E79:E88)) -> 192.20002 | F94: =IF(COUNT(F79:F88)=0,"N/M",MAX(F79:F88)) -> 291.60375 | G94: =IF(COUNT(G79:G88)=0,"N/M",MAX(G79:G88)) -> 289.04108 | H94: =IF(COUNT(H79:H88)=0,"N/M",MAX(H79:H88)) -> 203.41761 | I94: =IF(COUNT(I79:I88)=0,"N/M",MAX(I79:I88)) -> 203.64712
A96: 1.6 Cash flow from operations ratio [Net cash from operating activities / Current liabilities] - Liquidity; higher is better
A97: Tiger | B97: =Tiger!D99 -> 0.13468869 | C97: =Tiger!E99 -> 0.97027127 | D97: =Tiger!F99 -> 0.94446818 | E97: =Tiger!G99 -> 0.77193784 | F97: =Tiger!H99 -> -0.83051666 | G97: =Tiger!I99 -> -0.79096045 | H97: =Tiger!J99 -> -0.33923758 | I97: =Tiger!K99 -> 0.12295018 | J97: =IF(AND(ISNUMBER(I97),ISNUMBER(I$109)),IF(I97>I$109,"Above",IF(I97<I$109,"Below","At median")),"-") -> Below | K97: =IF(J97="Above","Better",IF(J97="Below","Weaker",IF(J97="At median","In line","-"))) -> Weaker | L97: =IF(ISNUMBER(I97),RANK(I97,I$97:I$106,0),"-") -> 7
A98: Allcargo | B98: =Allcargo!D99 -> 0.20585089 | C98: =Allcargo!E99 -> 0.11123818 | D98: =Allcargo!F99 -> 0.20614653 | E98: =Allcargo!G99 -> 0.48893928 | F98: =Allcargo!H99 -> -0.052126293 | G98: =Allcargo!I99 -> 0.69095477 | H98: =Allcargo!J99 -> 0.66950959 | I98: =Allcargo!K99 -> 0.33150185 | J98: =IF(AND(ISNUMBER(I98),ISNUMBER(I$109)),IF(I98>I$109,"Above",IF(I98<I$109,"Below","At median")),"-") -> Above | K98: =IF(J98="Above","Better",IF(J98="Below","Weaker",IF(J98="At median","In line","-"))) -> Better | L98: =IF(ISNUMBER(I98),RANK(I98,I$97:I$106,0),"-") -> 5
A99: Blue Dart | B99: =BlueDart!D99 -> 0.22476481 | C99: =BlueDart!E99 -> 0.9576929 | D99: =BlueDart!F99 -> 0.96515609 | E99: =BlueDart!G99 -> 0.7762471 | F99: =BlueDart!H99 -> 0.8295744 | G99: =BlueDart!I99 -> 0.67028348 | H99: =BlueDart!J99 -> 0.67067013 | I99: =BlueDart!K99 -> 0.72776984 | J99: =IF(AND(ISNUMBER(I99),ISNUMBER(I$109)),IF(I99>I$109,"Above",IF(I99<I$109,"Below","At median")),"-") -> Above | K99: =IF(J99="Above","Better",IF(J99="Below","Weaker",IF(J99="At median","In line","-"))) -> Better | L99: =IF(ISNUMBER(I99),RANK(I99,I$97:I$106,0),"-") -> 3
A100: CONCOR | B100: =CONCOR!D99 -> 2.5622482 | C100: =CONCOR!E99 -> 0.68592111 | D100: =CONCOR!F99 -> 0.90604262 | E100: =CONCOR!G99 -> 0.96264012 | F100: =CONCOR!H99 -> 1.087953 | G100: =CONCOR!I99 -> 1.3866034 | H100: =CONCOR!J99 -> 1.1681588 | I100: =CONCOR!K99 -> 1.2513667 | J100: =IF(AND(ISNUMBER(I100),ISNUMBER(I$109)),IF(I100>I$109,"Above",IF(I100<I$109,"Below","At median")),"-") -> Above | K100: =IF(J100="Above","Better",IF(J100="Below","Weaker",IF(J100="At median","In line","-"))) -> Better | L100: =IF(ISNUMBER(I100),RANK(I100,I$97:I$106,0),"-") -> 1
A101: Jet Freight | B101: =JetFreight!D99 -> 0.38443042 | C101: =JetFreight!E99 -> 0.21812596 | D101: =JetFreight!F99 -> -0.29003021 | E101: =JetFreight!G99 -> -1.2653659 | F101: =JetFreight!H99 -> 0.32345065 | G101: =JetFreight!I99 -> -0.016147636 | H101: =JetFreight!J99 -> -0.15350413 | I101: =JetFreight!K99 -> -0.11414869 | J101: =IF(AND(ISNUMBER(I101),ISNUMBER(I$109)),IF(I101>I$109,"Above",IF(I101<I$109,"Below","At median")),"-") -> Below | K101: =IF(J101="Above","Better",IF(J101="Below","Weaker",IF(J101="At median","In line","-"))) -> Weaker | L101: =IF(ISNUMBER(I101),RANK(I101,I$97:I$106,0),"-") -> 10
A102: Patel | B102: =Patel!D99 -> -0.61037441 | C102: =Patel!E99 -> 0.38043478 | D102: =Patel!F99 -> 0.66256336 | E102: =Patel!G99 -> -0.18793103 | F102: =Patel!H99 -> 0.25128627 | G102: =Patel!I99 -> 0.026355196 | H102: =Patel!J99 -> 0.23613596 | I102: =Patel!K99 -> 0.10835287 | J102: =IF(AND(ISNUMBER(I102),ISNUMBER(I$109)),IF(I102>I$109,"Above",IF(I102<I$109,"Below","At median")),"-") -> Below | K102: =IF(J102="Above","Better",IF(J102="Below","Weaker",IF(J102="At median","In line","-"))) -> Weaker | L102: =IF(ISNUMBER(I102),RANK(I102,I$97:I$106,0),"-") -> 9
A103: Sical | B103: =Sical!D99 -> 0.29352704 | C103: =Sical!E99 -> 0.13945392 | D103: =Sical!F99 -> 0.092525131 | E103: =Sical!G99 -> 0.025818295 | F103: =Sical!H99 -> 0.034503606 | G103: =Sical!I99 -> 0.078200719 | H103: =Sical!J99 -> 0.18013706 | I103: =Sical!K99 -> 0.12059511 | J103: =IF(AND(ISNUMBER(I103),ISNUMBER(I$109)),IF(I103>I$109,"Above",IF(I103<I$109,"Below","At median")),"-") -> Below | K103: =IF(J103="Above","Better",IF(J103="Below","Weaker",IF(J103="At median","In line","-"))) -> Weaker | L103: =IF(ISNUMBER(I103),RANK(I103,I$97:I$106,0),"-") -> 8
A104: TCI | B104: =TCI!D99 -> 1.0229168 | C104: =TCI!E99 -> 1.1218614 | D104: =TCI!F99 -> 1.2245774 | E104: =TCI!G99 -> 1.1737673 | F104: =TCI!H99 -> 0.98489635 | G104: =TCI!I99 -> 0.66835994 | H104: =TCI!J99 -> 0.7363912 | I104: =TCI!K99 -> 0.99039578 | J104: =IF(AND(ISNUMBER(I104),ISNUMBER(I$109)),IF(I104>I$109,"Above",IF(I104<I$109,"Below","At median")),"-") -> Above | K104: =IF(J104="Above","Better",IF(J104="Below","Weaker",IF(J104="At median","In line","-"))) -> Better | L104: =IF(ISNUMBER(I104),RANK(I104,I$97:I$106,0),"-") -> 2
A105: Shreeji | B105: =Shreeji!D99 -> 0.5554259 | C105: =Shreeji!E99 -> 0.61798839 | D105: =Shreeji!F99 -> 0.44409199 | E105: =Shreeji!G99 -> 0.56208054 | F105: =Shreeji!H99 -> 0.044657999 | G105: =Shreeji!I99 -> 0.76096096 | H105: =Shreeji!J99 -> 0.030506722 | I105: =Shreeji!K99 -> 0.43081607 | J105: =IF(AND(ISNUMBER(I105),ISNUMBER(I$109)),IF(I105>I$109,"Above",IF(I105<I$109,"Below","At median")),"-") -> Above | K105: =IF(J105="Above","Better",IF(J105="Below","Weaker",IF(J105="At median","In line","-"))) -> Better | L105: =IF(ISNUMBER(I105),RANK(I105,I$97:I$106,0),"-") -> 4
A106: Mahindra Log. | B106: =MahindraLog!D99 -> 0.12632233 | C106: =MahindraLog!E99 -> 0.34576578 | D106: =MahindraLog!F99 -> 0.18604243 | E106: =MahindraLog!G99 -> 0.10317831 | F106: =MahindraLog!H99 -> 0.18215249 | G106: =MahindraLog!I99 -> 0.26975805 | H106: =MahindraLog!J99 -> 0.19805854 | I106: =MahindraLog!K99 -> 0.20161113 | J106: =IF(AND(ISNUMBER(I106),ISNUMBER(I$109)),IF(I106>I$109,"Above",IF(I106<I$109,"Below","At median")),"-") -> Below | K106: =IF(J106="Above","Better",IF(J106="Below","Weaker",IF(J106="At median","In line","-"))) -> Weaker | L106: =IF(ISNUMBER(I106),RANK(I106,I$97:I$106,0),"-") -> 6
A107: Industry (aggregate) | B107: =Industry!D100 -> 0.81818195 | C107: =Industry!E100 -> 0.38332169 | D107: =Industry!F100 -> 0.43184673 | E107: =Industry!G100 -> 0.56161618 | F107: =Industry!H100 -> 0.37593579 | G107: =Industry!I100 -> 0.69894991 | H107: =Industry!J100 -> 0.63357276 | I107: =Industry!K100 -> 0.55763214
...

Sheet Statistics
A1: Statistical analysis of the ratio panel (10 firms x 7 years, FY2020-FY2026)
A2: Section A uses all 70 firm-years. Sections B and C use the 9 firms other than Sical Logistics (63 firm-years), which is left out as an outlier: its net worth was negative or close to zero in most years while it went through the IBC process.
A4: A. DESCRIPTIVE STATISTICS - pooled panel of 70 firm-years
A5: Variable | B5: N | C5: Mean | D5: Median | E5: Std. dev. | F5: Coeff. of variation | G5: Minimum | H5: Lower quartile | I5: Upper quartile | J5: Maximum | K5: Skewness | L5: Kurtosis | M5: Median ex-Sical
A6: Sales (Rs cr) | B6: =COUNT(Panel!$C$2:$C$71) -> 70 | C6: =AVERAGE(Panel!$C$2:$C$71) -> 3331.3929 | D6: =MEDIAN(Panel!$C$2:$C$71) -> 1483.42 | E6: =STDEV(Panel!$C$2:$C$71) -> 4086.3364 | F6: =IF(ABS(C6)>0,E6/ABS(C6),"N/M") -> 1.226615 | G6: =MIN(Panel!$C$2:$C$71) -> 108.23 | H6: =QUARTILE(Panel!$C$2:$C$71,1) -> 343.715 | I6: =QUARTILE(Panel!$C$2:$C$71,3) -> 5243.9275 | J6: =MAX(Panel!$C$2:$C$71) -> 19062.06 | K6: =SKEW(Panel!$C$2:$C$71) -> 1.8313391 | L6: =KURT(Panel!$C$2:$C$71) -> 4.0593186 | M6: =MEDIAN(Panel!$C$2:$C$64) -> 2802.39
A7: Total assets (Rs cr) | B7: =COUNT(Panel!$D$2:$D$71) -> 70 | C7: =AVERAGE(Panel!$D$2:$D$71) -> 2896.4641 | D7: =MEDIAN(Panel!$D$2:$D$71) -> 1685.125 | E7: =STDEV(Panel!$D$2:$D$71) -> 4078.1112 | F7: =IF(ABS(C7)>0,E7/ABS(C7),"N/M") -> 1.4079619 | G7: =MIN(Panel!$D$2:$D$71) -> 79.35 | H7: =QUARTILE(Panel!$D$2:$D$71,1) -> 168.73 | I7: =QUARTILE(Panel!$D$2:$D$71,3) -> 3062.265 | J7: =MAX(Panel!$D$2:$D$71) -> 15175.78 | K7: =SKEW(Panel!$D$2:$D$71) -> 1.8675486 | L7: =KURT(Panel!$D$2:$D$71) -> 2.4846677 | M7: =MEDIAN(Panel!$D$2:$D$64) -> 1736
A8: Asset intensity (Net block / Total assets) | B8: =COUNT(Panel!$E$2:$E$71) -> 70 | C8: =AVERAGE(Panel!$E$2:$E$71) -> 0.34297414 | D8: =MEDIAN(Panel!$E$2:$E$71) -> 0.33863637 | E8: =STDEV(Panel!$E$2:$E$71) -> 0.16287551 | F8: =IF(ABS(C8)>0,E8/ABS(C8),"N/M") -> 0.47489152 | G8: =MIN(Panel!$E$2:$E$71) -> 0.03739243 | H8: =QUARTILE(Panel!$E$2:$E$71,1) -> 0.2493843 | I8: =QUARTILE(Panel!$E$2:$E$71,3) -> 0.45298648 | J8: =MAX(Panel!$E$2:$E$71) -> 0.76336994 | K8: =SKEW(Panel!$E$2:$E$71) -> 0.22437037 | L8: =KURT(Panel!$E$2:$E$71) -> 0.0070443888 | M8: =MEDIAN(Panel!$E$2:$E$64) -> 0.32499001
A9: Current ratio | B9: =COUNT(Panel!$F$2:$F$71) -> 70 | C9: =AVERAGE(Panel!$F$2:$F$71) -> 3.0085821 | D9: =MEDIAN(Panel!$F$2:$F$71) -> 2.6540417 | E9: =STDEV(Panel!$F$2:$F$71) -> 2.0292796 | F9: =IF(ABS(C9)>0,E9/ABS(C9),"N/M") -> 0.67449701 | G9: =MIN(Panel!$F$2:$F$71) -> 0.43040965 | H9: =QUARTILE(Panel!$F$2:$F$71,1) -> 1.3732657 | I9: =QUARTILE(Panel!$F$2:$F$71,3) -> 4.4971896 | J9: =MAX(Panel!$F$2:$F$71) -> 10.618729 | K9: =SKEW(Panel!$F$2:$F$71) -> 1.2360351 | L9: =KURT(Panel!$F$2:$F$71) -> 1.9761816 | M9: =MEDIAN(Panel!$F$2:$F$64) -> 2.8559374
A10: Quick ratio | B10: =COUNT(Panel!$G$2:$G$71) -> 70 | C10: =AVERAGE(Panel!$G$2:$G$71) -> 2.1490874 | D10: =MEDIAN(Panel!$G$2:$G$71) -> 1.6964646 | E10: =STDEV(Panel!$G$2:$G$71) -> 1.6602266 | F10: =IF(ABS(C10)>0,E10/ABS(C10),"N/M") -> 0.77252633 | G10: =MIN(Panel!$G$2:$G$71) -> 0.24450927 | H10: =QUARTILE(Panel!$G$2:$G$71,1) -> 0.86424323 | I10: =QUARTILE(Panel!$G$2:$G$71,3) -> 3.0904257 | J10: =MAX(Panel!$G$2:$G$71) -> 7.9423077 | K10: =SKEW(Panel!$G$2:$G$71) -> 1.2873811 | L10: =KURT(Panel!$G$2:$G$71) -> 1.5536181 | M10: =MEDIAN(Panel!$G$2:$G$64) -> 1.8784838
A11: Debt-equity | B11: =COUNT(Panel!$H$2:$H$71) -> 67 | C11: =AVERAGE(Panel!$H$2:$H$71) -> 1.1566304 | D11: =MEDIAN(Panel!$H$2:$H$71) -> 0.66661121 | E11: =STDEV(Panel!$H$2:$H$71) -> 2.3997399 | F11: =IF(ABS(C11)>0,E11/ABS(C11),"N/M") -> 2.0747682 | G11: =MIN(Panel!$H$2:$H$71) -> 0 | H11: =QUARTILE(Panel!$H$2:$H$71,1) -> 0.16193747 | I11: =QUARTILE(Panel!$H$2:$H$71,3) -> 1.1668783 | J11: =MAX(Panel!$H$2:$H$71) -> 17.661908 | K11: =SKEW(Panel!$H$2:$H$71) -> 5.6286252 | L11: =KURT(Panel!$H$2:$H$71) -> 35.960985 | M11: =MEDIAN(Panel!$H$2:$H$64) -> 0.64266137
A12: Interest coverage | B12: =COUNT(Panel!$I$2:$I$71) -> 70 | C12: =AVERAGE(Panel!$I$2:$I$71) -> 6.3612962 | D12: =MEDIAN(Panel!$I$2:$I$71) -> 2.331245 | E12: =STDEV(Panel!$I$2:$I$71) -> 8.5706701 | F12: =IF(ABS(C12)>0,E12/ABS(C12),"N/M") -> 1.3473151 | G12: =MIN(Panel!$I$2:$I$71) -> -5.2959184 | H12: =QUARTILE(Panel!$I$2:$I$71,1) -> 0.67757728 | I12: =QUARTILE(Panel!$I$2:$I$71,3) -> 9.8382265 | J12: =MAX(Panel!$I$2:$I$71) -> 30.953157 | K12: =SKEW(Panel!$I$2:$I$71) -> 1.1726497 | L12: =KURT(Panel!$I$2:$I$71) -> 0.24681581 | M12: =MEDIAN(Panel!$I$2:$I$64) -> 3.1113801
A13: Collection period (days) | B13: =COUNT(Panel!$J$2:$J$71) -> 70 | C13: =AVERAGE(Panel!$J$2:$J$71) -> 66.831589 | D13: =MEDIAN(Panel!$J$2:$J$71) -> 61.71031 | E13: =STDEV(Panel!$J$2:$J$71) -> 32.46537 | F13: =IF(ABS(C13)>0,E13/ABS(C13),"N/M") -> 0.48577881 | G13: =MIN(Panel!$J$2:$J$71) -> 8.6672077 | H13: =QUARTILE(Panel!$J$2:$J$71,1) -> 46.443426 | I13: =QUARTILE(Panel!$J$2:$J$71,3) -> 90.485037 | J13: =MAX(Panel!$J$2:$J$71) -> 154.23158 | K13: =SKEW(Panel!$J$2:$J$71) -> 0.41181924 | L13: =KURT(Panel!$J$2:$J$71) -> 0.06596741 | M13: =MEDIAN(Panel!$J$2:$J$64) -> 58.904174
A14: Total assets turnover | B14: =COUNT(Panel!$K$2:$K$71) -> 70 | C14: =AVERAGE(Panel!$K$2:$K$71) -> 1.704162 | D14: =MEDIAN(Panel!$K$2:$K$71) -> 1.6155342 | E14: =STDEV(Panel!$K$2:$K$71) -> 0.93078738 | F14: =IF(ABS(C14)>0,E14/ABS(C14),"N/M") -> 0.54618481 | G14: =MIN(Panel!$K$2:$K$71) -> 0.22283754 | H14: =QUARTILE(Panel!$K$2:$K$71,1) -> 1.1896981 | I14: =QUARTILE(Panel!$K$2:$K$71,3) -> 2.1599108 | J14: =MAX(Panel!$K$2:$K$71) -> 5.0730722 | K14: =SKEW(Panel!$K$2:$K$71) -> 0.89462912 | L14: =KURT(Panel!$K$2:$K$71) -> 1.9330849 | M14: =MEDIAN(Panel!$K$2:$K$64) -> 1.7813873
A15: Operating EBITDA margin | B15: =COUNT(Panel!$L$2:$L$71) -> 70 | C15: =AVERAGE(Panel!$L$2:$L$71) -> 0.081391573 | D15: =MEDIAN(Panel!$L$2:$L$71) -> 0.0635277 | E15: =STDEV(Panel!$L$2:$L$71) -> 0.074728009 | F15: =IF(ABS(C15)>0,E15/ABS(C15),"N/M") -> 0.91812956 | G15: =MIN(Panel!$L$2:$L$71) -> -0.11224812 | H15: =QUARTILE(Panel!$L$2:$L$71,1) -> 0.033882781 | I15: =QUARTILE(Panel!$L$2:$L$71,3) -> 0.11073074 | J15: =MAX(Panel!$L$2:$L$71) -> 0.25944103 | K15: =SKEW(Panel!$L$2:$L$71) -> 0.47722233 | L15: =KURT(Panel!$L$2:$L$71) -> 0.20484275 | M15: =MEDIAN(Panel!$L$2:$L$64) -> 0.06316628
A16: Operating profit (EBIT) margin | B16: =COUNT(Panel!$M$2:$M$71) -> 70 | C16: =AVERAGE(Panel!$M$2:$M$71) -> 0.033938981 | D16: =MEDIAN(Panel!$M$2:$M$71) -> 0.032556558 | E16: =STDEV(Panel!$M$2:$M$71) -> 0.076624951 | F16: =IF(ABS(C16)>0,E16/ABS(C16),"N/M") -> 2.257727 | G16: =MIN(Panel!$M$2:$M$71) -> -0.31624961 | H16: =QUARTILE(Panel!$M$2:$M$71,1) -> 0.013402457 | I16: =QUARTILE(Panel!$M$2:$M$71,3) -> 0.075127348 | J16: =MAX(Panel!$M$2:$M$71) -> 0.17607388 | K16: =SKEW(Panel!$M$2:$M$71) -> -1.6566707 | L16: =KURT(Panel!$M$2:$M$71) -> 6.1919694 | M16: =MEDIAN(Panel!$M$2:$M$64) -> 0.040086548
A17: Net profit margin | B17: =COUNT(Panel!$N$2:$N$71) -> 70 | C17: =AVERAGE(Panel!$N$2:$N$71) -> -0.043119785 | D17: =MEDIAN(Panel!$N$2:$N$71) -> 0.024528847 | E17: =STDEV(Panel!$N$2:$N$71) -> 0.39058515 | F17: =IF(ABS(C17)>0,E17/ABS(C17),"N/M") -> 9.0581423 | G17: =MIN(Panel!$N$2:$N$71) -> -2.3024443 | H17: =QUARTILE(Panel!$N$2:$N$71,1) -> 0.0039756437 | I17: =QUARTILE(Panel!$N$2:$N$71,3) -> 0.054517136 | J17: =MAX(Panel!$N$2:$N$71) -> 0.14567552 | K17: =SKEW(Panel!$N$2:$N$71) -> -5.2218752 | L17: =KURT(Panel!$N$2:$N$71) -> 27.543751 | M17: =MEDIAN(Panel!$N$2:$N$64) -> 0.030914481
A18: ROA | B18: =COUNT(Panel!$O$2:$O$71) -> 70 | C18: =AVERAGE(Panel!$O$2:$O$71) -> 0.020263509 | D18: =MEDIAN(Panel!$O$2:$O$71) -> 0.036236451 | E18: =STDEV(Panel!$O$2:$O$71) -> 0.17178571 | F18: =IF(ABS(C18)>0,E18/ABS(C18),"N/M") -> 8.4775895 | G18: =MIN(Panel!$O$2:$O$71) -> -1.0516135 | H18: =QUARTILE(Panel!$O$2:$O$71,1) -> 0.0056785109 | I18: =QUARTILE(Panel!$O$2:$O$71,3) -> 0.08715172 | J18: =MAX(Panel!$O$2:$O$71) -> 0.27736082 | K18: =SKEW(Panel!$O$2:$O$71) -> -4.5150316 | L18: =KURT(Panel!$O$2:$O$71) -> 25.129478 | M18: =MEDIAN(Panel!$O$2:$O$64) -> 0.040712464
A19: ROCE (post-tax) | B19: =COUNT(Panel!$P$2:$P$71) -> 70 | C19: =AVERAGE(Panel!$P$2:$P$71) -> 0.062648884 | D19: =MEDIAN(Panel!$P$2:$P$71) -> 0.05941886 | E19: =STDEV(Panel!$P$2:$P$71) -> 0.089847077 | F19: =IF(ABS(C19)>0,E19/ABS(C19),"N/M") -> 1.4341369 | G19: =MIN(Panel!$P$2:$P$71) -> -0.18229715 | H19: =QUARTILE(Panel!$P$2:$P$71,1) -> 0.029580823 | I19: =QUARTILE(Panel!$P$2:$P$71,3) -> 0.10739896 | J19: =MAX(Panel!$P$2:$P$71) -> 0.44482314 | K19: =SKEW(Panel!$P$2:$P$71) -> 0.50057448 | L19: =KURT(Panel!$P$2:$P$71) -> 4.6674596 | M19: =MEDIAN(Panel!$P$2:$P$64) -> 0.072484988
A20: ROE | B20: =COUNT(Panel!$Q$2:$Q$71) -> 67 | C20: =AVERAGE(Panel!$Q$2:$Q$71) -> -0.15810305 | D20: =MEDIAN(Panel!$Q$2:$Q$71) -> 0.095948572 | E20: =STDEV(Panel!$Q$2:$Q$71) -> 1.923445 | F20: =IF(ABS(C20)>0,E20/ABS(C20),"N/M") -> 12.165768 | G20: =MIN(Panel!$Q$2:$Q$71) -> -15.581839 | H20: =QUARTILE(Panel!$Q$2:$Q$71,1) -> 0.029539516 | I20: =QUARTILE(Panel!$Q$2:$Q$71,3) -> 0.1735268 | J20: =MAX(Panel!$Q$2:$Q$71) -> 0.45183394 | K20: =SKEW(Panel!$Q$2:$Q$71) -> -8.0497001 | L20: =KURT(Panel!$Q$2:$Q$71) -> 65.469968 | M20: =MEDIAN(Panel!$Q$2:$Q$64) -> 0.098100051
A21: P/E | B21: =COUNT(Panel!$R$2:$R$71) -> 51 | C21: =AVERAGE(Panel!$R$2:$R$71) -> 114.77776 | D21: =MEDIAN(Panel!$R$2:$R$71) -> 30.117025 | E21: =STDEV(Panel!$R$2:$R$71) -> 293.23105 | F21: =IF(ABS(C21)>0,E21/ABS(C21),"N/M") -> 2.5547723 | G21: =MIN(Panel!$R$2:$R$71) -> 3.1335196 | H21: =QUARTILE(Panel!$R$2:$R$71,1) -> 14.82952 | I21: =QUARTILE(Panel!$R$2:$R$71,3) -> 48.268614 | J21: =MAX(Panel!$R$2:$R$71) -> 1441.6489 | K21: =SKEW(Panel!$R$2:$R$71) -> 3.8829253 | L21: =KURT(Panel!$R$2:$R$71) -> 14.622695 | M21: =MEDIAN(Panel!$R$2:$R$64) -> 31.390868
A22: P/B | B22: =COUNT(Panel!$S$2:$S$71) -> 61 | C22: =AVERAGE(Panel!$S$2:$S$71) -> 4.4933226 | D22: =MEDIAN(Panel!$S$2:$S$71) -> 2.9993067 | E22: =STDEV(Panel!$S$2:$S$71) -> 5.672244 | F22: =IF(ABS(C22)>0,E22/ABS(C22),"N/M") -> 1.2623719 | G22: =MIN(Panel!$S$2:$S$71) -> 0.062998015 | H22: =QUARTILE(Panel!$S$2:$S$71,1) -> 1.0894945 | I22: =QUARTILE(Panel!$S$2:$S$71,3) -> 5.4085612 | J22: =MAX(Panel!$S$2:$S$71) -> 33.431025 | K22: =SKEW(Panel!$S$2:$S$71) -> 3.1105405 | L22: =KURT(Panel!$S$2:$S$71) -> 12.059266 | M22: =MEDIAN(Panel!$S$2:$S$64) -> 2.9993067
A23: EV / EBITDA | B23: =COUNT(Panel!$T$2:$T$71) -> 58 | C23: =AVERAGE(Panel!$T$2:$T$71) -> 16.444459 | D23: =MEDIAN(Panel!$T$2:$T$71) -> 14.094482 | E23: =STDEV(Panel!$T$2:$T$71) -> 11.636817 | F23: =IF(ABS(C23)>0,E23/ABS(C23),"N/M") -> 0.70764368 | G23: =MIN(Panel!$T$2:$T$71) -> 3.5505882 | H23: =QUARTILE(Panel!$T$2:$T$71,1) -> 10.209307 | I23: =QUARTILE(Panel!$T$2:$T$71,3) -> 18.10445 | J23: =MAX(Panel!$T$2:$T$71) -> 81.20958 | K23: =SKEW(Panel!$T$2:$T$71) -> 3.5072987 | L23: =KURT(Panel!$T$2:$T$71) -> 16.787433 | M23: =MEDIAN(Panel!$T$2:$T$64) -> 14.028978
A25: N counts only meaningful values: P/E, P/B and EV/EBITDA exclude loss-making and N/C firm-years, and debt-equity / ROE exclude Sical's negative net-worth years. The coefficient of variation is SD / |mean|.
A27: B. CORRELATION MATRIX (Pearson r) - 63 firm-years of the 9 firms other than Sical
B28: Current ratio | C28: Debt-equity | D28: Interest coverage | E28: Collection period | F28: Total assets turnover | G28: Asset intensity | H28: Op. EBITDA margin | I28: EBIT margin | J28: Net profit margin | K28: ROCE (post-tax) | L28: ROE
A29: Current ratio | B29: =CORREL(Panel!$F$2:$F$64,Panel!$F$2:$F$64) -> 1 | C29: =CORREL(Panel!$F$2:$F$64,Panel!$H$2:$H$64) -> -0.22485167 | D29: =CORREL(Panel!$F$2:$F$64,Panel!$I$2:$I$64) -> 0.038065957 | E29: =CORREL(Panel!$F$2:$F$64,Panel!$J$2:$J$64) -> 0.48019311 | F29: =CORREL(Panel!$F$2:$F$64,Panel!$K$2:$K$64) -> -0.12028559 | G29: =CORREL(Panel!$F$2:$F$64,Panel!$E$2:$E$64) -> -0.3946427 | H29: =CORREL(Panel!$F$2:$F$64,Panel!$L$2:$L$64) -> -0.15873841 | I29: =CORREL(Panel!$F$2:$F$64,Panel!$M$2:$M$64) -> 0.013148005 | J29: =CORREL(Panel!$F$2:$F$64,Panel!$N$2:$N$64) -> 0.07048714 | K29: =CORREL(Panel!$F$2:$F$64,Panel!$P$2:$P$64) -> -0.16442048 | L29: =CORREL(Panel!$F$2:$F$64,Panel!$Q$2:$Q$64) -> -0.070966374
A30: Debt-equity | B30: =CORREL(Panel!$H$2:$H$64,Panel!$F$2:$F$64) -> -0.22485167 | C30: =CORREL(Panel!$H$2:$H$64,Panel!$H$2:$H$64) -> 1 | D30: =CORREL(Panel!$H$2:$H$64,Panel!$I$2:$I$64) -> -0.62198685 | E30: =CORREL(Panel!$H$2:$H$64,Panel!$J$2:$J$64) -> 0.15938267 | F30: =CORREL(Panel!$H$2:$H$64,Panel!$K$2:$K$64) -> 0.20057908 | G30: =CORREL(Panel!$H$2:$H$64,Panel!$E$2:$E$64) -> 0.091410862 | H30: =CORREL(Panel!$H$2:$H$64,Panel!$L$2:$L$64) -> -0.1632458 | I30: =CORREL(Panel!$H$2:$H$64,Panel!$M$2:$M$64) -> -0.3498151 | J30: =CORREL(Panel!$H$2:$H$64,Panel!$N$2:$N$64) -> -0.49373224 | K30: =CORREL(Panel!$H$2:$H$64,Panel!$P$2:$P$64) -> -0.22924303 | L30: =CORREL(Panel!$H$2:$H$64,Panel!$Q$2:$Q$64) -> -0.25542591
A31: Interest coverage | B31: =CORREL(Panel!$I$2:$I$64,Panel!$F$2:$F$64) -> 0.038065957 | C31: =CORREL(Panel!$I$2:$I$64,Panel!$H$2:$H$64) -> -0.62198685 | D31: =CORREL(Panel!$I$2:$I$64,Panel!$I$2:$I$64) -> 1 | E31: =CORREL(Panel!$I$2:$I$64,Panel!$J$2:$J$64) -> -0.45723383 | F31: =CORREL(Panel!$I$2:$I$64,Panel!$K$2:$K$64) -> -0.11076408 | G31: =CORREL(Panel!$I$2:$I$64,Panel!$E$2:$E$64) -> 0.10507898 | H31: =CORREL(Panel!$I$2:$I$64,Panel!$L$2:$L$64) -> 0.51678529 | I31: =CORREL(Panel!$I$2:$I$64,Panel!$M$2:$M$64) -> 0.6922336 | J31: =CORREL(Panel!$I$2:$I$64,Panel!$N$2:$N$64) -> 0.75183004 | K31: =CORREL(Panel!$I$2:$I$64,Panel!$P$2:$P$64) -> 0.57488598 | L31: =CORREL(Panel!$I$2:$I$64,Panel!$Q$2:$Q$64) -> 0.46054292
A32: Collection period | B32: =CORREL(Panel!$J$2:$J$64,Panel!$F$2:$F$64) -> 0.48019311 | C32: =CORREL(Panel!$J$2:$J$64,Panel!$H$2:$H$64) -> 0.15938267 | D32: =CORREL(Panel!$J$2:$J$64,Panel!$I$2:$I$64) -> -0.45723383 | E32: =CORREL(Panel!$J$2:$J$64,Panel!$J$2:$J$64) -> 1 | F32: =CORREL(Panel!$J$2:$J$64,Panel!$K$2:$K$64) -> 0.059497309 | G32: =CORREL(Panel!$J$2:$J$64,Panel!$E$2:$E$64) -> -0.41685773 | H32: =CORREL(Panel!$J$2:$J$64,Panel!$L$2:$L$64) -> -0.55989321 | I32: =CORREL(Panel!$J$2:$J$64,Panel!$M$2:$M$64) -> -0.52159593 | J32: =CORREL(Panel!$J$2:$J$64,Panel!$N$2:$N$64) -> -0.48955982 | K32: =CORREL(Panel!$J$2:$J$64,Panel!$P$2:$P$64) -> -0.24634147 | L32: =CORREL(Panel!$J$2:$J$64,Panel!$Q$2:$Q$64) -> -0.13365066
A33: Total assets turnover | B33: =CORREL(Panel!$K$2:$K$64,Panel!$F$2:$F$64) -> -0.12028559 | C33: =CORREL(Panel!$K$2:$K$64,Panel!$H$2:$H$64) -> 0.20057908 | D33: =CORREL(Panel!$K$2:$K$64,Panel!$I$2:$I$64) -> -0.11076408 | E33: =CORREL(Panel!$K$2:$K$64,Panel!$J$2:$J$64) -> 0.059497309 | F33: =CORREL(Panel!$K$2:$K$64,Panel!$K$2:$K$64) -> 1 | G33: =CORREL(Panel!$K$2:$K$64,Panel!$E$2:$E$64) -> -0.63444718 | H33: =CORREL(Panel!$K$2:$K$64,Panel!$L$2:$L$64) -> -0.62382056 | I33: =CORREL(Panel!$K$2:$K$64,Panel!$M$2:$M$64) -> -0.49393226 | J33: =CORREL(Panel!$K$2:$K$64,Panel!$N$2:$N$64) -> -0.44270552 | K33: =CORREL(Panel!$K$2:$K$64,Panel!$P$2:$P$64) -> 0.21565709 | L33: =CORREL(Panel!$K$2:$K$64,Panel!$Q$2:$Q$64) -> 0.012548545
A34: Asset intensity | B34: =CORREL(Panel!$E$2:$E$64,Panel!$F$2:$F$64) -> -0.3946427 | C34: =CORREL(Panel!$E$2:$E$64,Panel!$H$2:$H$64) -> 0.091410862 | D34: =CORREL(Panel!$E$2:$E$64,Panel!$I$2:$I$64) -> 0.10507898 | E34: =CORREL(Panel!$E$2:$E$64,Panel!$J$2:$J$64) -> -0.41685773 | F34: =CORREL(Panel!$E$2:$E$64,Panel!$K$2:$K$64) -> -0.63444718 | G34: =CORREL(Panel!$E$2:$E$64,Panel!$E$2:$E$64) -> 1 | H34: =CORREL(Panel!$E$2:$E$64,Panel!$L$2:$L$64) -> 0.70201305 | I34: =CORREL(Panel!$E$2:$E$64,Panel!$M$2:$M$64) -> 0.46912708 | J34: =CORREL(Panel!$E$2:$E$64,Panel!$N$2:$N$64) -> 0.37741255 | K34: =CORREL(Panel!$E$2:$E$64,Panel!$P$2:$P$64) -> 0.11845378 | L34: =CORREL(Panel!$E$2:$E$64,Panel!$Q$2:$Q$64) -> 0.15233806
A35: Op. EBITDA margin | B35: =CORREL(Panel!$L$2:$L$64,Panel!$F$2:$F$64) -> -0.15873841 | C35: =CORREL(Panel!$L$2:$L$64,Panel!$H$2:$H$64) -> -0.1632458 | D35: =CORREL(Panel!$L$2:$L$64,Panel!$I$2:$I$64) -> 0.51678529 | E35: =CORREL(Panel!$L$2:$L$64,Panel!$J$2:$J$64) -> -0.55989321 | F35: =CORREL(Panel!$L$2:$L$64,Panel!$K$2:$K$64) -> -0.62382056 | G35: =CORREL(Panel!$L$2:$L$64,Panel!$E$2:$E$64) -> 0.70201305 | H35: =CORREL(Panel!$L$2:$L$64,Panel!$L$2:$L$64) -> 1 | I35: =CORREL(Panel!$L$2:$L$64,Panel!$M$2:$M$64) -> 0.91852491 | J35: =CORREL(Panel!$L$2:$L$64,Panel!$N$2:$N$64) -> 0.78821557 | K35: =CORREL(Panel!$L$2:$L$64,Panel!$P$2:$P$64) -> 0.4190944 | L35: =CORREL(Panel!$L$2:$L$64,Panel!$Q$2:$Q$64) -> 0.4341613
A36: EBIT margin | B36: =CORREL(Panel!$M$2:$M$64,Panel!$F$2:$F$64) -> 0.013148005 | C36: =CORREL(Panel!$M$2:$M$64,Panel!$H$2:$H$64) -> -0.3498151 | D36: =CORREL(Panel!$M$2:$M$64,Panel!$I$2:$I$64) -> 0.6922336 | E36: =CORREL(Panel!$M$2:$M$64,Panel!$J$2:$J$64) -> -0.52159593 | F36: =CORREL(Panel!$M$2:$M$64,Panel!$K$2:$K$64) -> -0.49393226 | G36: =CORREL(Panel!$M$2:$M$64,Panel!$E$2:$E$64) -> 0.46912708 | H36: =CORREL(Panel!$M$2:$M$64,Panel!$L$2:$L$64) -> 0.91852491 | I36: =CORREL(Panel!$M$2:$M$64,Panel!$M$2:$M$64) -> 1 | J36: =CORREL(Panel!$M$2:$M$64,Panel!$N$2:$N$64) -> 0.91227214 | K36: =CORREL(Panel!$M$2:$M$64,Panel!$P$2:$P$64) -> 0.53629516 | L36: =CORREL(Panel!$M$2:$M$64,Panel!$Q$2:$Q$64) -> 0.54694762
A37: Net profit margin | B37: =CORREL(Panel!$N$2:$N$64,Panel!$F$2:$F$64) -> 0.07048714 | C37: =CORREL(Panel!$N$2:$N$64,Panel!$H$2:$H$64) -> -0.49373224 | D37: =CORREL(Panel!$N$2:$N$64,Panel!$I$2:$I$64) -> 0.75183004 | E37: =CORREL(Panel!$N$2:$N$64,Panel!$J$2:$J$64) -> -0.48955982 | F37: =CORREL(Panel!$N$2:$N$64,Panel!$K$2:$K$64) -> -0.44270552 | G37: =CORREL(Panel!$N$2:$N$64,Panel!$E$2:$E$64) -> 0.37741255 | H37: =CORREL(Panel!$N$2:$N$64,Panel!$L$2:$L$64) -> 0.78821557 | I37: =CORREL(Panel!$N$2:$N$64,Panel!$M$2:$M$64) -> 0.91227214 | J37: =CORREL(Panel!$N$2:$N$64,Panel!$N$2:$N$64) -> 1 | K37: =CORREL(Panel!$N$2:$N$64,Panel!$P$2:$P$64) -> 0.525976 | L37: =CORREL(Panel!$N$2:$N$64,Panel!$Q$2:$Q$64) -> 0.59375731
A38: ROCE (post-tax) | B38: =CORREL(Panel!$P$2:$P$64,Panel!$F$2:$F$64) -> -0.16442048 | C38: =CORREL(Panel!$P$2:$P$64,Panel!$H$2:$H$64) -> -0.22924303 | D38: =CORREL(Panel!$P$2:$P$64,Panel!$I$2:$I$64) -> 0.57488598 | E38: =CORREL(Panel!$P$2:$P$64,Panel!$J$2:$J$64) -> -0.24634147 | F38: =CORREL(Panel!$P$2:$P$64,Panel!$K$2:$K$64) -> 0.21565709 | G38: =CORREL(Panel!$P$2:$P$64,Panel!$E$2:$E$64) -> 0.11845378 | H38: =CORREL(Panel!$P$2:$P$64,Panel!$L$2:$L$64) -> 0.4190944 | I38: =CORREL(Panel!$P$2:$P$64,Panel!$M$2:$M$64) -> 0.53629516 | J38: =CORREL(Panel!$P$2:$P$64,Panel!$N$2:$N$64) -> 0.525976 | K38: =CORREL(Panel!$P$2:$P$64,Panel!$P$2:$P$64) -> 1 | L38: =CORREL(Panel!$P$2:$P$64,Panel!$Q$2:$Q$64) -> 0.85468293
A39: ROE | B39: =CORREL(Panel!$Q$2:$Q$64,Panel!$F$2:$F$64) -> -0.070966374 | C39: =CORREL(Panel!$Q$2:$Q$64,Panel!$H$2:$H$64) -> -0.25542591 | D39: =CORREL(Panel!$Q$2:$Q$64,Panel!$I$2:$I$64) -> 0.46054292 | E39: =CORREL(Panel!$Q$2:$Q$64,Panel!$J$2:$J$64) -> -0.13365066 | F39: =CORREL(Panel!$Q$2:$Q$64,Panel!$K$2:$K$64) -> 0.012548545 | G39: =CORREL(Panel!$Q$2:$Q$64,Panel!$E$2:$E$64) -> 0.15233806 | H39: =CORREL(Panel!$Q$2:$Q$64,Panel!$L$2:$L$64) -> 0.4341613 | I39: =CORREL(Panel!$Q$2:$Q$64,Panel!$M$2:$M$64) -> 0.54694762 | J39: =CORREL(Panel!$Q$2:$Q$64,Panel!$N$2:$N$64) -> 0.59375731 | K39: =CORREL(Panel!$Q$2:$Q$64,Panel!$P$2:$P$64) -> 0.85468293 | L39: =CORREL(Panel!$Q$2:$Q$64,Panel!$Q$2:$Q$64) -> 1
A41: How to read this matrix (important caution):
A42: - Green: r of +0.5 or more (strong positive); red: r of -0.5 or less (strong negative).
A43: - The 63 observations are repeated observations of the same 9 companies over seven years, not 63 independent companies. Ratios of the same firm move together from year to year, so the usual significance cut-off (|r| of about 0.25 for n = 63 at 5%) overstates the evidence; the effective sample is much closer to 9.
A44: - The correlations therefore describe association only. They are not used to draw causal conclusions (e.g. that higher asset turnover causes higher ROCE); some pairs are also linked by construction (EBITDA margin, EBIT margin and net margin share the same sales denominator).
A45: - The paired t-tests in section C are the more direct test of whether the typical firm's ratios changed between FY2020 and FY2026.
A47: C. PAIRED t-TESTS - did the typical firm's ratios change between FY2020 and FY2026? (H0: mean difference = 0; n = 9 firms)
A48: Ratio | B48: Mean FY2020 | C48: Mean FY2026 | D48: Mean difference | E48: SD of differences | F48: n | G48: t-statistic | H48: df | I48: p-value (two-tailed) | J48: Result at 5%
A49: Operating EBITDA margin | B49: =AVERAGE(B70:B78) -> 0.075506198 | C49: =AVERAGE(C70:C78) -> 0.087797989 | D49: =AVERAGE(D70:D78) -> 0.012291792 | E49: =STDEV(D70:D78) -> 0.040959639 | F49: =COUNT(D70:D78) -> 9 | G49: =IF(E49>0,D49/(E49/SQRT(F49)),"N/M") -> 0.90028564 | H49: =F49-1 -> 8 | I49: =TTEST(B70:B78,C70:C78,2,1) -> 0.39426109 | J49: =IF(I49<0.05,"Significant change","No significant change") -> No significant change
A50: Operating profit (EBIT) margin | B50: =AVERAGE(E70:E78) -> 0.038568321 | C50: =AVERAGE(F70:F78) -> 0.048909263 | D50: =AVERAGE(G70:G78) -> 0.010340943 | E50: =STDEV(G70:G78) -> 0.036896762 | F50: =COUNT(G70:G78) -> 9 | G50: =IF(E50>0,D50/(E50/SQRT(F50)),"N/M") -> 0.84080082 | H50: =F50-1 -> 8 | I50: =TTEST(E70:E78,F70:F78,2,1) -> 0.42487531 | J50: =IF(I50<0.05,"Significant change","No significant change") -> No significant change
A51: Net profit margin | B51: =AVERAGE(H70:H78) -> 0.013553624 | C51: =AVERAGE(I70:I78) -> 0.040813482 | D51: =AVERAGE(J70:J78) -> 0.027259859 | E51: =STDEV(J70:J78) -> 0.039489649 | F51: =COUNT(J70:J78) -> 9 | G51: =IF(E51>0,D51/(E51/SQRT(F51)),"N/M") -> 2.0709117 | H51: =F51-1 -> 8 | I51: =TTEST(H70:H78,I70:I78,2,1) -> 0.072126823 | J51: =IF(I51<0.05,"Significant change","No significant change") -> No significant change
A52: Return on assets | B52: =AVERAGE(K70:K78) -> 0.0044002139 | C52: =AVERAGE(L70:L78) -> 0.05337272 | D52: =AVERAGE(M70:M78) -> 0.048972507 | E52: =STDEV(M70:M78) -> 0.078157595 | F52: =COUNT(M70:M78) -> 9 | G52: =IF(E52>0,D52/(E52/SQRT(F52)),"N/M") -> 1.87976 | H52: =F52-1 -> 8 | I52: =TTEST(K70:K78,L70:L78,2,1) -> 0.096941304 | J52: =IF(I52<0.05,"Significant change","No significant change") -> No significant change
A53: ROCE (post-tax) | B53: =AVERAGE(N70:N78) -> 0.035259548 | C53: =AVERAGE(O70:O78) -> 0.067916194 | D53: =AVERAGE(P70:P78) -> 0.032656646 | E53: =STDEV(P70:P78) -> 0.084924963 | F53: =COUNT(P70:P78) -> 9 | G53: =IF(E53>0,D53/(E53/SQRT(F53)),"N/M") -> 1.1536059 | H53: =F53-1 -> 8 | I53: =TTEST(N70:N78,O70:O78,2,1) -> 0.28196024 | J53: =IF(I53<0.05,"Significant change","No significant change") -> No significant change
A54: Total assets turnover | B54: =AVERAGE(Q70:Q78) -> 1.8397683 | C54: =AVERAGE(R70:R78) -> 1.7282519 | D54: =AVERAGE(S70:S78) -> -0.11151641 | E54: =STDEV(S70:S78) -> 0.5479955 | F54: =COUNT(S70:S78) -> 9 | G54: =IF(E54>0,D54/(E54/SQRT(F54)),"N/M") -> -0.61049631 | H54: =F54-1 -> 8 | I54: =TTEST(Q70:Q78,R70:R78,2,1) -> 0.55847358 | J54: =IF(I54<0.05,"Significant change","No significant change") -> No significant change
A55: Average collection period (days) | B55: =AVERAGE(T70:T78) -> 63.748754 | C55: =AVERAGE(U70:U78) -> 68.81538 | D55: =AVERAGE(V70:V78) -> 5.0666251 | E55: =STDEV(V70:V78) -> 18.018605 | F55: =COUNT(V70:V78) -> 9 | G55: =IF(E55>0,D55/(E55/SQRT(F55)),"N/M") -> 0.84356562 | H55: =F55-1 -> 8 | I55: =TTEST(T70:T78,U70:U78,2,1) -> 0.42341632 | J55: =IF(I55<0.05,"Significant change","No significant change") -> No significant change
A56: Debt-equity | B56: =AVERAGE(W70:W78) -> 0.86498085 | C56: =AVERAGE(X70:X78) -> 0.51679178 | D56: =AVERAGE(Y70:Y78) -> -0.34818907 | E56: =STDEV(Y70:Y78) -> 0.5460735 | F56: =COUNT(Y70:Y78) -> 9 | G56: =IF(E56>0,D56/(E56/SQRT(F56)),"N/M") -> -1.9128693 | H56: =F56-1 -> 8 | I56: =TTEST(W70:W78,X70:X78,2,1) -> 0.092122863 | J56: =IF(I56<0.05,"Significant change","No significant change") -> No significant change
A57: Interest coverage | B57: =AVERAGE(Z70:Z78) -> 4.2099283 | C57: =AVERAGE(AA70:AA78) -> 7.9072676 | D57: =AVERAGE(AB70:AB78) -> 3.6973393 | E57: =STDEV(AB70:AB78) -> 9.1229487 | F57: =COUNT(AB70:AB78) -> 9 | G57: =IF(E57>0,D57/(E57/SQRT(F57)),"N/M") -> 1.2158369 | H57: =F57-1 -> 8 | I57: =TTEST(Z70:Z78,AA70:AA78,2,1) -> 0.25870389 | J57: =IF(I57<0.05,"Significant change","No significant change") -> No significant change
A58: Current ratio | B58: =AVERAGE(AC70:AC78) -> 3.2865311 | C58: =AVERAGE(AD70:AD78) -> 3.1463133 | D58: =AVERAGE(AE70:AE78) -> -0.14021777 | E58: =STDEV(AE70:AE78) -> 1.4356317 | F58: =COUNT(AE70:AE78) -> 9 | G58: =IF(E58>0,D58/(E58/SQRT(F58)),"N/M") -> -0.2930092 | H58: =F58-1 -> 8 | I58: =TTEST(AC70:AC78,AD70:AD78,2,1) -> 0.77697166 | J58: =IF(I58<0.05,"Significant change","No significant change") -> No significant change
A60: Interpretation notes:
A61: - With only 9 firms the tests have low power: a "no significant change" result does not prove the ratios were stable.
A62: - Allcargo demerged its international business on 1-Nov-2025, so its FY2026 figures are on a much smaller post-demerger perimeter than FY2020; its differences reflect restructuring as well as performance.
A63: - The t-statistic = mean difference / (SD of differences / sqrt(n)); the p-value comes from Excel's paired TTEST.
A68: Paired-test data (linked to the company sheets): FY2020, FY2026 and difference (FY2026 - FY2020)
A69: Firm | B69: Operating EBITDA margin FY20 | C69: Operating EBITDA margin FY26 | D69: Operating EBITDA margin diff | E69: Operating profit (EBIT) margin FY20 | F69: Operating profit (EBIT) margin FY26 | G69: Operating profit (EBIT) margin diff | H69: Net profit margin FY20 | I69: Net profit margin FY26 | J69: Net profit margin diff | K69: Return on assets FY20 | L69: Return on assets FY26 | M69: Return on assets diff | N69: ROCE (post-tax) FY20 | O69: ROCE (post-tax) FY26 | P69: ROCE (post-tax) diff | Q69: Total assets turnover FY20 | R69: Total assets turnover FY26 | S69: Total assets turnover diff | T69: Average collection period (days) FY20 | U69: Average collection period (days) FY26 | V69: Average collection period (days) diff | W69: Debt-equity FY20 | X69: Debt-equity FY26 | Y69: Debt-equity diff | Z69: Interest coverage FY20 | AA69: Interest coverage FY26 | AB69: Interest coverage diff | AC69: Current ratio FY20 | AD69: Current ratio FY26 | AE69: Current ratio diff
A70: Tiger | B70: =Tiger!D130 -> -0.027829375 | C70: =Tiger!J130 -> 0.047152683 | D70: =C70-B70 -> 0.074982058 | E70: =Tiger!D131 -> -0.031080005 | F70: =Tiger!J131 -> 0.045476764 | G70: =F70-E70 -> 0.076556769 | H70: =Tiger!D133 -> -0.040931405 | I70: =Tiger!J133 -> 0.037568521 | J70: =I70-H70 -> 0.078499926 | K70: =Tiger!D142 -> -0.11740082 | L70: =Tiger!J142 -> 0.081943492 | M70: =L70-K70 -> 0.19934431 | N70: =Tiger!D146 -> -0.10484503 | O70: =Tiger!J146 -> 0.091356384 | P70: =O70-N70 -> 0.19620141 | Q70: =Tiger!D124 -> 2.8682333 | R70: =Tiger!J124 -> 2.1811743 | S70: =R70-Q70 -> -0.68705896 | T70: =Tiger!D119 -> 79.324665 | U70: =Tiger!J119 -> 102.60806 | V70: =U70-T70 -> 23.283397 | W70: =Tiger!D101 -> 0.69582543 | X70: =Tiger!J101 -> 0.31691461 | Y70: =X70-W70 -> -0.37891081 | Z70: =Tiger!D109 -> -2.1103604 | AA70: =Tiger!J109 -> 4.943074 | AB70: =AA70-Z70 -> 7.0534344 | AC70: =Tiger!D95 -> 6.047014 | AD70: =Tiger!J95 -> 4.6170581 | AE70: =AD70-AC70 -> -1.4299558
A71: Allcargo | B71: =Allcargo!D130 -> 0.070124308 | C71: =Allcargo!J130 -> 0.11418853 | D71: =C71-B71 -> 0.044064224 | E71: =Allcargo!D131 -> 0.038597977 | F71: =Allcargo!J131 -> 0.015063168 | G71: =F71-E71 -> -0.023534809 | H71: =Allcargo!D133 -> 0.030355665 | I71: =Allcargo!J133 -> 0.0038872692 | J71: =I71-H71 -> -0.026468396 | K71: =Allcargo!D142 -> 0.042068011 | L71: =Allcargo!J142 -> 0.0046082949 | M71: =L71-K71 -> -0.037459716 | N71: =Allcargo!D146 -> 0.058026997 | O71: =Allcargo!J146 -> 0.024467245 | P71: =O71-N71 -> -0.033559751 | Q71: =Allcargo!D124 -> 1.3858372 | R71: =Allcargo!J124 -> 1.1854839 | S71: =R71-Q71 -> -0.20035336 | T71: =Allcargo!D119 -> 57.142545 | U71: =Allcargo!J119 -> 76.086006 | V71: =U71-T71 -> 18.943461 | W71: =Allcargo!D101 -> 0.747234 | X71: =Allcargo!J101 -> 1.2073171 | Y71: =X71-W71 -> 0.46008307 | Z71: =Allcargo!D109 -> 3.7963583 | AA71: =Allcargo!J109 -> 0.5 | AB71: =AA71-Z71 -> -3.2963583 | AC71: =Allcargo!D95 -> 1.6456859 | AD71: =Allcargo!J95 -> 2.0255864 | AE71: =AD71-AC71 -> 0.37990042
A72: Blue Dart | B72: =BlueDart!D130 -> 0.14947734 | C72: =BlueDart!J130 -> 0.15480843 | D72: =C72-B72 -> 0.0053310871 | E72: =BlueDart!D131 -> 0.040086548 | F72: =BlueDart!J131 -> 0.067513125 | G72: =F72-E72 -> 0.027426578 | H72: =BlueDart!D133 -> -0.013183712 | I72: =BlueDart!J133 -> 0.040285757 | J72: =I72-H72 -> 0.053469469 | K72: =BlueDart!D142 -> -0.015851317 | L72: =BlueDart!J142 -> 0.059946448 | M72: =L72-K72 -> 0.075797765 | N72: =BlueDart!D146 -> 0.12468286 | O72: =BlueDart!J146 -> 0.1075453 | P72: =O72-N72 -> -0.017137554 | Q72: =BlueDart!D124 -> 1.202341 | R72: =BlueDart!J124 -> 1.4880308 | S72: =R72-Q72 -> 0.28568986 | T72: =BlueDart!D119 -> 60.723167 | U72: =BlueDart!J119 -> 54.5787 | V72: =U72-T72 -> -6.1444668 | W72: =BlueDart!D101 -> 1.0798036 | X72: =BlueDart!J101 -> 0.64266137 | Y72: =X72-W72 -> -0.43714223 | Z72: =BlueDart!D109 -> 1.0843415 | AA72: =BlueDart!J109 -> 4.8410789 | AB72: =AA72-Z72 -> 3.7567375 | AC72: =BlueDart!D95 -> 0.59123682 | AD72: =BlueDart!J95 -> 1.3674138 | AE72: =AD72-AC72 -> 0.77617701
A73: CONCOR | B73: =CONCOR!D130 -> 0.25944103 | C73: =CONCOR!J130 -> 0.21492746 | D73: =C73-B73 -> -0.04451357 | E73: =CONCOR!D131 -> 0.17607388 | F73: =CONCOR!J131 -> 0.14713013 | G73: =F73-E73 -> -0.028943758 | H73: =CONCOR!D133 -> 0.061792238 | I73: =CONCOR!J133 -> 0.13677763 | J73: =I73-H73 -> 0.074985392 | K73: =CONCOR!D142 -> 0.034229215 | L73: =CONCOR!J142 -> 0.081827754 | M73: =L73-K73 -> 0.04759854 | N73: =CONCOR!D146 -> 0.084798224 | O73: =CONCOR!J146 -> 0.072484988 | P73: =O73-N73 -> -0.012313236 | Q73: =CONCOR!D124 -> 0.55394036 | R73: =CONCOR!J124 -> 0.59825393 | S73: =R73-Q73 -> 0.044313565 | T73: =CONCOR!D119 -> 9.2017558 | U73: =CONCOR!J119 -> 19.497553 | V73: =U73-T73 -> 10.295797 | W73: =CONCOR!D101 -> 0.0069678781 | X73: =CONCOR!J101 -> 0.074528196 | Y73: =X73-W73 -> 0.067560318 | Z73: =CONCOR!D109 -> 24.759044 | AA73: =CONCOR!J109 -> 17.009933 | AB73: =AA73-Z73 -> -7.7491114 | AC73: =CONCOR!D95 -> 2.5701338 | AD73: =CONCOR!J95 -> 4.7511388 | AE73: =AD73-AC73 -> 2.181005
A74: Jet Freight | B74: =JetFreight!D130 -> -0.011708586 | C74: =JetFreight!J130 -> 0.037313097 | D74: =C74-B74 -> 0.049021683 | E74: =JetFreight!D131 -> -0.015945026 | F74: =JetFreight!J131 -> 0.03301207 | G74: =F74-E74 -> 0.048957096 | H74: =JetFreight!D133 -> -0.028587631 | I74: =JetFreight!J133 -> 0.015312556 | J74: =I74-H74 -> 0.043900187 | K74: =JetFreight!D142 -> -0.097597085 | L74: =JetFreight!J142 -> 0.035035293 | M74: =L74-K74 -> 0.13263238 | N74: =JetFreight!D146 -> -0.087642098 | O74: =JetFreight!J146 -> 0.064940825 | P74: =O74-N74 -> 0.15258292 | Q74: =JetFreight!D124 -> 3.413962 | R74: =JetFreight!J124 -> 2.2880107 | S74: =R74-Q74 -> -1.1259512 | T74: =JetFreight!D119 -> 62.801721 | U74: =JetFreight!J119 -> 79.817037 | V74: =U74-T74 -> 17.015316 | W74: =JetFreight!D101 -> 2.1599073 | X74: =JetFreight!J101 -> 1.0175848 | Y74: =X74-W74 -> -1.1423225 | Z74: =JetFreight!D109 -> -1.0436681 | AA74: =JetFreight!J109 -> 2.0942857 | AB74: =AA74-Z74 -> 3.1379538 | AC74: =JetFreight!D95 -> 2.1770364 | AD74: =JetFreight!J95 -> 3.5881855 | AE74: =AD74-AC74 -> 1.4111491
A75: Patel | B75: =Patel!D130 -> 0.023286607 | C75: =Patel!J130 -> 0.029036232 | D75: =C75-B75 -> 0.0057496257 | E75: =Patel!D131 -> 0.012031893 | F75: =Patel!J131 -> 0.021896175 | G75: =F75-E75 -> 0.009864282 | H75: =Patel!D133 -> 0.030914481 | I75: =Patel!J133 -> 0.026880215 | J75: =I75-H75 -> -0.0040342664 | K75: =Patel!D142 -> 0.052290764 | L75: =Patel!J142 -> 0.058780309 | M75: =L75-K75 -> 0.0064895447 | N75: =Patel!D146 -> 0.019448246 | O75: =Patel!J146 -> 0.056047846 | P75: =O75-N75 -> 0.036599599 | Q75: =Patel!D124 -> 1.691465 | R75: =Patel!J124 -> 2.1867499 | S75: =R75-Q75 -> 0.49528492 | T75: =Patel!D119 -> 93.25408 | U75: =Patel!J119 -> 74.279554 | V75: =U75-T75 -> -18.974526 | W75: =Patel!D101 -> 0.5101235 | X75: =Patel!J101 -> 0.050680052 | Y75: =X75-W75 -> -0.45944345 | Z75: =Patel!D109 -> 0.56562923 | AA75: =Patel!J109 -> 22.342857 | AB75: =AA75-Z75 -> 21.777228 | AC75: =Patel!D95 -> 5.5191108 | AD75: =Patel!J95 -> 3.3649374 | AE75: =AD75-AC75 -> -2.1541734
A76: TCI | B76: =TCI!D130 -> 0.088835252 | C76: =TCI!J130 -> 0.1055571 | D76: =C76-B76 -> 0.016721852 | E76: =TCI!D131 -> 0.058483943 | F76: =TCI!J131 -> 0.079666122 | G76: =F76-E76 -> 0.021182179 | H76: =TCI!D133 -> 0.052379831 | I76: =TCI!J133 -> 0.09279466 | J76: =I76-H76 -> 0.040414829 | K76: =TCI!D142 -> 0.084570967 | L76: =TCI!J142 -> 0.13103629 | M76: =L76-K76 -> 0.046465318 | N76: =TCI!D146 -> 0.098929422 | O76: =TCI!J146 -> 0.12518854 | P76: =O76-N76 -> 0.026259115 | Q76: =TCI!D124 -> 1.6145712 | R76: =TCI!J124 -> 1.4121102 | S76: =R76-Q76 -> -0.20246101 | T76: =TCI!D119 -> 65.44333 | U76: =TCI!J119 -> 60.603079 | V76: =U76-T76 -> -4.8402511 | W76: =TCI!D101 -> 0.41220248 | X76: =TCI!J101 -> 0.12174638 | Y76: =X76-W76 -> -0.2904561 | Z76: =TCI!D109 -> 4.6314103 | AA76: =TCI!J109 -> 17.187363 | AB76: =AA76-Z76 -> 12.555953 | AC76: =TCI!D95 -> 3.1791642 | AD76: =TCI!J95 -> 2.4182809 | AE76: =AD76-AC76 -> -0.76088327
A77: Shreeji | B77: =Shreeji!D130 -> 0.082272727 | C77: =Shreeji!J130 -> 0.033078663 | D77: =C77-B77 -> -0.049194064 | E77: =Shreeji!D131 -> 0.044363636 | F77: =Shreeji!J131 -> 0.016005805 | G77: =F77-E77 -> -0.028357832 | H77: =Shreeji!D133 -> 0.013363636 | I77: =Shreeji!J133 -> 0.013487558 | J77: =I77-H77 -> 0.00012392179 | K77: =Shreeji!D142 -> 0.01852552 | L77: =Shreeji!J142 -> 0.02643909 | M77: =L77-K77 -> 0.0079135698 | N77: =Shreeji!D146 -> 0.046068484 | O77: =Shreeji!J146 -> 0.033226709 | P77: =O77-N77 -> -0.012841775 | Q77: =Shreeji!D124 -> 1.3862634 | R77: =Shreeji!J124 -> 1.9602577 | S77: =R77-Q77 -> 0.57399431 | T77: =Shreeji!D119 -> 89.524545 | U77: =Shreeji!J119 -> 115.90764 | V77: =U77-T77 -> 26.38309 | W77: =Shreeji!D101 -> 1.8031683 | X77: =Shreeji!J101 -> 0.66661121 | Y77: =X77-W77 -> -1.1365571 | Z77: =Shreeji!D109 -> 1.3824363 | AA77: =Shreeji!J109 -> 0.90144231 | AB77: =AA77-Z77 -> -0.48099395 | AC77: =Shreeji!D95 -> 6.1143524 | AD77: =Shreeji!J95 -> 4.7719752 | AE77: =AD77-AC77 -> -1.3423772
A78: Mahindra Log. | B78: =MahindraLog!D130 -> 0.04565647 | C78: =MahindraLog!J130 -> 0.054119698 | D78: =C78-B78 -> 0.0084632275 | E78: =MahindraLog!D131 -> 0.024502037 | F78: =MahindraLog!J131 -> 0.014420013 | G78: =F78-E78 -> -0.010082023 | H78: =MahindraLog!D133 -> 0.015879509 | I78: =MahindraLog!J133 -> 0.00032717557 | J78: =I78-H78 -> -0.015552334 | K78: =MahindraLog!D142 -> 0.038766669 | L78: =MahindraLog!J142 -> 0.00073751775 | M78: =L78-K78 -> -0.038029151 | N78: =MahindraLog!D146 -> 0.077868823 | O78: =MahindraLog!J146 -> 0.03598791 | P78: =O78-N78 -> -0.041880913 | Q78: =MahindraLog!D124 -> 2.4413014 | R78: =MahindraLog!J124 -> 2.2541956 | S78: =R78-Q78 -> -0.18710577 | T78: =MahindraLog!D119 -> 56.32298 | U78: =MahindraLog!J119 -> 35.960789 | V78: =U78-T78 -> -20.362191 | W78: =MahindraLog!D101 -> 0.36959515 | X78: =MahindraLog!J101 -> 0.55308228 | Y78: =X78-W78 -> 0.18348713 | Z78: =MahindraLog!D109 -> 4.8241634 | AA78: =MahindraLog!J109 -> 1.3453746 | AB78: =AA78-Z78 -> -3.4787888 | AC78: =MahindraLog!D95 -> 1.7350456 | AD78: =MahindraLog!J95 -> 1.4122438 | AE78: =AD78-AC78 -> -0.3228018
A80: D. GROWTH AND STABILITY BY FIRM, FY2020-FY2026
A81: Firm | B81: Sales FY2020 (Rs cr) | C81: Sales FY2026 (Rs cr) | D81: Sales CAGR FY20-26 | E81: ROCE 7-yr mean | F81: ROCE std. dev. | G81: ROCE coeff. of variation | H81: Op. EBITDA margin 7-yr mean | I81: Op. EBITDA margin std. dev. | J81: Debt-equity 7-yr mean | K81: Loss-making years (of 7)
A82: Tiger | B82: =Tiger!D7 -> 301.48 | C82: =Tiger!J7 -> 572.82 | D82: =(C82/B82)^(1/6)-1 -> 0.11290974 | E82: =Tiger!K146 -> 0.094712109 | F82: =STDEV(Tiger!D146:J146) -> 0.20437839 | G82: =IF(ABS(E82)>0,F82/ABS(E82),"N/M") -> 2.1578908 | H82: =Tiger!K130 -> 0.029629489 | I82: =STDEV(Tiger!D130:J130) -> 0.050035937 | J82: =Tiger!K101 -> 0.24661787 | K82: =COUNTIF(Tiger!D30:J30,"<0") -> 2
A83: Allcargo | B83: =Allcargo!D7 -> 7346.24 | C83: =Allcargo!J7 -> 2058 | D83: =(C83/B83)^(1/6)-1 -> -0.19109651 | E83: =Allcargo!K146 -> 0.067070152 | F83: =STDEV(Allcargo!D146:J146) -> 0.061725631 | G83: =IF(ABS(E83)>0,F83/ABS(E83),"N/M") -> 0.92031446 | H83: =Allcargo!K130 -> 0.073607981 | I83: =STDEV(Allcargo!D130:J130) -> 0.026514119 | J83: =Allcargo!K101 -> 0.87612163 | K83: =COUNTIF(Allcargo!D30:J30,"<0") -> 0
A84: Blue Dart | B84: =BlueDart!D7 -> 3175.13 | C84: =BlueDart!J7 -> 6140.88 | D84: =(C84/B84)^(1/6)-1 -> 0.11620728 | E84: =BlueDart!K146 -> 0.13833211 | F84: =STDEV(BlueDart!D146:J146) -> 0.049160543 | G84: =IF(ABS(E84)>0,F84/ABS(E84),"N/M") -> 0.35538055 | H84: =BlueDart!K130 -> 0.17658992 | I84: =STDEV(BlueDart!D130:J130) -> 0.030388731 | J84: =BlueDart!K101 -> 1.1280755 | K84: =COUNTIF(BlueDart!D30:J30,"<0") -> 1
A85: CONCOR | B85: =CONCOR!D7 -> 6530.27 | C85: =CONCOR!J7 -> 9078.97 | D85: =(C85/B85)^(1/6)-1 -> 0.056454767 | E85: =CONCOR!K146 -> 0.072251715 | F85: =STDEV(CONCOR!D146:J146) -> 0.017440952 | G85: =IF(ABS(E85)>0,F85/ABS(E85),"N/M") -> 0.24139153 | H85: =CONCOR!K130 -> 0.21971019 | I85: =STDEV(CONCOR!D130:J130) -> 0.02894977 | J85: =CONCOR!K101 -> 0.062736366 | K85: =COUNTIF(CONCOR!D30:J30,"<0") -> 0
A86: Jet Freight | B86: =JetFreight!D7 -> 299.78 | C86: =JetFreight!J7 -> 444.08 | D86: =(C86/B86)^(1/6)-1 -> 0.067684882 | E86: =JetFreight!K146 -> 0.036616476 | F86: =STDEV(JetFreight!D146:J146) -> 0.058895913 | G86: =IF(ABS(E86)>0,F86/ABS(E86),"N/M") -> 1.6084539 | H86: =JetFreight!K130 -> 0.020453399 | I86: =STDEV(JetFreight!D130:J130) -> 0.016060838 | J86: =JetFreight!K101 -> 1.3550845 | K86: =COUNTIF(JetFreight!D30:J30,"<0") -> 1
A87: Patel | B87: =Patel!D7 -> 347.41 | C87: =Patel!J7 -> 357.14 | D87: =(C87/B87)^(1/6)-1 -> 0.0046143172 | E87: =Patel!K146 -> 0.036368505 | F87: =STDEV(Patel!D146:J146) -> 0.016793735 | G87: =IF(ABS(E87)>0,F87/ABS(E87),"N/M") -> 0.46176588 | H87: =Patel!K130 -> 0.0290875 | I87: =STDEV(Patel!D130:J130) -> 0.0050050193 | J87: =Patel!K101 -> 0.29634174 | K87: =COUNTIF(Patel!D30:J30,"<0") -> 0
A88: Sical | B88: =Sical!D7 -> 1005.84 | C88: =Sical!J7 -> 385.68 | D88: =(C88/B88)^(1/6)-1 -> -0.14765313 | E88: =Sical!K146 -> -0.061079075 | F88: =STDEV(Sical!D146:J146) -> 0.066361373 | G88: =IF(ABS(E88)>0,F88/ABS(E88),"N/M") -> 1.0864829 | H88: =Sical!K130 -> 0.041720612 | I88: =STDEV(Sical!D130:J130) -> 0.10204413 | J88: =Sical!K101 -> 8.2478837 | K88: =COUNTIF(Sical!D30:J30,"<0") -> 6
A89: TCI | B89: =TCI!D7 -> 2717.84 | C89: =TCI!J7 -> 4916.77 | D89: =(C89/B89)^(1/6)-1 -> 0.10384815 | E89: =TCI!K146 -> 0.12781958 | F89: =STDEV(TCI!D146:J146) -> 0.026645348 | G89: =IF(ABS(E89)>0,F89/ABS(E89),"N/M") -> 0.20846061 | H89: =TCI!K130 -> 0.10460636 | I89: =STDEV(TCI!D130:J130) -> 0.01230961 | J89: =TCI!K101 -> 0.15977623 | K89: =COUNTIF(TCI!D30:J30,"<0") -> 0
A90: Shreeji | B90: =Shreeji!D7 -> 110 | C90: =Shreeji!J7 -> 234.29 | D90: =(C90/B90)^(1/6)-1 -> 0.13429716 | E90: =Shreeji!K146 -> 0.07357899 | F90: =STDEV(Shreeji!D146:J146) -> 0.04695316 | G90: =IF(ABS(E90)>0,F90/ABS(E90),"N/M") -> 0.63813271 | H90: =Shreeji!K130 -> 0.072103023 | I90: =STDEV(Shreeji!D130:J130) -> 0.027826194 | J90: =Shreeji!K101 -> 1.2179689 | K90: =COUNTIF(Shreeji!D30:J30,"<0") -> 1
A91: Mahindra Log. | B91: =MahindraLog!D7 -> 3471.14 | C91: =MahindraLog!J7 -> 6999.3 | D91: =(C91/B91)^(1/6)-1 -> 0.12399336 | E91: =MahindraLog!K146 -> 0.040818271 | F91: =STDEV(MahindraLog!D146:J146) -> 0.018539673 | G91: =IF(ABS(E91)>0,F91/ABS(E91),"N/M") -> 0.45420035 | H91: =MahindraLog!K130 -> 0.046407247 | I91: =STDEV(MahindraLog!D130:J130) -> 0.0046180092 | J91: =MahindraLog!K101 -> 1.0148062 | K91: =COUNTIF(MahindraLog!D30:J30,"<0") -> 2
A92: Industry (aggregate) | B92: =Industry!D7 -> 25305.13 | C92: =Industry!J7 -> 31187.93 | D92: =(C92/B92)^(1/6)-1 -> 0.035451265 | E92: =Industry!K147 -> 0.07527092 | F92: =STDEV(Industry!D147:J147) -> 0.021318347 | G92: =IF(ABS(E92)>0,F92/ABS(E92),"N/M") -> 0.28322155 | H92: =Industry!K131 -> 0.11740644 | I92: =STDEV(Industry!D131:J131) -> 0.012743653 | J92: =Industry!K102 -> 0.30963722 | K92: =COUNTIF(Industry!D30:J30,"<0") -> 1
A94: CAGR = (Sales FY2026 / Sales FY2020)^(1/6) - 1. Allcargo's negative CAGR reflects the 2025 restructuring (FY2025-FY2026 are on the post-demerger perimeter). Sical's debt-equity mean covers only its positive net-worth years.

Sheet Panel
A1: Firm | B1: FY | C1: Sales (Rs cr) | D1: Total assets (Rs cr) | E1: Asset intensity (Net block / Total assets) | F1: Current ratio | G1: Quick ratio | H1: Debt-equity | I1: Interest coverage | J1: Collection period (days) | K1: Total assets turnover | L1: Operating EBITDA margin | M1: Operating profit (EBIT) margin | N1: Net profit margin | O1: ROA | P1: ROCE (post-tax) | Q1: ROE | R1: P/E | S1: P/B | T1: EV / EBITDA
A2: Tiger | B2: 2020 | C2: =Tiger!D7 -> 301.48 | D2: =Tiger!D49 -> 105.11 | E2: =Tiger!D45/Tiger!D49 -> 0.091713443 | F2: =Tiger!D95 -> 6.047014 | G2: =Tiger!D96 -> 4.5463787 | H2: =Tiger!D101 -> 0.69582543 | I2: =Tiger!D109 -> -2.1103604 | J2: =Tiger!D119 -> 79.324665 | K2: =Tiger!D124 -> 2.8682333 | L2: =Tiger!D130 -> -0.027829375 | M2: =Tiger!D131 -> -0.031080005 | N2: =Tiger!D133 -> -0.040931405 | O2: =Tiger!D142 -> -0.11740082 | P2: =Tiger!D146 -> -0.10484503 | Q2: =Tiger!D147 -> -0.2341556 | R2: =Tiger!D158 -> N/M | S2: =Tiger!D159 -> 0.59970209 | T2: =Tiger!D160 -> N/M
A3: Tiger | B3: 2021 | C3: =Tiger!E7 -> 167.87 | D3: =Tiger!E49 -> 83.85 | E3: =Tiger!E45/Tiger!E49 -> 0.10280262 | F3: =Tiger!E95 -> 2.7896693 | G3: =Tiger!E96 -> 1.8784838 | H3: =Tiger!E101 -> 0.35636017 | I3: =Tiger!E109 -> -5.2959184 | J3: =Tiger!E119 -> 93.864598 | K3: =Tiger!E124 -> 2.0020274 | L3: =Tiger!E130 -> -0.05653184 | M3: =Tiger!E131 -> -0.061833562 | N3: =Tiger!E133 -> -0.073985822 | O3: =Tiger!E142 -> -0.14812165 | P3: =Tiger!E146 -> -0.18229715 | Q3: =Tiger!E147 -> -0.29585517 | R3: =Tiger!E158 -> N/M | S3: =Tiger!E159 -> 1.067575 | T3: =Tiger!E160 -> N/M
A4: Tiger | B4: 2022 | C4: =Tiger!F7 -> 615.11 | D4: =Tiger!F49 -> 121.25 | E4: =Tiger!F45/Tiger!F49 -> 0.064742268 | F4: =Tiger!F95 -> 2.310551 | G4: =Tiger!F96 -> 2.1405382 | H4: =Tiger!F101 -> 0 | I4: =Tiger!F109 -> 24.370861 | J4: =Tiger!F119 -> 40.742144 | K4: =Tiger!F124 -> 5.0730722 | L4: =Tiger!F130 -> 0.061127278 | M4: =Tiger!F131 -> 0.059826698 | N4: =Tiger!F133 -> 0.054673148 | O4: =Tiger!F142 -> 0.27736082 | P4: =Tiger!F146 -> 0.44482314 | Q4: =Tiger!F147 -> 0.45183394 | R4: =Tiger!F158 -> 6.6380731 | S4: =Tiger!F159 -> 2.9993067 | T4: =Tiger!F160 -> 5.0978298
A5: Tiger | B5: 2023 | C5: =Tiger!G7 -> 433.35 | D5: =Tiger!G49 -> 119.51 | E5: =Tiger!G45/Tiger!G49 -> 0.06283993 | F5: =Tiger!G95 -> 4.8683729 | G5: =Tiger!G96 -> 4.6480804 | H5: =Tiger!G101 -> 0 | I5: =Tiger!G109 -> 24.912621 | J5: =Tiger!G119 -> 41.524172 | K5: =Tiger!G124 -> 3.6260564 | L5: =Tiger!G130 -> 0.061013038 | M5: =Tiger!G131 -> 0.059213107 | N5: =Tiger!G133 -> 0.053559478 | O5: =Tiger!G142 -> 0.19420969 | P5: =Tiger!G146 -> 0.19464781 | Q5: =Tiger!G147 -> 0.2377343 | R5: =Tiger!G158 -> 16.544942 | S5: =Tiger!G159 -> 3.9333002 | T5: =Tiger!G160 -> 12.54191
A6: Tiger | B6: 2024 | C6: =Tiger!H7 -> 240.26 | D6: =Tiger!H49 -> 143.58 | E6: =Tiger!H45/Tiger!H49 -> 0.063031063 | F6: =Tiger!H95 -> 5.9541284 | G6: =Tiger!H96 -> 5.385804 | H6: =Tiger!H101 -> 0.10863485 | I6: =Tiger!H109 -> 19.171053 | J6: =Tiger!H119 -> 106.0241 | K6: =Tiger!H124 -> 1.6733528 | L6: =Tiger!H130 -> 0.06388912 | M6: =Tiger!H131 -> 0.060642637 | N6: =Tiger!H133 -> 0.053941563 | O6: =Tiger!H142 -> 0.090263268 | P6: =Tiger!H146 -> 0.086807176 | Q6: =Tiger!H147 -> 0.11693585 | R6: =Tiger!H158 -> 37.516975 | S6: =Tiger!H159 -> 4.3870793 | T6: =Tiger!H160 -> 29.740065
A7: Tiger | B7: 2025 | C7: =Tiger!I7 -> 536.31 | D7: =Tiger!I49 -> 195.69 | E7: =Tiger!I45/Tiger!I49 -> 0.045428995 | F7: =Tiger!I95 -> 7.5958279 | G7: =Tiger!I96 -> 6.6857888 | H7: =Tiger!I101 -> 0.24859002 | I7: =Tiger!I109 -> 9.1253731 | J7: =Tiger!I119 -> 69.881598 | K7: =Tiger!I124 -> 2.7406101 | L7: =Tiger!I130 -> 0.05858552 | M7: =Tiger!I131 -> 0.057000615 | N7: =Tiger!I133 -> 0.050362663 | O7: =Tiger!I142 -> 0.13802443 | P7: =Tiger!I146 -> 0.13249244 | Q7: =Tiger!I147 -> 0.19530007 | R7: =Tiger!I158 -> 18.588486 | S7: =Tiger!I159 -> 3.6303326 | T7: =Tiger!I160 -> 15.445417
A8: Tiger | B8: 2026 | C8: =Tiger!J7 -> 572.82 | D8: =Tiger!J49 -> 262.62 | E8: =Tiger!J45/Tiger!J49 -> 0.03739243 | F8: =Tiger!J95 -> 4.6170581 | G8: =Tiger!J96 -> 3.8983442 | H8: =Tiger!J101 -> 0.31691461 | I8: =Tiger!J109 -> 4.943074 | J8: =Tiger!J119 -> 102.60806 | K8: =Tiger!J124 -> 2.1811743 | L8: =Tiger!J130 -> 0.047152683 | M8: =Tiger!J131 -> 0.045476764 | N8: =Tiger!J133 -> 0.037568521 | O8: =Tiger!J142 -> 0.081943492 | P8: =Tiger!J146 -> 0.091356384 | Q8: =Tiger!J147 -> 0.13451681 | R8: =Tiger!J158 -> 11.738987 | S8: =Tiger!J159 -> 1.5790911 | T8: =Tiger!J160 -> 9.6954091
A9: Allcargo | B9: 2020 | C9: =Allcargo!D7 -> 7346.24 | D9: =Allcargo!D49 -> 5300.94 | E9: =Allcargo!D45/Allcargo!D49 -> 0.37125302 | F9: =Allcargo!D95 -> 1.6456859 | G9: =Allcargo!D96 -> 1.1198466 | H9: =Allcargo!D101 -> 0.747234 | I9: =Allcargo!D109 -> 3.7963583 | J9: =Allcargo!D119 -> 57.142545 | K9: =Allcargo!D124 -> 1.3858372 | L9: =Allcargo!D130 -> 0.070124308 | M9: =Allcargo!D131 -> 0.038597977 | N9: =Allcargo!D133 -> 0.030355665 | O9: =Allcargo!D142 -> 0.042068011 | P9: =Allcargo!D146 -> 0.058026997 | Q9: =Allcargo!D147 -> 0.10392879 | R9: =Allcargo!D158 -> N/C | S9: =Allcargo!D159 -> N/C | T9: =Allcargo!D160 -> N/C
A10: Allcargo | B10: 2021 | C10: =Allcargo!E7 -> 10498.1 | D10: =Allcargo!E49 -> 7313.27 | E10: =Allcargo!E45/Allcargo!E49 -> 0.43271478 | F10: =Allcargo!E95 -> 1.2893373 | G10: =Allcargo!E96 -> 0.86255381 | H10: =Allcargo!E101 -> 0.90445974 | I10: =Allcargo!E109 -> 2.3525305 | J10: =Allcargo!E119 -> 75.645164 | K10: =Allcargo!E124 -> 1.4354865 | L10: =Allcargo!E130 -> 0.061257751 | M10: =Allcargo!E131 -> 0.032101047 | N10: =Allcargo!E133 -> 0.016469647 | O10: =Allcargo!E142 -> 0.023641955 | P10: =Allcargo!E146 -> 0.050412338 | Q10: =Allcargo!E147 -> 0.075715775 | R10: =Allcargo!E158 -> N/C | S10: =Allcargo!E159 -> N/C | T10: =Allcargo!E160 -> N/C
A11: Allcargo | B11: 2022 | C11: =Allcargo!F7 -> 19062.06 | D11: =Allcargo!F49 -> 9604 | E11: =Allcargo!F45/Allcargo!F49 -> 0.36357351 | F11: =Allcargo!F95 -> 1.3437125 | G11: =Allcargo!F96 -> 0.90198137 | H11: =Allcargo!F101 -> 0.73291774 | I11: =Allcargo!F109 -> 10.848041 | J11: =Allcargo!F119 -> 58.904174 | K11: =Allcargo!F124 -> 1.9848042 | L11: =Allcargo!F130 -> 0.067215191 | M11: =Allcargo!F131 -> 0.054752215 | N11: =Allcargo!F133 -> 0.048563482 | O11: =Allcargo!F142 -> 0.096389005 | P11: =Allcargo!F146 -> 0.15040936 | Q11: =Allcargo!F147 -> 0.2927863 | R11: =Allcargo!F158 -> N/C | S11: =Allcargo!F159 -> N/C | T11: =Allcargo!F160 -> N/C
A12: Allcargo | B12: 2023 | C12: =Allcargo!G7 -> 18050.77 | D12: =Allcargo!G49 -> 7230.85 | E12: =Allcargo!G45/Allcargo!G49 -> 0.29483117 | F12: =Allcargo!G95 -> 1.3908215 | G12: =Allcargo!G96 -> 1.0338819 | H12: =Allcargo!G101 -> 0.41912146 | I12: =Allcargo!G109 -> 10.075844 | J12: =Allcargo!G119 -> 41.210887 | K12: =Allcargo!G124 -> 2.4963552 | L12: =Allcargo!G130 -> 0.06316628 | M12: =Allcargo!G131 -> 0.047764721 | N12: =Allcargo!G133 -> 0.034878845 | O12: =Allcargo!G142 -> 0.087069985 | P12: =Allcargo!G146 -> 0.1575035 | Q12: =Allcargo!G147 -> 0.22371741 | R12: =Allcargo!G158 -> N/C | S12: =Allcargo!G159 -> N/C | T12: =Allcargo!G160 -> N/C
A13: Allcargo | B13: 2024 | C13: =Allcargo!H7 -> 12968.68 | D13: =Allcargo!H49 -> 7163.48 | E13: =Allcargo!H45/Allcargo!H49 -> 0.39566663 | F13: =Allcargo!H95 -> 1.4445132 | G13: =Allcargo!H96 -> 0.99669494 | H13: =Allcargo!H101 -> 0.73212168 | I13: =Allcargo!H109 -> 0.50652143 | J13: =Allcargo!H119 -> 62.697453 | K13: =Allcargo!H124 -> 1.8103882 | L13: =Allcargo!H130 -> 0.036295136 | M13: =Allcargo!H131 -> 0.0054500535 | N13: =Allcargo!H133 -> 0.011543195 | O13: =Allcargo!H142 -> 0.020897664 | P13: =Allcargo!H146 -> 0.013779599 | Q13: =Allcargo!H147 -> 0.059366362 | R13: =Allcargo!H158 -> N/C | S13: =Allcargo!H159 -> N/C | T13: =Allcargo!H160 -> N/C
A14: Allcargo | B14: 2025 | C14: =Allcargo!I7 -> 1961 | D14: =Allcargo!I49 -> 1741 | E14: =Allcargo!I45/Allcargo!I49 -> 0.43595635 | F14: =Allcargo!I95 -> 2.4522613 | G14: =Allcargo!I96 -> 1.3366834 | H14: =Allcargo!I101 -> 1.3896797 | I14: =Allcargo!I109 -> 0.26666667 | J14: =Allcargo!I119 -> 69.798572 | K14: =Allcargo!I124 -> 1.1263642 | L14: =Allcargo!I130 -> 0.10300867 | M14: =Allcargo!I131 -> 0.010198878 | N14: =Allcargo!I133 -> 0.033146354 | O14: =Allcargo!I142 -> 0.037334865 | P14: =Allcargo!I146 -> 0.014892033 | Q14: =Allcargo!I147 -> 0.11565836 | R14: =Allcargo!I158 -> N/C | S14: =Allcargo!I159 -> N/C | T14: =Allcargo!I160 -> N/C
A15: Allcargo | B15: 2026 | C15: =Allcargo!J7 -> 2058 | D15: =Allcargo!J49 -> 1736 | E15: =Allcargo!J45/Allcargo!J49 -> 0.45103687 | F15: =Allcargo!J95 -> 2.0255864 | G15: =Allcargo!J96 -> 1.1940299 | H15: =Allcargo!J101 -> 1.2073171 | I15: =Allcargo!J109 -> 0.5 | J15: =Allcargo!J119 -> 76.086006 | K15: =Allcargo!J124 -> 1.1854839 | L15: =Allcargo!J130 -> 0.11418853 | M15: =Allcargo!J131 -> 0.015063168 | N15: =Allcargo!J133 -> 0.0038872692 | O15: =Allcargo!J142 -> 0.0046082949 | P15: =Allcargo!J146 -> 0.024467245 | Q15: =Allcargo!J147 -> 0.013937282 | R15: =Allcargo!J158 -> 134.42755 | S15: =Allcargo!J159 -> 1.8735547 | T15: =Allcargo!J160 -> 6.9677464
A16: Blue Dart | B16: 2020 | C16: =BlueDart!D7 -> 3175.13 | D16: =BlueDart!D49 -> 2640.79 | E16: =BlueDart!D45/BlueDart!D49 -> 0.63048557 | F16: =BlueDart!D95 -> 0.59123682 | G16: =BlueDart!D96 -> 0.38780587 | H16: =BlueDart!D101 -> 1.0798036 | I16: =BlueDart!D109 -> 1.0843415 | J16: =BlueDart!D119 -> 60.723167 | K16: =BlueDart!D124 -> 1.202341 | L16: =BlueDart!D130 -> 0.14947734 | M16: =BlueDart!D131 -> 0.040086548 | N16: =BlueDart!D133 -> -0.013183712 | O16: =BlueDart!D142 -> -0.015851317 | P16: =BlueDart!D146 -> 0.12468286 | Q16: =BlueDart!D147 -> -0.085284111 | R16: =BlueDart!D158 -> N/M | S16: =BlueDart!D159 -> 10.618235 | T16: =BlueDart!D160 -> 11.887125
A17: Blue Dart | B17: 2021 | C17: =BlueDart!E7 -> 3288.13 | D17: =BlueDart!E49 -> 2897.43 | E17: =BlueDart!E45/BlueDart!E49 -> 0.54640837 | F17: =BlueDart!E95 -> 1.4776847 | G17: =BlueDart!E96 -> 1.057601 | H17: =BlueDart!E101 -> 2.5713731 | I17: =BlueDart!E109 -> 2.3099594 | J17: =BlueDart!E119 -> 57.491887 | K17: =BlueDart!E124 -> 1.1348436 | L17: =BlueDart!E130 -> 0.20871742 | M17: =BlueDart!E131 -> 0.077943999 | N17: =BlueDart!E133 -> 0.030962888 | O17: =BlueDart!E142 -> 0.035138036 | P17: =BlueDart!E146 -> 0.088291402 | Q17: =BlueDart!E147 -> 0.17198797 | R17: =BlueDart!E158 -> 129.76338 | S17: =BlueDart!E159 -> 22.31774 | T17: =BlueDart!E160 -> 21.015663
A18: Blue Dart | B18: 2022 | C18: =BlueDart!F7 -> 4410.49 | D18: =BlueDart!F49 -> 2828.76 | E18: =BlueDart!F45/BlueDart!F49 -> 0.50795048 | F18: =BlueDart!F95 -> 1.2520571 | G18: =BlueDart!F96 -> 0.85800882 | H18: =BlueDart!F101 -> 1.2224223 | I18: =BlueDart!F109 -> 6.9522824 | J18: =BlueDart!F119 -> 48.000029 | K18: =BlueDart!F124 -> 1.5591602 | L18: =BlueDart!F130 -> 0.22673444 | M18: =BlueDart!F131 -> 0.13709134 | N18: =BlueDart!F133 -> 0.086659305 | O18: =BlueDart!F142 -> 0.13511574 | P18: =BlueDart!F146 -> 0.23277962 | Q18: =BlueDart!F147 -> 0.43831925 | R18: =BlueDart!F158 -> 42.5513 | S18: =BlueDart!F159 -> 18.651054 | T18: =BlueDart!F160 -> 17.144971
A19: Blue Dart | B19: 2023 | C19: =BlueDart!G7 -> 5172.22 | D19: =BlueDart!G49 -> 3223.04 | E19: =BlueDart!G45/BlueDart!G49 -> 0.44586167 | F19: =BlueDart!G95 -> 1.2738644 | G19: =BlueDart!G96 -> 0.792969 | H19: =BlueDart!G101 -> 0.94962528 | I19: =BlueDart!G109 -> 8.1246073 | J19: =BlueDart!G119 -> 44.928657 | K19: =BlueDart!G124 -> 1.6047644 | L19: =BlueDart!G130 -> 0.18127806 | M19: =BlueDart!G131 -> 0.10500907 | N19: =BlueDart!G133 -> 0.071638484 | O19: =BlueDart!G142 -> 0.11496289 | P19: =BlueDart!G146 -> 0.17219531 | Q19: =BlueDart!G147 -> 0.31412561 | R19: =BlueDart!G158 -> 39.739539 | S19: =BlueDart!G159 -> 12.483207 | T19: =BlueDart!G160 -> 16.797295
A20: Blue Dart | B20: 2024 | C20: =BlueDart!H7 -> 5267.83 | D20: =BlueDart!H49 -> 3460.9 | E20: =BlueDart!H45/BlueDart!H49 -> 0.52660869 | F20: =BlueDart!H95 -> 1.2317475 | G20: =BlueDart!H96 -> 0.81971823 | H20: =BlueDart!H101 -> 0.78473893 | I20: =BlueDart!H109 -> 5.38227 | J20: =BlueDart!H119 -> 46.453084 | K20: =BlueDart!H124 -> 1.5220983 | L20: =BlueDart!H130 -> 0.16192626 | M20: =BlueDart!H131 -> 0.079755801 | N20: =BlueDart!H133 -> 0.057141176 | O20: =BlueDart!H142 -> 0.086974486 | P20: =BlueDart!H146 -> 0.13197299 | Q20: =BlueDart!H147 -> 0.22015403 | R20: =BlueDart!H158 -> 48.689284 | S20: =BlueDart!H159 -> 10.719142 | T20: =BlueDart!H160 -> 18.244632
A21: Blue Dart | B21: 2025 | C21: =BlueDart!I7 -> 5720.18 | D21: =BlueDart!I49 -> 3662.76 | E21: =BlueDart!I45/BlueDart!I49 -> 0.49514028 | F21: =BlueDart!I95 -> 1.2641671 | G21: =BlueDart!I96 -> 0.8693115 | H21: =BlueDart!I101 -> 0.64590389 | I21: =BlueDart!I109 -> 4.7496055 | J21: =BlueDart!I119 -> 50.159759 | K21: =BlueDart!I124 -> 1.561713 | L21: =BlueDart!I130 -> 0.15318749 | M21: =BlueDart!I131 -> 0.068410435 | N21: =BlueDart!I133 -> 0.044127982 | O21: =BlueDart!I142 -> 0.068915244 | P21: =BlueDart!I146 -> 0.11085731 | Q21: =BlueDart!I147 -> 0.16190733 | R21: =BlueDart!I158 -> 57.616294 | S21: =BlueDart!I159 -> 9.3285002 | T21: =BlueDart!I160 -> 17.555503
A22: Blue Dart | B22: 2026 | C22: =BlueDart!J7 -> 6140.88 | D22: =BlueDart!J49 -> 4126.85 | E22: =BlueDart!J45/BlueDart!J49 -> 0.49320426 | F22: =BlueDart!J95 -> 1.3674138 | G22: =BlueDart!J96 -> 0.9578767 | H22: =BlueDart!J101 -> 0.64266137 | I22: =BlueDart!J109 -> 4.8410789 | J22: =BlueDart!J119 -> 54.5787 | K22: =BlueDart!J124 -> 1.4880308 | L22: =BlueDart!J130 -> 0.15480843 | M22: =BlueDart!J131 -> 0.067513125 | N22: =BlueDart!J133 -> 0.040285757 | O22: =BlueDart!J142 -> 0.059946448 | P22: =BlueDart!J146 -> 0.1075453 | Q22: =BlueDart!J147 -> 0.1392311 | R22: =BlueDart!J158 -> 45.476333 | S22: =BlueDart!J159 -> 6.33172 | T22: =BlueDart!J160 -> 12.784076
A23: CONCOR | B23: 2020 | C23: =CONCOR!D7 -> 6530.27 | D23: =CONCOR!D49 -> 11788.76 | E23: =CONCOR!D45/CONCOR!D49 -> 0.45363635 | F23: =CONCOR!D95 -> 2.5701338 | G23: =CONCOR!D96 -> 1.4086844 | H23: =CONCOR!D101 -> 0.0069678781 | I23: =CONCOR!D109 -> 24.759044 | J23: =CONCOR!D119 -> 9.2017558 | K23: =CONCOR!D124 -> 0.55394036 | L23: =CONCOR!D130 -> 0.25944103 | M23: =CONCOR!D131 -> 0.17607388 | N23: =CONCOR!D133 -> 0.061792238 | O23: =CONCOR!D142 -> 0.034229215 | P23: =CONCOR!D146 -> 0.084798224 | Q23: =CONCOR!D147 -> 0.040166831 | R23: =CONCOR!D158 -> 50.076257 | S23: =CONCOR!D159 -> 2.0114045 | T23: =CONCOR!D160 -> 10.674618
A24: CONCOR | B24: 2021 | C24: =CONCOR!E7 -> 6427.08 | D24: =CONCOR!E49 -> 12410.45 | E24: =CONCOR!E45/CONCOR!E49 -> 0.45628321 | F24: =CONCOR!E95 -> 3.042066 | G24: =CONCOR!E96 -> 1.7689134 | H24: =CONCOR!E101 -> 0.070964126 | I24: =CONCOR!E109 -> 11.380097 | J24: =CONCOR!E119 -> 9.1450472 | K24: =CONCOR!E124 -> 0.51787647 | L24: =CONCOR!E130 -> 0.16296514 | M24: =CONCOR!E131 -> 0.076863832 | N24: =CONCOR!E133 -> 0.078614239 | O24: =CONCOR!E142 -> 0.040712464 | P24: =CONCOR!E146 -> 0.033653277 | Q24: =CONCOR!E147 -> 0.049597242 | R24: =CONCOR!E158 -> 72.111277 | S24: =CONCOR!E159 -> 3.5765205 | T24: =CONCOR!E160 -> 33.096625
A25: CONCOR | B25: 2022 | C25: =CONCOR!F7 -> 7652.73 | D25: =CONCOR!F49 -> 13002.26 | E25: =CONCOR!F45/CONCOR!F49 -> 0.44013195 | F25: =CONCOR!F95 -> 3.5179069 | G25: =CONCOR!F96 -> 2.0507466 | H25: =CONCOR!F101 -> 0.068362845 | I25: =CONCOR!F109 -> 18.890038 | J25: =CONCOR!F119 -> 8.6672077 | K25: =CONCOR!F124 -> 0.58856922 | L25: =CONCOR!F130 -> 0.22847664 | M25: =CONCOR!F131 -> 0.15511458 | N25: =CONCOR!F133 -> 0.13787498 | O25: =CONCOR!F142 -> 0.081148969 | P25: =CONCOR!F146 -> 0.077953501 | Q25: =CONCOR!F147 -> 0.098100051 | R25: =CONCOR!F158 -> 38.813363 | S25: =CONCOR!F159 -> 3.8075928 | T25: =CONCOR!F160 -> 22.173783
A26: CONCOR | B26: 2023 | C26: =CONCOR!G7 -> 8169.12 | D26: =CONCOR!G49 -> 13465.06 | E26: =CONCOR!G45/CONCOR!G49 -> 0.41742777 | F26: =CONCOR!G95 -> 3.9676867 | G26: =CONCOR!G96 -> 2.272078 | H26: =CONCOR!G101 -> 0.069360228 | I26: =CONCOR!G109 -> 20.018398 | J26: =CONCOR!G119 -> 9.6509783 | K26: =CONCOR!G124 -> 0.6066902 | L26: =CONCOR!G130 -> 0.22864152 | M26: =CONCOR!G131 -> 0.1584981 | N26: =CONCOR!G133 -> 0.14369602 | O26: =CONCOR!G142 -> 0.087178965 | P26: =CONCOR!G146 -> 0.08096724 | Q26: =CONCOR!G147 -> 0.1045668 | R26: =CONCOR!G158 -> 30.117025 | S26: =CONCOR!G159 -> 3.1492408 | T26: =CONCOR!G160 -> 17.683902
A27: CONCOR | B27: 2024 | C27: =CONCOR!H7 -> 8653.41 | D27: =CONCOR!H49 -> 14038.16 | E27: =CONCOR!H45/CONCOR!H49 -> 0.42845786 | F27: =CONCOR!H95 -> 4.7198355 | G27: =CONCOR!H96 -> 2.8440509 | H27: =CONCOR!H101 -> 0.079394682 | I27: =CONCOR!H109 -> 18.682141 | J27: =CONCOR!H119 -> 14.072481 | K27: =CONCOR!H124 -> 0.61642053 | L27: =CONCOR!H130 -> 0.22634776 | M27: =CONCOR!H131 -> 0.15486034 | N27: =CONCOR!H133 -> 0.14567552 | O27: =CONCOR!H142 -> 0.089797381 | P27: =CONCOR!H146 -> 0.079426516 | Q27: =CONCOR!H147 -> 0.10661995 | R27: =CONCOR!H158 -> 42.634472 | S27: =CONCOR!H159 -> 4.545685 | T27: =CONCOR!H160 -> 26.235627
A28: CONCOR | B28: 2025 | C28: =CONCOR!I7 -> 8887.02 | D28: =CONCOR!I49 -> 14477.26 | E28: =CONCOR!I45/CONCOR!I49 -> 0.45440021 | F28: =CONCOR!I95 -> 4.7991234 | G28: =CONCOR!I96 -> 3.2917024 | H28: =CONCOR!I101 -> 0.069576609 | I28: =CONCOR!I109 -> 18.335644 | J28: =CONCOR!I119 -> 16.427633 | K28: =CONCOR!I124 -> 0.61386063 | L28: =CONCOR!I130 -> 0.21717179 | M28: =CONCOR!I131 -> 0.15176853 | N28: =CONCOR!I133 -> 0.14515664 | O28: =CONCOR!I142 -> 0.08910595 | P28: =CONCOR!I146 -> 0.076478256 | Q28: =CONCOR!I147 -> 0.10418884 | R28: =CONCOR!I158 -> 32.664712 | S28: =CONCOR!I159 -> 3.4032985 | T28: =CONCOR!I160 -> 20.381327
A29: CONCOR | B29: 2026 | C29: =CONCOR!J7 -> 9078.97 | D29: =CONCOR!J49 -> 15175.78 | E29: =CONCOR!J45/CONCOR!J49 -> 0.4726281 | F29: =CONCOR!J95 -> 4.7511388 | G29: =CONCOR!J96 -> 3.1306054 | H29: =CONCOR!J101 -> 0.074528196 | I29: =CONCOR!J109 -> 17.009933 | J29: =CONCOR!J119 -> 19.497553 | K29: =CONCOR!J124 -> 0.59825393 | L29: =CONCOR!J130 -> 0.21492746 | M29: =CONCOR!J131 -> 0.14713013 | N29: =CONCOR!J133 -> 0.13677763 | O29: =CONCOR!J142 -> 0.081827754 | P29: =CONCOR!J146 -> 0.072484988 | Q29: =CONCOR!J147 -> 0.095948572 | R29: =CONCOR!J158 -> 26.083788 | S29: =CONCOR!J159 -> 2.5027022 | T29: =CONCOR!J160 -> 15.306612
A30: Jet Freight | B30: 2020 | C30: =JetFreight!D7 -> 299.78 | D30: =JetFreight!D49 -> 87.81 | E30: =JetFreight!D45/JetFreight!D49 -> 0.16342102 | F30: =JetFreight!D95 -> 2.1770364 | G30: =JetFreight!D96 -> 1.6537421 | H30: =JetFreight!D101 -> 2.1599073 | I30: =JetFreight!D109 -> -1.0436681 | J30: =JetFreight!D119 -> 62.801721 | K30: =JetFreight!D124 -> 3.413962 | L30: =JetFreight!D130 -> -0.011708586 | M30: =JetFreight!D131 -> -0.015945026 | N30: =JetFreight!D133 -> -0.028587631 | O30: =JetFreight!D142 -> -0.097597085 | P30: =JetFreight!D146 -> -0.087642098 | Q30: =JetFreight!D147 -> -0.49652375 | R30: =JetFreight!D158 -> N/M | S30: =JetFreight!D159 -> 1.5269525 | T30: =JetFreight!D160 -> N/M
A31: Jet Freight | B31: 2021 | C31: =JetFreight!E7 -> 346.79 | D31: =JetFreight!E49 -> 98.17 | E31: =JetFreight!E45/JetFreight!E49 -> 0.29082204 | F31: =JetFreight!E95 -> 1.5218345 | G31: =JetFreight!E96 -> 0.93877551 | H31: =JetFreight!E101 -> 1.4431026 | I31: =JetFreight!E109 -> 1.8427835 | J31: =JetFreight!E119 -> 41.668877 | K31: =JetFreight!E124 -> 3.5325456 | L31: =JetFreight!E130 -> 0.026846218 | M31: =JetFreight!E131 -> 0.020617665 | N31: =JetFreight!E133 -> 0.0072378096 | O31: =JetFreight!E142 -> 0.025567892 | P31: =JetFreight!E146 -> 0.088431635 | Q31: =JetFreight!E147 -> 0.11658151 | R31: =JetFreight!E158 -> 13.291474 | S31: =JetFreight!E159 -> 1.5495402 | T31: =JetFreight!E160 -> 6.5780451
A32: Jet Freight | B32: 2022 | C32: =JetFreight!F7 -> 456.76 | D32: =JetFreight!F49 -> 110.01 | E32: =JetFreight!F45/JetFreight!F49 -> 0.28324698 | F32: =JetFreight!F95 -> 2.1581983 | G32: =JetFreight!F96 -> 1.331777 | H32: =JetFreight!F101 -> 2.0201067 | I32: =JetFreight!F109 -> 1.990099 | J32: =JetFreight!F119 -> 33.482573 | K32: =JetFreight!F124 -> 4.1519862 | L32: =JetFreight!F130 -> 0.023601016 | M32: =JetFreight!F131 -> 0.017602242 | N32: =JetFreight!F133 -> 0.0061739207 | O32: =JetFreight!F142 -> 0.025634033 | P32: =JetFreight!F146 -> 0.071066609 | Q32: =JetFreight!F147 -> 0.11571604 | R32: =JetFreight!F158 -> 47.847943 | S32: =JetFreight!F159 -> 5.5367747 | T32: =JetFreight!F160 -> 16.472282
A33: Jet Freight | B33: 2023 | C33: =JetFreight!G7 -> 416.69 | D33: =JetFreight!G49 -> 153.86 | E33: =JetFreight!G45/JetFreight!G49 -> 0.19855713 | F33: =JetFreight!G95 -> 4.0013008 | G33: =JetFreight!G96 -> 1.739187 | H33: =JetFreight!G101 -> 0.97798843 | I33: =JetFreight!G109 -> 1.0277228 | J33: =JetFreight!G119 -> 39.409033 | K33: =JetFreight!G124 -> 2.7082413 | L33: =JetFreight!G130 -> 0.019198925 | M33: =JetFreight!G131 -> 0.012455303 | N33: =JetFreight!G133 -> 0.00014399194 | O33: =JetFreight!G142 -> 0.0003899649 | P33: =JetFreight!G146 -> 0.027425931 | Q33: =JetFreight!G147 -> 0.00096401028 | R33: =JetFreight!G158 -> 912.53333 | S33: =JetFreight!G159 -> 0.87969152 | T33: =JetFreight!G160 -> 13.3915
A34: Jet Freight | B34: 2024 | C34: =JetFreight!H7 -> 387.77 | D34: =JetFreight!H49 -> 170.56 | E34: =JetFreight!H45/JetFreight!H49 -> 0.15924015 | F34: =JetFreight!H95 -> 2.7379495 | G34: =JetFreight!H96 -> 1.5774675 | H34: =JetFreight!H101 -> 0.89308579 | I34: =JetFreight!H109 -> 0.62289562 | J34: =JetFreight!H119 -> 65.108312 | K34: =JetFreight!H124 -> 2.2735108 | L34: =JetFreight!H130 -> 0.015240993 | M34: =JetFreight!H131 -> 0.0095417387 | N34: =JetFreight!H133 -> 0.00067050055 | O34: =JetFreight!H142 -> 0.0015243902 | P34: =JetFreight!H146 -> 0.031281704 | Q34: =JetFreight!H147 -> 0.0041613316 | R34: =JetFreight!H158 -> 222.18462 | S34: =JetFreight!H159 -> 0.92458387 | T34: =JetFreight!H160 -> 16.965821
A35: Jet Freight | B35: 2025 | C35: =JetFreight!I7 -> 436.63 | D35: =JetFreight!I49 -> 182.43 | E35: =JetFreight!I45/JetFreight!I49 -> 0.14454859 | F35: =JetFreight!I95 -> 2.9950019 | G35: =JetFreight!I96 -> 1.739331 | H35: =JetFreight!I101 -> 0.97381565 | I35: =JetFreight!I109 -> 1.7666667 | J35: =JetFreight!I119 -> 65.245746 | K35: =JetFreight!I124 -> 2.3934112 | L35: =JetFreight!I130 -> 0.032682134 | M35: =JetFreight!I131 -> 0.027918375 | N35: =JetFreight!I133 -> 0.0085427021 | O35: =JetFreight!I142 -> 0.020446199 | P35: =JetFreight!I146 -> 0.060810723 | Q35: =JetFreight!I147 -> 0.056455275 | R35: =JetFreight!I158 -> 14.330509 | S35: =JetFreight!I159 -> 0.80903284 | T35: =JetFreight!I160 -> 7.3835179
A36: Jet Freight | B36: 2026 | C36: =JetFreight!J7 -> 444.08 | D36: =JetFreight!J49 -> 194.09 | E36: =JetFreight!J45/JetFreight!J49 -> 0.12550878 | F36: =JetFreight!J95 -> 3.5881855 | G36: =JetFreight!J96 -> 2.3645988 | H36: =JetFreight!J101 -> 1.0175848 | I36: =JetFreight!J109 -> 2.0942857 | J36: =JetFreight!J119 -> 79.817037 | K36: =JetFreight!J124 -> 2.2880107 | L36: =JetFreight!J130 -> 0.037313097 | M36: =JetFreight!J131 -> 0.03301207 | N36: =JetFreight!J133 -> 0.015312556 | O36: =JetFreight!J142 -> 0.035035293 | P36: =JetFreight!J146 -> 0.064940825 | Q36: =JetFreight!J147 -> 0.093419426 | R36: =JetFreight!J158 -> 11.640941 | S36: =JetFreight!J159 -> 1.08749 | T36: =JetFreight!J160 -> 8.3680386
A37: Patel | B37: 2020 | C37: =Patel!D7 -> 347.41 | D37: =Patel!D49 -> 205.39 | E37: =Patel!D45/Patel!D49 -> 0.24879498 | F37: =Patel!D95 -> 5.5191108 | G37: =Patel!D96 -> 3.9637285 | H37: =Patel!D101 -> 0.5101235 | I37: =Patel!D109 -> 0.56562923 | J37: =Patel!D119 -> 93.25408 | K37: =Patel!D124 -> 1.691465 | L37: =Patel!D130 -> 0.023286607 | M37: =Patel!D131 -> 0.012031893 | N37: =Patel!D133 -> 0.030914481 | O37: =Patel!D142 -> 0.052290764 | P37: =Patel!D146 -> 0.019448246 | Q37: =Patel!D147 -> 0.090229354 | R37: =Patel!D158 -> 3.1335196 | S37: =Patel!D159 -> 0.28273544 | T37: =Patel!D160 -> 10.07466
A38: Patel | B38: 2021 | C38: =Patel!E7 -> 212.25 | D38: =Patel!E49 -> 190.3 | E38: =Patel!E45/Patel!E49 -> 0.27919075 | F38: =Patel!E95 -> 10.618729 | G38: =Patel!E96 -> 7.9423077 | H38: =Patel!E101 -> 0.52924027 | I38: =Patel!E109 -> 0.3715415 | J38: =Patel!E119 -> 123.66148 | K38: =Patel!E124 -> 1.1153442 | L38: =Patel!E130 -> 0.024358068 | M38: =Patel!E131 -> 0.013286219 | N38: =Patel!E133 -> 0.00023557126 | O38: =Patel!E142 -> 0.00026274304 | P38: =Patel!E146 -> 0.010286975 | Q38: =Patel!E147 -> 0.00042874293 | R38: =Patel!E158 -> 1350.422 | S38: =Patel!E159 -> 0.57898388 | T38: =Patel!E160 -> 20.534062
A39: Patel | B39: 2022 | C39: =Patel!F7 -> 234.32 | D39: =Patel!F49 -> 179.05 | E39: =Patel!F45/Patel!F49 -> 0.31784418 | F39: =Patel!F95 -> 8.4062274 | G39: =Patel!F96 -> 6.2280956 | H39: =Patel!F101 -> 0.40917619 | I39: =Patel!F109 -> 0.94756554 | J39: =Patel!F119 -> 100.22235 | K39: =Patel!F124 -> 1.3086847 | L39: =Patel!F130 -> 0.032818368 | M39: =Patel!F131 -> 0.021594401 | N39: =Patel!F133 -> 0.0096876067 | O39: =Patel!F142 -> 0.012678023 | P39: =Patel!F146 -> 0.030622125 | Q39: =Patel!F147 -> 0.01935869 | R39: =Patel!F158 -> 39.796079 | S39: =Patel!F159 -> 0.77039997 | T39: =Patel!F160 -> 15.168674
A40: Patel | B40: 2023 | C40: =Patel!G7 -> 278.28 | D40: =Patel!G49 -> 172.15 | E40: =Patel!G45/Patel!G49 -> 0.31995353 | F40: =Patel!G95 -> 4.8155172 | G40: =Patel!G96 -> 4.225 | H40: =Patel!G101 -> 0.26561305 | I40: =Patel!G109 -> 1.5513627 | J40: =Patel!G119 -> 96.876887 | K40: =Patel!G124 -> 1.6164972 | L40: =Patel!G130 -> 0.03708495 | M40: =Patel!G131 -> 0.026591922 | N40: =Patel!G133 -> 0.017608164 | O40: =Patel!G142 -> 0.028463549 | P40: =Patel!G146 -> 0.049681101 | Q40: =Patel!G147 -> 0.041634803 | R40: =Patel!G158 -> 15.340408 | S40: =Patel!G159 -> 0.63869488 | T40: =Patel!G160 -> 7.9717054
A41: Patel | B41: 2024 | C41: =Patel!H7 -> 290.55 | D41: =Patel!H49 -> 192.04 | E41: =Patel!H45/Patel!H49 -> 0.25255155 | F41: =Patel!H95 -> 2.8559374 | G41: =Patel!H96 -> 2.5336489 | H41: =Patel!H101 -> 0.20212855 | I41: =Patel!H109 -> 2.4324324 | J41: =Patel!H119 -> 114.01618 | K41: =Patel!H124 -> 1.512966 | L41: =Patel!H130 -> 0.031319911 | M41: =Patel!H131 -> 0.021683015 | N41: =Patel!H133 -> 0.019067286 | O41: =Patel!H142 -> 0.028848157 | P41: =Patel!H146 -> 0.042835262 | Q41: =Patel!H147 -> 0.046425878 | R41: =Patel!H158 -> 24.736895 | S41: =Patel!H159 -> 1.1484321 | T41: =Patel!H160 -> 14.155209
A42: Patel | B42: 2025 | C42: =Patel!I7 -> 342.69 | D42: =Patel!I49 -> 168.12 | E42: =Patel!I45/Patel!I49 -> 0.28033547 | F42: =Patel!I95 -> 3.4914645 | G42: =Patel!I96 -> 2.8772087 | H42: =Patel!I101 -> 0.10743054 | I42: =Patel!I109 -> 5.2542373 | J42: =Patel!I119 -> 71.883773 | K42: =Patel!I124 -> 2.0383655 | L42: =Patel!I130 -> 0.025708366 | M42: =Patel!I131 -> 0.018092153 | N42: =Patel!I133 -> 0.022177478 | O42: =Patel!I142 -> 0.045205805 | P42: =Patel!I146 -> 0.045657978 | Q42: =Patel!I147 -> 0.062469176 | R42: =Patel!I158 -> 12.234947 | S42: =Patel!I159 -> 0.76430709 | T42: =Patel!I160 -> 8.7940522
A43: Patel | B43: 2026 | C43: =Patel!J7 -> 357.14 | D43: =Patel!J49 -> 163.32 | E43: =Patel!J45/Patel!J49 -> 0.2807372 | F43: =Patel!J95 -> 3.3649374 | G43: =Patel!J96 -> 2.9698867 | H43: =Patel!J101 -> 0.050680052 | I43: =Patel!J109 -> 22.342857 | J43: =Patel!J119 -> 74.279554 | K43: =Patel!J124 -> 2.1867499 | L43: =Patel!J130 -> 0.029036232 | M43: =Patel!J131 -> 0.021896175 | N43: =Patel!J133 -> 0.026880215 | O43: =Patel!J142 -> 0.058780309 | P43: =Patel!J146 -> 0.056047846 | Q43: =Patel!J147 -> 0.077720207 | R43: =Patel!J158 -> 5.9885 | S43: =Patel!J159 -> 0.46542746 | T43: =Patel!J160 -> 3.5505882
A44: TCI | B44: 2020 | C44: =TCI!D7 -> 2717.84 | D44: =TCI!D49 -> 1683.32 | E44: =TCI!D45/TCI!D49 -> 0.45845116 | F44: =TCI!D95 -> 3.1791642 | G44: =TCI!D96 -> 2.1620187 | H44: =TCI!D101 -> 0.41220248 | I44: =TCI!D109 -> 4.6314103 | J44: =TCI!D119 -> 65.44333 | K44: =TCI!D124 -> 1.6145712 | L44: =TCI!D130 -> 0.088835252 | M44: =TCI!D131 -> 0.058483943 | N44: =TCI!D133 -> 0.052379831 | O44: =TCI!D142 -> 0.084570967 | P44: =TCI!D146 -> 0.098929422 | Q44: =TCI!D147 -> 0.13903837 | R44: =TCI!D158 -> 10.144872 | S44: =TCI!D159 -> 1.4105265 | T44: =TCI!D160 -> 7.6224072
A45: TCI | B45: 2021 | C45: =TCI!E7 -> 2802.39 | D45: =TCI!E49 -> 1738.81 | E45: =TCI!E45/TCI!E49 -> 0.46274751 | F45: =TCI!E95 -> 2.8679037 | G45: =TCI!E96 -> 2.0269126 | H45: =TCI!E101 -> 0.25431945 | I45: =TCI!E109 -> 6.3749064 | J45: =TCI!E119 -> 66.5609 | K45: =TCI!E124 -> 1.6116712 | L45: =TCI!E130 -> 0.093855602 | M45: =TCI!E131 -> 0.060737442 | N45: =TCI!E133 -> 0.052501615 | O45: =TCI!E142 -> 0.08461534 | P45: =TCI!E146 -> 0.10014552 | Q45: =TCI!E147 -> 0.12578331 | R45: =TCI!E158 -> 13.422935 | S45: =TCI!E159 -> 1.6883813 | T45: =TCI!E160 -> 8.4894172
A46: TCI | B46: 2022 | C46: =TCI!F7 -> 3258.81 | D46: =TCI!F49 -> 1827.03 | E46: =TCI!F45/TCI!F49 -> 0.43860801 | F46: =TCI!F95 -> 2.7474711 | G46: =TCI!F96 -> 1.9389724 | H46: =TCI!F101 -> 0.067280532 | I46: =TCI!F109 -> 23.289945 | J46: =TCI!F119 -> 56.926071 | K46: =TCI!F124 -> 1.7836653 | L46: =TCI!F130 -> 0.12637435 | M46: =TCI!F131 -> 0.09169298 | N46: =TCI!F133 -> 0.088869864 | O46: =TCI!F142 -> 0.15851409 | P46: =TCI!F146 -> 0.17344595 | Q46: =TCI!F147 -> 0.20248483 | R46: =TCI!F158 -> 15.990618 | S46: =TCI!F159 -> 3.2378576 | T46: =TCI!F160 -> 11.297921
A47: TCI | B47: 2023 | C47: =TCI!G7 -> 3782.57 | D47: =TCI!G49 -> 2100.91 | E47: =TCI!G45/TCI!G49 -> 0.37662727 | F47: =TCI!G95 -> 3.2474207 | G47: =TCI!G96 -> 2.4263303 | H47: =TCI!G101 -> 0.053984334 | I47: =TCI!G109 -> 30.953157 | J47: =TCI!G119 -> 54.125145 | K47: =TCI!G124 -> 1.8004436 | L47: =TCI!G130 -> 0.11245529 | M47: =TCI!G131 -> 0.080358063 | N47: =TCI!G133 -> 0.083895341 | O47: =TCI!G142 -> 0.15104883 | P47: =TCI!G146 -> 0.14924133 | Q47: =TCI!G147 -> 0.18647424 | R47: =TCI!G158 -> 15.328531 | S47: =TCI!G159 -> 2.8583762 | T47: =TCI!G160 -> 11.217636
A48: TCI | B48: 2024 | C48: =TCI!H7 -> 4024.26 | D48: =TCI!H49 -> 2501.4 | E48: =TCI!H45/TCI!H49 -> 0.34451907 | F48: =TCI!H95 -> 3.2510365 | G48: =TCI!H96 -> 2.2909839 | H48: =TCI!H101 -> 0.096655388 | I48: =TCI!H109 -> 21.309721 | J48: =TCI!H119 -> 54.477084 | K48: =TCI!H124 -> 1.6088031 | L48: =TCI!H130 -> 0.10218773 | M48: =TCI!H131 -> 0.07026882 | N48: =TCI!H133 -> 0.087171306 | O48: =TCI!H142 -> 0.14024146 | P48: =TCI!H146 -> 0.11753158 | Q48: =TCI!H147 -> 0.17506562 | R48: =TCI!H158 -> 17.976431 | S48: =TCI!H159 -> 3.1470551 | T48: =TCI!H160 -> 15.573309
A49: TCI | B49: 2025 | C49: =TCI!I7 -> 4491.78 | D49: =TCI!I49 -> 2934.03 | E49: =TCI!I45/TCI!I49 -> 0.32845608 | F49: =TCI!I95 -> 2.4267054 | G49: =TCI!I96 -> 1.5013025 | H49: =TCI!I101 -> 0.11224504 | I49: =TCI!I109 -> 17.099702 | J49: =TCI!I119 -> 58.663703 | K49: =TCI!I124 -> 1.530925 | L49: =TCI!I130 -> 0.10297922 | M49: =TCI!I131 -> 0.076746858 | N49: =TCI!I133 -> 0.091807702 | O49: =TCI!I142 -> 0.14055071 | P49: =TCI!I146 -> 0.13025473 | Q49: =TCI!I147 -> 0.19138183 | R49: =TCI!I158 -> 20.479048 | S49: =TCI!I159 -> 3.9193178 | T49: =TCI!I160 -> 18.596744
A50: TCI | B50: 2026 | C50: =TCI!J7 -> 4916.77 | D50: =TCI!J49 -> 3481.86 | E50: =TCI!J45/TCI!J49 -> 0.34254393 | F50: =TCI!J95 -> 2.4182809 | G50: =TCI!J96 -> 1.5404411 | H50: =TCI!J101 -> 0.12174638 | I50: =TCI!J109 -> 17.187363 | J50: =TCI!J119 -> 60.603079 | K50: =TCI!J124 -> 1.4121102 | L50: =TCI!J130 -> 0.1055571 | M50: =TCI!J131 -> 0.079666122 | N50: =TCI!J133 -> 0.09279466 | O50: =TCI!J142 -> 0.13103629 | P50: =TCI!J146 -> 0.12518854 | Q50: =TCI!J147 -> 0.17780662 | R50: =TCI!J158 -> 15.516515 | S50: =TCI!J159 -> 2.758939 | T50: =TCI!J160 -> 14.0242
A51: Shreeji | B51: 2020 | C51: =Shreeji!D7 -> 110 | D51: =Shreeji!D49 -> 79.35 | E51: =Shreeji!D45/Shreeji!D49 -> 0.33484562 | F51: =Shreeji!D95 -> 6.1143524 | G51: =Shreeji!D96 -> 3.5227538 | H51: =Shreeji!D101 -> 1.8031683 | I51: =Shreeji!D109 -> 1.3824363 | J51: =Shreeji!D119 -> 89.524545 | K51: =Shreeji!D124 -> 1.3862634 | L51: =Shreeji!D130 -> 0.082272727 | M51: =Shreeji!D131 -> 0.044363636 | N51: =Shreeji!D133 -> 0.013363636 | O51: =Shreeji!D142 -> 0.01852552 | P51: =Shreeji!D146 -> 0.046068484 | Q51: =Shreeji!D147 -> 0.058217822 | R51: =Shreeji!D158 -> 21.47619 | S51: =Shreeji!D159 -> 1.250297 | T51: =Shreeji!D160 -> 8.1646409
A52: Shreeji | B52: 2021 | C52: =Shreeji!E7 -> 108.23 | D52: =Shreeji!E49 -> 81.98 | E52: =Shreeji!E45/Shreeji!E49 -> 0.30141498 | F52: =Shreeji!E95 -> 5.4709865 | G52: =Shreeji!E96 -> 4.0522244 | H52: =Shreeji!E101 -> 1.9652318 | I52: =Shreeji!E109 -> 0.66508314 | J52: =Shreeji!E119 -> 122.92571 | K52: =Shreeji!E124 -> 1.3202 | L52: =Shreeji!E130 -> 0.065693431 | M52: =Shreeji!E131 -> 0.025870831 | N52: =Shreeji!E133 -> -0.010071145 | O52: =Shreeji!E142 -> -0.013295926 | P52: =Shreeji!E146 -> 0.03908431 | Q52: =Shreeji!E147 -> -0.045115894 | R52: =Shreeji!E158 -> N/M | S52: =Shreeji!E159 -> 2.3903146 | T52: =Shreeji!E160 -> 14.033755
A53: Shreeji | B53: 2022 | C53: =Shreeji!F7 -> 163.74 | D53: =Shreeji!F49 -> 89.59 | E53: =Shreeji!F45/Shreeji!F49 -> 0.22748075 | F53: =Shreeji!F95 -> 5.4686757 | G53: =Shreeji!F96 -> 3.8818398 | H53: =Shreeji!F101 -> 1.3966376 | I53: =Shreeji!F109 -> 3.1113801 | J53: =Shreeji!F119 -> 99.553561 | K53: =Shreeji!F124 -> 1.8276593 | L53: =Shreeji!F130 -> 0.10205203 | M53: =Shreeji!F131 -> 0.078478075 | N53: =Shreeji!F133 -> 0.054049102 | O53: =Shreeji!F142 -> 0.098783346 | P53: =Shreeji!F146 -> 0.12505339 | Q53: =Shreeji!F147 -> 0.27552927 | R53: =Shreeji!F158 -> 24.061017 | S53: =Shreeji!F159 -> 6.6295143 | T53: =Shreeji!F160 -> 15.171155
A54: Shreeji | B54: 2023 | C54: =Shreeji!G7 -> 186.44 | D54: =Shreeji!G49 -> 104.66 | E54: =Shreeji!G45/Shreeji!G49 -> 0.19262373 | F54: =Shreeji!G95 -> 4.1375839 | G54: =Shreeji!G96 -> 3.4765101 | H54: =Shreeji!G101 -> 1.1264396 | I54: =Shreeji!G109 -> 4.3854447 | J54: =Shreeji!G119 -> 108.51722 | K54: =Shreeji!G124 -> 1.7813873 | L54: =Shreeji!G130 -> 0.10528856 | M54: =Shreeji!G131 -> 0.087266681 | N54: =Shreeji!G133 -> 0.051920189 | O54: =Shreeji!G142 -> 0.092489968 | P54: =Shreeji!G146 -> 0.13588148 | Q54: =Shreeji!G147 -> 0.23719677 | R54: =Shreeji!G158 -> 35.997056 | S54: =Shreeji!G159 -> 8.5383852 | T54: =Shreeji!G160 -> 19.749949
A55: Shreeji | B55: 2024 | C55: =Shreeji!H7 -> 250.5 | D55: =Shreeji!H49 -> 120.4 | E55: =Shreeji!H45/Shreeji!H49 -> 0.27591362 | F55: =Shreeji!H95 -> 4.7823629 | G55: =Shreeji!H96 -> 3.924251 | H55: =Shreeji!H101 -> 0.8357462 | I55: =Shreeji!H109 -> 2.9173387 | J55: =Shreeji!H119 -> 94.535729 | K55: =Shreeji!H124 -> 2.0805648 | L55: =Shreeji!H130 -> 0.075369261 | M55: =Shreeji!H131 -> 0.057764471 | N55: =Shreeji!H133 -> 0.06499002 | O55: =Shreeji!H142 -> 0.13521595 | P55: =Shreeji!H146 -> 0.10695995 | Q55: =Shreeji!H147 -> 0.29097408 | R55: =Shreeji!H158 -> 11.171978 | S55: =Shreeji!H159 -> 3.250756 | T55: =Shreeji!H160 -> 11.869693
A56: Shreeji | B56: 2025 | C56: =Shreeji!I7 -> 220.18 | D56: =Shreeji!I49 -> 114.99 | E56: =Shreeji!I45/Shreeji!I49 -> 0.25115227 | F56: =Shreeji!I95 -> 4.9369369 | G56: =Shreeji!I96 -> 4.1321321 | H56: =Shreeji!I101 -> 0.73194787 | I56: =Shreeji!I109 -> 0.956621 | J56: =Shreeji!I119 -> 101.30416 | K56: =Shreeji!I124 -> 1.9147752 | L56: =Shreeji!I130 -> 0.040966482 | M56: =Shreeji!I131 -> 0.019029885 | N56: =Shreeji!I133 -> 0.00694886 | O56: =Shreeji!I142 -> 0.013305505 | P56: =Shreeji!I146 -> 0.028778602 | Q56: =Shreeji!I147 -> 0.026946108 | R56: =Shreeji!I158 -> 40.432353 | S56: =Shreeji!I159 -> 1.0894945 | T56: =Shreeji!I160 -> 10.613248
A57: Shreeji | B57: 2026 | C57: =Shreeji!J7 -> 234.29 | D57: =Shreeji!J49 -> 119.52 | E57: =Shreeji!J45/Shreeji!J49 -> 0.20866801 | F57: =Shreeji!J95 -> 4.7719752 | G57: =Shreeji!J96 -> 4.1773526 | H57: =Shreeji!J101 -> 0.66661121 | I57: =Shreeji!J109 -> 0.90144231 | J57: =Shreeji!J119 -> 115.90764 | K57: =Shreeji!J124 -> 1.9602577 | L57: =Shreeji!J130 -> 0.033078663 | M57: =Shreeji!J131 -> 0.016005805 | N57: =Shreeji!J133 -> 0.013487558 | O57: =Shreeji!J142 -> 0.02643909 | P57: =Shreeji!J146 -> 0.033226709 | Q57: =Shreeji!J147 -> 0.052570288 | R57: =Shreeji!J158 -> 13.006709 | S57: =Shreeji!J159 -> 0.68376643 | T57: =Shreeji!J160 -> 9.6491871
A58: Mahindra Log. | B58: 2020 | C58: =MahindraLog!D7 -> 3471.14 | D58: =MahindraLog!D49 -> 1421.84 | E58: =MahindraLog!D45/MahindraLog!D49 -> 0.16243741 | F58: =MahindraLog!D95 -> 1.7350456 | G58: =MahindraLog!D96 -> 0.93973871 | H58: =MahindraLog!D101 -> 0.36959515 | I58: =MahindraLog!D109 -> 4.8241634 | J58: =MahindraLog!D119 -> 56.32298 | K58: =MahindraLog!D124 -> 2.4413014 | L58: =MahindraLog!D130 -> 0.04565647 | M58: =MahindraLog!D131 -> 0.024502037 | N58: =MahindraLog!D133 -> 0.015879509 | O58: =MahindraLog!D142 -> 0.038766669 | P58: =MahindraLog!D146 -> 0.077868823 | Q58: =MahindraLog!D147 -> 0.10120261 | R58: =MahindraLog!D158 -> 36.924993 | S58: =MahindraLog!D159 -> 3.7369055 | T58: =MahindraLog!D160 -> 13.484828
A59: Mahindra Log. | B59: 2021 | C59: =MahindraLog!E7 -> 3263.72 | D59: =MahindraLog!E49 -> 1686.93 | E59: =MahindraLog!E45/MahindraLog!E49 -> 0.21383223 | F59: =MahindraLog!E95 -> 1.4929302 | G59: =MahindraLog!E96 -> 0.80454208 | H59: =MahindraLog!E101 -> 0.47438651 | I59: =MahindraLog!E109 -> 2.2414136 | J59: =MahindraLog!E119 -> 54.307355 | K59: =MahindraLog!E124 -> 1.9347098 | L59: =MahindraLog!E130 -> 0.041265795 | M59: =MahindraLog!E131 -> 0.013797139 | N59: =MahindraLog!E133 -> 0.009191965 | O59: =MahindraLog!E142 -> 0.017783785 | P59: =MahindraLog!E146 -> 0.040021707 | Q59: =MahindraLog!E147 -> 0.052811323 | R59: =MahindraLog!E158 -> 173.7146 | S59: =MahindraLog!E159 -> 9.1740978 | T59: =MahindraLog!E160 -> 39.227413
A60: Mahindra Log. | B60: 2022 | C60: =MahindraLog!F7 -> 4140.76 | D60: =MahindraLog!F49 -> 1975.44 | E60: =MahindraLog!F45/MahindraLog!F49 -> 0.25338659 | F60: =MahindraLog!F95 -> 1.30859 | G60: =MahindraLog!F96 -> 0.60711711 | H60: =MahindraLog!F101 -> 0.7363856 | I60: =MahindraLog!F109 -> 1.4299128 | J60: =MahindraLog!F119 -> 43.095591 | K60: =MahindraLog!F124 -> 2.0961204 | L60: =MahindraLog!F130 -> 0.044523228 | M60: =MahindraLog!F131 -> 0.010297627 | N60: =MahindraLog!F133 -> 0.0042407674 | O60: =MahindraLog!F142 -> 0.0088891589 | P60: =MahindraLog!F146 -> 0.029233722 | Q60: =MahindraLog!F147 -> 0.032132923 | R60: =MahindraLog!F158 -> 259.09681 | S60: =MahindraLog!F159 -> 8.325538 | T60: =MahindraLog!F160 -> 26.132729
A61: Mahindra Log. | B61: 2023 | C61: =MahindraLog!G7 -> 5128.29 | D61: =MahindraLog!G49 -> 2552.94 | E61: =MahindraLog!G45/MahindraLog!G49 -> 0.32499001 | F61: =MahindraLog!G95 -> 1.3995697 | G61: =MahindraLog!G96 -> 0.67292304 | H61: =MahindraLog!G101 -> 1.4849467 | I61: =MahindraLog!G109 -> 1.3674617 | J61: =MahindraLog!G119 -> 46.440207 | K61: =MahindraLog!G124 -> 2.0087781 | L61: =MahindraLog!G130 -> 0.050703061 | M61: =MahindraLog!G131 -> 0.013751172 | N61: =MahindraLog!G133 -> 0.0051245152 | O61: =MahindraLog!G142 -> 0.010294014 | P61: =MahindraLog!G146 -> 0.040110596 | Q61: =MahindraLog!G147 -> 0.04678904 | R61: =MahindraLog!G158 -> 121.8024 | S61: =MahindraLog!G159 -> 5.6990172 | T61: =MahindraLog!G160 -> 15.03264
A62: Mahindra Log. | B62: 2024 | C62: =MahindraLog!H7 -> 5505.97 | D62: =MahindraLog!H49 -> 2477.2 | E62: =MahindraLog!H45/MahindraLog!H49 -> 0.3375545 | F62: =MahindraLog!H95 -> 1.2998699 | G62: =MahindraLog!H96 -> 0.6206401 | H62: =MahindraLog!H101 -> 1.5011879 | I62: =MahindraLog!H109 -> 0.32643779 | J62: =MahindraLog!H119 -> 46.53013 | K62: =MahindraLog!H124 -> 2.2226586 | L62: =MahindraLog!H130 -> 0.041998049 | M62: =MahindraLog!H131 -> 0.0040410681 | N62: =MahindraLog!H133 -> -0.0099419358 | O62: =MahindraLog!H142 -> -0.022097529 | P62: =MahindraLog!H146 -> 0.018063584 | Q62: =MahindraLog!H147 -> -0.11115398 | R62: =MahindraLog!H158 -> N/M | S62: =MahindraLog!H159 -> 7.5007371 | T62: =MahindraLog!H160 -> 18.863985
A63: Mahindra Log. | B63: 2025 | C63: =MahindraLog!I7 -> 6104.83 | D63: =MahindraLog!I49 -> 2578.8 | E63: =MahindraLog!I45/MahindraLog!I49 -> 0.36046223 | F63: =MahindraLog!I95 -> 1.2426698 | G63: =MahindraLog!I96 -> 0.55109501 | H63: =MahindraLog!I101 -> 1.9840596 | I63: =MahindraLog!I109 -> 0.71505972 | J63: =MahindraLog!I119 -> 37.373932 | K63: =MahindraLog!I124 -> 2.3673143 | L63: =MahindraLog!I130 -> 0.046584426 | M63: =MahindraLog!I131 -> 0.0095121404 | N63: =MahindraLog!I133 -> -0.0058723994 | O63: =MahindraLog!I142 -> -0.013901815 | P63: =MahindraLog!I146 -> 0.044441553 | Q63: =MahindraLog!I147 -> -0.081871746 | R63: =MahindraLog!I158 -> N/M | S63: =MahindraLog!I159 -> 5.4085612 | T63: =MahindraLog!I160 -> 11.115408
A64: Mahindra Log. | B64: 2026 | C64: =MahindraLog!J7 -> 6999.3 | D64: =MahindraLog!J49 -> 3105.01 | E64: =MahindraLog!J45/MahindraLog!J49 -> 0.36955114 | F64: =MahindraLog!J95 -> 1.4122438 | G64: =MahindraLog!J96 -> 0.69438023 | H64: =MahindraLog!J101 -> 0.55308228 | I64: =MahindraLog!J109 -> 1.3453746 | J64: =MahindraLog!J119 -> 35.960789 | K64: =MahindraLog!J124 -> 2.2541956 | L64: =MahindraLog!J130 -> 0.054119698 | M64: =MahindraLog!J131 -> 0.014420013 | N64: =MahindraLog!J133 -> 0.00032717557 | O64: =MahindraLog!J142 -> 0.00073751775 | P64: =MahindraLog!J146 -> 0.03598791 | Q64: =MahindraLog!J147 -> 0.0019493011 | R64: =MahindraLog!J158 -> 1441.6489 | S64: =MahindraLog!J159 -> 2.8102079 | T64: =MahindraLog!J160 -> 9.9038437
A65: Sical | B65: 2020 | C65: =Sical!D7 -> 1005.84 | D65: =Sical!D49 -> 2766.94 | E65: =Sical!D45/Sical!D49 -> 0.33971824 | F65: =Sical!D95 -> 0.53880059 | G65: =Sical!D96 -> 0.29196076 | H65: =Sical!D101 -> 2.601688 | I65: =Sical!D109 -> -1.9436466 | J65: =Sical!D119 -> 87.283713 | K65: =Sical!D124 -> 0.36352071 | L65: =Sical!D130 -> -0.022339537 | M65: =Sical!D131 -> -0.10629921 | N65: =Sical!D133 -> -0.10641852 | O65: =Sical!D142 -> -0.038685335 | P65: =Sical!D146 -> -0.060374375 | Q65: =Sical!D147 -> -0.21769372 | R65: =Sical!D158 -> N/M | S65: =Sical!D159 -> 0.062998015 | T65: =Sical!D160 -> N/M
A66: Sical | B66: 2021 | C66: =Sical!E7 -> 503.63 | D66: =Sical!E49 -> 1731.06 | E66: =Sical!E45/Sical!E49 -> 0.48494564 | F66: =Sical!E95 -> 0.43040965 | G66: =Sical!E96 -> 0.24450927 | H66: =Sical!E101 -> N/M | I66: =Sical!E109 -> -0.63366621 | J66: =Sical!E119 -> 154.23158 | K66: =Sical!E124 -> 0.29093734 | L66: =Sical!E130 -> -0.018763775 | M66: =Sical!E131 -> -0.17512857 | N66: =Sical!E133 -> -2.3024443 | O66: =Sical!E142 -> -0.66986702 | P66: =Sical!E146 -> -0.14788236 | Q66: =Sical!E147 -> N/M | R66: =Sical!E158 -> N/M | S66: =Sical!E159 -> N/M | T66: =Sical!E160 -> N/M
A67: Sical | B67: 2022 | C67: =Sical!F7 -> 348.87 | D67: =Sical!F49 -> 1565.58 | E67: =Sical!F45/Sical!F49 -> 0.48799806 | F67: =Sical!F95 -> 0.53771673 | G67: =Sical!F96 -> 0.31262155 | H67: =Sical!F101 -> N/M | I67: =Sical!F109 -> -5.1701031 | J67: =Sical!F119 -> 148.30381 | K67: =Sical!F124 -> 0.22283754 | L67: =Sical!F130 -> -0.11224812 | M67: =Sical!F131 -> -0.31624961 | N67: =Sical!F133 -> -0.74646717 | O67: =Sical!F142 -> -0.16634091 | P67: =Sical!F146 -> -0.13206847 | Q67: =Sical!F147 -> N/M | R67: =Sical!F158 -> N/M | S67: =Sical!F159 -> N/M | T67: =Sical!F160 -> N/M
A68: Sical | B68: 2023 | C68: =Sical!G7 -> 392.11 | D68: =Sical!G49 -> 793.01 | E68: =Sical!G45/Sical!G49 -> 0.76336994 | F68: =Sical!G95 -> 0.73076322 | G68: =Sical!G96 -> 0.53558316 | H68: =Sical!G101 -> 9.0334454 | I68: =Sical!G109 -> -1.4496644 | J68: =Sical!G119 -> 50.880875 | K68: =Sical!G124 -> 0.49445783 | L68: =Sical!G130 -> 0.070362908 | M68: =Sical!G131 -> -0.071612558 | N68: =Sical!G133 -> -2.1268012 | O68: =Sical!G142 -> -1.0516135 | P68: =Sical!G146 -> -0.052291477 | Q68: =Sical!G147 -> -15.581839 | R68: =Sical!G158 -> N/M | S68: =Sical!G159 -> 0.7826954 | T68: =Sical!G160 -> 16.052913
A69: Sical | B69: 2024 | C69: =Sical!H7 -> 221.09 | D69: =Sical!H49 -> 767.54 | E69: =Sical!H45/Sical!H49 -> 0.72605988 | F69: =Sical!H95 -> 0.86142419 | G69: =Sical!H96 -> 0.70548862 | H69: =Sical!H101 -> 17.661908 | I69: =Sical!H109 -> -0.80959673 | J69: =Sical!H119 -> 72.739156 | K69: =Sical!H124 -> 0.28805013 | L69: =Sical!H130 -> 0.075082546 | M69: =Sical!H131 -> -0.14347098 | N69: =Sical!H133 -> -0.12795694 | O69: =Sical!H142 -> -0.036858014 | P69: =Sical!H146 -> -0.059182417 | Q69: =Sical!H147 -> -0.98502786 | R69: =Sical!H158 -> N/M | S69: =Sical!H159 -> 33.431025 | T69: =Sical!H160 -> 81.20958
A70: Sical | B70: 2025 | C70: =Sical!I7 -> 221.82 | D70: =Sical!I49 -> 858.91 | E70: =Sical!I45/Sical!I49 -> 0.70084176 | F70: =Sical!I95 -> 0.79756136 | G70: =Sical!I96 -> 0.61997811 | H70: =Sical!I101 -> N/M | I70: =Sical!I109 -> -0.37549133 | J70: =Sical!I119 -> 118.68835 | K70: =Sical!I124 -> 0.25825756 | L70: =Sical!I130 -> 0.096880353 | M70: =Sical!I131 -> -0.073212515 | N70: =Sical!I133 -> -0.11644577 | O70: =Sical!I142 -> -0.030072999 | P70: =Sical!I146 -> -0.026930667 | Q70: =Sical!I147 -> N/M | R70: =Sical!I158 -> N/M | S70: =Sical!I159 -> N/M | T70: =Sical!I160 -> 45.034384
A71: Sical | B71: 2026 | C71: =Sical!J7 -> 385.68 | D71: =Sical!J49 -> 906.73 | E71: =Sical!J45/Sical!J49 -> 0.61263 | F71: =Sical!J95 -> 1.1402597 | G71: =Sical!J96 -> 0.55759496 | H71: =Sical!J101 -> 3.6944931 | I71: =Sical!J109 -> 0.50860872 | J71: =Sical!J119 -> 90.805201 | K71: =Sical!J124 -> 0.42535264 | L71: =Sical!J130 -> 0.2030699 | M71: =Sical!J131 -> 0.094975109 | N71: =Sical!J133 -> 0.12777432 | O71: =Sical!J142 -> 0.054349145 | P71: =Sical!J146 -> 0.051176243 | Q71: =Sical!J147 -> 0.37535227 | R71: =Sical!J158 -> 10.200767 | S71: =Sical!J159 -> 3.828881 | T71: =Sical!J160 -> 11.769328

Sheet Industry
A1: Industry aggregate - the 10 logistics companies taken together (FY2020-FY2026)
A2: Every input line is the SUM of the same line on the 10 company sheets (3-D sum, green). Ratios use the same formulas on the summed figures, i.e. size-weighted industry ratios. Per-share data: n.a.
A3: Source: the 10 company sheets; see the Sources sheet for the annual reports behind each company.
A5: Particulars | B5: Formula / basis | C5: Norm / unit | D5: FY2020 | E5: FY2021 | F5: FY2022 | G5: FY2023 | H5: FY2024 | I5: FY2025 | J5: FY2026 | K5: 7-Yr Average | L5: Change FY26 vs FY20
A6: 1. STATEMENT OF PROFIT & LOSS (Rs crore)
A7: Revenue from operations (net sales) | B7: P&L: revenue from operations | C7: Rs crore | D7: =SUM(Tiger:MahindraLog!D7) -> 25305.13 | E7: =SUM(Tiger:MahindraLog!E7) -> 27618.19 | F7: =SUM(Tiger:MahindraLog!F7) -> 40343.65 | G7: =SUM(Tiger:MahindraLog!G7) -> 42009.84 | H7: =SUM(Tiger:MahindraLog!H7) -> 37810.32 | I7: =SUM(Tiger:MahindraLog!I7) -> 28922.44 | J7: =SUM(Tiger:MahindraLog!J7) -> 31187.93 | K7: =AVERAGE(D7:J7) -> 33313.929 | L7: =J7-D7 -> 5882.8
A8: Direct operating costs
A9: Cost of materials / purchases | B9: P&L: materials consumed and purchases | C9: Rs crore | D9: =SUM(Tiger:MahindraLog!D9) -> 284.13 | E9: =SUM(Tiger:MahindraLog!E9) -> 0 | F9: =SUM(Tiger:MahindraLog!F9) -> 9.81 | G9: =SUM(Tiger:MahindraLog!G9) -> 17.94 | H9: =SUM(Tiger:MahindraLog!H9) -> 55.68 | I9: =SUM(Tiger:MahindraLog!I9) -> 21.36 | J9: =SUM(Tiger:MahindraLog!J9) -> 0.41 | K9: =AVERAGE(D9:J9) -> 55.618571 | L9: =J9-D9 -> -283.72
A10: Change in inventories (increase = +) | B10: P&L: changes in inventories (deducted from cost) | C10: Rs crore | D10: =SUM(Tiger:MahindraLog!D10) -> 0.04 | E10: =SUM(Tiger:MahindraLog!E10) -> -3.5 | F10: =SUM(Tiger:MahindraLog!F10) -> -0.12 | G10: =SUM(Tiger:MahindraLog!G10) -> -0.81 | H10: =SUM(Tiger:MahindraLog!H10) -> -1.24 | I10: =SUM(Tiger:MahindraLog!I10) -> -0.83 | J10: =SUM(Tiger:MahindraLog!J10) -> -1.13 | K10: =AVERAGE(D10:J10) -> -1.0842857 | L10: =J10-D10 -> -1.17
A11: Power & fuel | B11: P&L: power and fuel | C11: Rs crore | D11: =SUM(Tiger:MahindraLog!D11) -> 402.68 | E11: =SUM(Tiger:MahindraLog!E11) -> 253.51 | F11: =SUM(Tiger:MahindraLog!F11) -> 394.79 | G11: =SUM(Tiger:MahindraLog!G11) -> 589.75 | H11: =SUM(Tiger:MahindraLog!H11) -> 489.81 | I11: =SUM(Tiger:MahindraLog!I11) -> 546.46 | J11: =SUM(Tiger:MahindraLog!J11) -> 506.37 | K11: =AVERAGE(D11:J11) -> 454.76714 | L11: =J11-D11 -> 103.69
A12: Freight, handling, vehicle hire & other direct costs | B12: P&L: operating / freight & handling expenses | C12: Rs crore | D12: =SUM(Tiger:MahindraLog!D12) -> 17707.69 | E12: =SUM(Tiger:MahindraLog!E12) -> 19854.74 | F12: =SUM(Tiger:MahindraLog!F12) -> 30303.7 | G12: =SUM(Tiger:MahindraLog!G12) -> 31150.56 | H12: =SUM(Tiger:MahindraLog!H12) -> 27453.74 | I12: =SUM(Tiger:MahindraLog!I12) -> 20767.36 | J12: =SUM(Tiger:MahindraLog!J12) -> 22486.28 | K12: =AVERAGE(D12:J12) -> 24246.296 | L12: =J12-D12 -> 4778.59
A13: Direct operating cost (COGS-equivalent) | B13: Materials + Power & fuel + Other direct costs - Change in inventories | C13: Rs crore | D13: =D9+D11+D12-D10 -> 18394.46 | E13: =E9+E11+E12-E10 -> 20111.75 | F13: =F9+F11+F12-F10 -> 30708.42 | G13: =G9+G11+G12-G10 -> 31759.06 | H13: =H9+H11+H12-H10 -> 28000.47 | I13: =I9+I11+I12-I10 -> 21336.01 | J13: =J9+J11+J12-J10 -> 22994.19 | K13: =AVERAGE(D13:J13) -> 24757.766 | L13: =J13-D13 -> 4599.73
A14: Gross profit | B14: Sales - Direct operating cost | C14: Rs crore | D14: =D7-D13 -> 6910.67 | E14: =E7-E13 -> 7506.44 | F14: =F7-F13 -> 9635.23 | G14: =G7-G13 -> 10250.78 | H14: =H7-H13 -> 9809.85 | I14: =I7-I13 -> 7586.43 | J14: =J7-J13 -> 8193.74 | K14: =AVERAGE(D14:J14) -> 8556.1629 | L14: =J14-D14 -> 1283.07
A15: Indirect operating expenses
A16: Employee benefits expense | B16: P&L: employee benefits expense | C16: Rs crore | D16: =SUM(Tiger:MahindraLog!D16) -> 2824.58 | E16: =SUM(Tiger:MahindraLog!E16) -> 3010.2 | F16: =SUM(Tiger:MahindraLog!F16) -> 3357.45 | G16: =SUM(Tiger:MahindraLog!G16) -> 3804.17 | H16: =SUM(Tiger:MahindraLog!H16) -> 4027.98 | I16: =SUM(Tiger:MahindraLog!I16) -> 2423.15 | J16: =SUM(Tiger:MahindraLog!J16) -> 2580.12 | K16: =AVERAGE(D16:J16) -> 3146.8071 | L16: =J16-D16 -> -244.46
A17: Selling & administrative expenses | B17: P&L: selling, general & administrative expenses | C17: Rs crore | D17: =SUM(Tiger:MahindraLog!D17) -> 927.3 | E17: =SUM(Tiger:MahindraLog!E17) -> 1545.35 | F17: =SUM(Tiger:MahindraLog!F17) -> 1528.29 | G17: =SUM(Tiger:MahindraLog!G17) -> 1610.76 | H17: =SUM(Tiger:MahindraLog!H17) -> 1675.53 | I17: =SUM(Tiger:MahindraLog!I17) -> 1299.43 | J17: =SUM(Tiger:MahindraLog!J17) -> 1435.17 | K17: =AVERAGE(D17:J17) -> 1431.69 | L17: =J17-D17 -> 507.87
A18: Other expenses | B18: P&L: other expenses | C18: Rs crore | D18: =SUM(Tiger:MahindraLog!D18) -> 92.12 | E18: =SUM(Tiger:MahindraLog!E18) -> 173.77 | F18: =SUM(Tiger:MahindraLog!F18) -> 89.94 | G18: =SUM(Tiger:MahindraLog!G18) -> 112.87 | H18: =SUM(Tiger:MahindraLog!H18) -> 115.65 | I18: =SUM(Tiger:MahindraLog!I18) -> 23.62 | J18: =SUM(Tiger:MahindraLog!J18) -> 3.65 | K18: =AVERAGE(D18:J18) -> 87.374286 | L18: =J18-D18 -> -88.47
A19: Indirect operating expenses | B19: Employee + Selling & admin + Other expenses | C19: Rs crore | D19: =D16+D17+D18 -> 3844 | E19: =E16+E17+E18 -> 4729.32 | F19: =F16+F17+F18 -> 4975.68 | G19: =G16+G17+G18 -> 5527.8 | H19: =H16+H17+H18 -> 5819.16 | I19: =I16+I17+I18 -> 3746.2 | J19: =J16+J17+J18 -> 4018.94 | K19: =AVERAGE(D19:J19) -> 4665.8714 | L19: =J19-D19 -> 174.94
A20: Total operating expenses (before depreciation) | B20: Direct operating cost + Indirect operating expenses | C20: Rs crore | D20: =D13+D19 -> 22238.46 | E20: =E13+E19 -> 24841.07 | F20: =F13+F19 -> 35684.1 | G20: =G13+G19 -> 37286.86 | H20: =H13+H19 -> 33819.63 | I20: =I13+I19 -> 25082.21 | J20: =J13+J19 -> 27013.13 | K20: =AVERAGE(D20:J20) -> 29423.637 | L20: =J20-D20 -> 4774.67
A21: Operating EBITDA | B21: Sales - Total operating expenses (excludes other income) | C21: Rs crore | D21: =D7-D20 -> 3066.67 | E21: =E7-E20 -> 2777.12 | F21: =F7-F20 -> 4659.55 | G21: =G7-G20 -> 4722.98 | H21: =H7-H20 -> 3990.69 | I21: =I7-I20 -> 3840.23 | J21: =J7-J20 -> 4174.8 | K21: =AVERAGE(D21:J21) -> 3890.2914 | L21: =J21-D21 -> 1108.13
A22: Depreciation & amortisation | B22: P&L: depreciation and amortisation expense | C22: Rs crore | D22: =SUM(Tiger:MahindraLog!D22) -> 1374.04 | E22: =SUM(Tiger:MahindraLog!E22) -> 1560.39 | F22: =SUM(Tiger:MahindraLog!F22) -> 1530.3 | G22: =SUM(Tiger:MahindraLog!G22) -> 1621.95 | H22: =SUM(Tiger:MahindraLog!H22) -> 1847.45 | I22: =SUM(Tiger:MahindraLog!I22) -> 1640.43 | J22: =SUM(Tiger:MahindraLog!J22) -> 1811.88 | K22: =AVERAGE(D22:J22) -> 1626.6343 | L22: =J22-D22 -> 437.84
A23: Operating profit (EBIT) | B23: Operating EBITDA - Depreciation (excludes other income & exceptional items) | C23: Rs crore | D23: =D21-D22 -> 1692.63 | E23: =E21-E22 -> 1216.73 | F23: =F21-F22 -> 3129.25 | G23: =G21-G22 -> 3101.03 | H23: =H21-H22 -> 2143.24 | I23: =I21-I22 -> 2199.8 | J23: =J21-J22 -> 2362.92 | K23: =AVERAGE(D23:J23) -> 2263.6571 | L23: =J23-D23 -> 670.29
A24: Other income (incl. exceptional items) | B24: P&L: other income and exceptional items (net) | C24: Rs crore | D24: =SUM(Tiger:MahindraLog!D24) -> -415.51 | E24: =SUM(Tiger:MahindraLog!E24) -> -705.13 | F24: =SUM(Tiger:MahindraLog!F24) -> 484.72 | G24: =SUM(Tiger:MahindraLog!G24) -> -200.64 | H24: =SUM(Tiger:MahindraLog!H24) -> 889.55 | I24: =SUM(Tiger:MahindraLog!I24) -> 749.23 | J24: =SUM(Tiger:MahindraLog!J24) -> 676.12 | K24: =AVERAGE(D24:J24) -> 211.19143 | L24: =J24-D24 -> 1091.63
A25: Finance costs | B25: P&L: finance costs | C25: Rs crore | D25: =SUM(Tiger:MahindraLog!D25) -> 365.41 | E25: =SUM(Tiger:MahindraLog!E25) -> 501.23 | F25: =SUM(Tiger:MahindraLog!F25) -> 325.03 | G25: =SUM(Tiger:MahindraLog!G25) -> 312.42 | H25: =SUM(Tiger:MahindraLog!H25) -> 424.19 | I25: =SUM(Tiger:MahindraLog!I25) -> 391.38 | J25: =SUM(Tiger:MahindraLog!J25) -> 412.78 | K25: =AVERAGE(D25:J25) -> 390.34857 | L25: =J25-D25 -> 47.37
A26: Profit before tax | B26: EBIT + Other income - Finance costs | C26: Rs crore | D26: =D23+D24-D25 -> 911.71 | E26: =E23+E24-E25 -> 10.37 | F26: =F23+F24-F25 -> 3288.94 | G26: =G23+G24-G25 -> 2587.97 | H26: =H23+H24-H25 -> 2608.6 | I26: =I23+I24-I25 -> 2557.65 | J26: =J23+J24-J25 -> 2626.26 | K26: =AVERAGE(D26:J26) -> 2084.5 | L26: =J26-D26 -> 1714.55
A27: Tax expense | B27: P&L: current + deferred tax | C27: Rs crore | D27: =SUM(Tiger:MahindraLog!D27) -> 233.02 | E27: =SUM(Tiger:MahindraLog!E27) -> 313.11 | F27: =SUM(Tiger:MahindraLog!F27) -> 791.72 | G27: =SUM(Tiger:MahindraLog!G27) -> 838.81 | H27: =SUM(Tiger:MahindraLog!H27) -> 596.39 | I27: =SUM(Tiger:MahindraLog!I27) -> 547.23 | J27: =SUM(Tiger:MahindraLog!J27) -> 564.44 | K27: =AVERAGE(D27:J27) -> 554.96 | L27: =J27-D27 -> 331.42
A28: Profit after tax (before associates / minority interest) | B28: PBT - Tax | C28: Rs crore | D28: =D26-D27 -> 678.69 | E28: =E26-E27 -> -302.74 | F28: =F26-F27 -> 2497.22 | G28: =G26-G27 -> 1749.16 | H28: =H26-H27 -> 2012.21 | I28: =I26-I27 -> 2010.42 | J28: =J26-J27 -> 2061.82 | K28: =AVERAGE(D28:J28) -> 1529.54 | L28: =J28-D28 -> 1383.13
A29: Share of associates / JVs less minority interest | B29: Net profit - (PBT - Tax) | C29: Rs crore | D29: =D30-D28 -> -12.29 | E29: =E30-E28 -> 89.31 | F29: =F30-F28 -> -39.85 | G29: =G30-G28 -> -27.64 | H29: =H30-H28 -> 1.9 | I29: =I30-I28 -> -12.42 | J29: =J30-J28 -> -15.73 | K29: =AVERAGE(D29:J29) -> -2.3885714 | L29: =J29-D29 -> -3.44
A30: Net profit (PAT) attributable to shareholders | B30: P&L: profit attributable to owners of the company | C30: Rs crore | D30: =SUM(Tiger:MahindraLog!D30) -> 666.4 | E30: =SUM(Tiger:MahindraLog!E30) -> -213.43 | F30: =SUM(Tiger:MahindraLog!F30) -> 2457.37 | G30: =SUM(Tiger:MahindraLog!G30) -> 1721.52 | H30: =SUM(Tiger:MahindraLog!H30) -> 2014.11 | I30: =SUM(Tiger:MahindraLog!I30) -> 1998 | J30: =SUM(Tiger:MahindraLog!J30) -> 2046.09 | K30: =AVERAGE(D30:J30) -> 1527.1514 | L30: =J30-D30 -> 1379.69
A31: Equity dividend for the year | B31: Dividend declared on equity shares for the year | C31: Rs crore | D31: =SUM(Tiger:MahindraLog!D31) -> 319.85 | E31: =SUM(Tiger:MahindraLog!E31) -> 427.94 | F31: =SUM(Tiger:MahindraLog!F31) -> 813.59 | G31: =SUM(Tiger:MahindraLog!G31) -> 895.34 | H31: =SUM(Tiger:MahindraLog!H31) -> 932.16 | I31: =SUM(Tiger:MahindraLog!I31) -> 1156.5 | J31: =SUM(Tiger:MahindraLog!J31) -> 817.33 | K31: =AVERAGE(D31:J31) -> 766.10143 | L31: =J31-D31 -> 497.48
A32: Preference dividend | B32: Nil - no preference capital reported | C32: Rs crore | D32: =SUM(Tiger:MahindraLog!D32) -> 0 | E32: =SUM(Tiger:MahindraLog!E32) -> 0 | F32: =SUM(Tiger:MahindraLog!F32) -> 0 | G32: =SUM(Tiger:MahindraLog!G32) -> 0 | H32: =SUM(Tiger:MahindraLog!H32) -> 0 | I32: =SUM(Tiger:MahindraLog!I32) -> 0 | J32: =SUM(Tiger:MahindraLog!J32) -> 0 | K32: =AVERAGE(D32:J32) -> 0 | L32: =J32-D32 -> 0
A34: 2. BALANCE SHEET AS AT 31 MARCH (closing balances, Rs crore)
A35: Shareholders' funds & liabilities
A36: Equity share capital | B36: Balance sheet: equity share capital | C36: Rs crore | D36: =SUM(Tiger:MahindraLog!D36) -> 572.19 | E36: =SUM(Tiger:MahindraLog!E36) -> 581.87 | F36: =SUM(Tiger:MahindraLog!F36) -> 592.12 | G36: =SUM(Tiger:MahindraLog!G36) -> 639.49 | H36: =SUM(Tiger:MahindraLog!H36) -> 790.15 | I36: =SUM(Tiger:MahindraLog!I36) -> 898.45 | J36: =SUM(Tiger:MahindraLog!J36) -> 1016.26 | K36: =AVERAGE(D36:J36) -> 727.21857 | L36: =J36-D36 -> 444.07
A37: Preference share capital | B37: Nil - no preference capital reported | C37: Rs crore | D37: =SUM(Tiger:MahindraLog!D37) -> 0 | E37: =SUM(Tiger:MahindraLog!E37) -> 0 | F37: =SUM(Tiger:MahindraLog!F37) -> 0 | G37: =SUM(Tiger:MahindraLog!G37) -> 0 | H37: =SUM(Tiger:MahindraLog!H37) -> 0 | I37: =SUM(Tiger:MahindraLog!I37) -> 0 | J37: =SUM(Tiger:MahindraLog!J37) -> 0 | K37: =AVERAGE(D37:J37) -> 0 | L37: =J37-D37 -> 0
A38: Reserves & surplus (other equity) | B38: Balance sheet: other equity | C38: Rs crore | D38: =SUM(Tiger:MahindraLog!D38) -> 14384.92 | E38: =SUM(Tiger:MahindraLog!E38) -> 13755.07 | F38: =SUM(Tiger:MahindraLog!F38) -> 15491.23 | G38: =SUM(Tiger:MahindraLog!G38) -> 17215.67 | H38: =SUM(Tiger:MahindraLog!H38) -> 17795.56 | I38: =SUM(Tiger:MahindraLog!I38) -> 16574.72 | J38: =SUM(Tiger:MahindraLog!J38) -> 18565.38 | K38: =AVERAGE(D38:J38) -> 16254.65 | L38: =J38-D38 -> 4180.46
A39: Equity shareholders' funds (net worth) | B39: Equity share capital + Reserves & surplus | C39: Rs crore | D39: =D36+D38 -> 14957.11 | E39: =E36+E38 -> 14336.94 | F39: =F36+F38 -> 16083.35 | G39: =G36+G38 -> 17855.16 | H39: =H36+H38 -> 18585.71 | I39: =I36+I38 -> 17473.17 | J39: =J36+J38 -> 19581.64 | K39: =AVERAGE(D39:J39) -> 16981.869 | L39: =J39-D39 -> 4624.53
A40: Total shareholders' funds | B40: Net worth + Preference share capital | C40: Rs crore | D40: =D39+D37 -> 14957.11 | E40: =E39+E37 -> 14336.94 | F40: =F39+F37 -> 16083.35 | G40: =G39+G37 -> 17855.16 | H40: =H39+H37 -> 18585.71 | I40: =I39+I37 -> 17473.17 | J40: =J39+J37 -> 19581.64 | K40: =AVERAGE(D40:J40) -> 16981.869 | L40: =J40-D40 -> 4624.53
A41: Borrowings (incl. lease liabilities) | B41: Balance sheet: non-current + current borrowings and lease liabilities | C41: Rs crore | D41: =SUM(Tiger:MahindraLog!D41) -> 4286.14 | E41: =SUM(Tiger:MahindraLog!E41) -> 6296.94 | F41: =SUM(Tiger:MahindraLog!F41) -> 6525.54 | G41: =SUM(Tiger:MahindraLog!G41) -> 4625.77 | H41: =SUM(Tiger:MahindraLog!H41) -> 5436.73 | I41: =SUM(Tiger:MahindraLog!I41) -> 4521.24 | J41: =SUM(Tiger:MahindraLog!J41) -> 4417.77 | K41: =AVERAGE(D41:J41) -> 5158.59 | L41: =J41-D41 -> 131.63
A42: Other liabilities (trade payables, provisions, other) | B42: Balance sheet: all other liabilities | C42: Rs crore | D42: =SUM(Tiger:MahindraLog!D42) -> 6837 | E42: =SUM(Tiger:MahindraLog!E42) -> 7598.37 | F42: =SUM(Tiger:MahindraLog!F42) -> 8694.08 | G42: =SUM(Tiger:MahindraLog!G42) -> 7435.06 | H42: =SUM(Tiger:MahindraLog!H42) -> 7012.82 | I42: =SUM(Tiger:MahindraLog!I42) -> 4919.58 | J42: =SUM(Tiger:MahindraLog!J42) -> 5272.37 | K42: =AVERAGE(D42:J42) -> 6824.1829 | L42: =J42-D42 -> -1564.63
A43: Total equity & liabilities | B43: Shareholders' funds + Borrowings + Other liabilities | C43: Rs crore | D43: =D40+D41+D42 -> 26080.25 | E43: =E40+E41+E42 -> 28232.25 | F43: =F40+F41+F42 -> 31302.97 | G43: =G40+G41+G42 -> 29915.99 | H43: =H40+H41+H42 -> 31035.26 | I43: =I40+I41+I42 -> 26913.99 | J43: =J40+J41+J42 -> 29271.78 | K43: =AVERAGE(D43:J43) -> 28964.641 | L43: =J43-D43 -> 3191.53
A44: Assets
A45: Net block (PPE, right-of-use & intangible assets) | B45: Balance sheet: fixed assets net of depreciation | C45: Rs crore | D45: =SUM(Tiger:MahindraLog!D45) -> 11025.1 | E45: =SUM(Tiger:MahindraLog!E45) -> 12530.25 | F45: =SUM(Tiger:MahindraLog!F45) -> 12833.54 | G45: =SUM(Tiger:MahindraLog!G45) -> 11529.2 | H45: =SUM(Tiger:MahindraLog!H45) -> 13044.83 | I45: =SUM(Tiger:MahindraLog!I45) -> 11757.54 | J45: =SUM(Tiger:MahindraLog!J45) -> 12991.49 | K45: =AVERAGE(D45:J45) -> 12244.564 | L45: =J45-D45 -> 1966.39
A46: Capital work-in-progress | B46: Balance sheet: capital work-in-progress | C46: Rs crore | D46: =SUM(Tiger:MahindraLog!D46) -> 2554.61 | E46: =SUM(Tiger:MahindraLog!E46) -> 1335.9 | F46: =SUM(Tiger:MahindraLog!F46) -> 1257.08 | G46: =SUM(Tiger:MahindraLog!G46) -> 1327.89 | H46: =SUM(Tiger:MahindraLog!H46) -> 1148.78 | I46: =SUM(Tiger:MahindraLog!I46) -> 1287.22 | J46: =SUM(Tiger:MahindraLog!J46) -> 1307.85 | K46: =AVERAGE(D46:J46) -> 1459.9043 | L46: =J46-D46 -> -1246.76
A47: Investments | B47: Balance sheet: non-current + current investments | C47: Rs crore | D47: =SUM(Tiger:MahindraLog!D47) -> 1864.33 | E47: =SUM(Tiger:MahindraLog!E47) -> 1959.24 | F47: =SUM(Tiger:MahindraLog!F47) -> 2303.76 | G47: =SUM(Tiger:MahindraLog!G47) -> 2366.32 | H47: =SUM(Tiger:MahindraLog!H47) -> 2226.1 | I47: =SUM(Tiger:MahindraLog!I47) -> 1964.58 | J47: =SUM(Tiger:MahindraLog!J47) -> 2128.65 | K47: =AVERAGE(D47:J47) -> 2116.14 | L47: =J47-D47 -> 264.32
A48: Other assets (receivables, inventory, cash, advances) | B48: Balance sheet: all other assets | C48: Rs crore | D48: =SUM(Tiger:MahindraLog!D48) -> 10636.21 | E48: =SUM(Tiger:MahindraLog!E48) -> 12406.86 | F48: =SUM(Tiger:MahindraLog!F48) -> 14908.59 | G48: =SUM(Tiger:MahindraLog!G48) -> 14692.58 | H48: =SUM(Tiger:MahindraLog!H48) -> 14615.55 | I48: =SUM(Tiger:MahindraLog!I48) -> 11904.65 | J48: =SUM(Tiger:MahindraLog!J48) -> 12843.79 | K48: =AVERAGE(D48:J48) -> 13144.033 | L48: =J48-D48 -> 2207.58
A49: Total assets | B49: Net block + CWIP + Investments + Other assets | C49: Rs crore | D49: =D45+D46+D47+D48 -> 26080.25 | E49: =E45+E46+E47+E48 -> 28232.25 | F49: =F45+F46+F47+F48 -> 31302.97 | G49: =G45+G46+G47+G48 -> 29915.99 | H49: =H45+H46+H47+H48 -> 31035.26 | I49: =I45+I46+I47+I48 -> 26913.99 | J49: =J45+J46+J47+J48 -> 29271.78 | K49: =AVERAGE(D49:J49) -> 28964.641 | L49: =J49-D49 -> 3191.53
A50: of which: Trade receivables | B50: Included in other assets | C50: Rs crore | D50: =SUM(Tiger:MahindraLog!D50) -> 3339.25 | E50: =SUM(Tiger:MahindraLog!E50) -> 4255.22 | F50: =SUM(Tiger:MahindraLog!F50) -> 5196.45 | G50: =SUM(Tiger:MahindraLog!G50) -> 4382.35 | H50: =SUM(Tiger:MahindraLog!H50) -> 4872.93 | I50: =SUM(Tiger:MahindraLog!I50) -> 3289.56 | J50: =SUM(Tiger:MahindraLog!J50) -> 3839.35 | K50: =AVERAGE(D50:J50) -> 4167.8729 | L50: =J50-D50 -> 500.1
A51: of which: Inventories | B51: Included in other assets | C51: Rs crore | D51: =SUM(Tiger:MahindraLog!D51) -> 87.75 | E51: =SUM(Tiger:MahindraLog!E51) -> 93.07 | F51: =SUM(Tiger:MahindraLog!F51) -> 99.41 | G51: =SUM(Tiger:MahindraLog!G51) -> 87.18 | H51: =SUM(Tiger:MahindraLog!H51) -> 117.85 | I51: =SUM(Tiger:MahindraLog!I51) -> 110.31 | J51: =SUM(Tiger:MahindraLog!J51) -> 123.15 | K51: =AVERAGE(D51:J51) -> 102.67429 | L51: =J51-D51 -> 35.4
A52: of which: Cash & bank balances | B52: Included in other assets | C52: Rs crore | D52: =SUM(Tiger:MahindraLog!D52) -> 3080.69 | E52: =SUM(Tiger:MahindraLog!E52) -> 3525.54 | F52: =SUM(Tiger:MahindraLog!F52) -> 4105.93 | G52: =SUM(Tiger:MahindraLog!G52) -> 4991.45 | H52: =SUM(Tiger:MahindraLog!H52) -> 4399.04 | I52: =SUM(Tiger:MahindraLog!I52) -> 4334.65 | J52: =SUM(Tiger:MahindraLog!J52) -> 4325.41 | K52: =AVERAGE(D52:J52) -> 4108.9586 | L52: =J52-D52 -> 1244.72
A53: Balance sheet check (should be zero) | B53: Total assets - Total equity & liabilities | C53: Rs crore | D53: =D49-D43 -> 0 | E53: =E49-E43 -> 0 | F53: =F49-F43 -> 0 | G53: =G49-G43 -> 0 | H53: =H49-H43 -> 0 | I53: =I49-I43 -> 0 | J53: =J49-J43 -> 0
A55: 3. CASH FLOW STATEMENT (Rs crore)
A56: A. Cash flow from operating activities
A57: Profit before tax | B57: From the P&L | C57: Rs crore | D57: =D26 -> 911.71 | E57: =E26 -> 10.37 | F57: =F26 -> 3288.94 | G57: =G26 -> 2587.97 | H57: =H26 -> 2608.6 | I57: =I26 -> 2557.65 | J57: =J26 -> 2626.26 | K57: =AVERAGE(D57:J57) -> 2084.5 | L57: =J57-D57 -> 1714.55
A58: Add: Depreciation & amortisation | B58: Non-cash charge | C58: Rs crore | D58: =D22 -> 1374.04 | E58: =E22 -> 1560.39 | F58: =F22 -> 1530.3 | G58: =G22 -> 1621.95 | H58: =H22 -> 1847.45 | I58: =I22 -> 1640.43 | J58: =J22 -> 1811.88 | K58: =AVERAGE(D58:J58) -> 1626.6343 | L58: =J58-D58 -> 437.84
A59: Add: Finance costs | B59: Shown under financing activities | C59: Rs crore | D59: =D25 -> 365.41 | E59: =E25 -> 501.23 | F59: =F25 -> 325.03 | G59: =G25 -> 312.42 | H59: =H25 -> 424.19 | I59: =I25 -> 391.38 | J59: =J25 -> 412.78 | K59: =AVERAGE(D59:J59) -> 390.34857 | L59: =J59-D59 -> 47.37
A60: Less: Other income (incl. exceptional items) | B60: Non-operating / investing items | C60: Rs crore | D60: =-D24 -> 415.51 | E60: =-E24 -> 705.13 | F60: =-F24 -> -484.72 | G60: =-G24 -> 200.64 | H60: =-H24 -> -889.55 | I60: =-I24 -> -749.23 | J60: =-J24 -> -676.12 | K60: =AVERAGE(D60:J60) -> -211.19143 | L60: =J60-D60 -> -1091.63
A61: Operating profit before working-capital changes | B61: Sum of the four lines above (= Operating EBITDA) | C61: Rs crore | D61: =D57+D58+D59+D60 -> 3066.67 | E61: =E57+E58+E59+E60 -> 2777.12 | F61: =F57+F58+F59+F60 -> 4659.55 | G61: =G57+G58+G59+G60 -> 4722.98 | H61: =H57+H58+H59+H60 -> 3990.69 | I61: =I57+I58+I59+I60 -> 3840.23 | J61: =J57+J58+J59+J60 -> 4174.8 | K61: =AVERAGE(D61:J61) -> 3890.2914 | L61: =J61-D61 -> 1108.13
A62: Working-capital changes, income tax paid & other items | B62: Net cash from operations - Operating profit before WC changes | C62: Rs crore | D62: =D63-D61 -> 2527.24 | E62: =E63-E61 -> 135.5 | F62: =F63-F61 -> -905.04 | G62: =G63-G61 -> -547.33 | H62: =H63-H61 -> -1354.32 | I62: =I63-I61 -> -401.69 | J62: =J63-J61 -> -834.37 | K62: =AVERAGE(D62:J62) -> -197.14429 | L62: =J62-D62 -> -3361.61
A63: Net cash from operating activities (A) | B63: Cash flow statement: net cash from operating activities | C63: Rs crore | D63: =SUM(Tiger:MahindraLog!D63) -> 5593.91 | E63: =SUM(Tiger:MahindraLog!E63) -> 2912.62 | F63: =SUM(Tiger:MahindraLog!F63) -> 3754.51 | G63: =SUM(Tiger:MahindraLog!G63) -> 4175.65 | H63: =SUM(Tiger:MahindraLog!H63) -> 2636.37 | I63: =SUM(Tiger:MahindraLog!I63) -> 3438.54 | J63: =SUM(Tiger:MahindraLog!J63) -> 3340.43 | K63: =AVERAGE(D63:J63) -> 3693.1471 | L63: =J63-D63 -> -2253.48
A64: B. Cash flow from investing activities
A65: Net cash from / (used in) investing activities (B) | B65: Cash flow statement: net cash from investing activities | C65: Rs crore | D65: =SUM(Tiger:MahindraLog!D65) -> -4377.39 | E65: =SUM(Tiger:MahindraLog!E65) -> -692.62 | F65: =SUM(Tiger:MahindraLog!F65) -> -1900.07 | G65: =SUM(Tiger:MahindraLog!G65) -> -1923.15 | H65: =SUM(Tiger:MahindraLog!H65) -> -1854.84 | I65: =SUM(Tiger:MahindraLog!I65) -> -1093.56 | J65: =SUM(Tiger:MahindraLog!J65) -> -1145.27 | K65: =AVERAGE(D65:J65) -> -1855.2714 | L65: =J65-D65 -> 3232.12
A66: C. Cash flow from financing activities
A67: Finance costs paid | B67: Taken as the finance cost charged in the P&L | C67: Rs crore | D67: =-D25 -> -365.41 | E67: =-E25 -> -501.23 | F67: =-F25 -> -325.03 | G67: =-G25 -> -312.42 | H67: =-H25 -> -424.19 | I67: =-I25 -> -391.38 | J67: =-J25 -> -412.78 | K67: =AVERAGE(D67:J67) -> -390.34857 | L67: =J67-D67 -> -47.37
