Workbook

Sheet ReadMe
A1: DECISION MAKING USING FINANCIAL STATEMENTS - Group Project: Excel workings
A2: Industry: Indian listed logistics & freight-transport services | 10 firms | 7 financial years FY2020-FY2026 (FY2019 used only as opening balance for averages)
A3: 1. Purpose
A4: Ratio analysis (liquidity, leverage, turnover, profitability, valuation), industry comparison, 7-year trend analysis, DuPont, common-size, trend-index and statistical analysis for 10 listed logistics companies, under the assumption that these 10 firms constitute the entire industry. Every industry benchmark is computed only from these 10 firms.
A5: 2. Sheet map
A6: Firm_Profiles - the 10 firms, segments, business models and quantitative evidence of operating homogeneity (supports the industry/firm-selection justification).
A7: Scorecard - 24 key ratios for every firm vs the industry aggregate and the 10-firm median; green = better than median, red = weaker (FY2026 and 7-year average).
A8: Industry_Compare - every ratio (76) for every firm and year with Industry aggregate, Mean, Median, SD, Min, Max, position vs median, assessment and rank.
A9: Statistics - descriptive statistics, correlation matrix, multiple regression, paired t-tests (FY2020 vs FY2026), Welch t-test (asset-light vs asset-heavy), two-way ANOVA, growth/stability.
A10: Panel - 70 firm-year observations of key variables (linked), the data used by the Statistics sheet.
A11: Industry - aggregate of the 10 firms (sum of each line item) with the same ratio formulas: the size-weighted industry ratio.
A12: Tiger ... MahindraLog - one sheet per company: raw statements (inputs), derived items, all ratios, DuPont, growth, common-size P&L and balance sheet, trend index (FY2020 = 100). Columns K-M: 7-year average, change FY26 vs FY20, linear trend slope per year.
... A32: This workbook was built with the assistance of Claude (Anthropic) - an AI assistant - which wrote the formulas and layout from the group's data file and the course formula list. All inputs come from the group-supplied Screener.in export; every ratio is a live formula and was cross-checked against an independent Python computation (all cells matched). The group remains responsible for the interpretation.

Sheet Firm_Profiles
A1: FIRM SELECTION - the 10 listed Indian logistics companies and evidence of operating homogeneity
A2: Columns H-P are linked to the company sheets. Low dispersion in cost structure (direct operating cost dominant, negligible inventory, receivable-led working capital) shows the firms share one operating model; asset intensity shows the different value propositions.
A4: # | B4: Company | C4: NSE symbol | D4: BSE code | E4: Segment / value proposition | F4: Business model | G4: Asset group (vs median NB/TA) | H4: Sales FY2026 (Rs cr) | I4: Total assets FY2026 (Rs cr) | J4: Market cap FY2026 (Rs cr) | K4: Sales CAGR FY20-26 | L4: Direct operating cost % sales (7-yr) | M4: Employee cost % sales (7-yr) | N4: Inventory % total assets (7-yr) | O4: Receivables % total assets (7-yr) | P4: Net block % total assets (7-yr) | Q4: Operating EBITDA margin (7-yr)
A5: 1 | B5: Tiger Logistics (India) Ltd | C5: TIGERLOGS | D5: 536264 | E5: International freight forwarding (sea & air), customs brokerage, project cargo | F5: Asset-light forwarder | G5: =IF(P5>=MEDIAN($P$5:$P$14),"Asset-heavy","Asset-light") -> Asset-light | H5: =Tiger!J9 -> 572.82 | I5: =Tiger!J35 -> 262.62 | J5: =Tiger!J69 -> 252.623 | K5: =(Tiger!J9/Tiger!D9)^(1/6)-1 -> 0.11290974 | L5: =Tiger!K127 -> 0.90008469 | M5: =Tiger!K129 -> 0.042590791 | N5: =Tiger!K200 -> 0 | O5: =Tiger!K199 -> 0.534418 | P5: =Tiger!K195 -> 0.066850107 | Q5: =Tiger!K121 -> 0.029629489
A6: 2 | B6: Allcargo Logistics Ltd | C6: ALLCARGO | D6: 532749 | E6: LCL consolidation/NVOCC (international business demerged to Allcargo Global w.e.f. 1-Nov-2025); domestic express & contract logistics | F6: Asset-light network operator | G6: =IF(P6>=MEDIAN($P$5:$P$14),"Asset-heavy","Asset-light") -> Asset-heavy | H6: =Allcargo!J9 -> 2058 | I6: =Allcargo!J35 -> 1736 | J6: =Allcargo!J69 -> 1075.4204 | K6: =(Allcargo!J9/Allcargo!D9)^(1/6)-1 -> -0.19109651 | L6: =Allcargo!K127 -> 0.76369076 | M6: =Allcargo!K129 -> 0.11942794 | N6: =Allcargo!K200 -> 0.00063859079 | O6: =Allcargo!K199 -> 0.27001652 | P6: =Allcargo!K195 -> 0.39214748 | Q6: =Allcargo!K121 -> 0.073607981
A7: 3 | B7: Blue Dart Express Ltd | C7: BLUEDART | D7: 526612 | E7: Express air & ground courier and integrated transport (DHL Group); dedicated freighter fleet | F7: Asset-heavy express network | G7: =IF(P7>=MEDIAN($P$5:$P$14),"Asset-heavy","Asset-light") -> Asset-heavy | H7: =BlueDart!J9 -> 6140.88 | I7: =BlueDart!J35 -> 4126.85 | J7: =BlueDart!J69 -> 11250.39 | K7: =(BlueDart!J9/BlueDart!D9)^(1/6)-1 -> 0.11620728 | L7: =BlueDart!K127 -> 0.57413445 | M7: =BlueDart!K129 -> 0.18587756 | N7: =BlueDart!K200 -> 0.012623821 | O7: =BlueDart!K199 -> 0.20174168 | P7: =BlueDart!K195 -> 0.52080847 | Q7: =BlueDart!K121 -> 0.17658992
A8: 4 | B8: Container Corporation of India Ltd | C8: CONCOR | D8: 531344 | E8: Rail-based EXIM & domestic container logistics, ICDs/CFSs (Navratna CPSE, Ministry of Railways) | F8: Asset-heavy multimodal | G8: =IF(P8>=MEDIAN($P$5:$P$14),"Asset-heavy","Asset-light") -> Asset-heavy | H8: =CONCOR!J9 -> 9078.97 | I8: =CONCOR!J35 -> 15175.78 | J8: =CONCOR!J69 -> 32390.848 | K8: =(CONCOR!J9/CONCOR!D9)^(1/6)-1 -> 0.056454767 | L8: =CONCOR!K127 -> 0.65386661 | M8: =CONCOR!K129 -> 0.05554146 | N8: =CONCOR!K200 -> 0.0028375504 | O8: =CONCOR!K199 -> 0.020044213 | P8: =CONCOR!K195 -> 0.44613792 | Q8: =CONCOR!K121 -> 0.21971019
A9: 5 | B9: Jet Freight Logistics Ltd | C9: JETFREIGHT | D9: 543420 | E9: International air & ocean freight forwarding (incl. perishables), customs clearance | F9: Asset-light forwarder | G9: =IF(P9>=MEDIAN($P$5:$P$14),"Asset-heavy","Asset-light") -> Asset-light | H9: =JetFreight!J9 -> 444.08 | I9: =JetFreight!J35 -> 194.09 | J9: =JetFreight!J69 -> 79.1584 | K9: =(JetFreight!J9/JetFreight!D9)^(1/6)-1 -> 0.067684882 | L9: =JetFreight!K127 -> 0.924891 | M9: =JetFreight!K129 -> 0.040392871 | N9: =JetFreight!K200 -> 0 | O9: =JetFreight!K199 -> 0.42824064 | P9: =JetFreight!K195 -> 0.19504924 | Q9: =JetFreight!K121 -> 0.020453399
A10: 6 | B10: Patel Integrated Logistics Ltd | C10: PATINTLOG | D10: 526381 | E10: Surface transport (Patel Roadways), domestic & international air-freight consolidation | F10: Asset-light carrier/consolidator | G10: =IF(P10>=MEDIAN($P$5:$P$14),"Asset-heavy","Asset-light") -> Asset-light | H10: =Patel!J9 -> 357.14 | I10: =Patel!J35 -> 163.32 | J10: =Patel!J69 -> 57.4896 | K10: =(Patel!J9/Patel!D9)^(1/6)-1 -> 0.0046143172 | L10: =Patel!K127 -> 0.90083674 | M10: =Patel!K129 -> 0.046566838 | N10: =Patel!K200 -> 0 | O10: =Patel!K199 -> 0.41678302 | P10: =Patel!K195 -> 0.28277252 | Q10: =Patel!K121 -> 0.0290875
A11: 7 | B11: Sical Logistics Ltd | C11: SICALLOG | D11: 520086 | E11: Bulk/mining logistics (coal), port & rail-road handling; IBC resolution plan of Pristine Malwa Logistics Park approved by NCLT Chennai (8-Dec-2022) | F11: Asset-heavy bulk logistics | G11: =IF(P11>=MEDIAN($P$5:$P$14),"Asset-heavy","Asset-light") -> Asset-heavy | H11: =Sical!J9 -> 385.68 | I11: =Sical!J35 -> 906.73 | J11: =Sical!J69 -> 502.69378 | K11: =(Sical!J9/Sical!D9)^(1/6)-1 -> -0.14765313 | L11: =Sical!K127 -> 0.77007687 | M11: =Sical!K129 -> 0.094975198 | N11: =Sical!K200 -> 0.0039427599 | O11: =Sical!K199 -> 0.088076785 | P11: =Sical!K195 -> 0.58793765 | Q11: =Sical!K121 -> 0.041720612
A12: 8 | B12: Transport Corporation of India Ltd | C12: TCI | D12: 532349 | E12: Integrated multimodal: road freight, supply-chain solutions/warehousing, coastal seaways, rail (JV with CONCOR) | F12: Hybrid multimodal | G12: =IF(P12>=MEDIAN($P$5:$P$14),"Asset-heavy","Asset-light") -> Asset-heavy | H12: =TCI!J9 -> 4916.77 | I12: =TCI!J35 -> 3481.86 | J12: =TCI!J69 -> 7079.41 | K12: =(TCI!J9/TCI!D9)^(1/6)-1 -> 0.10384815 | L12: =TCI!K127 -> 0.8143326 | M12: =TCI!K129 -> 0.054711809 | N12: =TCI!K200 -> 0.0036727148 | O12: =TCI!K199 -> 0.26417002 | P12: =TCI!K195 -> 0.39313615 | Q12: =TCI!K121 -> 0.10460636
A13: 9 | B13: Shreeji Translogistics Ltd | C13: — (BSE only) | D13: 540738 | E13: Road freight transport (full & part truck-load) and allied logistics | F13: Asset-light road carrier | G13: =IF(P13>=MEDIAN($P$5:$P$14),"Asset-heavy","Asset-light") -> Asset-light | H13: =Shreeji!J9 -> 234.29 | I13: =Shreeji!J35 -> 119.52 | J13: =Shreeji!J69 -> 41.1012 | K13: =(Shreeji!J9/Shreeji!D9)^(1/6)-1 -> 0.13429716 | L13: =Shreeji!K127 -> 0.80428674 | M13: =Shreeji!K129 -> 0.059367831 | N13: =Shreeji!K200 -> 0.025994572 | O13: =Shreeji!K199 -> 0.500792 | P13: =Shreeji!K195 -> 0.25601414 | Q13: =Shreeji!K121 -> 0.072103023
A14: 10 | B14: Mahindra Logistics Ltd | C14: MAHLOG | D14: 540768 | E14: Integrated 3PL: contract logistics & warehousing, B2B express, freight forwarding, last-mile, enterprise mobility | F14: Asset-light 3PL (leased) | G14: =IF(P14>=MEDIAN($P$5:$P$14),"Asset-heavy","Asset-light") -> Asset-light | H14: =MahindraLog!J9 -> 6999.3 | I14: =MahindraLog!J35 -> 3105.01 | J14: =MahindraLog!J69 -> 3301.376 | K14: =(MahindraLog!J9/MahindraLog!D9)^(1/6)-1 -> 0.12399336 | L14: =MahindraLog!K127 -> 0.85615338 | M14: =MahindraLog!K129 -> 0.07499944 | N14: =MahindraLog!K200 -> 0.0001263555 | O14: =MahindraLog!K199 -> 0.27364033 | P14: =MahindraLog!K195 -> 0.28888773 | Q14: =MahindraLog!K121 -> 0.046407247
B15: Median | H15: =MEDIAN(H5:H14) -> 1315.41 | I15: =MEDIAN(I5:I14) -> 1321.365 | J15: =MEDIAN(J5:J14) -> 789.05709 | K15: =MEDIAN(K5:K14) -> 0.085766516 | L15: =MEDIAN(L5:L14) -> 0.80930967 | M15: =MEDIAN(M5:M14) -> 0.057454646 | N15: =MEDIAN(N5:N14) -> 0.0017380706 | O15: =MEDIAN(O5:O14) -> 0.27182843 | ... Q15: =MEDIAN(Q5:Q14) -> 0.059255135
B16: Mean | H16: =AVERAGE(H5:H14) -> 3118.793 | I16: =AVERAGE(I5:I14) -> 2927.178 | J16: =AVERAGE(J5:J14) -> 5603.051 | K16: =AVERAGE(K5:K14) -> 0.038126002 | L16: =AVERAGE(L5:L14) -> 0.79623538 | M16: =AVERAGE(M5:M14) -> 0.077445173 | N16: =AVERAGE(N5:N14) -> 0.0049836364 | O16: =AVERAGE(O5:O14) -> 0.29979232 | ... Q16: =AVERAGE(Q5:Q14) -> 0.081391573
B17: Minimum | H17: =MIN(H5:H14) -> 234.29 | I17: =MIN(I5:I14) -> 119.52 | J17: =MIN(J5:J14) -> 41.1012 | K17: =MIN(K5:K14) -> -0.19109651 | L17: =MIN(L5:L14) -> 0.57413445 | M17: =MIN(M5:M14) -> 0.040392871 | N17: =MIN(N5:N14) -> 0 | O17: =MIN(O5:O14) -> 0.020044213 | ... Q17: =MIN(Q5:Q14) -> 0.020453399
B18: Maximum | H18: =MAX(H5:H14) -> 9078.97 | I18: =MAX(I5:I14) -> 15175.78 | J18: =MAX(J5:J14) -> 32390.848 | K18: =MAX(K5:K14) -> 0.13429716 | L18: =MAX(L5:L14) -> 0.924891 | M18: =MAX(M5:M14) -> 0.18587756 | N18: =MAX(N5:N14) -> 0.025994572 | O18: =MAX(O5:O14) -> 0.534418 | ... Q18: =MAX(Q5:Q14) -> 0.21971019
B19: Coeff. of variation (SD/mean) | H19: =STDEV(H5:H14)/AVERAGE(H5:H14) -> 1.0747906 | I19: =STDEV(I5:I14)/AVERAGE(I5:I14) -> 1.5588836 | J19: =STDEV(J5:J14)/AVERAGE(J5:J14) -> 1.8086734 | K19: =STDEV(K5:K14)/AVERAGE(K5:K14) -> 3.0540321 | L19: =STDEV(L5:L14)/AVERAGE(L5:L14) -> 0.14110106 | M19: =STDEV(M5:M14)/AVERAGE(M5:M14) -> 0.58854746 | N19: =STDEV(N5:N14)/AVERAGE(N5:N14) -> 1.671098 | O19: =STDEV(O5:O14)/AVERAGE(O5:O14) -> 0.56822631 | ... Q19: =STDEV(Q5:Q14)/AVERAGE(Q5:Q14) -> 0.82730417

Sheet Scorecard
A1: SCORECARD - key ratios vs industry (green = better than the 10-firm median, red = weaker)
A2: Block A: latest year FY2026. Block B: 7-year average FY2020-FY2026. Valuation ratios have no normative direction and are not coloured.
A4: Block A: FY2026
A5: Ratio | B5: Category | C5: Tiger | D5: Allcargo | E5: Blue Dart | F5: CONCOR | G5: Jet Freight | H5: Patel | I5: Sical | J5: TCI | K5: Shreeji | L5: Mahindra Log. | M5: Industry (agg.) | N5: Median
A6: Current ratio | B6: Liquidity | C6: =Tiger!J80 -> 4.6170581 | D6: =Allcargo!J80 -> 2.0255864 | E6: =BlueDart!J80 -> 1.3674138 | F6: =CONCOR!J80 -> 4.7511388 | G6: =JetFreight!J80 -> 3.5881855 | H6: =Patel!J80 -> 3.3649374 | I6: =Sical!J80 -> 1.1402597 | J6: =TCI!J80 -> 2.4182809 | K6: =Shreeji!J80 -> 4.7719752 | L6: =MahindraLog!J80 -> 1.4122438 | M6: =Industry!J80 -> 2.4360563 | N6: =IFERROR(MEDIAN(C6:L6),"N/M") -> 2.8916092
A7: Acid-test (quick) ratio | B7: Liquidity | C7: =Tiger!J81 -> 3.8983442 | D7: =Allcargo!J81 -> 1.1940299 | E7: =BlueDart!J81 -> 0.9578767 | F7: =CONCOR!J81 -> 3.1306054 | G7: =JetFreight!J81 -> 2.3645988 | H7: =Patel!J81 -> 2.9698867 | I7: =Sical!J81 -> 0.55759496 | J7: =TCI!J81 -> 1.5404411 | K7: =Shreeji!J81 -> 4.1773526 | L7: =MahindraLog!J81 -> 0.69438023 | M7: =Industry!J81 -> 1.5485939 | N7: =IFERROR(MEDIAN(C7:L7),"N/M") -> 1.9525199
A8: Cash flow from operations ratio | B8: Liquidity | C8: =Tiger!J84 -> -0.33923758 | D8: =Allcargo!J84 -> 0.66950959 | E8: =BlueDart!J84 -> 0.67067013 | F8: =CONCOR!J84 -> 1.1681588 | G8: =JetFreight!J84 -> -0.15350413 | H8: =Patel!J84 -> 0.23613596 | I8: =Sical!J84 -> 0.18013706 | J8: =TCI!J84 -> 0.7363912 | K8: =Shreeji!J84 -> 0.030506722 | L8: =MahindraLog!J84 -> 0.19805854 | M8: =Industry!J84 -> 0.63357276 | N8: =IFERROR(MEDIAN(C8:L8),"N/M") -> 0.21709725
A9: Debt-equity (Khan & Jain) | B9: Leverage | C9: =Tiger!J87 -> 0.31691461 | D9: =Allcargo!J87 -> 1.2073171 | E9: =BlueDart!J87 -> 0.64266137 | F9: =CONCOR!J87 -> 0.074528196 | G9: =JetFreight!J87 -> 1.0175848 | H9: =Patel!J87 -> 0.050680052 | I9: =Sical!J87 -> 3.6944931 | J9: =TCI!J87 -> 0.12174638 | K9: =Shreeji!J87 -> 0.66661121 | L9: =MahindraLog!J87 -> 0.55308228 | M9: =Industry!J87 -> 0.22560776 | N9: =IFERROR(MEDIAN(C9:L9),"N/M") -> 0.59787182
A10: Proprietary ratio | B10: Leverage | C10: =Tiger!J91 -> 0.60916914 | D10: =Allcargo!J91 -> 0.33064516 | E10: =BlueDart!J91 -> 0.43055357 | F10: =CONCOR!J91 -> 0.85282931 | G10: =JetFreight!J91 -> 0.3750322 | H10: =Patel!J91 -> 0.75630664 | I10: =Sical!J91 -> 0.14479503 | J10: =TCI!J91 -> 0.73695956 | K10: =Shreeji!J91 -> 0.50292838 | L10: =MahindraLog!J91 -> 0.37834983 | M10: =Industry!J91 -> 0.66895966 | N10: =IFERROR(MEDIAN(C10:L10),"N/M") -> 0.46674098
A11: Debt / EBITDA | B11: Leverage | C11: =Tiger!J93 -> 1.4334182 | D11: =Allcargo!J93 -> 2.5666667 | E11: =BlueDart!J93 -> 1.2039517 | F11: =CONCOR!J93 -> 0.41136031 | G11: =JetFreight!J93 -> 3.6131707 | H11: =Patel!J93 -> 0.47388342 | I11: =Sical!J93 -> 2.8398712 | J11: =TCI!J93 -> 0.48063017 | K11: =Shreeji!J93 -> 3.418942 | L11: =MahindraLog!J93 -> 1.6830721 | M11: =Industry!J93 -> 0.91070766 | N11: =IFERROR(MEDIAN(C11:L11),"N/M") -> 1.5582451
A12: Interest coverage | B12: Coverage | C12: =Tiger!J96 -> 6.5294118 | D12: =Allcargo!J96 -> 1.0645161 | E12: =BlueDart!J96 -> 4.81539 | F12: =CONCOR!J96 -> 22.020884 | G12: =JetFreight!J96 -> 2.6557143 | H12: =Patel!J96 -> 30.457143 | I12: =Sical!J96 -> 1.7926965 | J12: =TCI!J96 -> 22.93462 | K12: =Shreeji!J96 -> 1.8557692 | L12: =MahindraLog!J96 -> 1.4420155 | M12: =Industry!J96 -> 7.3623722 | N12: =IFERROR(MEDIAN(C12:L12),"N/M") -> 3.7355521
A13: Debt-service coverage ratio (DSCR) | B13: Coverage | C13: =Tiger!J102 -> 5.2656546 | D13: =Allcargo!J102 -> 1.8266667 | E13: =BlueDart!J102 -> 10.148295 | F13: =CONCOR!J102 -> 24.651216 | G13: =JetFreight!J102 -> 2.2442857 | H13: =Patel!J102 -> 1.7458101 | I13: =Sical!J102 -> 0.83683319 | J13: =TCI!J102 -> 26.605529 | K13: =Shreeji!J102 -> 2.0035398 | L13: =MahindraLog!J102 -> 1.2078898 | M13: =Industry!J102 -> 5.0193334 | N13: =IFERROR(MEDIAN(C13:L13),"N/M") -> 2.1239128
A14: Average collection period (days) | B14: Turnover | C14: =Tiger!J108 -> 84.017798 | D14: =Allcargo!J108 -> 71.297376 | E14: =BlueDart!J108 -> 50.651055 | F14: =CONCOR!J108 -> 17.788934 | G14: =JetFreight!J108 -> 71.984102 | H14: =Patel!J108 -> 71.627443 | I14: =Sical!J108 -> 79.53381 | J14: =TCI!J108 -> 57.098039 | K14: =Shreeji!J108 -> 105.5554 | L14: =MahindraLog!J108 -> 34.279274 | M14: =Industry!J108 -> 41.715692 | N14: =IFERROR(MEDIAN(C14:L14),"N/M") -> 71.46241
A15: Fixed assets turnover | B15: Turnover | C15: =Tiger!J112 -> 61.231427 | D15: =Allcargo!J112 -> 2.6692607 | E15: =BlueDart!J112 -> 3.1909295 | F15: =CONCOR!J112 -> 1.3204843 | G15: =JetFreight!J112 -> 17.507589 | H15: =Patel!J112 -> 7.6820822 | I15: =Sical!J112 -> 0.66643052 | J15: =TCI!J112 -> 4.5601862 | K15: =Shreeji!J112 -> 8.7064288 | L15: =MahindraLog!J112 -> 6.7397521 | M15: =Industry!J112 -> 2.5203355 | N15: =IFERROR(MEDIAN(C15:L15),"N/M") -> 5.6499692
A16: Total assets turnover | B16: Turnover | C16: =Tiger!J113 -> 2.4997054 | D16: =Allcargo!J113 -> 1.1837791 | E16: =BlueDart!J113 -> 1.5766848 | F16: =CONCOR!J113 -> 0.61234666 | G16: =JetFreight!J113 -> 2.3588654 | H16: =Patel!J113 -> 2.1550809 | I16: =Sical!J113 -> 0.43687275 | J16: =TCI!J113 -> 1.5326853 | K16: =Shreeji!J113 -> 1.9981237 | L16: =MahindraLog!J113 -> 2.4628902 | M16: =Industry!J113 -> 1.1101718 | N16: =IFERROR(MEDIAN(C16:L16),"N/M") -> 1.7874043
A17: Gross profit margin | B17: Profitability | C17: =Tiger!J119 -> 0.10107887 | D17: =Allcargo!J119 -> 0.26724976 | E17: =BlueDart!J119 -> 0.39087557 | F17: =CONCOR!J119 -> 0.33656461 | G17: =JetFreight!J119 -> 0.098856062 | H17: =Patel!J119 -> 0.092064737 | I17: =Sical!J119 -> 0.33465567 | J17: =TCI!J119 -> 0.18871739 | K17: =Shreeji!J119 -> 0.14328396 | L17: =MahindraLog!J119 -> 0.13752232 | M17: =Industry!J119 -> 0.26272151 | N17: =IFERROR(MEDIAN(C17:L17),"N/M") -> 0.16600068
A18: Operating EBITDA margin (core) | B18: Profitability | C18: =Tiger!J121 -> 0.047152683 | D18: =Allcargo!J121 -> 0.11418853 | E18: =BlueDart!J121 -> 0.15480843 | F18: =CONCOR!J121 -> 0.21492746 | G18: =JetFreight!J121 -> 0.037313097 | H18: =Patel!J121 -> 0.029036232 | I18: =Sical!J121 -> 0.2030699 | J18: =TCI!J121 -> 0.1055571 | K18: =Shreeji!J121 -> 0.033078663 | L18: =MahindraLog!J121 -> 0.054119698 | M18: =Industry!J121 -> 0.13385948 | N18: =IFERROR(MEDIAN(C18:L18),"N/M") -> 0.079838401
A19: Net profit margin | B19: Profitability | C19: =Tiger!J124 -> 0.037568521 | D19: =Allcargo!J124 -> 0.0038872692 | E19: =BlueDart!J124 -> 0.040285757 | F19: =CONCOR!J124 -> 0.13677763 | G19: =JetFreight!J124 -> 0.015312556 | H19: =Patel!J124 -> 0.026880215 | I19: =Sical!J124 -> 0.12777432 | J19: =TCI!J124 -> 0.09279466 | K19: =Shreeji!J124 -> 0.013487558 | L19: =MahindraLog!J124 -> 0.00032717557 | M19: =Industry!J124 -> 0.065605188 | N19: =IFERROR(MEDIAN(C19:L19),"N/M") -> 0.032224368
A20: Operating ratio | B20: Profitability | C20: =Tiger!J132 -> 0.95284732 | D20: =Allcargo!J132 -> 0.88581147 | E20: =BlueDart!J132 -> 0.84519157 | F20: =CONCOR!J132 -> 0.78507254 | G20: =JetFreight!J132 -> 0.9626869 | H20: =Patel!J132 -> 0.97096377 | I20: =Sical!J132 -> 0.7969301 | J20: =TCI!J132 -> 0.8944429 | K20: =Shreeji!J132 -> 0.96692134 | L20: =MahindraLog!J132 -> 0.9458803 | M20: =Industry!J132 -> 0.86614052 | N20: =IFERROR(MEDIAN(C20:L20),"N/M") -> 0.9201616
A21: Return on assets (ROA) | B21: Returns | C21: =Tiger!J135 -> 0.093910235 | D21: =Allcargo!J135 -> 0.0046016681 | E21: =BlueDart!J135 -> 0.063517942 | F21: =CONCOR!J135 -> 0.083755325 | G21: =JetFreight!J135 -> 0.036120259 | H21: =Patel!J135 -> 0.057929037 | I21: =Sical!J135 -> 0.055821119 | J21: =TCI!J135 -> 0.14222501 | K21: =Shreeji!J135 -> 0.02694981 | L21: =MahindraLog!J135 -> 0.00080579752 | M21: =Industry!J135 -> 0.072833032 | N21: =IFERROR(MEDIAN(C21:L21),"N/M") -> 0.056875078
A22: ROCE (post-tax) | B22: Returns | C22: =Tiger!J138 -> 0.13263629 | D22: =Allcargo!J138 -> 0.050574713 | E22: =BlueDart!J138 -> 0.11385367 | F22: =CONCOR!J138 -> 0.096133312 | G22: =JetFreight!J138 -> 0.078789833 | H22: =Patel!J138 -> 0.074973027 | I22: =Sical!J138 -> 0.18235018 | J22: =TCI!J138 -> 0.18230729 | K22: =Shreeji!J138 -> 0.069036714 | L22: =MahindraLog!J138 -> 0.022025614 | M22: =Industry!J138 -> 0.10374805 | N22: =IFERROR(MEDIAN(C22:L22),"N/M") -> 0.087461572
A23: Return on total shareholders' equity | B23: Returns | C23: =Tiger!J139 -> 0.14429395 | D23: =Allcargo!J139 -> 0.014084507 | E23: =BlueDart!J139 -> 0.14832113 | F23: =CONCOR!J139 -> 0.09807371 | G23: =JetFreight!J139 -> 0.097940372 | H23: =Patel!J139 -> 0.078309813 | I23: =Sical!J139 -> 0.77900727 | J23: =TCI!J139 -> 0.19329597 | K23: =Shreeji!J139 -> 0.054067927 | L23: =MahindraLog!J139 -> 0.0028400283 | M23: =Industry!J139 -> 0.11043587 | N23: =IFERROR(MEDIAN(C23:L23),"N/M") -> 0.098007041
A24: Price-earnings (P/E) | B24: Valuation | C24: =Tiger!J152 -> 11.738987 | D24: =Allcargo!J152 -> 134.42755 | E24: =BlueDart!J152 -> 45.476333 | F24: =CONCOR!J152 -> 26.083788 | G24: =JetFreight!J152 -> 11.640941 | H24: =Patel!J152 -> 5.9885 | I24: =Sical!J152 -> 10.200767 | J24: =TCI!J152 -> 15.516515 | K24: =Shreeji!J152 -> 13.006709 | L24: =MahindraLog!J152 -> 1441.6489 | M24: =Industry!J152 -> 27.384187 | N24: =IFERROR(MEDIAN(C24:L24),"N/M") -> 14.261612
A25: Price-to-book (P/B) | B25: Valuation | C25: =Tiger!J146 -> 1.5790911 | D25: =Allcargo!J146 -> 1.8735547 | E25: =BlueDart!J146 -> 6.33172 | F25: =CONCOR!J146 -> 2.5027022 | G25: =JetFreight!J146 -> 1.08749 | H25: =Patel!J146 -> 0.46542746 | I25: =Sical!J146 -> 3.828881 | J25: =TCI!J146 -> 2.758939 | K25: =Shreeji!J146 -> 0.68376643 | L25: =MahindraLog!J146 -> 2.8102079 | M25: =Industry!J146 -> 2.8613799 | N25: =IFERROR(MEDIAN(C25:L25),"N/M") -> 2.1881285
A26: Dividend yield | B26: Valuation | C26: =Tiger!J151 -> 0 | D26: =Allcargo!J151 -> 0 | E26: =BlueDart!J151 -> 0.005279817 | F26: =CONCOR!J151 -> 0.020221453 | G26: =JetFreight!J151 -> 0 | H26: =Patel!J151 -> 0.024178286 | I26: =Sical!J151 -> 0 | J26: =TCI!J151 -> 0.010841299 | K26: =Shreeji!J151 -> 0 | L26: =MahindraLog!J151 -> 0.0075120192 | M26: =Industry!J151 -> 0.014587231 | N26: =IFERROR(MEDIAN(C26:L26),"N/M") -> 0.0026399085
A27: EV / EBITDA | B27: Valuation | C27: =Tiger!J154 -> 7.4038168 | D27: =Allcargo!J154 -> 6.06452 | E27: =BlueDart!J154 -> 12.81373 | F27: =CONCOR!J154 -> 12.737852 | G27: =JetFreight!J154 -> 6.7638244 | H27: =Patel!J154 -> 2.7872521 | I27: =Sical!J154 -> 5.396802 | J27: =TCI!J154 -> 11.198129 | K27: =Shreeji!J154 -> 6.3806485 | L27: =MahindraLog!J154 -> 9.71785 | M27: =Industry!J154 -> 11.569531 | N27: =IFERROR(MEDIAN(C27:L27),"N/M") -> 7.0838206
A28: Total shareholder return (yield) | B28: Valuation | C28: =Tiger!J153 -> -0.49684211 | D28: =Allcargo!J153 -> -0.27911647 | E28: =BlueDart!J153 -> -0.22234771 | F28: =CONCOR!J153 -> -0.21576745 | G28: =JetFreight!J153 -> 0.48090278 | H28: =Patel!J153 -> -0.36678798 | I28: =Sical!J153 -> -0.079205027 | J28: =TCI!J153 -> -0.15373558 | K28: =Shreeji!J153 -> -0.33559322 | L28: =MahindraLog!J153 -> 0.40445673 | M28: =Industry!J153 -> n.a. | N28: =IFERROR(MEDIAN(C28:L28),"N/M") -> -0.21905758
A29: Internal growth rate | B29: Growth | C29: =Tiger!J170 -> 0.10364341 | D29: =Allcargo!J170 -> 0.0046229413 | E29: =BlueDart!J170 -> 0.050714697 | F29: =CONCOR!J170 -> 0.041209407 | G29: =JetFreight!J170 -> 0.037473823 | H29: =Patel!J170 -> 0.052123675 | I29: =Sical!J170 -> 0.059121338 | J29: =TCI!J170 -> 0.13417266 | K29: =Shreeji!J170 -> 0.027696218 | L29: =MahindraLog!J170 -> -0.0078584982 | M29: =Industry!J170 -> 0.045739811 | N29: =IFERROR(MEDIAN(C29:L29),"N/M") -> 0.045962052
A33: Block B: 7-yr average FY2020-26
A34: Ratio | B34: Category | C34: Tiger | D34: Allcargo | E34: Blue Dart | F34: CONCOR | G34: Jet Freight | H34: Patel | I34: Sical | J34: TCI | K34: Shreeji | L34: Mahindra Log. | M34: Industry (agg.) | N34: Median
A35: Current ratio | B35: Liquidity | C35: =Tiger!K80 -> 4.8832317 | D35: =Allcargo!K80 -> 1.6559883 | E35: =BlueDart!K80 -> 1.2083102 | F35: =CONCOR!K80 -> 3.9096987 | G35: =JetFreight!K80 -> 2.7399296 | H35: =Patel!K80 -> 5.5817034 | I35: =Sical!K80 -> 0.7195622 | J35: =TCI!K80 -> 2.8768546 | K35: =Shreeji!K80 -> 5.0975533 | L35: =MahindraLog!K80 -> 1.4129884 | M35: =Industry!K80 -> 1.9742087 | N35: =IFERROR(MEDIAN(C35:L35),"N/M") -> 2.8083921
A36: Acid-test (quick) ratio | B36: Liquidity | C36: =Tiger!K81 -> 4.1690597 | D36: =Allcargo!K81 -> 1.0636674 | E36: =BlueDart!K81 -> 0.82047016 | F36: =CONCOR!K81 -> 2.3952545 | G36: =JetFreight!K81 -> 1.620697 | H36: =Patel!K81 -> 4.3914109 | I36: =Sical!K81 -> 0.46681949 | J36: =TCI!K81 -> 1.9838517 | K36: =Shreeji!K81 -> 3.8810091 | L36: =MahindraLog!K81 -> 0.69863375 | M36: =Industry!K81 -> 1.2448907 | N36: =IFERROR(MEDIAN(C36:L36),"N/M") -> 1.8022743
A37: Cash flow from operations ratio | B37: Liquidity | C37: =Tiger!K84 -> 0.12295018 | D37: =Allcargo!K84 -> 0.33150185 | E37: =BlueDart!K84 -> 0.72776984 | F37: =CONCOR!K84 -> 1.2513667 | G37: =JetFreight!K84 -> -0.11414869 | H37: =Patel!K84 -> 0.10835287 | I37: =Sical!K84 -> 0.12059511 | J37: =TCI!K84 -> 0.99039578 | K37: =Shreeji!K84 -> 0.43081607 | L37: =MahindraLog!K84 -> 0.20161113 | M37: =Industry!K84 -> 0.55763214 | N37: =IFERROR(MEDIAN(C37:L37),"N/M") -> 0.26655649
A38: Debt-equity (Khan & Jain) | B38: Leverage | C38: =Tiger!K87 -> 0.24661787 | D38: =Allcargo!K87 -> 0.87612163 | E38: =BlueDart!K87 -> 1.1280755 | F38: =CONCOR!K87 -> 0.062736366 | G38: =JetFreight!K87 -> 1.3550845 | H38: =Patel!K87 -> 0.29634174 | I38: =Sical!K87 -> 8.2478837 | J38: =TCI!K87 -> 0.15977623 | K38: =Shreeji!K87 -> 1.2179689 | L38: =MahindraLog!K87 -> 1.0148062 | M38: =Industry!K87 -> 0.30963722 | N38: =IFERROR(MEDIAN(C38:L38),"N/M") -> 0.94546393
A39: Proprietary ratio | B39: Leverage | C39: =Tiger!K91 -> 0.64580193 | D39: =Allcargo!K91 -> 0.34869893 | E39: =BlueDart!K91 -> 0.33080972 | F39: =CONCOR!K91 -> 0.84060615 | G39: =JetFreight!K91 -> 0.30649204 | H39: =Patel!K91 -> 0.66174853 | I39: =Sical!K91 -> -0.079794883 | J39: =TCI!K91 -> 0.73518162 | K39: =Shreeji!K91 -> 0.4032542 | L39: =MahindraLog!K91 -> 0.28048555 | M39: =Industry!K91 -> 0.58700064 | N39: =IFERROR(MEDIAN(C39:L39),"N/M") -> 0.37597656
A40: Debt / EBITDA | B40: Leverage | C40: =Tiger!K93 -> 0.58256733 | D40: =Allcargo!K93 -> 2.3575529 | E40: =BlueDart!K93 -> 1.314398 | F40: =CONCOR!K93 -> 0.36006765 | G40: =JetFreight!K93 -> 4.8279833 | H40: =Patel!K93 -> 2.7982777 | I40: =Sical!K93 -> 54.774084 | J40: =TCI!K93 -> 0.59853111 | K40: =Shreeji!K93 -> 3.4213455 | L40: =MahindraLog!K93 -> 2.2238123 | M40: =Industry!K93 -> 1.4224331 | N40: =IFERROR(MEDIAN(C40:L40),"N/M") -> 2.2906826
A41: Interest coverage | B41: Coverage | C41: =Tiger!K96 -> 13.264266 | D41: =Allcargo!K96 -> 5.2576089 | E41: =BlueDart!K96 -> 4.9257002 | F41: =CONCOR!K96 -> 21.182849 | G41: =JetFreight!K96 -> 1.4276612 | H41: =Patel!K96 -> 6.9019376 | I41: =Sical!K96 -> -8.4085999 | J41: =TCI!K96 -> 22.136806 | K41: =Shreeji!K96 -> 2.7932856 | L41: =MahindraLog!K96 -> 2.1526989 | M41: =Industry!K96 -> 6.709308 | N41: =IFERROR(MEDIAN(C41:L41),"N/M") -> 5.0916545
A42: Debt-service coverage ratio (DSCR) | B42: Coverage | C42: =Tiger!K102 -> 8.3102234 | D42: =Allcargo!K102 -> 4.6259727 | E42: =BlueDart!K102 -> 6.3752773 | F42: =CONCOR!K102 -> 20.885259 | G42: =JetFreight!K102 -> 1.3408533 | H42: =Patel!K102 -> 1.0281497 | I42: =Sical!K102 -> -1.5379693 | J42: =TCI!K102 -> 18.499634 | K42: =Shreeji!K102 -> 2.809745 | L42: =MahindraLog!K102 -> 4.6701835 | M42: =Industry!K102 -> 3.5858462 | N42: =IFERROR(MEDIAN(C42:L42),"N/M") -> 4.6480781
A43: Average collection period (days) | B43: Turnover | C43: =Tiger!K108 -> 76.455526 | D43: =Allcargo!K108 -> 83.618072 | E43: =BlueDart!K108 -> 49.630432 | F43: =CONCOR!K108 -> 11.14588 | G43: =JetFreight!K108 -> 53.795498 | H43: =Patel!K108 -> 99.004829 | I43: =Sical!K108 -> 116.20477 | J43: =TCI!K108 -> 57.785641 | K43: =Shreeji!K108 -> 98.188972 | L43: =MahindraLog!K108 -> 44.989336 | M43: =Industry!K108 -> 45.713795 | N43: =IFERROR(MEDIAN(C43:L43),"N/M") -> 67.120583
A44: Fixed assets turnover | B44: Turnover | C44: =Tiger!K112 -> 47.069011 | D44: =Allcargo!K112 -> 4.1918699 | E44: =BlueDart!K112 -> 2.9788976 | F44: =CONCOR!K112 -> 1.355579 | G44: =JetFreight!K112 -> 16.059752 | H44: =Patel!K112 -> 5.7184543 | I44: =Sical!K112 -> 0.58461596 | J44: =TCI!K112 -> 4.3345309 | K44: =Shreeji!K112 -> 7.2256921 | L44: =MahindraLog!K112 -> 10.22712 | M44: =Industry!K112 -> 2.7828711 | N44: =IFERROR(MEDIAN(C44:L44),"N/M") -> 5.0264926
A45: Total assets turnover | B45: Turnover | C45: =Tiger!K113 -> 3.0689379 | D45: =Allcargo!K113 -> 1.5832864 | E45: =BlueDart!K113 -> 1.5174992 | F45: =CONCOR!K113 -> 0.59241299 | G45: =JetFreight!K113 -> 3.1148906 | H45: =Patel!K113 -> 1.5981271 | I45: =Sical!K113 -> 0.30368275 | J45: =TCI!K113 -> 1.7104834 | K45: =Shreeji!K113 -> 1.8179609 | L45: =MahindraLog!K113 -> 2.3336528 | M45: =Industry!K113 -> 1.1560297 | N45: =IFERROR(MEDIAN(C45:L45),"N/M") -> 1.6543052
A46: Gross profit margin | B46: Profitability | C46: =Tiger!K119 -> 0.099915313 | D46: =Allcargo!K119 -> 0.23630924 | E46: =BlueDart!K119 -> 0.42586555 | F46: =CONCOR!K119 -> 0.34613339 | G46: =JetFreight!K119 -> 0.075109 | H46: =Patel!K119 -> 0.099163264 | I46: =Sical!K119 -> 0.22992313 | J46: =TCI!K119 -> 0.1856674 | K46: =Shreeji!K119 -> 0.19571326 | L46: =MahindraLog!K119 -> 0.14384662 | M46: =Industry!K119 -> 0.25888543 | N46: =IFERROR(MEDIAN(C46:L46),"N/M") -> 0.19069033
A47: Operating EBITDA margin (core) | B47: Profitability | C47: =Tiger!K121 -> 0.029629489 | D47: =Allcargo!K121 -> 0.073607981 | E47: =BlueDart!K121 -> 0.17658992 | F47: =CONCOR!K121 -> 0.21971019 | G47: =JetFreight!K121 -> 0.020453399 | H47: =Patel!K121 -> 0.0290875 | I47: =Sical!K121 -> 0.041720612 | J47: =TCI!K121 -> 0.10460636 | K47: =Shreeji!K121 -> 0.072103023 | L47: =MahindraLog!K121 -> 0.046407247 | M47: =Industry!K121 -> 0.11740644 | N47: =IFERROR(MEDIAN(C47:L47),"N/M") -> 0.059255135
A48: Net profit margin | B48: Profitability | C48: =Tiger!K124 -> 0.019312592 | D48: =Allcargo!K124 -> 0.025549208 | E48: =BlueDart!K124 -> 0.045375983 | F48: =CONCOR!K124 -> 0.12136961 | G48: =JetFreight!K124 -> 0.0013562643 | H48: =Patel!K124 -> 0.018081543 | I48: =Sical!K124 -> -0.77125135 | J48: =TCI!K124 -> 0.078488617 | K48: =Shreeji!K124 -> 0.027812603 | L48: =MahindraLog!K124 -> 0.0027070853 | M48: =Industry!K124 -> 0.044064558 | N48: =IFERROR(MEDIAN(C48:L48),"N/M") -> 0.0224309
A49: Operating ratio | B49: Profitability | C49: =Tiger!K132 -> 0.97037051 | D49: =Allcargo!K132 -> 0.92639202 | E49: =BlueDart!K132 -> 0.82341008 | F49: =CONCOR!K132 -> 0.78028981 | G49: =JetFreight!K132 -> 0.9795466 | H49: =Patel!K132 -> 0.9709125 | I49: =Sical!K132 -> 0.95827939 | J49: =TCI!K132 -> 0.89539364 | K49: =Shreeji!K132 -> 0.92789698 | L49: =MahindraLog!K132 -> 0.95359275 | M49: =Industry!K132 -> 0.88259356 | N49: =IFERROR(MEDIAN(C49:L49),"N/M") -> 0.94074487
A50: Return on assets (ROA) | B50: Returns | C50: =Tiger!K135 -> 0.090528493 | D50: =Allcargo!K135 -> 0.042864146 | E50: =BlueDart!K135 -> 0.071195052 | F50: =CONCOR!K135 -> 0.073175301 | G50: =JetFreight!K135 -> 0.0027012001 | H50: =Patel!K135 -> 0.031525739 | I50: =Sical!K135 -> -0.20453573 | J50: =TCI!K135 -> 0.13467284 | K50: =Shreeji!K135 -> 0.056208608 | L50: =MahindraLog!K135 -> 0.0067601854 | M50: =Industry!K135 -> 0.052157997 | N50: =IFERROR(MEDIAN(C50:L50),"N/M") -> 0.049536377
A51: ROCE (post-tax) | B51: Returns | C51: =Tiger!K138 -> 0.14951229 | D51: =Allcargo!K138 -> 0.091915108 | E51: =BlueDart!K138 -> 0.14257551 | F51: =CONCOR!K138 -> 0.085792284 | G51: =JetFreight!K138 -> 0.044213263 | H51: =Patel!K138 -> 0.056385123 | I51: =Sical!K138 -> -0.31089339 | J51: =TCI!K138 -> 0.17138129 | K51: =Shreeji!K138 -> 0.10576238 | L51: =MahindraLog!K138 -> 0.052441099 | M51: =Industry!K138 -> 0.081205452 | N51: =IFERROR(MEDIAN(C51:L51),"N/M") -> 0.088853696
A52: Return on total shareholders' equity | B52: Returns | C52: =Tiger!K139 -> 0.12304841 | D52: =Allcargo!K139 -> 0.12125037 | E52: =BlueDart!K139 -> 0.22147188 | F52: =CONCOR!K139 -> 0.08731004 | G52: =JetFreight!K139 -> 0.0022922337 | H52: =Patel!K139 -> 0.048085994 | I52: =Sical!K139 -> -0.56540655 | J52: =TCI!K139 -> 0.18416184 | K52: =Shreeji!K139 -> 0.14475157 | L52: =MahindraLog!K139 -> 0.008640991 | M52: =Industry!K139 -> 0.089216964 | N52: =IFERROR(MEDIAN(C52:L52),"N/M") -> 0.1042802
A53: Price-earnings (P/E) | B53: Valuation | C53: =Tiger!K152 -> 18.205493 | D53: =Allcargo!K152 -> 134.42755 | E53: =BlueDart!K152 -> 60.639355 | F53: =CONCOR!K152 -> 41.785842 | G53: =JetFreight!K152 -> 203.63814 | H53: =Patel!K152 -> 207.37891 | I53: =Sical!K152 -> 10.200767 | J53: =TCI!K152 -> 15.551279 | K53: =Shreeji!K152 -> 24.35755 | L53: =MahindraLog!K152 -> 406.63754 | M53: =Industry!K152 -> 44.890973 | N53: =IFERROR(MEDIAN(C53:L53),"N/M") -> 51.212598
A54: Price-to-book (P/B) | B54: Valuation | C54: =Tiger!K146 -> 2.5994839 | D54: =Allcargo!K146 -> 1.8735547 | E54: =BlueDart!K146 -> 12.921371 | F54: =CONCOR!K146 -> 3.2852064 | G54: =JetFreight!K146 -> 1.7591522 | H54: =Patel!K146 -> 0.66414011 | I54: =Sical!K146 -> 9.5263998 | J54: =TCI!K146 -> 2.7172077 | K54: =Shreeji!K146 -> 3.4046469 | L54: =MahindraLog!K146 -> 6.0935807 | M54: =Industry!K146 -> 4.0055146 | N54: =IFERROR(MEDIAN(C54:L54),"N/M") -> 3.001207
A55: Dividend yield | B55: Valuation | C55: =Tiger!K151 -> 0.00067832672 | D55: =Allcargo!K151 -> 0 | E55: =BlueDart!K151 -> 0.0042458934 | F55: =CONCOR!K151 -> 0.014493263 | G55: =JetFreight!K151 -> 0.00012704887 | H55: =Patel!K151 -> 0.010418909 | I55: =Sical!K151 -> 0 | J55: =TCI!K151 -> 0.0092816836 | K55: =Shreeji!K151 -> 0.0073395875 | L55: =MahindraLog!K151 -> 0.0053561347 | M55: =Industry!K151 -> 0.011025959 | N55: =IFERROR(MEDIAN(C55:L55),"N/M") -> 0.004801014
A56: EV / EBITDA | B56: Valuation | C56: =Tiger!K154 -> 11.604197 | D56: =Allcargo!K154 -> 6.06452 | E56: =BlueDart!K154 -> 16.39739 | F56: =CONCOR!K154 -> 18.358468 | G56: =JetFreight!K154 -> 9.9736536 | H56: =Patel!K154 -> 7.5796292 | I56: =Sical!K154 -> 59.762941 | J56: =TCI!K154 -> 10.255369 | K56: =Shreeji!K154 -> 10.632527 | L56: =MahindraLog!K154 -> 17.723867 | M56: =Industry!K154 -> 19.647937 | N56: =IFERROR(MEDIAN(C56:L56),"N/M") -> 11.118362
A57: Total shareholder return (yield) | B57: Valuation | C57: =Tiger!K153 -> 0.60564767 | D57: =Allcargo!K153 -> 0.30541645 | E57: =BlueDart!K153 -> 0.15408778 | F57: =CONCOR!K153 -> 0.085201718 | G57: =JetFreight!K153 -> 0.38513905 | H57: =Patel!K153 -> 0.084569459 | I57: =Sical!K153 -> 2.9678184 | J57: =TCI!K153 -> 0.27051341 | K57: =Shreeji!K153 -> 0.3519437 | L57: =MahindraLog!K153 -> 0.11250702 | M57: =Industry!K153 -> n.a. | N57: =IFERROR(MEDIAN(C57:L57),"N/M") -> 0.28796493
A58: Internal growth rate | B58: Growth | C58: =Tiger!K170 -> 0.22131765 | D58: =Allcargo!K170 -> 0.027719315 | E58: =BlueDart!K170 -> 0.068586786 | F58: =CONCOR!K170 -> 0.034276693 | G58: =JetFreight!K170 -> 0.019249173 | H58: =Patel!K170 -> 0.028125309 | I58: =Sical!K170 -> 0.059121338 | J58: =TCI!K170 -> 0.1312687 | K58: =Shreeji!K170 -> 0.066211652 | L58: =MahindraLog!K170 -> 0.0080734663 | M58: =Industry!K170 -> 0.03541842 | N58: =IFERROR(MEDIAN(C58:L58),"N/M") -> 0.046699015
A62: Block C: Composite ranking - 7-yr average FY2020-26 (rank 1 = best among the 10 firms; ties share the better rank)
A63: Ratio | B63: Direction | C63: Tiger | D63: Allcargo | E63: Blue Dart | F63: CONCOR | G63: Jet Freight | H63: Patel | I63: Sical | J63: TCI | K63: Shreeji | L63: Mahindra Log.
A64: Current ratio | B64: higher better | C64: =IF(ISNUMBER(C35),RANK(C35,$C$35:$L$35,0),"-") -> 3 | D64: =IF(ISNUMBER(D35),RANK(D35,$C$35:$L$35,0),"-") -> 7 | E64: =IF(ISNUMBER(E35),RANK(E35,$C$35:$L$35,0),"-") -> 9 | F64: =IF(ISNUMBER(F35),RANK(F35,$C$35:$L$35,0),"-") -> 4 | G64: =IF(ISNUMBER(G35),RANK(G35,$C$35:$L$35,0),"-") -> 6 | H64: =IF(ISNUMBER(H35),RANK(H35,$C$35:$L$35,0),"-") -> 1 | I64: =IF(ISNUMBER(I35),RANK(I35,$C$35:$L$35,0),"-") -> 10 | J64: =IF(ISNUMBER(J35),RANK(J35,$C$35:$L$35,0),"-") -> 5 | ... L64: =IF(ISNUMBER(L35),RANK(L35,$C$35:$L$35,0),"-") -> 8
A65: Cash flow from operations ratio | B65: higher better | C65: =IF(ISNUMBER(C37),RANK(C37,$C$37:$L$37,0),"-") -> 7 | D65: =IF(ISNUMBER(D37),RANK(D37,$C$37:$L$37,0),"-") -> 5 | E65: =IF(ISNUMBER(E37),RANK(E37,$C$37:$L$37,0),"-") -> 3 | F65: =IF(ISNUMBER(F37),RANK(F37,$C$37:$L$37,0),"-") -> 1 | G65: =IF(ISNUMBER(G37),RANK(G37,$C$37:$L$37,0),"-") -> 10 | H65: =IF(ISNUMBER(H37),RANK(H37,$C$37:$L$37,0),"-") -> 9 | I65: =IF(ISNUMBER(I37),RANK(I37,$C$37:$L$37,0),"-") -> 8 | J65: =IF(ISNUMBER(J37),RANK(J37,$C$37:$L$37,0),"-") -> 2 | ... L65: =IF(ISNUMBER(L37),RANK(L37,$C$37:$L$37,0),"-") -> 6
A66: Debt-equity (Khan & Jain) | B66: lower better | C66: =IF(ISNUMBER(C38),RANK(C38,$C$38:$L$38,1),"-") -> 3 | D66: =IF(ISNUMBER(D38),RANK(D38,$C$38:$L$38,1),"-") -> 5 | E66: =IF(ISNUMBER(E38),RANK(E38,$C$38:$L$38,1),"-") -> 7 | F66: =IF(ISNUMBER(F38),RANK(F38,$C$38:$L$38,1),"-") -> 1 | G66: =IF(ISNUMBER(G38),RANK(G38,$C$38:$L$38,1),"-") -> 9 | H66: =IF(ISNUMBER(H38),RANK(H38,$C$38:$L$38,1),"-") -> 4 | I66: =IF(ISNUMBER(I38),RANK(I38,$C$38:$L$38,1),"-") -> 10 | J66: =IF(ISNUMBER(J38),RANK(J38,$C$38:$L$38,1),"-") -> 2 | ... L66: =IF(ISNUMBER(L38),RANK(L38,$C$38:$L$38,1),"-") -> 6
A67: Interest coverage | B67: higher better | C67: =IF(ISNUMBER(C41),RANK(C41,$C$41:$L$41,0),"-") -> 3 | D67: =IF(ISNUMBER(D41),RANK(D41,$C$41:$L$41,0),"-") -> 5 | E67: =IF(ISNUMBER(E41),RANK(E41,$C$41:$L$41,0),"-") -> 6 | F67: =IF(ISNUMBER(F41),RANK(F41,$C$41:$L$41,0),"-") -> 2 | G67: =IF(ISNUMBER(G41),RANK(G41,$C$41:$L$41,0),"-") -> 9 | H67: =IF(ISNUMBER(H41),RANK(H41,$C$41:$L$41,0),"-") -> 4 | I67: =IF(ISNUMBER(I41),RANK(I41,$C$41:$L$41,0),"-") -> 10 | J67: =IF(ISNUMBER(J41),RANK(J41,$C$41:$L$41,0),"-") -> 1 | ... L67: =IF(ISNUMBER(L41),RANK(L41,$C$41:$L$41,0),"-") -> 8
A68: Average collection period (days) | B68: lower better | C68: =IF(ISNUMBER(C43),RANK(C43,$C$43:$L$43,1),"-") -> 6 | D68: =IF(ISNUMBER(D43),RANK(D43,$C$43:$L$43,1),"-") -> 7 | E68: =IF(ISNUMBER(E43),RANK(E43,$C$43:$L$43,1),"-") -> 3 | F68: =IF(ISNUMBER(F43),RANK(F43,$C$43:$L$43,1),"-") -> 1 | G68: =IF(ISNUMBER(G43),RANK(G43,$C$43:$L$43,1),"-") -> 4 | H68: =IF(ISNUMBER(H43),RANK(H43,$C$43:$L$43,1),"-") -> 9 | I68: =IF(ISNUMBER(I43),RANK(I43,$C$43:$L$43,1),"-") -> 10 | J68: =IF(ISNUMBER(J43),RANK(J43,$C$43:$L$43,1),"-") -> 5 | ... L68: =IF(ISNUMBER(L43),RANK(L43,$C$43:$L$43,1),"-") -> 2
A69: Total assets turnover | B69: higher better | C69: =IF(ISNUMBER(C45),RANK(C45,$C$45:$L$45,0),"-") -> 2 | D69: =IF(ISNUMBER(D45),RANK(D45,$C$45:$L$45,0),"-") -> 7 | E69: =IF(ISNUMBER(E45),RANK(E45,$C$45:$L$45,0),"-") -> 8 | F69: =IF(ISNUMBER(F45),RANK(F45,$C$45:$L$45,0),"-") -> 9 | G69: =IF(ISNUMBER(G45),RANK(G45,$C$45:$L$45,0),"-") -> 1 | H69: =IF(ISNUMBER(H45),RANK(H45,$C$45:$L$45,0),"-") -> 6 | I69: =IF(ISNUMBER(I45),RANK(I45,$C$45:$L$45,0),"-") -> 10 | J69: =IF(ISNUMBER(J45),RANK(J45,$C$45:$L$45,0),"-") -> 5 | ... L69: =IF(ISNUMBER(L45),RANK(L45,$C$45:$L$45,0),"-") -> 3
A70: Operating EBITDA margin (core) | B70: higher better | C70: =IF(ISNUMBER(C47),RANK(C47,$C$47:$L$47,0),"-") -> 8 | D70: =IF(ISNUMBER(D47),RANK(D47,$C$47:$L$47,0),"-") -> 4 | E70: =IF(ISNUMBER(E47),RANK(E47,$C$47:$L$47,0),"-") -> 2 | F70: =IF(ISNUMBER(F47),RANK(F47,$C$47:$L$47,0),"-") -> 1 | G70: =IF(ISNUMBER(G47),RANK(G47,$C$47:$L$47,0),"-") -> 10 | H70: =IF(ISNUMBER(H47),RANK(H47,$C$47:$L$47,0),"-") -> 9 | I70: =IF(ISNUMBER(I47),RANK(I47,$C$47:$L$47,0),"-") -> 7 | J70: =IF(ISNUMBER(J47),RANK(J47,$C$47:$L$47,0),"-") -> 3 | ... L70: =IF(ISNUMBER(L47),RANK(L47,$C$47:$L$47,0),"-") -> 6
A71: Net profit margin | B71: higher better | C71: =IF(ISNUMBER(C48),RANK(C48,$C$48:$L$48,0),"-") -> 6 | D71: =IF(ISNUMBER(D48),RANK(D48,$C$48:$L$48,0),"-") -> 5 | E71: =IF(ISNUMBER(E48),RANK(E48,$C$48:$L$48,0),"-") -> 3 | F71: =IF(ISNUMBER(F48),RANK(F48,$C$48:$L$48,0),"-") -> 1 | G71: =IF(ISNUMBER(G48),RANK(G48,$C$48:$L$48,0),"-") -> 9 | H71: =IF(ISNUMBER(H48),RANK(H48,$C$48:$L$48,0),"-") -> 7 | I71: =IF(ISNUMBER(I48),RANK(I48,$C$48:$L$48,0),"-") -> 10 | J71: =IF(ISNUMBER(J48),RANK(J48,$C$48:$L$48,0),"-") -> 2 | ... L71: =IF(ISNUMBER(L48),RANK(L48,$C$48:$L$48,0),"-") -> 8
A72: ROCE (post-tax) | B72: higher better | C72: =IF(ISNUMBER(C51),RANK(C51,$C$51:$L$51,0),"-") -> 2 | D72: =IF(ISNUMBER(D51),RANK(D51,$C$51:$L$51,0),"-") -> 5 | E72: =IF(ISNUMBER(E51),RANK(E51,$C$51:$L$51,0),"-") -> 3 | F72: =IF(ISNUMBER(F51),RANK(F51,$C$51:$L$51,0),"-") -> 6 | G72: =IF(ISNUMBER(G51),RANK(G51,$C$51:$L$51,0),"-") -> 9 | H72: =IF(ISNUMBER(H51),RANK(H51,$C$51:$L$51,0),"-") -> 7 | I72: =IF(ISNUMBER(I51),RANK(I51,$C$51:$L$51,0),"-") -> 10 | J72: =IF(ISNUMBER(J51),RANK(J51,$C$51:$L$51,0),"-") -> 1 | ... L72: =IF(ISNUMBER(L51),RANK(L51,$C$51:$L$51,0),"-") -> 8
A73: Return on total shareholders' equity | B73: higher better | C73: =IF(ISNUMBER(C52),RANK(C52,$C$52:$L$52,0),"-") -> 4 | D73: =IF(ISNUMBER(D52),RANK(D52,$C$52:$L$52,0),"-") -> 5 | E73: =IF(ISNUMBER(E52),RANK(E52,$C$52:$L$52,0),"-") -> 1 | F73: =IF(ISNUMBER(F52),RANK(F52,$C$52:$L$52,0),"-") -> 6 | G73: =IF(ISNUMBER(G52),RANK(G52,$C$52:$L$52,0),"-") -> 9 | H73: =IF(ISNUMBER(H52),RANK(H52,$C$52:$L$52,0),"-") -> 7 | I73: =IF(ISNUMBER(I52),RANK(I52,$C$52:$L$52,0),"-") -> 10 | J73: =IF(ISNUMBER(J52),RANK(J52,$C$52:$L$52,0),"-") -> 2 | ... L73: =IF(ISNUMBER(L52),RANK(L52,$C$52:$L$52,0),"-") -> 8
A74: Composite score (average rank) | C74: =AVERAGE(C64:C73) -> 4.4 | D74: =AVERAGE(D64:D73) -> 5.5 | E74: =AVERAGE(E64:E73) -> 4.5 | F74: =AVERAGE(F64:F73) -> 3.2 | G74: =AVERAGE(G64:G73) -> 7.6 | H74: =AVERAGE(H64:H73) -> 6.3 | I74: =AVERAGE(I64:I73) -> 9.5 | J74: =AVERAGE(J64:J73) -> 2.8 | ... L74: =AVERAGE(L64:L73) -> 6.3
A75: Overall position (1 = strongest) | C75: =RANK(C74,$C$74:$L$74,1) -> 3 | D75: =RANK(D74,$C$74:$L$74,1) -> 6 | E75: =RANK(E74,$C$74:$L$74,1) -> 4 | F75: =RANK(F74,$C$74:$L$74,1) -> 2 | G75: =RANK(G74,$C$74:$L$74,1) -> 9 | H75: =RANK(H74,$C$74:$L$74,1) -> 7 | I75: =RANK(I74,$C$74:$L$74,1) -> 10 | J75: =RANK(J74,$C$74:$L$74,1) -> 1 | ... L75: =RANK(L74,$C$74:$L$74,1) -> 7
A79: Block D: Composite ranking - FY2026 (rank 1 = best among the 10 firms; ties share the better rank)
A80: Ratio | B80: Direction | C80: Tiger | D80: Allcargo | E80: Blue Dart | F80: CONCOR | G80: Jet Freight | H80: Patel | I80: Sical | J80: TCI | K80: Shreeji | L80: Mahindra Log.
A81: Current ratio | B81: higher better | C81: =IF(ISNUMBER(C6),RANK(C6,$C$6:$L$6,0),"-") -> 3 | D81: =IF(ISNUMBER(D6),RANK(D6,$C$6:$L$6,0),"-") -> 7 | E81: =IF(ISNUMBER(E6),RANK(E6,$C$6:$L$6,0),"-") -> 9 | F81: =IF(ISNUMBER(F6),RANK(F6,$C$6:$L$6,0),"-") -> 2 | G81: =IF(ISNUMBER(G6),RANK(G6,$C$6:$L$6,0),"-") -> 4 | H81: =IF(ISNUMBER(H6),RANK(H6,$C$6:$L$6,0),"-") -> 5 | I81: =IF(ISNUMBER(I6),RANK(I6,$C$6:$L$6,0),"-") -> 10 | J81: =IF(ISNUMBER(J6),RANK(J6,$C$6:$L$6,0),"-") -> 6 | ... L81: =IF(ISNUMBER(L6),RANK(L6,$C$6:$L$6,0),"-") -> 8
A82: Cash flow from operations ratio | B82: higher better | C82: =IF(ISNUMBER(C8),RANK(C8,$C$8:$L$8,0),"-") -> 10 | D82: =IF(ISNUMBER(D8),RANK(D8,$C$8:$L$8,0),"-") -> 4 | E82: =IF(ISNUMBER(E8),RANK(E8,$C$8:$L$8,0),"-") -> 3 | F82: =IF(ISNUMBER(F8),RANK(F8,$C$8:$L$8,0),"-") -> 1 | G82: =IF(ISNUMBER(G8),RANK(G8,$C$8:$L$8,0),"-") -> 9 | H82: =IF(ISNUMBER(H8),RANK(H8,$C$8:$L$8,0),"-") -> 5 | I82: =IF(ISNUMBER(I8),RANK(I8,$C$8:$L$8,0),"-") -> 7 | J82: =IF(ISNUMBER(J8),RANK(J8,$C$8:$L$8,0),"-") -> 2 | ... L82: =IF(ISNUMBER(L8),RANK(L8,$C$8:$L$8,0),"-") -> 6
A83: Debt-equity (Khan & Jain) | B83: lower better | C83: =IF(ISNUMBER(C9),RANK(C9,$C$9:$L$9,1),"-") -> 4 | D83: =IF(ISNUMBER(D9),RANK(D9,$C$9:$L$9,1),"-") -> 9 | E83: =IF(ISNUMBER(E9),RANK(E9,$C$9:$L$9,1),"-") -> 6 | F83: =IF(ISNUMBER(F9),RANK(F9,$C$9:$L$9,1),"-") -> 2 | G83: =IF(ISNUMBER(G9),RANK(G9,$C$9:$L$9,1),"-") -> 8 | H83: =IF(ISNUMBER(H9),RANK(H9,$C$9:$L$9,1),"-") -> 1 | I83: =IF(ISNUMBER(I9),RANK(I9,$C$9:$L$9,1),"-") -> 10 | J83: =IF(ISNUMBER(J9),RANK(J9,$C$9:$L$9,1),"-") -> 3 | ... L83: =IF(ISNUMBER(L9),RANK(L9,$C$9:$L$9,1),"-") -> 5
A84: Interest coverage | B84: higher better | C84: =IF(ISNUMBER(C12),RANK(C12,$C$12:$L$12,0),"-") -> 4 | D84: =IF(ISNUMBER(D12),RANK(D12,$C$12:$L$12,0),"-") -> 10 | E84: =IF(ISNUMBER(E12),RANK(E12,$C$12:$L$12,0),"-") -> 5 | F84: =IF(ISNUMBER(F12),RANK(F12,$C$12:$L$12,0),"-") -> 3 | G84: =IF(ISNUMBER(G12),RANK(G12,$C$12:$L$12,0),"-") -> 6 | H84: =IF(ISNUMBER(H12),RANK(H12,$C$12:$L$12,0),"-") -> 1 | I84: =IF(ISNUMBER(I12),RANK(I12,$C$12:$L$12,0),"-") -> 8 | J84: =IF(ISNUMBER(J12),RANK(J12,$C$12:$L$12,0),"-") -> 2 | ... L84: =IF(ISNUMBER(L12),RANK(L12,$C$12:$L$12,0),"-") -> 9
A85: Average collection period (days) | B85: lower better | C85: =IF(ISNUMBER(C14),RANK(C14,$C$14:$L$14,1),"-") -> 9 | D85: =IF(ISNUMBER(D14),RANK(D14,$C$14:$L$14,1),"-") -> 5 | E85: =IF(ISNUMBER(E14),RANK(E14,$C$14:$L$14,1),"-") -> 3 | F85: =IF(ISNUMBER(F14),RANK(F14,$C$14:$L$14,1),"-") -> 1 | G85: =IF(ISNUMBER(G14),RANK(G14,$C$14:$L$14,1),"-") -> 7 | H85: =IF(ISNUMBER(H14),RANK(H14,$C$14:$L$14,1),"-") -> 6 | I85: =IF(ISNUMBER(I14),RANK(I14,$C$14:$L$14,1),"-") -> 8 | J85: =IF(ISNUMBER(J14),RANK(J14,$C$14:$L$14,1),"-") -> 4 | ... L85: =IF(ISNUMBER(L14),RANK(L14,$C$14:$L$14,1),"-") -> 2
A86: Total assets turnover | B86: higher better | C86: =IF(ISNUMBER(C16),RANK(C16,$C$16:$L$16,0),"-") -> 1 | D86: =IF(ISNUMBER(D16),RANK(D16,$C$16:$L$16,0),"-") -> 8 | E86: =IF(ISNUMBER(E16),RANK(E16,$C$16:$L$16,0),"-") -> 6 | F86: =IF(ISNUMBER(F16),RANK(F16,$C$16:$L$16,0),"-") -> 9 | G86: =IF(ISNUMBER(G16),RANK(G16,$C$16:$L$16,0),"-") -> 3 | H86: =IF(ISNUMBER(H16),RANK(H16,$C$16:$L$16,0),"-") -> 4 | I86: =IF(ISNUMBER(I16),RANK(I16,$C$16:$L$16,0),"-") -> 10 | J86: =IF(ISNUMBER(J16),RANK(J16,$C$16:$L$16,0),"-") -> 7 | ... L86: =IF(ISNUMBER(L16),RANK(L16,$C$16:$L$16,0),"-") -> 2
A87: Operating EBITDA margin (core) | B87: higher better | C87: =IF(ISNUMBER(C18),RANK(C18,$C$18:$L$18,0),"-") -> 7 | D87: =IF(ISNUMBER(D18),RANK(D18,$C$18:$L$18,0),"-") -> 4 | E87: =IF(ISNUMBER(E18),RANK(E18,$C$18:$L$18,0),"-") -> 3 | F87: =IF(ISNUMBER(F18),RANK(F18,$C$18:$L$18,0),"-") -> 1 | G87: =IF(ISNUMBER(G18),RANK(G18,$C$18:$L$18,0),"-") -> 8 | H87: =IF(ISNUMBER(H18),RANK(H18,$C$18:$L$18,0),"-") -> 10 | I87: =IF(ISNUMBER(I18),RANK(I18,$C$18:$L$18,0),"-") -> 2 | J87: =IF(ISNUMBER(J18),RANK(J18,$C$18:$L$18,0),"-") -> 5 | ... L87: =IF(ISNUMBER(L18),RANK(L18,$C$18:$L$18,0),"-") -> 6
A88: Net profit margin | B88: higher better | C88: =IF(ISNUMBER(C19),RANK(C19,$C$19:$L$19,0),"-") -> 5 | D88: =IF(ISNUMBER(D19),RANK(D19,$C$19:$L$19,0),"-") -> 9 | E88: =IF(ISNUMBER(E19),RANK(E19,$C$19:$L$19,0),"-") -> 4 | F88: =IF(ISNUMBER(F19),RANK(F19,$C$19:$L$19,0),"-") -> 1 | G88: =IF(ISNUMBER(G19),RANK(G19,$C$19:$L$19,0),"-") -> 7 | H88: =IF(ISNUMBER(H19),RANK(H19,$C$19:$L$19,0),"-") -> 6 | I88: =IF(ISNUMBER(I19),RANK(I19,$C$19:$L$19,0),"-") -> 2 | J88: =IF(ISNUMBER(J19),RANK(J19,$C$19:$L$19,0),"-") -> 3 | ... L88: =IF(ISNUMBER(L19),RANK(L19,$C$19:$L$19,0),"-") -> 10
A89: ROCE (post-tax) | B89: higher better | C89: =IF(ISNUMBER(C22),RANK(C22,$C$22:$L$22,0),"-") -> 3 | D89: =IF(ISNUMBER(D22),RANK(D22,$C$22:$L$22,0),"-") -> 9 | E89: =IF(ISNUMBER(E22),RANK(E22,$C$22:$L$22,0),"-") -> 4 | F89: =IF(ISNUMBER(F22),RANK(F22,$C$22:$L$22,0),"-") -> 5 | G89: =IF(ISNUMBER(G22),RANK(G22,$C$22:$L$22,0),"-") -> 6 | H89: =IF(ISNUMBER(H22),RANK(H22,$C$22:$L$22,0),"-") -> 7 | I89: =IF(ISNUMBER(I22),RANK(I22,$C$22:$L$22,0),"-") -> 1 | J89: =IF(ISNUMBER(J22),RANK(J22,$C$22:$L$22,0),"-") -> 2 | ... L89: =IF(ISNUMBER(L22),RANK(L22,$C$22:$L$22,0),"-") -> 10
A90: Return on total shareholders' equity | B90: higher better | C90: =IF(ISNUMBER(C23),RANK(C23,$C$23:$L$23,0),"-") -> 4 | D90: =IF(ISNUMBER(D23),RANK(D23,$C$23:$L$23,0),"-") -> 9 | E90: =IF(ISNUMBER(E23),RANK(E23,$C$23:$L$23,0),"-") -> 3 | F90: =IF(ISNUMBER(F23),RANK(F23,$C$23:$L$23,0),"-") -> 5 | G90: =IF(ISNUMBER(G23),RANK(G23,$C$23:$L$23,0),"-") -> 6 | H90: =IF(ISNUMBER(H23),RANK(H23,$C$23:$L$23,0),"-") -> 7 | I90: =IF(ISNUMBER(I23),RANK(I23,$C$23:$L$23,0),"-") -> 1 | J90: =IF(ISNUMBER(J23),RANK(J23,$C$23:$L$23,0),"-") -> 2 | ... L90: =IF(ISNUMBER(L23),RANK(L23,$C$23:$L$23,0),"-") -> 10
A91: Composite score (average rank) | C91: =AVERAGE(C81:C90) -> 5 | D91: =AVERAGE(D81:D90) -> 7.4 | E91: =AVERAGE(E81:E90) -> 4.6 | F91: =AVERAGE(F81:F90) -> 3 | G91: =AVERAGE(G81:G90) -> 6.4 | H91: =AVERAGE(H81:H90) -> 5.2 | I91: =AVERAGE(I81:I90) -> 5.9 | J91: =AVERAGE(J81:J90) -> 3.6 | ... L91: =AVERAGE(L81:L90) -> 6.8
A92: Overall position (1 = strongest) | C92: =RANK(C91,$C$91:$L$91,1) -> 4 | D92: =RANK(D91,$C$91:$L$91,1) -> 10 | E92: =RANK(E91,$C$91:$L$91,1) -> 3 | F92: =RANK(F91,$C$91:$L$91,1) -> 1 | G92: =RANK(G91,$C$91:$L$91,1) -> 7 | H92: =RANK(H91,$C$91:$L$91,1) -> 5 | I92: =RANK(I91,$C$91:$L$91,1) -> 6 | J92: =RANK(J91,$C$91:$L$91,1) -> 2 | ... L92: =RANK(L91,$C$91:$L$91,1) -> 8

Sheet Industry_Compare
A1: INDUSTRY COMPARISON - every ratio, every firm, FY2020-FY2026
A2: Industry (aggregate) = ratio computed on summed financials of the 10 firms (size-weighted). Mean / Median / SD = simple statistics of the 10 firm ratios (N/M, N/C ignored). Assessment uses the median as the typical-firm benchmark.
A4: Firm / statistic | B4: FY2020 | C4: FY2021 | D4: FY2022 | E4: FY2023 | F4: FY2024 | G4: FY2025 | H4: FY2026 | I4: 7-yr avg | J4: FY26 vs median | K4: Assessment FY26 | L4: Rank FY26 (1 = best) | M4: 7-yr avg vs median | N4: Assessment 7-yr
A6: Net working capital (Rs cr) [CA - CL] - Liquidity; higher is better
A7: Tiger | B7: =Tiger!D79 -> 79.44 | C7: =Tiger!E79 -> 48.16 | D7: =Tiger!F79 -> 61.36 | E7: =Tiger!G79 -> 84.64 | F7: =Tiger!H79 -> 102.6 | G7: =Tiger!I79 -> 151.77 | H7: =Tiger!J79 -> 187.87 | I7: =Tiger!K79 -> 102.26286 | J7: =IF(AND(ISNUMBER(H7),ISNUMBER(H$19)),IF(H7>H$19,"Above",IF(H7<H$19,"Below","At")),"-") -> Below | K7: =IF(J7="Above","Better",IF(J7="Below","Weaker","-")) -> Weaker | L7: =IF(ISNUMBER(H7),RANK(H7,H$7:H$16,0),"-") -> 6 | N7: =IF(AND(ISNUMBER(I7),ISNUMBER(I$19)),IF(I7>I$19,"Above",IF(I7<I$19,"Below","At")),"-") -> Below | O7: =IF(N7="Above","Better",IF(N7="Below","Weaker","-")) -> Weaker
A8: Allcargo | B8: =Allcargo!D79 -> 1002.04 | C8: =Allcargo!E79 -> 857.7 | D8: =Allcargo!F79 -> 1417.79 | E8: =Allcargo!G79 -> 1265.14 | F8: =Allcargo!H79 -> 1242.73 | G8: =Allcargo!I79 -> 578 | H8: =Allcargo!J79 -> 481 | I8: =Allcargo!K79 -> 977.77143 | J8: =IF(AND(ISNUMBER(H8),ISNUMBER(H$19)),IF(H8>H$19,"Above",IF(H8<H$19,"Below","At")),"-") -> Above | K8: =IF(J8="Above","Better",IF(J8="Below","Weaker","-")) -> Better | L8: =IF(ISNUMBER(H8),RANK(H8,H$7:H$16,0),"-") -> 4 | N8: =IF(AND(ISNUMBER(I8),ISNUMBER(I$19)),IF(I8>I$19,"Above",IF(I8<I$19,"Below","At")),"-") -> Above | O8: =IF(N8="Above","Better",IF(N8="Below","Weaker","-")) -> Better
A9: Blue Dart | B9: =BlueDart!D79 -> -662.18 | C9: =BlueDart!E79 -> 374.18 | D9: =BlueDart!F79 -> 224.54 | E9: =BlueDart!G79 -> 252.87 | F9: =BlueDart!H79 -> 236.54 | G9: =BlueDart!I79 -> 289.72 | H9: =BlueDart!J79 -> 443.88 | I9: =BlueDart!K79 -> 165.65 | J9: =IF(AND(ISNUMBER(H9),ISNUMBER(H$19)),IF(H9>H$19,"Above",IF(H9<H$19,"Below","At")),"-") -> Above | K9: =IF(J9="Above","Better",IF(J9="Below","Weaker","-")) -> Better | L9: =IF(ISNUMBER(H9),RANK(H9,H$7:H$16,0),"-") -> 5 | N9: =IF(AND(ISNUMBER(I9),ISNUMBER(I$19)),IF(I9>I$19,"Above",IF(I9<I$19,"Below","At")),"-") -> Above | O9: =IF(N9="Above","Better",IF(N9="Below","Weaker","-")) -> Better
A10: CONCOR | B10: =CONCOR!D79 -> 2626.3 | C10: =CONCOR!E79 -> 3063.63 | D10: =CONCOR!F79 -> 3805.64 | E10: =CONCOR!G79 -> 4333.98 | F10: =CONCOR!H79 -> 4747.44 | G10: =CONCOR!I79 -> 4689.41 | H10: =CONCOR!J79 -> 4759.67 | I10: =CONCOR!K79 -> 4003.7243 | J10: =IF(AND(ISNUMBER(H10),ISNUMBER(H$19)),IF(H10>H$19,"Above",IF(H10<H$19,"Below","At")),"-") -> Above | K10: =IF(J10="Above","Better",IF(J10="Below","Weaker","-")) -> Better | L10: =IF(ISNUMBER(H10),RANK(H10,H$7:H$16,0),"-") -> 1 | N10: =IF(AND(ISNUMBER(I10),ISNUMBER(I$19)),IF(I10>I$19,"Above",IF(I10<I$19,"Below","At")),"-") -> Above | O10: =IF(N10="Above","Better",IF(N10="Below","Weaker","-")) -> Better
A11: Jet Freight | B11: =JetFreight!D79 -> 39.16 | C11: =JetFreight!E79 -> 23.78 | D11: =JetFreight!F79 -> 42.17 | E11: =JetFreight!G79 -> 92.29 | F11: =JetFreight!H79 -> 90.86 | G11: =JetFreight!I79 -> 103.78 | H11: =JetFreight!J79 -> 122.24 | I11: =JetFreight!K79 -> 73.468571 | J11: =IF(AND(ISNUMBER(H11),ISNUMBER(H$19)),IF(H11>H$19,"Above",IF(H11<H$19,"Below","At")),"-") -> Below | K11: =IF(J11="Above","Better",IF(J11="Below","Weaker","-")) -> Weaker | L11: =IF(ISNUMBER(H11),RANK(H11,H$7:H$16,0),"-") -> 7 | N11: =IF(AND(ISNUMBER(I11),ISNUMBER(I$19)),IF(I11>I$19,"Above",IF(I11<I$19,"Below","At")),"-") -> Below | O11: =IF(N11="Above","Better",IF(N11="Below","Weaker","-")) -> Weaker
A12: Patel | B12: =Patel!D79 -> 115.87 | C12: =Patel!E79 -> 115.04 | D12: =Patel!F79 -> 102.28 | E12: =Patel!G79 -> 88.52 | F12: =Patel!H79 -> 90.18 | G12: =Patel!I79 -> 83.19 | H12: =Patel!J79 -> 79.32 | I12: =Patel!K79 -> 96.342857 | J12: =IF(AND(ISNUMBER(H12),ISNUMBER(H$19)),IF(H12>H$19,"Above",IF(H12<H$19,"Below","At")),"-") -> Below | K12: =IF(J12="Above","Better",IF(J12="Below","Weaker","-")) -> Weaker | L12: =IF(ISNUMBER(H12),RANK(H12,H$7:H$16,0),"-") -> 8 | N12: =IF(AND(ISNUMBER(I12),ISNUMBER(I$19)),IF(I12>I$19,"Above",IF(I12<I$19,"Below","At")),"-") -> Below | O12: =IF(N12="Above","Better",IF(N12="Below","Weaker","-")) -> Weaker
A13: Sical | B13: =Sical!D79 -> -459.35 | C13: =Sical!E79 -> -646.28 | D13: =Sical!F79 -> -337.55 | E13: =Sical!G79 -> -68.93 | F13: =Sical!H79 -> -32.09 | G13: =Sical!I79 -> -51.8 | H13: =Sical!J79 -> 40.73 | I13: =Sical!K79 -> -222.18143 | J13: =IF(AND(ISNUMBER(H13),ISNUMBER(H$19)),IF(H13>H$19,"Above",IF(H13<H$19,"Below","At")),"-") -> Below | K13: =IF(J13="Above","Better",IF(J13="Below","Weaker","-")) -> Weaker | L13: =IF(ISNUMBER(H13),RANK(H13,H$7:H$16,0),"-") -> 10 | N13: =IF(AND(ISNUMBER(I13),ISNUMBER(I$19)),IF(I13>I$19,"Above",IF(I13<I$19,"Below","At")),"-") -> Below | O13: =IF(N13="Above","Better",IF(N13="Below","Weaker","-")) -> Weaker
A14: TCI | B14: =TCI!D79 -> 517.29 | C14: =TCI!E79 -> 507.36 | D14: =TCI!F79 -> 525.15 | E14: =TCI!G79 -> 690.52 | F14: =TCI!H79 -> 684.09 | G14: =TCI!I79 -> 766.74 | H14: =TCI!J79 -> 855.89 | I14: =TCI!K79 -> 649.57714 | J14: =IF(AND(ISNUMBER(H14),ISNUMBER(H$19)),IF(H14>H$19,"Above",IF(H14<H$19,"Below","At")),"-") -> Above | K14: =IF(J14="Above","Better",IF(J14="Below","Weaker","-")) -> Better | L14: =IF(ISNUMBER(H14),RANK(H14,H$7:H$16,0),"-") -> 2 | N14: =IF(AND(ISNUMBER(I14),ISNUMBER(I$19)),IF(I14>I$19,"Above",IF(I14<I$19,"Below","At")),"-") -> Above | O14: =IF(N14="Above","Better",IF(N14="Below","Weaker","-")) -> Better
A15: Shreeji | B15: =Shreeji!D79 -> 43.83 | C15: =Shreeji!E79 -> 46.23 | D15: =Shreeji!F79 -> 56.35 | E15: =Shreeji!G79 -> 56.1 | F15: =Shreeji!H79 -> 66.91 | G15: =Shreeji!I79 -> 65.55 | H15: =Shreeji!J79 -> 72.95 | I15: =Shreeji!K79 -> 58.274286 | J15: =IF(AND(ISNUMBER(H15),ISNUMBER(H$19)),IF(H15>H$19,"Above",IF(H15<H$19,"Below","At")),"-") -> Below | K15: =IF(J15="Above","Better",IF(J15="Below","Weaker","-")) -> Weaker | L15: =IF(ISNUMBER(H15),RANK(H15,H$7:H$16,0),"-") -> 9 | N15: =IF(AND(ISNUMBER(I15),ISNUMBER(I$19)),IF(I15>I$19,"Above",IF(I15<I$19,"Below","At")),"-") -> Below | O15: =IF(N15="Above","Better",IF(N15="Below","Weaker","-")) -> Weaker
A16: Mahindra Log. | B16: =MahindraLog!D79 -> 496.81 | C16: =MahindraLog!E79 -> 418.69 | D16: =MahindraLog!F79 -> 316.78 | E16: =MahindraLog!G79 -> 462.39 | F16: =MahindraLog!H79 -> 373.47 | G16: =MahindraLog!I79 -> 308.71 | H16: =MahindraLog!J79 -> 527.87 | I16: =MahindraLog!K79 -> 414.96 | J16: =IF(AND(ISNUMBER(H16),ISNUMBER(H$19)),IF(H16>H$19,"Above",IF(H16<H$19,"Below","At")),"-") -> Above | K16: =IF(J16="Above","Better",IF(J16="Below","Weaker","-")) -> Better | L16: =IF(ISNUMBER(H16),RANK(H16,H$7:H$16,0),"-") -> 3 | N16: =IF(AND(ISNUMBER(I16),ISNUMBER(I$19)),IF(I16>I$19,"Above",IF(I16<I$19,"Below","At")),"-") -> Above | O16: =IF(N16="Above","Better",IF(N16="Below","Weaker","-")) -> Better
A17: Industry (aggregate) | B17: =Industry!D79 -> 3799.21 | C17: =Industry!E79 -> 4808.49 | D17: =Industry!F79 -> 6214.51 | E17: =Industry!G79 -> 7257.52 | F17: =Industry!H79 -> 7602.73 | G17: =Industry!I79 -> 6985.07 | H17: =Industry!J79 -> 7571.42 | I17: =Industry!K79 -> 6319.85
A18: Mean (10 firms) | B18: =IFERROR(AVERAGE(B7:B16),"N/M") -> 379.921 | C18: =IFERROR(AVERAGE(C7:C16),"N/M") -> 480.849 | D18: =IFERROR(AVERAGE(D7:D16),"N/M") -> 621.451 | E18: =IFERROR(AVERAGE(E7:E16),"N/M") -> 725.752 | F18: =IFERROR(AVERAGE(F7:F16),"N/M") -> 760.273 | G18: =IFERROR(AVERAGE(G7:G16),"N/M") -> 698.507 | H18: =IFERROR(AVERAGE(H7:H16),"N/M") -> 757.142 | I18: =IFERROR(AVERAGE(I7:I16),"N/M") -> 631.985
A19: Median (10 firms) | B19: =IFERROR(MEDIAN(B7:B16),"N/M") -> 97.655 | C19: =IFERROR(MEDIAN(C7:C16),"N/M") -> 244.61 | D19: =IFERROR(MEDIAN(D7:D16),"N/M") -> 163.41 | E19: =IFERROR(MEDIAN(E7:E16),"N/M") -> 172.58 | F19: =IFERROR(MEDIAN(F7:F16),"N/M") -> 169.57 | G19: =IFERROR(MEDIAN(G7:G16),"N/M") -> 220.745 | H19: =IFERROR(MEDIAN(H7:H16),"N/M") -> 315.875 | I19: =IFERROR(MEDIAN(I7:I16),"N/M") -> 133.95643
A20: Std. deviation | B20: =IFERROR(STDEV(B7:B16),"N/M") -> 921.66644 | C20: =IFERROR(STDEV(C7:C16),"N/M") -> 989.83617 | D20: =IFERROR(STDEV(D7:D16),"N/M") -> 1210.6326 | E20: =IFERROR(STDEV(E7:E16),"N/M") -> 1329.2765 | F20: =IFERROR(STDEV(F7:F16),"N/M") -> 1452.8992 | G20: =IFERROR(STDEV(G7:G16),"N/M") -> 1424.4049 | H20: =IFERROR(STDEV(H7:H16),"N/M") -> 1430.8084 | I20: =IFERROR(STDEV(I7:I16),"N/M") -> 1233.3907
A21: Minimum | B21: =IFERROR(MIN(B7:B16),"N/M") -> -662.18 | C21: =IFERROR(MIN(C7:C16),"N/M") -> -646.28 | D21: =IFERROR(MIN(D7:D16),"N/M") -> -337.55 | E21: =IFERROR(MIN(E7:E16),"N/M") -> -68.93 | F21: =IFERROR(MIN(F7:F16),"N/M") -> -32.09 | G21: =IFERROR(MIN(G7:G16),"N/M") -> -51.8 | H21: =IFERROR(MIN(H7:H16),"N/M") -> 40.73 | I21: =IFERROR(MIN(I7:I16),"N/M") -> -222.18143
A22: Maximum | B22: =IFERROR(MAX(B7:B16),"N/M") -> 2626.3 | C22: =IFERROR(MAX(C7:C16),"N/M") -> 3063.63 | D22: =IFERROR(MAX(D7:D16),"N/M") -> 3805.64 | E22: =IFERROR(MAX(E7:E16),"N/M") -> 4333.98 | F22: =IFERROR(MAX(F7:F16),"N/M") -> 4747.44 | G22: =IFERROR(MAX(G7:G16),"N/M") -> 4689.41 | H22: =IFERROR(MAX(H7:H16),"N/M") -> 4759.67 | I22: =IFERROR(MAX(I7:I16),"N/M") -> 4003.7243
A24: Current ratio [CA / CL] - Liquidity; higher is better
A25: Tiger | B25: =Tiger!D80 -> 6.047014 | C25: =Tiger!E80 -> 2.7896693 | D25: =Tiger!F80 -> 2.310551 | E25: =Tiger!G80 -> 4.8683729 | F25: =Tiger!H80 -> 5.9541284 | G25: =Tiger!I80 -> 7.5958279 | H25: =Tiger!J80 -> 4.6170581 | I25: =Tiger!K80 -> 4.8832317 | J25: =IF(AND(ISNUMBER(H25),ISNUMBER(H$37)),IF(H25>H$37,"Above",IF(H25<H$37,"Below","At")),"-") -> Above | K25: =IF(J25="Above","Better",IF(J25="Below","Weaker","-")) -> Better | L25: =IF(ISNUMBER(H25),RANK(H25,H$25:H$34,0),"-") -> 3 | N25: =IF(AND(ISNUMBER(I25),ISNUMBER(I$37)),IF(I25>I$37,"Above",IF(I25<I$37,"Below","At")),"-") -> Above | O25: =IF(N25="Above","Better",IF(N25="Below","Weaker","-")) -> Better
A26: Allcargo | B26: =Allcargo!D80 -> 1.6456859 | C26: =Allcargo!E80 -> 1.2893373 | D26: =Allcargo!F80 -> 1.3437125 | E26: =Allcargo!G80 -> 1.3908215 | F26: =Allcargo!H80 -> 1.4445132 | G26: =Allcargo!I80 -> 2.4522613 | H26: =Allcargo!J80 -> 2.0255864 | I26: =Allcargo!K80 -> 1.6559883 | J26: =IF(AND(ISNUMBER(H26),ISNUMBER(H$37)),IF(H26>H$37,"Above",IF(H26<H$37,"Below","At")),"-") -> Below | K26: =IF(J26="Above","Better",IF(J26="Below","Weaker","-")) -> Weaker | L26: =IF(ISNUMBER(H26),RANK(H26,H$25:H$34,0),"-") -> 7 | N26: =IF(AND(ISNUMBER(I26),ISNUMBER(I$37)),IF(I26>I$37,"Above",IF(I26<I$37,"Below","At")),"-") -> Below | O26: =IF(N26="Above","Better",IF(N26="Below","Weaker","-")) -> Weaker
A27: Blue Dart | B27: =BlueDart!D80 -> 0.59123682 | C27: =BlueDart!E80 -> 1.4776847 | D27: =BlueDart!F80 -> 1.2520571 | E27: =BlueDart!G80 -> 1.2738644 | F27: =BlueDart!H80 -> 1.2317475 | G27: =BlueDart!I80 -> 1.2641671 | H27: =BlueDart!J80 -> 1.3674138 | I27: =BlueDart!K80 -> 1.2083102 | J27: =IF(AND(ISNUMBER(H27),ISNUMBER(H$37)),IF(H27>H$37,"Above",IF(H27<H$37,"Below","At")),"-") -> Below | K27: =IF(J27="Above","Better",IF(J27="Below","Weaker","-")) -> Weaker | L27: =IF(ISNUMBER(H27),RANK(H27,H$25:H$34,0),"-") -> 9 | N27: =IF(AND(ISNUMBER(I27),ISNUMBER(I$37)),IF(I27>I$37,"Above",IF(I27<I$37,"Below","At")),"-") -> Below | O27: =IF(N27="Above","Better",IF(N27="Below","Weaker","-")) -> Weaker
A28: CONCOR | B28: =CONCOR!D80 -> 2.5701338 | C28: =CONCOR!E80 -> 3.042066 | D28: =CONCOR!F80 -> 3.5179069 | E28: =CONCOR!G80 -> 3.9676867 | F28: =CONCOR!H80 -> 4.7198355 | G28: =CONCOR!I80 -> 4.7991234 | H28: =CONCOR!J80 -> 4.7511388 | I28: =CONCOR!K80 -> 3.9096987 | J28: =IF(AND(ISNUMBER(H28),ISNUMBER(H$37)),IF(H28>H$37,"Above",IF(H28<H$37,"Below","At")),"-") -> Above | K28: =IF(J28="Above","Better",IF(J28="Below","Weaker","-")) -> Better | L28: =IF(ISNUMBER(H28),RANK(H28,H$25:H$34,0),"-") -> 2 | N28: =IF(AND(ISNUMBER(I28),ISNUMBER(I$37)),IF(I28>I$37,"Above",IF(I28<I$37,"Below","At")),"-") -> Above | O28: =IF(N28="Above","Better",IF(N28="Below","Weaker","-")) -> Better
A29: Jet Freight | B29: =JetFreight!D80 -> 2.1770364 | C29: =JetFreight!E80 -> 1.5218345 | D29: =JetFreight!F80 -> 2.1581983 | E29: =JetFreight!G80 -> 4.0013008 | F29: =JetFreight!H80 -> 2.7379495 | G29: =JetFreight!I80 -> 2.9950019 | H29: =JetFreight!J80 -> 3.5881855 | I29: =JetFreight!K80 -> 2.7399296 | J29: =IF(AND(ISNUMBER(H29),ISNUMBER(H$37)),IF(H29>H$37,"Above",IF(H29<H$37,"Below","At")),"-") -> Above | K29: =IF(J29="Above","Better",IF(J29="Below","Weaker","-")) -> Better | L29: =IF(ISNUMBER(H29),RANK(H29,H$25:H$34,0),"-") -> 4 | N29: =IF(AND(ISNUMBER(I29),ISNUMBER(I$37)),IF(I29>I$37,"Above",IF(I29<I$37,"Below","At")),"-") -> Below | O29: =IF(N29="Above","Better",IF(N29="Below","Weaker","-")) -> Weaker
A30: Patel | B30: =Patel!D80 -> 5.5191108 | C30: =Patel!E80 -> 10.618729 | D30: =Patel!F80 -> 8.4062274 | E30: =Patel!G80 -> 4.8155172 | F30: =Patel!H80 -> 2.8559374 | G30: =Patel!I80 -> 3.4914645 | H30: =Patel!J80 -> 3.3649374 | I30: =Patel!K80 -> 5.5817034 | J30: =IF(AND(ISNUMBER(H30),ISNUMBER(H$37)),IF(H30>H$37,"Above",IF(H30<H$37,"Below","At")),"-") -> Above | K30: =IF(J30="Above","Better",IF(J30="Below","Weaker","-")) -> Better | L30: =IF(ISNUMBER(H30),RANK(H30,H$25:H$34,0),"-") -> 5 | N30: =IF(AND(ISNUMBER(I30),ISNUMBER(I$37)),IF(I30>I$37,"Above",IF(I30<I$37,"Below","At")),"-") -> Above | O30: =IF(N30="Above","Better",IF(N30="Below","Weaker","-")) -> Better
A31: Sical | B31: =Sical!D80 -> 0.53880059 | C31: =Sical!E80 -> 0.43040965 | D31: =Sical!F80 -> 0.53771673 | E31: =Sical!G80 -> 0.73076322 | F31: =Sical!H80 -> 0.86142419 | G31: =Sical!I80 -> 0.79756136 | H31: =Sical!J80 -> 1.1402597 | I31: =Sical!K80 -> 0.7195622 | J31: =IF(AND(ISNUMBER(H31),ISNUMBER(H$37)),IF(H31>H$37,"Above",IF(H31<H$37,"Below","At")),"-") -> Below | K31: =IF(J31="Above","Better",IF(J31="Below","Weaker","-")) -> Weaker | L31: =IF(ISNUMBER(H31),RANK(H31,H$25:H$34,0),"-") -> 10 | N31: =IF(AND(ISNUMBER(I31),ISNUMBER(I$37)),IF(I31>I$37,"Above",IF(I31<I$37,"Below","At")),"-") -> Below | O31: =IF(N31="Above","Better",IF(N31="Below","Weaker","-")) -> Weaker
A32: TCI | B32: =TCI!D80 -> 3.1791642 | C32: =TCI!E80 -> 2.8679037 | D32: =TCI!F80 -> 2.7474711 | E32: =TCI!G80 -> 3.2474207 | F32: =TCI!H80 -> 3.2510365 | G32: =TCI!I80 -> 2.4267054 | H32: =TCI!J80 -> 2.4182809 | I32: =TCI!K80 -> 2.8768546 | J32: =IF(AND(ISNUMBER(H32),ISNUMBER(H$37)),IF(H32>H$37,"Above",IF(H32<H$37,"Below","At")),"-") -> Below | K32: =IF(J32="Above","Better",IF(J32="Below","Weaker","-")) -> Weaker | L32: =IF(ISNUMBER(H32),RANK(H32,H$25:H$34,0),"-") -> 6 | N32: =IF(AND(ISNUMBER(I32),ISNUMBER(I$37)),IF(I32>I$37,"Above",IF(I32<I$37,"Below","At")),"-") -> Above | O32: =IF(N32="Above","Better",IF(N32="Below","Weaker","-")) -> Better
A33: Shreeji | B33: =Shreeji!D80 -> 6.1143524 | C33: =Shreeji!E80 -> 5.4709865 | D33: =Shreeji!F80 -> 5.4686757 | E33: =Shreeji!G80 -> 4.1375839 | F33: =Shreeji!H80 -> 4.7823629 | G33: =Shreeji!I80 -> 4.9369369 | H33: =Shreeji!J80 -> 4.7719752 | I33: =Shreeji!K80 -> 5.0975533 | J33: =IF(AND(ISNUMBER(H33),ISNUMBER(H$37)),IF(H33>H$37,"Above",IF(H33<H$37,"Below","At")),"-") -> Above | K33: =IF(J33="Above","Better",IF(J33="Below","Weaker","-")) -> Better | L33: =IF(ISNUMBER(H33),RANK(H33,H$25:H$34,0),"-") -> 1 | N33: =IF(AND(ISNUMBER(I33),ISNUMBER(I$37)),IF(I33>I$37,"Above",IF(I33<I$37,"Below","At")),"-") -> Above | O33: =IF(N33="Above","Better",IF(N33="Below","Weaker","-")) -> Better
A34: Mahindra Log. | B34: =MahindraLog!D80 -> 1.7350456 | C34: =MahindraLog!E80 -> 1.4929302 | D34: =MahindraLog!F80 -> 1.30859 | E34: =MahindraLog!G80 -> 1.3995697 | F34: =MahindraLog!H80 -> 1.2998699 | G34: =MahindraLog!I80 -> 1.2426698 | H34: =MahindraLog!J80 -> 1.4122438 | I34: =MahindraLog!K80 -> 1.4129884 | J34: =IF(AND(ISNUMBER(H34),ISNUMBER(H$37)),IF(H34>H$37,"Above",IF(H34<H$37,"Below","At")),"-") -> Below | K34: =IF(J34="Above","Better",IF(J34="Below","Weaker","-")) -> Weaker | L34: =IF(ISNUMBER(H34),RANK(H34,H$25:H$34,0),"-") -> 8 | N34: =IF(AND(ISNUMBER(I34),ISNUMBER(I$37)),IF(I34>I$37,"Above",IF(I34<I$37,"Below","At")),"-") -> Below | O34: =IF(N34="Above","Better",IF(N34="Below","Weaker","-")) -> Weaker
A35: Industry (aggregate) | B35: =Industry!D80 -> 1.5556838 | C35: =Industry!E80 -> 1.6328318 | D35: =Industry!F80 -> 1.7147979 | E35: =Industry!G80 -> 1.9761212 | F35: =Industry!H80 -> 2.0841188 | G35: =Industry!I80 -> 2.4198509 | H35: =Industry!J80 -> 2.4360563 | I35: =Industry!K80 -> 1.9742087
A36: Mean (10 firms) | B36: =IFERROR(AVERAGE(B25:B34),"N/M") -> 3.011758 | C36: =IFERROR(AVERAGE(C25:C34),"N/M") -> 3.1001551 | D36: =IFERROR(AVERAGE(D25:D34),"N/M") -> 2.9051107 | E36: =IFERROR(AVERAGE(E25:E34),"N/M") -> 2.9832901 | F36: =IFERROR(AVERAGE(F25:F34),"N/M") -> 2.9138805 | G36: =IFERROR(AVERAGE(G25:G34),"N/M") -> 3.200172 | H36: =IFERROR(AVERAGE(H25:H34),"N/M") -> 2.945708 | I36: =IFERROR(AVERAGE(I25:I34),"N/M") -> 3.0085821
A37: Median (10 firms) | B37: =IFERROR(MEDIAN(B25:B34),"N/M") -> 2.3735851 | C37: =IFERROR(MEDIAN(C25:C34),"N/M") -> 2.1557519 | D37: =IFERROR(MEDIAN(D25:D34),"N/M") -> 2.2343747 | E37: =IFERROR(MEDIAN(E25:E34),"N/M") -> 3.6075537 | F37: =IFERROR(MEDIAN(F25:F34),"N/M") -> 2.7969435 | G37: =IFERROR(MEDIAN(G25:G34),"N/M") -> 2.7236316 | H37: =IFERROR(MEDIAN(H25:H34),"N/M") -> 2.8916092 | I37: =IFERROR(MEDIAN(I25:I34),"N/M") -> 2.8083921
A38: Std. deviation | B38: =IFERROR(STDEV(B25:B34),"N/M") -> 2.1477661 | C38: =IFERROR(STDEV(C25:C34),"N/M") -> 2.9891803 | D38: =IFERROR(STDEV(D25:D34),"N/M") -> 2.3914171 | E38: =IFERROR(STDEV(E25:E34),"N/M") -> 1.6110133 | F38: =IFERROR(STDEV(F25:F34),"N/M") -> 1.762259 | G38: =IFERROR(STDEV(G25:G34),"N/M") -> 2.0958113 | H38: =IFERROR(STDEV(H25:H34),"N/M") -> 1.460736 | I38: =IFERROR(STDEV(I25:I34),"N/M") -> 1.7718986
A39: Minimum | B39: =IFERROR(MIN(B25:B34),"N/M") -> 0.53880059 | C39: =IFERROR(MIN(C25:C34),"N/M") -> 0.43040965 | D39: =IFERROR(MIN(D25:D34),"N/M") -> 0.53771673 | E39: =IFERROR(MIN(E25:E34),"N/M") -> 0.73076322 | F39: =IFERROR(MIN(F25:F34),"N/M") -> 0.86142419 | G39: =IFERROR(MIN(G25:G34),"N/M") -> 0.79756136 | H39: =IFERROR(MIN(H25:H34),"N/M") -> 1.1402597 | I39: =IFERROR(MIN(I25:I34),"N/M") -> 0.7195622
A40: Maximum | B40: =IFERROR(MAX(B25:B34),"N/M") -> 6.1143524 | C40: =IFERROR(MAX(C25:C34),"N/M") -> 10.618729 | D40: =IFERROR(MAX(D25:D34),"N/M") -> 8.4062274 | E40: =IFERROR(MAX(E25:E34),"N/M") -> 4.8683729 | F40: =IFERROR(MAX(F25:F34),"N/M") -> 5.9541284 | G40: =IFERROR(MAX(G25:G34),"N/M") -> 7.5958279 | H40: =IFERROR(MAX(H25:H34),"N/M") -> 4.7719752 | I40: =IFERROR(MAX(I25:I34),"N/M") -> 5.5817034
A42: Acid-test (quick) ratio [(CA - Inventory - Prepaids) / CL = (Receivables + Cash) / CL] - Liquidity; higher is better
A43: Tiger | B43: =Tiger!D81 -> 4.5463787 | C43: =Tiger!E81 -> 1.8784838 | D43: =Tiger!F81 -> 2.1405382 | E43: =Tiger!G81 -> 4.6480804 | F43: =Tiger!H81 -> 5.385804 | G43: =Tiger!I81 -> 6.6857888 | H43: =Tiger!J81 -> 3.8983442 | I43: =Tiger!K81 -> 4.1690597 | J43: =IF(AND(ISNUMBER(H43),ISNUMBER(H$55)),IF(H43>H$55,"Above",IF(H43<H$55,"Below","At")),"-") -> Above | K43: =IF(J43="Above","Better",IF(J43="Below","Weaker","-")) -> Better | L43: =IF(ISNUMBER(H43),RANK(H43,H$43:H$52,0),"-") -> 2 | N43: =IF(AND(ISNUMBER(I43),ISNUMBER(I$55)),IF(I43>I$55,"Above",IF(I43<I$55,"Below","At")),"-") -> Above | O43: =IF(N43="Above","Better",IF(N43="Below","Weaker","-")) -> Better
A44: Allcargo | B44: =Allcargo!D81 -> 1.1198466 | C44: =Allcargo!E81 -> 0.86255381 | D44: =Allcargo!F81 -> 0.90198137 | E44: =Allcargo!G81 -> 1.0338819 | F44: =Allcargo!H81 -> 0.99669494 | G44: =Allcargo!I81 -> 1.3366834 | H44: =Allcargo!J81 -> 1.1940299 | I44: =Allcargo!K81 -> 1.0636674 | J44: =IF(AND(ISNUMBER(H44),ISNUMBER(H$55)),IF(H44>H$55,"Above",IF(H44<H$55,"Below","At")),"-") -> Below | K44: =IF(J44="Above","Better",IF(J44="Below","Weaker","-")) -> Weaker | L44: =IF(ISNUMBER(H44),RANK(H44,H$43:H$52,0),"-") -> 7 | N44: =IF(AND(ISNUMBER(I44),ISNUMBER(I$55)),IF(I44>I$55,"Above",IF(I44<I$55,"Below","At")),"-") -> Below | O44: =IF(N44="Above","Better",IF(N44="Below","Weaker","-")) -> Weaker
A45: Blue Dart | B45: =BlueDart!D81 -> 0.38780587 | C45: =BlueDart!E81 -> 1.057601 | D45: =BlueDart!F81 -> 0.85800882 | E45: =BlueDart!G81 -> 0.792969 | F45: =BlueDart!H81 -> 0.81971823 | G45: =BlueDart!I81 -> 0.8693115 | H45: =BlueDart!J81 -> 0.9578767 | I45: =BlueDart!K81 -> 0.82047016 | J45: =IF(AND(ISNUMBER(H45),ISNUMBER(H$55)),IF(H45>H$55,"Above",IF(H45<H$55,"Below","At")),"-") -> Below | K45: =IF(J45="Above","Better",IF(J45="Below","Weaker","-")) -> Weaker | L45: =IF(ISNUMBER(H45),RANK(H45,H$43:H$52,0),"-") -> 8 | N45: =IF(AND(ISNUMBER(I45),ISNUMBER(I$55)),IF(I45>I$55,"Above",IF(I45<I$55,"Below","At")),"-") -> Below | O45: =IF(N45="Above","Better",IF(N45="Below","Weaker","-")) -> Weaker
A46: CONCOR | B46: =CONCOR!D81 -> 1.4086844 | C46: =CONCOR!E81 -> 1.7689134 | D46: =CONCOR!F81 -> 2.0507466 | E46: =CONCOR!G81 -> 2.272078 | F46: =CONCOR!H81 -> 2.8440509 | G46: =CONCOR!I81 -> 3.2917024 | H46: =CONCOR!J81 -> 3.1306054 | I46: =CONCOR!K81 -> 2.3952545 | J46: =IF(AND(ISNUMBER(H46),ISNUMBER(H$55)),IF(H46>H$55,"Above",IF(H46<H$55,"Below","At")),"-") -> Above | K46: =IF(J46="Above","Better",IF(J46="Below","Weaker","-")) -> Better | L46: =IF(ISNUMBER(H46),RANK(H46,H$43:H$52,0),"-") -> 3 | N46: =IF(AND(ISNUMBER(I46),ISNUMBER(I$55)),IF(I46>I$55,"Above",IF(I46<I$55,"Below","At")),"-") -> Above | O46: =IF(N46="Above","Better",IF(N46="Below","Weaker","-")) -> Better
A47: Jet Freight | B47: =JetFreight!D81 -> 1.6537421 | C47: =JetFreight!E81 -> 0.93877551 | D47: =JetFreight!F81 -> 1.331777 | E47: =JetFreight!G81 -> 1.739187 | F47: =JetFreight!H81 -> 1.5774675 | G47: =JetFreight!I81 -> 1.739331 | H47: =JetFreight!J81 -> 2.3645988 | I47: =JetFreight!K81 -> 1.620697 | J47: =IF(AND(ISNUMBER(H47),ISNUMBER(H$55)),IF(H47>H$55,"Above",IF(H47<H$55,"Below","At")),"-") -> Above | K47: =IF(J47="Above","Better",IF(J47="Below","Weaker","-")) -> Better | L47: =IF(ISNUMBER(H47),RANK(H47,H$43:H$52,0),"-") -> 5 | N47: =IF(AND(ISNUMBER(I47),ISNUMBER(I$55)),IF(I47>I$55,"Above",IF(I47<I$55,"Below","At")),"-") -> Below | O47: =IF(N47="Above","Better",IF(N47="Below","Weaker","-")) -> Weaker
A48: Patel | B48: =Patel!D81 -> 3.9637285 | C48: =Patel!E81 -> 7.9423077 | D48: =Patel!F81 -> 6.2280956 | E48: =Patel!G81 -> 4.225 | F48: =Patel!H81 -> 2.5336489 | G48: =Patel!I81 -> 2.8772087 | H48: =Patel!J81 -> 2.9698867 | I48: =Patel!K81 -> 4.3914109 | J48: =IF(AND(ISNUMBER(H48),ISNUMBER(H$55)),IF(H48>H$55,"Above",IF(H48<H$55,"Below","At")),"-") -> Above | K48: =IF(J48="Above","Better",IF(J48="Below","Weaker","-")) -> Better | L48: =IF(ISNUMBER(H48),RANK(H48,H$43:H$52,0),"-") -> 4 | N48: =IF(AND(ISNUMBER(I48),ISNUMBER(I$55)),IF(I48>I$55,"Above",IF(I48<I$55,"Below","At")),"-") -> Above | O48: =IF(N48="Above","Better",IF(N48="Below","Weaker","-")) -> Better
A49: Sical | B49: =Sical!D81 -> 0.29196076 | C49: =Sical!E81 -> 0.24450927 | D49: =Sical!F81 -> 0.31262155 | E49: =Sical!G81 -> 0.53558316 | F49: =Sical!H81 -> 0.70548862 | G49: =Sical!I81 -> 0.61997811 | H49: =Sical!J81 -> 0.55759496 | I49: =Sical!K81 -> 0.46681949 | J49: =IF(AND(ISNUMBER(H49),ISNUMBER(H$55)),IF(H49>H$55,"Above",IF(H49<H$55,"Below","At")),"-") -> Below | K49: =IF(J49="Above","Better",IF(J49="Below","Weaker","-")) -> Weaker | L49: =IF(ISNUMBER(H49),RANK(H49,H$43:H$52,0),"-") -> 10 | N49: =IF(AND(ISNUMBER(I49),ISNUMBER(I$55)),IF(I49>I$55,"Above",IF(I49<I$55,"Below","At")),"-") -> Below | O49: =IF(N49="Above","Better",IF(N49="Below","Weaker","-")) -> Weaker
A50: TCI | B50: =TCI!D81 -> 2.1620187 | C50: =TCI!E81 -> 2.0269126 | D50: =TCI!F81 -> 1.9389724 | E50: =TCI!G81 -> 2.4263303 | F50: =TCI!H81 -> 2.2909839 | G50: =TCI!I81 -> 1.5013025 | H50: =TCI!J81 -> 1.5404411 | I50: =TCI!K81 -> 1.9838517 | J50: =IF(AND(ISNUMBER(H50),ISNUMBER(H$55)),IF(H50>H$55,"Above",IF(H50<H$55,"Below","At")),"-") -> Below | K50: =IF(J50="Above","Better",IF(J50="Below","Weaker","-")) -> Weaker | L50: =IF(ISNUMBER(H50),RANK(H50,H$43:H$52,0),"-") -> 6 | N50: =IF(AND(ISNUMBER(I50),ISNUMBER(I$55)),IF(I50>I$55,"Above",IF(I50<I$55,"Below","At")),"-") -> Above | O50: =IF(N50="Above","Better",IF(N50="Below","Weaker","-")) -> Better
A51: Shreeji | B51: =Shreeji!D81 -> 3.5227538 | C51: =Shreeji!E81 -> 4.0522244 | D51: =Shreeji!F81 -> 3.8818398 | E51: =Shreeji!G81 -> 3.4765101 | F51: =Shreeji!H81 -> 3.924251 | G51: =Shreeji!I81 -> 4.1321321 | H51: =Shreeji!J81 -> 4.1773526 | I51: =Shreeji!K81 -> 3.8810091 | J51: =IF(AND(ISNUMBER(H51),ISNUMBER(H$55)),IF(H51>H$55,"Above",IF(H51<H$55,"Below","At")),"-") -> Above | K51: =IF(J51="Above","Better",IF(J51="Below","Weaker","-")) -> Better | L51: =IF(ISNUMBER(H51),RANK(H51,H$43:H$52,0),"-") -> 1 | N51: =IF(AND(ISNUMBER(I51),ISNUMBER(I$55)),IF(I51>I$55,"Above",IF(I51<I$55,"Below","At")),"-") -> Above | O51: =IF(N51="Above","Better",IF(N51="Below","Weaker","-")) -> Better
A52: Mahindra Log. | B52: =MahindraLog!D81 -> 0.93973871 | C52: =MahindraLog!E81 -> 0.80454208 | D52: =MahindraLog!F81 -> 0.60711711 | E52: =MahindraLog!G81 -> 0.67292304 | F52: =MahindraLog!H81 -> 0.6206401 | G52: =MahindraLog!I81 -> 0.55109501 | H52: =MahindraLog!J81 -> 0.69438023 | I52: =MahindraLog!K81 -> 0.69863375 | J52: =IF(AND(ISNUMBER(H52),ISNUMBER(H$55)),IF(H52>H$55,"Above",IF(H52<H$55,"Below","At")),"-") -> Below | K52: =IF(J52="Above","Better",IF(J52="Below","Weaker","-")) -> Weaker | L52: =IF(ISNUMBER(H52),RANK(H52,H$43:H$52,0),"-") -> 9 | N52: =IF(AND(ISNUMBER(I52),ISNUMBER(I$55)),IF(I52>I$55,"Above",IF(I52<I$55,"Below","At")),"-") -> Below | O52: =IF(N52="Above","Better",IF(N52="Below","Weaker","-")) -> Weaker
A53: Industry (aggregate) | B53: =Industry!D81 -> 0.93899956 | C53: =Industry!E81 -> 1.0240038 | D53: =Industry!F81 -> 1.0699672 | E53: =Industry!G81 -> 1.2607565 | F53: =Industry!H81 -> 1.3221457 | G53: =Industry!I81 -> 1.5497685 | H53: =Industry!J81 -> 1.5485939 | I53: =Industry!K81 -> 1.2448907
A54: Mean (10 firms) | B54: =IFERROR(AVERAGE(B43:B52),"N/M") -> 1.9996658 | C54: =IFERROR(AVERAGE(C43:C52),"N/M") -> 2.1576824 | D54: =IFERROR(AVERAGE(D43:D52),"N/M") -> 2.0251699 | E54: =IFERROR(AVERAGE(E43:E52),"N/M") -> 2.1822543 | F54: =IFERROR(AVERAGE(F43:F52),"N/M") -> 2.1698748 | G54: =IFERROR(AVERAGE(G43:G52),"N/M") -> 2.3604534 | H54: =IFERROR(AVERAGE(H43:H52),"N/M") -> 2.1485111 | I54: =IFERROR(AVERAGE(I43:I52),"N/M") -> 2.1490874
A55: Median (10 firms) | B55: =IFERROR(MEDIAN(B43:B52),"N/M") -> 1.5312132 | C55: =IFERROR(MEDIAN(C43:C52),"N/M") -> 1.4132572 | D55: =IFERROR(MEDIAN(D43:D52),"N/M") -> 1.6353747 | E55: =IFERROR(MEDIAN(E43:E52),"N/M") -> 2.0056325 | F55: =IFERROR(MEDIAN(F43:F52),"N/M") -> 1.9342257 | G55: =IFERROR(MEDIAN(G43:G52),"N/M") -> 1.6203168 | H55: =IFERROR(MEDIAN(H43:H52),"N/M") -> 1.9525199 | I55: =IFERROR(MEDIAN(I43:I52),"N/M") -> 1.8022743
A56: Std. deviation | B56: =IFERROR(STDEV(B43:B52),"N/M") -> 1.5118143 | C56: =IFERROR(STDEV(C43:C52),"N/M") -> 2.2891499 | D56: =IFERROR(STDEV(D43:D52),"N/M") -> 1.8006637 | E56: =IFERROR(STDEV(E43:E52),"N/M") -> 1.5066754 | F56: =IFERROR(STDEV(F43:F52),"N/M") -> 1.5675999 | G56: =IFERROR(STDEV(G43:G52),"N/M") -> 1.9344884 | H56: =IFERROR(STDEV(H43:H52),"N/M") -> 1.341967 | I56: =IFERROR(STDEV(I43:I52),"N/M") -> 1.5037787
A57: Minimum | B57: =IFERROR(MIN(B43:B52),"N/M") -> 0.29196076 | C57: =IFERROR(MIN(C43:C52),"N/M") -> 0.24450927 | D57: =IFERROR(MIN(D43:D52),"N/M") -> 0.31262155 | E57: =IFERROR(MIN(E43:E52),"N/M") -> 0.53558316 | F57: =IFERROR(MIN(F43:F52),"N/M") -> 0.6206401 | G57: =IFERROR(MIN(G43:G52),"N/M") -> 0.55109501 | H57: =IFERROR(MIN(H43:H52),"N/M") -> 0.55759496 | I57: =IFERROR(MIN(I43:I52),"N/M") -> 0.46681949
A58: Maximum | B58: =IFERROR(MAX(B43:B52),"N/M") -> 4.5463787 | C58: =IFERROR(MAX(C43:C52),"N/M") -> 7.9423077 | D58: =IFERROR(MAX(D43:D52),"N/M") -> 6.2280956 | E58: =IFERROR(MAX(E43:E52),"N/M") -> 4.6480804 | F58: =IFERROR(MAX(F43:F52),"N/M") -> 5.385804 | G58: =IFERROR(MAX(G43:G52),"N/M") -> 6.6857888 | H58: =IFERROR(MAX(H43:H52),"N/M") -> 4.1773526 | I58: =IFERROR(MAX(I43:I52),"N/M") -> 4.3914109
A60: Cash ratio [(Cash + Bank + Current investments) / CL] - Liquidity; higher is better
A61: Tiger | B61: =Tiger!D82 -> 0.38373571 | C61: =Tiger!E82 -> 0.27424749 | D61: =Tiger!F82 -> 0.67407091 | E61: =Tiger!G82 -> 2.3948812 | F61: =Tiger!H82 -> 2.0159343 | G61: =Tiger!I82 -> 2.2233811 | H61: =Tiger!J82 -> 0.7980362 | I61: =Tiger!K82 -> 1.252041 | J61: =IF(AND(ISNUMBER(H61),ISNUMBER(H$73)),IF(H61>H$73,"Above",IF(H61<H$73,"Below","At")),"-") -> Above | K61: =IF(J61="Above","Better",IF(J61="Below","Weaker","-")) -> Better | L61: =IF(ISNUMBER(H61),RANK(H61,H$61:H$70,0),"-") -> 3 | N61: =IF(AND(ISNUMBER(I61),ISNUMBER(I$73)),IF(I61>I$73,"Above",IF(I61<I$73,"Below","At")),"-") -> Above | O61: =IF(N61="Above","Better",IF(N61="Below","Weaker","-")) -> Better
A62: Allcargo | B62: =Allcargo!D82 -> 0.37876152 | C62: =Allcargo!E82 -> 0.12860111 | D62: =Allcargo!F82 -> 0.15620871 | E62: =Allcargo!G82 -> 0.4042964 | F62: =Allcargo!H82 -> 0.19987409 | G62: =Allcargo!I82 -> 0.39447236 | H62: =Allcargo!J82 -> 0.2793177 | I62: =Allcargo!K82 -> 0.2773617 | J62: =IF(AND(ISNUMBER(H62),ISNUMBER(H$73)),IF(H62>H$73,"Above",IF(H62<H$73,"Below","At")),"-") -> Below | K62: =IF(J62="Above","Better",IF(J62="Below","Weaker","-")) -> Weaker | L62: =IF(ISNUMBER(H62),RANK(H62,H$61:H$70,0),"-") -> 6 | N62: =IF(AND(ISNUMBER(I62),ISNUMBER(I$73)),IF(I62>I$73,"Above",IF(I62<I$73,"Below","At")),"-") -> Above | O62: =IF(N62="Above","Better",IF(N62="Below","Weaker","-")) -> Better
A63: Blue Dart | B63: =BlueDart!D82 -> 0.061729919 | C63: =BlueDart!E82 -> 0.39641526 | D63: =BlueDart!F82 -> 0.20691939 | E63: =BlueDart!G82 -> 0.10345052 | F63: =BlueDart!H82 -> 0.16287181 | G63: =BlueDart!I82 -> 0.1525535 | H63: =BlueDart!J82 -> 0.19781148 | I63: =BlueDart!K82 -> 0.18310741 | J63: =IF(AND(ISNUMBER(H63),ISNUMBER(H$73)),IF(H63>H$73,"Above",IF(H63<H$73,"Below","At")),"-") -> Below | K63: =IF(J63="Above","Better",IF(J63="Below","Weaker","-")) -> Weaker | L63: =IF(ISNUMBER(H63),RANK(H63,H$61:H$70,0),"-") -> 8 | N63: =IF(AND(ISNUMBER(I63),ISNUMBER(I$73)),IF(I63>I$73,"Above",IF(I63<I$73,"Below","At")),"-") -> Below | O63: =IF(N63="Above","Better",IF(N63="Below","Weaker","-")) -> Weaker
A64: CONCOR | B64: =CONCOR!D82 -> 1.3102603 | C64: =CONCOR!E82 -> 1.6615787 | D64: =CONCOR!F82 -> 1.9305161 | E64: =CONCOR!G82 -> 2.1241723 | F64: =CONCOR!H82 -> 2.5826366 | G64: =CONCOR!I82 -> 2.9676588 | H64: =CONCOR!J82 -> 2.7483883 | I64: =CONCOR!K82 -> 2.1893159 | J64: =IF(AND(ISNUMBER(H64),ISNUMBER(H$73)),IF(H64>H$73,"Above",IF(H64<H$73,"Below","At")),"-") -> Above | K64: =IF(J64="Above","Better",IF(J64="Below","Weaker","-")) -> Better | L64: =IF(ISNUMBER(H64),RANK(H64,H$61:H$70,0),"-") -> 1 | N64: =IF(AND(ISNUMBER(I64),ISNUMBER(I$73)),IF(I64>I$73,"Above",IF(I64<I$73,"Below","At")),"-") -> Above | O64: =IF(N64="Above","Better",IF(N64="Below","Weaker","-")) -> Better
A65: Jet Freight | B65: =JetFreight!D82 -> 0.10339645 | C65: =JetFreight!E82 -> 0.070002194 | D65: =JetFreight!F82 -> 0.18099423 | E65: =JetFreight!G82 -> 0.27609756 | F65: =JetFreight!H82 -> 0.25439939 | G65: =JetFreight!I82 -> 0.23894656 | H65: =JetFreight!J82 -> 0.30849037 | I65: =JetFreight!K82 -> 0.20461811 | J65: =IF(AND(ISNUMBER(H65),ISNUMBER(H$73)),IF(H65>H$73,"Above",IF(H65<H$73,"Below","At")),"-") -> Above | K65: =IF(J65="Above","Better",IF(J65="Below","Weaker","-")) -> Better | L65: =IF(ISNUMBER(H65),RANK(H65,H$61:H$70,0),"-") -> 5 | N65: =IF(AND(ISNUMBER(I65),ISNUMBER(I$73)),IF(I65>I$73,"Above",IF(I65<I$73,"Below","At")),"-") -> Below | O65: =IF(N65="Above","Better",IF(N65="Below","Weaker","-")) -> Weaker
A66: Patel | B66: =Patel!D82 -> 0.50195008 | C66: =Patel!E82 -> 1.9297659 | D66: =Patel!F82 -> 1.5691528 | E66: =Patel!G82 -> 1.0413793 | F66: =Patel!H82 -> 0.66577485 | G66: =Patel!I82 -> 0.85594489 | H66: =Patel!J82 -> 0.80292188 | I66: =Patel!K82 -> 1.0524128 | J66: =IF(AND(ISNUMBER(H66),ISNUMBER(H$73)),IF(H66>H$73,"Above",IF(H66<H$73,"Below","At")),"-") -> Above | K66: =IF(J66="Above","Better",IF(J66="Below","Weaker","-")) -> Better | L66: =IF(ISNUMBER(H66),RANK(H66,H$61:H$70,0),"-") -> 2 | N66: =IF(AND(ISNUMBER(I66),ISNUMBER(I$73)),IF(I66>I$73,"Above",IF(I66<I$73,"Below","At")),"-") -> Above | O66: =IF(N66="Above","Better",IF(N66="Below","Weaker","-")) -> Better
A67: Sical | B67: =Sical!D82 -> 0.050462354 | C67: =Sical!E82 -> 0.056951985 | D67: =Sical!F82 -> 0.11849133 | E67: =Sical!G82 -> 0.32208421 | F67: =Sical!H82 -> 0.51522218 | G67: =Sical!I82 -> 0.33808817 | H67: =Sical!J82 -> 0.22717724 | I67: =Sical!K82 -> 0.23263964 | J67: =IF(AND(ISNUMBER(H67),ISNUMBER(H$73)),IF(H67>H$73,"Above",IF(H67<H$73,"Below","At")),"-") -> Below | K67: =IF(J67="Above","Better",IF(J67="Below","Weaker","-")) -> Weaker | L67: =IF(ISNUMBER(H67),RANK(H67,H$61:H$70,0),"-") -> 7 | N67: =IF(AND(ISNUMBER(I67),ISNUMBER(I$73)),IF(I67>I$73,"Above",IF(I67<I$73,"Below","At")),"-") -> Below | O67: =IF(N67="Above","Better",IF(N67="Below","Weaker","-")) -> Weaker
A68: TCI | B68: =TCI!D82 -> 0.10919201 | C68: =TCI!E82 -> 0.14546057 | D68: =TCI!F82 -> 0.24773726 | E68: =TCI!G82 -> 0.60074858 | F68: =TCI!H82 -> 0.31457716 | G68: =TCI!I82 -> 0.157977 | H68: =TCI!J82 -> 0.18766467 | I68: =TCI!K82 -> 0.25190818 | J68: =IF(AND(ISNUMBER(H68),ISNUMBER(H$73)),IF(H68>H$73,"Above",IF(H68<H$73,"Below","At")),"-") -> Below | K68: =IF(J68="Above","Better",IF(J68="Below","Weaker","-")) -> Weaker | L68: =IF(ISNUMBER(H68),RANK(H68,H$61:H$70,0),"-") -> 9 | N68: =IF(AND(ISNUMBER(I68),ISNUMBER(I$73)),IF(I68>I$73,"Above",IF(I68<I$73,"Below","At")),"-") -> Below | O68: =IF(N68="Above","Better",IF(N68="Below","Weaker","-")) -> Weaker
A69: Shreeji | B69: =Shreeji!D82 -> 0.37456243 | C69: =Shreeji!E82 -> 0.5270793 | D69: =Shreeji!F82 -> 0.34020619 | E69: =Shreeji!G82 -> 0.37639821 | F69: =Shreeji!H82 -> 0.25664217 | G69: =Shreeji!I82 -> 0.46186186 | H69: =Shreeji!J82 -> 0.33040331 | I69: =Shreeji!K82 -> 0.38102192 | J69: =IF(AND(ISNUMBER(H69),ISNUMBER(H$73)),IF(H69>H$73,"Above",IF(H69<H$73,"Below","At")),"-") -> Above | K69: =IF(J69="Above","Better",IF(J69="Below","Weaker","-")) -> Better | L69: =IF(ISNUMBER(H69),RANK(H69,H$61:H$70,0),"-") -> 4 | N69: =IF(AND(ISNUMBER(I69),ISNUMBER(I$73)),IF(I69>I$73,"Above",IF(I69<I$73,"Below","At")),"-") -> Above | O69: =IF(N69="Above","Better",IF(N69="Below","Weaker","-")) -> Better
A70: Mahindra Log. | B70: =MahindraLog!D82 -> 0.14725769 | C70: =MahindraLog!E82 -> 0.23283768 | D70: =MahindraLog!F82 -> 0.13085705 | E70: =MahindraLog!G82 -> 0.10908038 | F70: =MahindraLog!H82 -> 0.05706417 | G70: =MahindraLog!I82 -> 0.05971827 | H70: =MahindraLog!J82 -> 0.15584 | I70: =MahindraLog!K82 -> 0.12752218 | J70: =IF(AND(ISNUMBER(H70),ISNUMBER(H$73)),IF(H70>H$73,"Above",IF(H70<H$73,"Below","At")),"-") -> Below | K70: =IF(J70="Above","Better",IF(J70="Below","Weaker","-")) -> Weaker | L70: =IF(ISNUMBER(H70),RANK(H70,H$61:H$70,0),"-") -> 10 | N70: =IF(AND(ISNUMBER(I70),ISNUMBER(I$73)),IF(I70>I$73,"Above",IF(I70<I$73,"Below","At")),"-") -> Below | O70: =IF(N70="Above","Better",IF(N70="Below","Weaker","-")) -> Weaker
A71: Industry (aggregate) | B71: =Industry!D82 -> 0.4505909 | C71: =Industry!E82 -> 0.46398635 | D71: =Industry!F82 -> 0.47226734 | E71: =Industry!G82 -> 0.67133957 | F71: =Industry!H82 -> 0.62728546 | G71: =Industry!I82 -> 0.88110164 | H71: =Industry!J82 -> 0.82039197 | I71: =Industry!K82 -> 0.62670903
A72: Mean (10 firms) | B72: =IFERROR(AVERAGE(B61:B70),"N/M") -> 0.34213085 | C72: =IFERROR(AVERAGE(C61:C70),"N/M") -> 0.54229401 | D72: =IFERROR(AVERAGE(D61:D70),"N/M") -> 0.5555154 | E72: =IFERROR(AVERAGE(E61:E70),"N/M") -> 0.77525886 | F72: =IFERROR(AVERAGE(F61:F70),"N/M") -> 0.70249968 | G72: =IFERROR(AVERAGE(G61:G70),"N/M") -> 0.78506026 | H72: =IFERROR(AVERAGE(H61:H70),"N/M") -> 0.60360512 | I72: =IFERROR(AVERAGE(I61:I70),"N/M") -> 0.61519488
A73: Median (10 firms) | B73: =IFERROR(MEDIAN(B61:B70),"N/M") -> 0.26091006 | C73: =IFERROR(MEDIAN(C61:C70),"N/M") -> 0.25354259 | D73: =IFERROR(MEDIAN(D61:D70),"N/M") -> 0.22732832 | E73: =IFERROR(MEDIAN(E61:E70),"N/M") -> 0.3903473 | F73: =IFERROR(MEDIAN(F61:F70),"N/M") -> 0.28560967 | G73: =IFERROR(MEDIAN(G61:G70),"N/M") -> 0.36628026 | H73: =IFERROR(MEDIAN(H61:H70),"N/M") -> 0.29390403 | I73: =IFERROR(MEDIAN(I61:I70),"N/M") -> 0.26463494
A74: Std. deviation | B74: =IFERROR(STDEV(B61:B70),"N/M") -> 0.37710399 | C74: =IFERROR(STDEV(C61:C70),"N/M") -> 0.67939807 | D74: =IFERROR(STDEV(D61:D70),"N/M") -> 0.65538661 | E74: =IFERROR(STDEV(E61:E70),"N/M") -> 0.82934849 | F74: =IFERROR(STDEV(F61:F70),"N/M") -> 0.86966989 | G74: =IFERROR(STDEV(G61:G70),"N/M") -> 0.99509841 | H74: =IFERROR(STDEV(H61:H70),"N/M") -> 0.79052629 | I74: =IFERROR(STDEV(I61:I70),"N/M") -> 0.67618053
A75: Minimum | B75: =IFERROR(MIN(B61:B70),"N/M") -> 0.050462354 | C75: =IFERROR(MIN(C61:C70),"N/M") -> 0.056951985 | D75: =IFERROR(MIN(D61:D70),"N/M") -> 0.11849133 | E75: =IFERROR(MIN(E61:E70),"N/M") -> 0.10345052 | F75: =IFERROR(MIN(F61:F70),"N/M") -> 0.05706417 | G75: =IFERROR(MIN(G61:G70),"N/M") -> 0.05971827 | H75: =IFERROR(MIN(H61:H70),"N/M") -> 0.15584 | I75: =IFERROR(MIN(I61:I70),"N/M") -> 0.12752218
A76: Maximum | B76: =IFERROR(MAX(B61:B70),"N/M") -> 1.3102603 | C76: =IFERROR(MAX(C61:C70),"N/M") -> 1.9297659 | D76: =IFERROR(MAX(D61:D70),"N/M") -> 1.9305161 | E76: =IFERROR(MAX(E61:E70),"N/M") -> 2.3948812 | F76: =IFERROR(MAX(F61:F70),"N/M") -> 2.5826366 | G76: =IFERROR(MAX(G61:G70),"N/M") -> 2.9676588 | H76: =IFERROR(MAX(H61:H70),"N/M") -> 2.7483883 | I76: =IFERROR(MAX(I61:I70),"N/M") -> 2.1893159
A78: Defensive-interval ratio (days) [Liquid assets / (Cash operating expenses / 365)] - Liquidity; higher is better
A79: Tiger | B79: =Tiger!D83 -> 84.291477 | C79: =Tiger!E83 -> 104.02994 | D79: =Tiger!F83 -> 63.341414 | E79: =Tiger!G83 -> 91.225332 | F79: =Tiger!H83 -> 181.01507 | G79: =Tiger!I83 -> 111.21551 | H79: =Tiger!J83 -> 135.40463 | I79: =Tiger!K83 -> 110.07477 | J79: =IF(AND(ISNUMBER(H79),ISNUMBER(H$91)),IF(H79>H$91,"Above",IF(H79<H$91,"Below","At")),"-") -> Above | K79: =IF(J79="Above","Better",IF(J79="Below","Weaker","-")) -> Better | L79: =IF(ISNUMBER(H79),RANK(H79,H$79:H$88,0),"-") -> 3 | N79: =IF(AND(ISNUMBER(I79),ISNUMBER(I$91)),IF(I79>I$91,"Above",IF(I79<I$91,"Below","At")),"-") -> Above | O79: =IF(N79="Above","Better",IF(N79="Below","Weaker","-")) -> Better
A80: Allcargo | B80: =Allcargo!D83 -> 92.859244 | C80: =Allcargo!E83 -> 94.700645 | D80: =Allcargo!F83 -> 76.37579 | E80: =Allcargo!G83 -> 72.237994 | F80: =Allcargo!H83 -> 81.378075 | G80: =Allcargo!I83 -> 110.39227 | H80: =Allcargo!J83 -> 112.12287 | I80: =Allcargo!K83 -> 91.438127 | J80: =IF(AND(ISNUMBER(H80),ISNUMBER(H$91)),IF(H80>H$91,"Above",IF(H80<H$91,"Below","At")),"-") -> Above | K80: =IF(J80="Above","Better",IF(J80="Below","Weaker","-")) -> Better | L80: =IF(ISNUMBER(H80),RANK(H80,H$79:H$88,0),"-") -> 5 | N80: =IF(AND(ISNUMBER(I80),ISNUMBER(I$91)),IF(I80>I$91,"Above",IF(I80<I$91,"Below","At")),"-") -> Below | O80: =IF(N80="Above","Better",IF(N80="Below","Weaker","-")) -> Weaker
A81: Blue Dart | B81: =BlueDart!D83 -> 84.911036 | C81: =BlueDart!E83 -> 116.21798 | D81: =BlueDart!F83 -> 81.802004 | E81: =BlueDart!G83 -> 63.109873 | F81: =BlueDart!H83 -> 69.172437 | G81: =BlueDart!I83 -> 71.840782 | H81: =BlueDart!J83 -> 81.381704 | I81: =BlueDart!K83 -> 81.205117 | J81: =IF(AND(ISNUMBER(H81),ISNUMBER(H$91)),IF(H81>H$91,"Above",IF(H81<H$91,"Below","At")),"-") -> Below | K81: =IF(J81="Above","Better",IF(J81="Below","Weaker","-")) -> Weaker | L81: =IF(ISNUMBER(H81),RANK(H81,H$79:H$88,0),"-") -> 8 | N81: =IF(AND(ISNUMBER(I81),ISNUMBER(I$91)),IF(I81>I$91,"Above",IF(I81<I$91,"Below","At")),"-") -> Below | O81: =IF(N81="Above","Better",IF(N81="Below","Weaker","-")) -> Weaker
A82: CONCOR | B82: =CONCOR!D83 -> 177.83754 | C82: =CONCOR!E83 -> 180.05646 | D82: =CONCOR!F83 -> 191.61409 | E82: =CONCOR!G83 -> 192.20002 | F82: =CONCOR!H83 -> 197.89413 | G82: =CONCOR!I83 -> 213.16977 | H82: =CONCOR!J83 -> 203.41761 | I82: =CONCOR!K83 -> 193.74137 | J82: =IF(AND(ISNUMBER(H82),ISNUMBER(H$91)),IF(H82>H$91,"Above",IF(H82<H$91,"Below","At")),"-") -> Above | K82: =IF(J82="Above","Better",IF(J82="Below","Weaker","-")) -> Better | L82: =IF(ISNUMBER(H82),RANK(H82,H$79:H$88,0),"-") -> 1 | N82: =IF(AND(ISNUMBER(I82),ISNUMBER(I$91)),IF(I82>I$91,"Above",IF(I82<I$91,"Below","At")),"-") -> Above | O82: =IF(N82="Above","Better",IF(N82="Below","Weaker","-")) -> Better
A83: Jet Freight | B83: =JetFreight!D83 -> 66.214844 | C83: =JetFreight!E83 -> 46.26852 | D83: =JetFreight!F83 -> 39.6853 | E83: =JetFreight!G83 -> 47.762852 | F83: =JetFreight!H83 -> 78.828759 | G83: =JetFreight!I83 -> 78.192064 | H83: =JetFreight!J83 -> 95.350284 | I83: =JetFreight!K83 -> 64.61466 | J83: =IF(AND(ISNUMBER(H83),ISNUMBER(H$91)),IF(H83>H$91,"Above",IF(H83<H$91,"Below","At")),"-") -> Below | K83: =IF(J83="Above","Better",IF(J83="Below","Weaker","-")) -> Weaker | L83: =IF(ISNUMBER(H83),RANK(H83,H$79:H$88,0),"-") -> 7 | N83: =IF(AND(ISNUMBER(I83),ISNUMBER(I$91)),IF(I83>I$91,"Above",IF(I83<I$91,"Below","At")),"-") -> Below | O83: =IF(N83="Above","Better",IF(N83="Below","Weaker","-")) -> Weaker
A84: Patel | B84: =Patel!D83 -> 109.32144 | C84: =Patel!E83 -> 167.42974 | D84: =Patel!F83 -> 138.52381 | E84: =Patel!G83 -> 133.51732 | F84: =Patel!H83 -> 159.65589 | G84: =Patel!I83 -> 105.02441 | H84: =Patel!J83 -> 104.84658 | I84: =Patel!K83 -> 131.18845 | J84: =IF(AND(ISNUMBER(H84),ISNUMBER(H$91)),IF(H84>H$91,"Above",IF(H84<H$91,"Below","At")),"-") -> Below | K84: =IF(J84="Above","Better",IF(J84="Below","Weaker","-")) -> Weaker | L84: =IF(ISNUMBER(H84),RANK(H84,H$79:H$88,0),"-") -> 6 | N84: =IF(AND(ISNUMBER(I84),ISNUMBER(I$91)),IF(I84>I$91,"Above",IF(I84<I$91,"Below","At")),"-") -> Above | O84: =IF(N84="Above","Better",IF(N84="Below","Weaker","-")) -> Better
A85: Sical | B85: =Sical!D83 -> 103.2163 | C85: =Sical!E83 -> 197.36094 | D85: =Sical!F83 -> 214.72193 | E85: =Sical!G83 -> 137.30056 | F85: =Sical!H83 -> 291.60375 | G85: =Sical!I83 -> 289.04108 | H85: =Sical!J83 -> 192.28527 | I85: =Sical!K83 -> 203.64712 | J85: =IF(AND(ISNUMBER(H85),ISNUMBER(H$91)),IF(H85>H$91,"Above",IF(H85<H$91,"Below","At")),"-") -> Above | K85: =IF(J85="Above","Better",IF(J85="Below","Weaker","-")) -> Better | L85: =IF(ISNUMBER(H85),RANK(H85,H$79:H$88,0),"-") -> 2 | N85: =IF(AND(ISNUMBER(I85),ISNUMBER(I$91)),IF(I85>I$91,"Above",IF(I85<I$91,"Below","At")),"-") -> Above | O85: =IF(N85="Above","Better",IF(N85="Below","Weaker","-")) -> Better
A86: TCI | B86: =TCI!D83 -> 75.644201 | C86: =TCI!E83 -> 79.134096 | D86: =TCI!F83 -> 74.705653 | E86: =TCI!G83 -> 81.050831 | F86: =TCI!H83 -> 70.335411 | G86: =TCI!I83 -> 73.08932 | H86: =TCI!J83 -> 77.154478 | I86: =TCI!K83 -> 75.873427 | J86: =IF(AND(ISNUMBER(H86),ISNUMBER(H$91)),IF(H86>H$91,"Above",IF(H86<H$91,"Below","At")),"-") -> Below | K86: =IF(J86="Above","Better",IF(J86="Below","Weaker","-")) -> Weaker | L86: =IF(ISNUMBER(H86),RANK(H86,H$79:H$88,0),"-") -> 9 | N86: =IF(AND(ISNUMBER(I86),ISNUMBER(I$91)),IF(I86>I$91,"Above",IF(I86<I$91,"Below","At")),"-") -> Below | O86: =IF(N86="Above","Better",IF(N86="Below","Weaker","-")) -> Weaker
A87: Shreeji | B87: =Shreeji!D83 -> 109.15651 | C87: =Shreeji!E83 -> 151.2411 | D87: =Shreeji!F83 -> 121.51772 | E87: =Shreeji!G83 -> 136.01343 | F87: =Shreeji!H83 -> 109.39599 | G87: =Shreeji!I83 -> 118.92404 | H87: =Shreeji!J83 -> 130.1684 | I87: =Shreeji!K83 -> 125.20246 | J87: =IF(AND(ISNUMBER(H87),ISNUMBER(H$91)),IF(H87>H$91,"Above",IF(H87<H$91,"Below","At")),"-") -> Above | K87: =IF(J87="Above","Better",IF(J87="Below","Weaker","-")) -> Better | L87: =IF(ISNUMBER(H87),RANK(H87,H$79:H$88,0),"-") -> 4 | N87: =IF(AND(ISNUMBER(I87),ISNUMBER(I$91)),IF(I87>I$91,"Above",IF(I87<I$91,"Below","At")),"-") -> Above | O87: =IF(N87="Above","Better",IF(N87="Below","Weaker","-")) -> Better
A88: Mahindra Log. | B88: =MahindraLog!D83 -> 69.984061 | C88: =MahindraLog!E83 -> 79.714561 | D88: =MahindraLog!F83 -> 57.496449 | E88: =MahindraLog!G83 -> 58.384765 | F88: =MahindraLog!H83 -> 53.487866 | G88: =MahindraLog!I83 -> 43.964125 | H88: =MahindraLog!J83 -> 49.019878 | I88: =MahindraLog!K83 -> 58.864529 | J88: =IF(AND(ISNUMBER(H88),ISNUMBER(H$91)),IF(H88>H$91,"Above",IF(H88<H$91,"Below","At")),"-") -> Below | K88: =IF(J88="Above","Better",IF(J88="Below","Weaker","-")) -> Weaker | L88: =IF(ISNUMBER(H88),RANK(H88,H$79:H$88,0),"-") -> 10 | N88: =IF(AND(ISNUMBER(I88),ISNUMBER(I$91)),IF(I88>I$91,"Above",IF(I88<I$91,"Below","At")),"-") -> Below | O88: =IF(N88="Above","Better",IF(N88="Below","Weaker","-")) -> Weaker
A89: Industry (aggregate) | B89: =Industry!D83 -> 105.37052 | C89: =Industry!E83 -> 114.32589 | D89: =Industry!F83 -> 95.150745 | E89: =Industry!G83 -> 91.759859 | F89: =Industry!H83 -> 100.06819 | G89: =Industry!I83 -> 110.94862 | H89: =Industry!J83 -> 110.32181 | I89: =Industry!K83 -> 103.99223
A90: Mean (10 firms) | B90: =IFERROR(AVERAGE(B79:B88),"N/M") -> 97.343665 | C90: =IFERROR(AVERAGE(C79:C88),"N/M") -> 121.6154 | D90: =IFERROR(AVERAGE(D79:D88),"N/M") -> 105.97842 | E90: =IFERROR(AVERAGE(E79:E88),"N/M") -> 101.2803 | F90: =IFERROR(AVERAGE(F79:F88),"N/M") -> 129.27674 | G90: =IFERROR(AVERAGE(G79:G88),"N/M") -> 121.48534 | H90: =IFERROR(AVERAGE(H79:H88),"N/M") -> 118.11517 | I90: =IFERROR(AVERAGE(I79:I88),"N/M") -> 113.585
A91: Median (10 firms) | B91: =IFERROR(MEDIAN(B79:B88),"N/M") -> 88.88514 | C91: =IFERROR(MEDIAN(C79:C88),"N/M") -> 110.12396 | D91: =IFERROR(MEDIAN(D79:D88),"N/M") -> 79.088897 | E91: =IFERROR(MEDIAN(E79:E88),"N/M") -> 86.138082 | F91: =IFERROR(MEDIAN(F79:F88),"N/M") -> 95.387034 | G91: =IFERROR(MEDIAN(G79:G88),"N/M") -> 107.70834 | H91: =IFERROR(MEDIAN(H79:H88),"N/M") -> 108.48473 | I91: =IFERROR(MEDIAN(I79:I88),"N/M") -> 100.75645
A92: Std. deviation | B92: =IFERROR(STDEV(B79:B88),"N/M") -> 32.197689 | C92: =IFERROR(STDEV(C79:C88),"N/M") -> 49.921781 | D92: =IFERROR(STDEV(D79:D88),"N/M") -> 59.124431 | E92: =IFERROR(STDEV(E79:E88),"N/M") -> 46.337391 | F92: =IFERROR(STDEV(F79:F88),"N/M") -> 76.538471 | G92: =IFERROR(STDEV(G79:G88),"N/M") -> 74.294917 | H92: =IFERROR(STDEV(H79:H88),"N/M") -> 49.16345 | I92: =IFERROR(STDEV(I79:I88),"N/M") -> 50.932336
A93: Minimum | B93: =IFERROR(MIN(B79:B88),"N/M") -> 66.214844 | C93: =IFERROR(MIN(C79:C88),"N/M") -> 46.26852 | D93: =IFERROR(MIN(D79:D88),"N/M") -> 39.6853 | E93: =IFERROR(MIN(E79:E88),"N/M") -> 47.762852 | F93: =IFERROR(MIN(F79:F88),"N/M") -> 53.487866 | G93: =IFERROR(MIN(G79:G88),"N/M") -> 43.964125 | H93: =IFERROR(MIN(H79:H88),"N/M") -> 49.019878 | I93: =IFERROR(MIN(I79:I88),"N/M") -> 58.864529
A94: Maximum | B94: =IFERROR(MAX(B79:B88),"N/M") -> 177.83754 | C94: =IFERROR(MAX(C79:C88),"N/M") -> 197.36094 | D94: =IFERROR(MAX(D79:D88),"N/M") -> 214.72193 | E94: =IFERROR(MAX(E79:E88),"N/M") -> 192.20002 | F94: =IFERROR(MAX(F79:F88),"N/M") -> 291.60375 | G94: =IFERROR(MAX(G79:G88),"N/M") -> 289.04108 | H94: =IFERROR(MAX(H79:H88),"N/M") -> 203.41761 | I94: =IFERROR(MAX(I79:I88),"N/M") -> 203.64712
A96: Cash flow from operations ratio [CFO / CL] - Liquidity; higher is better
A97: Tiger | B97: =Tiger!D84 -> 0.13468869 | C97: =Tiger!E84 -> 0.97027127 | D97: =Tiger!F84 -> 0.94446818 | E97: =Tiger!G84 -> 0.77193784 | F97: =Tiger!H84 -> -0.83051666 | G97: =Tiger!I84 -> -0.79096045 | H97: =Tiger!J84 -> -0.33923758 | I97: =Tiger!K84 -> 0.12295018 | J97: =IF(AND(ISNUMBER(H97),ISNUMBER(H$109)),IF(H97>H$109,"Above",IF(H97<H$109,"Below","At")),"-") -> Below | K97: =IF(J97="Above","Better",IF(J97="Below","Weaker","-")) -> Weaker | L97: =IF(ISNUMBER(H97),RANK(H97,H$97:H$106,0),"-") -> 10 | N97: =IF(AND(ISNUMBER(I97),ISNUMBER(I$109)),IF(I97>I$109,"Above",IF(I97<I$109,"Below","At")),"-") -> Below | O97: =IF(N97="Above","Better",IF(N97="Below","Weaker","-")) -> Weaker
A98: Allcargo | B98: =Allcargo!D84 -> 0.20585089 | C98: =Allcargo!E84 -> 0.11123818 | D98: =Allcargo!F84 -> 0.20614653 | E98: =Allcargo!G84 -> 0.48893928 | F98: =Allcargo!H84 -> -0.052126293 | G98: =Allcargo!I84 -> 0.69095477 | H98: =Allcargo!J84 -> 0.66950959 | I98: =Allcargo!K84 -> 0.33150185 | J98: =IF(AND(ISNUMBER(H98),ISNUMBER(H$109)),IF(H98>H$109,"Above",IF(H98<H$109,"Below","At")),"-") -> Above | K98: =IF(J98="Above","Better",IF(J98="Below","Weaker","-")) -> Better | L98: =IF(ISNUMBER(H98),RANK(H98,H$97:H$106,0),"-") -> 4 | N98: =IF(AND(ISNUMBER(I98),ISNUMBER(I$109)),IF(I98>I$109,"Above",IF(I98<I$109,"Below","At")),"-") -> Above | O98: =IF(N98="Above","Better",IF(N98="Below","Weaker","-")) -> Better
A99: Blue Dart | B99: =BlueDart!D84 -> 0.22476481 | C99: =BlueDart!E84 -> 0.9576929 | D99: =BlueDart!F84 -> 0.96515609 | E99: =BlueDart!G84 -> 0.7762471 | F99: =BlueDart!H84 -> 0.8295744 | G99: =BlueDart!I84 -> 0.67028348 | H99: =BlueDart!J84 -> 0.67067013 | I99: =BlueDart!K84 -> 0.72776984 | J99: =IF(AND(ISNUMBER(H99),ISNUMBER(H$109)),IF(H99>H$109,"Above",IF(H99<H$109,"Below","At")),"-") -> Above | K99: =IF(J99="Above","Better",IF(J99="Below","Weaker","-")) -> Better | L99: =IF(ISNUMBER(H99),RANK(H99,H$97:H$106,0),"-") -> 3 | N99: =IF(AND(ISNUMBER(I99),ISNUMBER(I$109)),IF(I99>I$109,"Above",IF(I99<I$109,"Below","At")),"-") -> Above | O99: =IF(N99="Above","Better",IF(N99="Below","Weaker","-")) -> Better
A100: CONCOR | B100: =CONCOR!D84 -> 2.5622482 | C100: =CONCOR!E84 -> 0.68592111 | D100: =CONCOR!F84 -> 0.90604262 | E100: =CONCOR!G84 -> 0.96264012 | F100: =CONCOR!H84 -> 1.087953 | G100: =CONCOR!I84 -> 1.3866034 | H100: =CONCOR!J84 -> 1.1681588 | I100: =CONCOR!K84 -> 1.2513667 | J100: =IF(AND(ISNUMBER(H100),ISNUMBER(H$109)),IF(H100>H$109,"Above",IF(H100<H$109,"Below","At")),"-") -> Above | K100: =IF(J100="Above","Better",IF(J100="Below","Weaker","-")) -> Better | L100: =IF(ISNUMBER(H100),RANK(H100,H$97:H$106,0),"-") -> 1 | N100: =IF(AND(ISNUMBER(I100),ISNUMBER(I$109)),IF(I100>I$109,"Above",IF(I100<I$109,"Below","At")),"-") -> Above | O100: =IF(N100="Above","Better",IF(N100="Below","Weaker","-")) -> Better
A101: Jet Freight | B101: =JetFreight!D84 -> 0.38443042 | C101: =JetFreight!E84 -> 0.21812596 | D101: =JetFreight!F84 -> -0.29003021 | E101: =JetFreight!G84 -> -1.2653659 | F101: =JetFreight!H84 -> 0.32345065 | G101: =JetFreight!I84 -> -0.016147636 | H101: =JetFreight!J84 -> -0.15350413 | I101: =JetFreight!K84 -> -0.11414869 | J101: =IF(AND(ISNUMBER(H101),ISNUMBER(H$109)),IF(H101>H$109,"Above",IF(H101<H$109,"Below","At")),"-") -> Below | K101: =IF(J101="Above","Better",IF(J101="Below","Weaker","-")) -> Weaker | L101: =IF(ISNUMBER(H101),RANK(H101,H$97:H$106,0),"-") -> 9 | N101: =IF(AND(ISNUMBER(I101),ISNUMBER(I$109)),IF(I101>I$109,"Above",IF(I101<I$109,"Below","At")),"-") -> Below | O101: =IF(N101="Above","Better",IF(N101="Below","Weaker","-")) -> Weaker
A102: Patel | B102: =Patel!D84 -> -0.61037441 | C102: =Patel!E84 -> 0.38043478 | D102: =Patel!F84 -> 0.66256336 | E102: =Patel!G84 -> -0.18793103 | F102: =Patel!H84 -> 0.25128627 | G102: =Patel!I84 -> 0.026355196 | H102: =Patel!J84 -> 0.23613596 | I102: =Patel!K84 -> 0.10835287 | J102: =IF(AND(ISNUMBER(H102),ISNUMBER(H$109)),IF(H102>H$109,"Above",IF(H102<H$109,"Below","At")),"-") -> Above | K102: =IF(J102="Above","Better",IF(J102="Below","Weaker","-")) -> Better | L102: =IF(ISNUMBER(H102),RANK(H102,H$97:H$106,0),"-") -> 5 | N102: =IF(AND(ISNUMBER(I102),ISNUMBER(I$109)),IF(I102>I$109,"Above",IF(I102<I$109,"Below","At")),"-") -> Below | O102: =IF(N102="Above","Better",IF(N102="Below","Weaker","-")) -> Weaker
A103: Sical | B103: =Sical!D84 -> 0.29352704 | C103: =Sical!E84 -> 0.13945392 | D103: =Sical!F84 -> 0.092525131 | E103: =Sical!G84 -> 0.025818295 | F103: =Sical!H84 -> 0.034503606 | G103: =Sical!I84 -> 0.078200719 | H103: =Sical!J84 -> 0.18013706 | I103: =Sical!K84 -> 0.12059511 | J103: =IF(AND(ISNUMBER(H103),ISNUMBER(H$109)),IF(H103>H$109,"Above",IF(H103<H$109,"Below","At")),"-") -> Below | K103: =IF(J103="Above","Better",IF(J103="Below","Weaker","-")) -> Weaker | L103: =IF(ISNUMBER(H103),RANK(H103,H$97:H$106,0),"-") -> 7 | N103: =IF(AND(ISNUMBER(I103),ISNUMBER(I$109)),IF(I103>I$109,"Above",IF(I103<I$109,"Below","At")),"-") -> Below | O103: =IF(N103="Above","Better",IF(N103="Below","Weaker","-")) -> Weaker
A104: TCI | B104: =TCI!D84 -> 1.0229168 | C104: =TCI!E84 -> 1.1218614 | D104: =TCI!F84 -> 1.2245774 | E104: =TCI!G84 -> 1.1737673 | F104: =TCI!H84 -> 0.98489635 | G104: =TCI!I84 -> 0.66835994 | H104: =TCI!J84 -> 0.7363912 | I104: =TCI!K84 -> 0.99039578 | J104: =IF(AND(ISNUMBER(H104),ISNUMBER(H$109)),IF(H104>H$109,"Above",IF(H104<H$109,"Below","At")),"-") -> Above | K104: =IF(J104="Above","Better",IF(J104="Below","Weaker","-")) -> Better | L104: =IF(ISNUMBER(H104),RANK(H104,H$97:H$106,0),"-") -> 2 | N104: =IF(AND(ISNUMBER(I104),ISNUMBER(I$109)),IF(I104>I$109,"Above",IF(I104<I$109,"Below","At")),"-") -> Above | O104: =IF(N104="Above","Better",IF(N104="Below","Weaker","-")) -> Better
A105: Shreeji | B105: =Shreeji!D84 -> 0.5554259 | C105: =Shreeji!E84 -> 0.61798839 | D105: =Shreeji!F84 -> 0.44409199 | E105: =Shreeji!G84 -> 0.56208054 | F105: =Shreeji!H84 -> 0.044657999 | G105: =Shreeji!I84 -> 0.76096096 | H105: =Shreeji!J84 -> 0.030506722 | I105: =Shreeji!K84 -> 0.43081607 | J105: =IF(AND(ISNUMBER(H105),ISNUMBER(H$109)),IF(H105>H$109,"Above",IF(H105<H$109,"Below","At")),"-") -> Below | K105: =IF(J105="Above","Better",IF(J105="Below","Weaker","-")) -> Weaker | L105: =IF(ISNUMBER(H105),RANK(H105,H$97:H$106,0),"-") -> 8 | N105: =IF(AND(ISNUMBER(I105),ISNUMBER(I$109)),IF(I105>I$109,"Above",IF(I105<I$109,"Below","At")),"-") -> Above | O105: =IF(N105="Above","Better",IF(N105="Below","Weaker","-")) -> Better
A106: Mahindra Log. | B106: =MahindraLog!D84 -> 0.12632233 | C106: =MahindraLog!E84 -> 0.34576578 | D106: =MahindraLog!F84 -> 0.18604243 | E106: =MahindraLog!G84 -> 0.10317831 | F106: =MahindraLog!H84 -> 0.18215249 | G106: =MahindraLog!I84 -> 0.26975805 | H106: =MahindraLog!J84 -> 0.19805854 | I106: =MahindraLog!K84 -> 0.20161113 | J106: =IF(AND(ISNUMBER(H106),ISNUMBER(H$109)),IF(H106>H$109,"Above",IF(H106<H$109,"Below","At")),"-") -> Below | K106: =IF(J106="Above","Better",IF(J106="Below","Weaker","-")) -> Weaker | L106: =IF(ISNUMBER(H106),RANK(H106,H$97:H$106,0),"-") -> 6 | N106: =IF(AND(ISNUMBER(I106),ISNUMBER(I$109)),IF(I106>I$109,"Above",IF(I106<I$109,"Below","At")),"-") -> Below | O106: =IF(N106="Above","Better",IF(N106="Below","Weaker","-")) -> Weaker
A107: Industry (aggregate) | B107: =Industry!D84 -> 0.81818195 | C107: =Industry!E84 -> 0.38332169 | D107: =Industry!F84 -> 0.43184673 | E107: =Industry!G84 -> 0.56161618 | F107: =Industry!H84 -> 0.37593579 | G107: =Industry!I84 -> 0.69894991 | H107: =Industry!J84 -> 0.63357276 | I107: =Industry!K84 -> 0.55763214
...

Sheet Statistics
A1: STATISTICAL ANALYSIS of the ratio panel (10 firms x 7 years, FY2020-FY2026)
A2: Descriptive statistics use all 70 firm-years. Inferential tests (B-F) use the 63 firm-years of 9 firms: Sical Logistics is excluded as an outlier (negative/near-zero net worth in 5 of 7 years under IBC resolution).
A4: A. DESCRIPTIVE STATISTICS - pooled panel
A5: Variable | B5: N | C5: Mean | D5: Median | E5: Std. dev. | F5: Coeff. of variation | G5: Minimum | H5: Maximum | I5: Skewness | J5: Kurtosis | K5: Mean ex-Sical | L5: Median ex-Sical
A6: Sales (Rs cr) | B6: =COUNT(Panel!$C$2:$C$71) -> 70 | C6: =AVERAGE(Panel!$C$2:$C$71) -> 3331.3929 | D6: =MEDIAN(Panel!$C$2:$C$71) -> 1483.42 | E6: =STDEV(Panel!$C$2:$C$71) -> 4086.3364 | F6: =IFERROR(E6/ABS(C6),"N/M") -> 1.226615 | G6: =MIN(Panel!$C$2:$C$71) -> 108.23 | H6: =MAX(Panel!$C$2:$C$71) -> 19062.06 | I6: =SKEW(Panel!$C$2:$C$71) -> 1.8313391 | J6: =KURT(Panel!$C$2:$C$71) -> 4.0593186 | K6: =AVERAGE(Panel!$C$2:$C$64) -> 3652.674 | L6: =MEDIAN(Panel!$C$2:$C$64) -> 2802.39
A7: Total assets (Rs cr) | B7: =COUNT(Panel!$D$2:$D$71) -> 70 | C7: =AVERAGE(Panel!$D$2:$D$71) -> 2896.4641 | D7: =MEDIAN(Panel!$D$2:$D$71) -> 1685.125 | E7: =STDEV(Panel!$D$2:$D$71) -> 4078.1112 | F7: =IFERROR(E7/ABS(C7),"N/M") -> 1.4079619 | G7: =MIN(Panel!$D$2:$D$71) -> 79.35 | H7: =MAX(Panel!$D$2:$D$71) -> 15175.78 | I7: =SKEW(Panel!$D$2:$D$71) -> 1.8675486 | J7: =KURT(Panel!$D$2:$D$71) -> 2.4846677 | K7: =AVERAGE(Panel!$D$2:$D$64) -> 3069.2495 | L7: =MEDIAN(Panel!$D$2:$D$64) -> 1736
A8: Net block | B8: =COUNT(Panel!$E$2:$E$71) -> 70 | C8: =AVERAGE(Panel!$E$2:$E$71) -> 0.34297414 | D8: =MEDIAN(Panel!$E$2:$E$71) -> 0.33863637 | E8: =STDEV(Panel!$E$2:$E$71) -> 0.16287551 | F8: =IFERROR(E8/ABS(C8),"N/M") -> 0.47489152 | G8: =MIN(Panel!$E$2:$E$71) -> 0.03739243 | H8: =MAX(Panel!$E$2:$E$71) -> 0.76336994 | I8: =SKEW(Panel!$E$2:$E$71) -> 0.22437037 | J8: =KURT(Panel!$E$2:$E$71) -> 0.0070443888 | K8: =AVERAGE(Panel!$E$2:$E$64) -> 0.31575597 | L8: =MEDIAN(Panel!$E$2:$E$64) -> 0.32499001
A9: Current ratio | B9: =COUNT(Panel!$F$2:$F$71) -> 70 | C9: =AVERAGE(Panel!$F$2:$F$71) -> 3.0085821 | D9: =MEDIAN(Panel!$F$2:$F$71) -> 2.6540417 | E9: =STDEV(Panel!$F$2:$F$71) -> 2.0292796 | F9: =IFERROR(E9/ABS(C9),"N/M") -> 0.67449701 | G9: =MIN(Panel!$F$2:$F$71) -> 0.43040965 | H9: =MAX(Panel!$F$2:$F$71) -> 10.618729 | I9: =SKEW(Panel!$F$2:$F$71) -> 1.2360351 | J9: =KURT(Panel!$F$2:$F$71) -> 1.9761816 | K9: =AVERAGE(Panel!$F$2:$F$64) -> 3.2629176 | L9: =MEDIAN(Panel!$F$2:$F$64) -> 2.8559374
A10: Acid-test (quick) ratio | B10: =COUNT(Panel!$G$2:$G$71) -> 70 | C10: =AVERAGE(Panel!$G$2:$G$71) -> 2.1490874 | D10: =MEDIAN(Panel!$G$2:$G$71) -> 1.6964646 | E10: =STDEV(Panel!$G$2:$G$71) -> 1.6602266 | F10: =IFERROR(E10/ABS(C10),"N/M") -> 0.77252633 | G10: =MIN(Panel!$G$2:$G$71) -> 0.24450927 | H10: =MAX(Panel!$G$2:$G$71) -> 7.9423077 | I10: =SKEW(Panel!$G$2:$G$71) -> 1.2873811 | J10: =KURT(Panel!$G$2:$G$71) -> 1.5536181 | K10: =AVERAGE(Panel!$G$2:$G$64) -> 2.336006 | L10: =MEDIAN(Panel!$G$2:$G$64) -> 1.8784838
A11: Interest coverage | B11: =COUNT(Panel!$H$2:$H$71) -> 70 | C11: =AVERAGE(Panel!$H$2:$H$71) -> 7.1634213 | D11: =MEDIAN(Panel!$H$2:$H$71) -> 2.8436747 | E11: =STDEV(Panel!$H$2:$H$71) -> 12.060859 | F11: =IFERROR(E11/ABS(C11),"N/M") -> 1.683673 | G11: =MIN(Panel!$H$2:$H$71) -> -41.722767 | H11: =MAX(Panel!$H$2:$H$71) -> 38.070265 | I11: =SKEW(Panel!$H$2:$H$71) -> -0.11833648 | J11: =KURT(Panel!$H$2:$H$71) -> 3.3388255 | K11: =AVERAGE(Panel!$H$2:$H$64) -> 8.8936459 | L11: =MEDIAN(Panel!$H$2:$H$64) -> 4.6037736
A12: Average collection period (days) | B12: =COUNT(Panel!$I$2:$I$71) -> 70 | C12: =AVERAGE(Panel!$I$2:$I$71) -> 69.081895 | D12: =MEDIAN(Panel!$I$2:$I$71) -> 58.324266 | E12: =STDEV(Panel!$I$2:$I$71) -> 40.57288 | F12: =IFERROR(E12/ABS(C12),"N/M") -> 0.58731568 | G12: =MIN(Panel!$I$2:$I$71) -> 7.2692362 | H12: =MAX(Panel!$I$2:$I$71) -> 242.2178 | I12: =SKEW(Panel!$I$2:$I$71) -> 1.5277615 | J12: =KURT(Panel!$I$2:$I$71) -> 4.4609806 | K12: =AVERAGE(Panel!$I$2:$I$64) -> 63.846021 | L12: =MEDIAN(Panel!$I$2:$I$64) -> 57.098039
A13: Fixed assets turnover | B13: =COUNT(Panel!$J$2:$J$71) -> 70 | C13: =AVERAGE(Panel!$J$2:$J$71) -> 9.9745523 | D13: =MEDIAN(Panel!$J$2:$J$71) -> 4.8950623 | E13: =STDEV(Panel!$J$2:$J$71) -> 14.726542 | F13: =IFERROR(E13/ABS(C13),"N/M") -> 1.4764113 | G13: =MIN(Panel!$J$2:$J$71) -> 0.38032409 | H13: =MAX(Panel!$J$2:$J$71) -> 74.694596 | I13: =SKEW(Panel!$J$2:$J$71) -> 2.9548839 | J13: =KURT(Panel!$J$2:$J$71) -> 8.8785515 | K13: =AVERAGE(Panel!$J$2:$J$64) -> 11.017879 | L13: =MEDIAN(Panel!$J$2:$J$64) -> 5.6101564
A14: Net profit margin | B14: =COUNT(Panel!$K$2:$K$71) -> 70 | C14: =AVERAGE(Panel!$K$2:$K$71) -> -0.043119785 | D14: =MEDIAN(Panel!$K$2:$K$71) -> 0.024528847 | E14: =STDEV(Panel!$K$2:$K$71) -> 0.39058515 | F14: =IFERROR(E14/ABS(C14),"N/M") -> 9.0581423 | G14: =MIN(Panel!$K$2:$K$71) -> -2.3024443 | H14: =MAX(Panel!$K$2:$K$71) -> 0.14567552 | I14: =SKEW(Panel!$K$2:$K$71) -> -5.2218752 | J14: =KURT(Panel!$K$2:$K$71) -> 27.543751 | K14: =AVERAGE(Panel!$K$2:$K$64) -> 0.037783723 | L14: =MEDIAN(Panel!$K$2:$K$64) -> 0.030914481
A15: Return on assets (ROA) | B15: =COUNT(Panel!$L$2:$L$71) -> 70 | C15: =AVERAGE(Panel!$L$2:$L$71) -> 0.030509583 | D15: =MEDIAN(Panel!$L$2:$L$71) -> 0.036443292 | E15: =STDEV(Panel!$L$2:$L$71) -> 0.13543673 | F15: =IFERROR(E15/ABS(C15),"N/M") -> 4.4391538 | G15: =MIN(Panel!$L$2:$L$71) -> -0.70715131 | H15: =MAX(Panel!$L$2:$L$71) -> 0.32793759 | I15: =SKEW(Panel!$L$2:$L$71) -> -3.1955002 | J15: =KURT(Panel!$L$2:$L$71) -> 15.576852 | K15: =AVERAGE(Panel!$L$2:$L$64) -> 0.056625729 | L15: =MEDIAN(Panel!$L$2:$L$64) -> 0.041965016
A16: Return on total shareholders' equity | B16: =COUNT(Panel!$M$2:$M$71) -> 67 | C16: =AVERAGE(Panel!$M$2:$M$71) -> 0.06455921 | D16: =MEDIAN(Panel!$M$2:$M$71) -> 0.097940372 | E16: =STDEV(Panel!$M$2:$M$71) -> 0.34117068 | F16: =IFERROR(E16/ABS(C16),"N/M") -> 5.2846168 | G16: =MIN(Panel!$M$2:$M$71) -> -2.1569937 | H16: =MAX(Panel!$M$2:$M$71) -> 0.77900727 | I16: =SKEW(Panel!$M$2:$M$71) -> -4.2666836 | J16: =KURT(Panel!$M$2:$M$71) -> 27.663679 | K16: =AVERAGE(Panel!$M$2:$M$64) -> 0.10455704 | L16: =MEDIAN(Panel!$M$2:$M$64) -> 0.09807371
A17: Price-earnings (P/E) | B17: =COUNT(Panel!$N$2:$N$71) -> 51 | C17: =AVERAGE(Panel!$N$2:$N$71) -> 114.77776 | D17: =MEDIAN(Panel!$N$2:$N$71) -> 30.117025 | E17: =STDEV(Panel!$N$2:$N$71) -> 293.23105 | F17: =IFERROR(E17/ABS(C17),"N/M") -> 2.5547723 | G17: =MIN(Panel!$N$2:$N$71) -> 3.1335196 | H17: =MAX(Panel!$N$2:$N$71) -> 1441.6489 | I17: =SKEW(Panel!$N$2:$N$71) -> 3.8829253 | J17: =KURT(Panel!$N$2:$N$71) -> 14.622695 | K17: =AVERAGE(Panel!$N$2:$N$64) -> 116.8693 | L17: =MEDIAN(Panel!$N$2:$N$64) -> 31.390868
A18: Price-to-book (P/B) | B18: =COUNT(Panel!$O$2:$O$71) -> 61 | C18: =AVERAGE(Panel!$O$2:$O$71) -> 4.4933226 | D18: =MEDIAN(Panel!$O$2:$O$71) -> 2.9993067 | E18: =STDEV(Panel!$O$2:$O$71) -> 5.672244 | F18: =IFERROR(E18/ABS(C18),"N/M") -> 1.2623719 | G18: =MIN(Panel!$O$2:$O$71) -> 0.062998015 | H18: =MAX(Panel!$O$2:$O$71) -> 33.431025 | I18: =SKEW(Panel!$O$2:$O$71) -> 3.1105405 | J18: =KURT(Panel!$O$2:$O$71) -> 12.059266 | K18: =AVERAGE(Panel!$O$2:$O$64) -> 4.1401242 | L18: =MEDIAN(Panel!$O$2:$O$64) -> 2.9993067
A19: EV / EBITDA | B19: =COUNT(Panel!$P$2:$P$71) -> 58 | C19: =AVERAGE(Panel!$P$2:$P$71) -> 16.027757 | D19: =MEDIAN(Panel!$P$2:$P$71) -> 12.186766 | E19: =STDEV(Panel!$P$2:$P$71) -> 24.50013 | F19: =IFERROR(E19/ABS(C19),"N/M") -> 1.5286063 | G19: =MIN(Panel!$P$2:$P$71) -> 2.7872521 | H19: =MAX(Panel!$P$2:$P$71) -> 193.24634 | I19: =SKEW(Panel!$P$2:$P$71) -> 6.8664143 | J19: =KURT(Panel!$P$2:$P$71) -> 50.214892 | K19: =AVERAGE(Panel!$P$2:$P$64) -> 12.788114 | L19: =MEDIAN(Panel!$P$2:$P$64) -> 12.0664
A20: ROCE (post-tax) | B20: =COUNT(Panel!$Q$2:$Q$71) -> 70 | C20: =AVERAGE(Panel!$Q$2:$Q$71) -> 0.058908496 | D20: =MEDIAN(Panel!$Q$2:$Q$71) -> 0.07688143 | E20: =STDEV(Panel!$Q$2:$Q$71) -> 0.21531167 | F20: =IFERROR(E20/ABS(C20),"N/M") -> 3.655019 | G20: =MIN(Panel!$Q$2:$Q$71) -> -1.1777556 | H20: =MAX(Panel!$Q$2:$Q$71) -> 0.53267131 | I20: =SKEW(Panel!$Q$2:$Q$71) -> -3.8918335 | J20: =KURT(Panel!$Q$2:$Q$71) -> 20.097013 | K20: =AVERAGE(Panel!$Q$2:$Q$64) -> 0.099997594 | L20: =MEDIAN(Panel!$Q$2:$Q$64) -> 0.088036094
A21: Total assets turnover | B21: =COUNT(Panel!$R$2:$R$71) -> 70 | C21: =AVERAGE(Panel!$R$2:$R$71) -> 1.7640934 | D21: =MEDIAN(Panel!$R$2:$R$71) -> 1.6869021 | E21: =STDEV(Panel!$R$2:$R$71) -> 1.0265913 | F21: =IFERROR(E21/ABS(C21),"N/M") -> 0.58193707 | G21: =MIN(Panel!$R$2:$R$71) -> 0.21165186 | H21: =MAX(Panel!$R$2:$R$71) -> 5.9981472 | I21: =SKEW(Panel!$R$2:$R$71) -> 1.1592733 | J21: =KURT(Panel!$R$2:$R$71) -> 3.4164363 | K21: =AVERAGE(Panel!$R$2:$R$64) -> 1.9263613 | L21: =MEDIAN(Panel!$R$2:$R$64) -> 1.8019151
A22: Operating EBITDA margin (core) | B22: =COUNT(Panel!$S$2:$S$71) -> 70 | C22: =AVERAGE(Panel!$S$2:$S$71) -> 0.081391573 | D22: =MEDIAN(Panel!$S$2:$S$71) -> 0.0635277 | E22: =STDEV(Panel!$S$2:$S$71) -> 0.074728009 | F22: =IFERROR(E22/ABS(C22),"N/M") -> 0.91812956 | G22: =MIN(Panel!$S$2:$S$71) -> -0.11224812 | H22: =MAX(Panel!$S$2:$S$71) -> 0.25944103 | I22: =SKEW(Panel!$S$2:$S$71) -> 0.47722233 | J22: =KURT(Panel!$S$2:$S$71) -> 0.20484275 | K22: =AVERAGE(Panel!$S$2:$S$64) -> 0.085799457 | L22: =MEDIAN(Panel!$S$2:$S$64) -> 0.06316628
A23: Debt-equity (Khan & Jain) | B23: =COUNT(Panel!$T$2:$T$71) -> 67 | C23: =AVERAGE(Panel!$T$2:$T$71) -> 1.1566304 | D23: =MEDIAN(Panel!$T$2:$T$71) -> 0.66661121 | E23: =STDEV(Panel!$T$2:$T$71) -> 2.3997399 | F23: =IFERROR(E23/ABS(C23),"N/M") -> 2.0747682 | G23: =MIN(Panel!$T$2:$T$71) -> 0 | H23: =MAX(Panel!$T$2:$T$71) -> 17.661908 | I23: =SKEW(Panel!$T$2:$T$71) -> 5.6286252 | J23: =KURT(Panel!$T$2:$T$71) -> 35.960985 | K23: =AVERAGE(Panel!$T$2:$T$64) -> 0.70639211 | L23: =MEDIAN(Panel!$T$2:$T$64) -> 0.64266137
A25: B. CORRELATION MATRIX (Pearson) - 63 firm-years, 9 firms
B26: Current ratio | C26: Debt-equity (Khan & Ja | D26: Interest coverage | E26: Average collection per | F26: Total assets turnover | G26: Operating EBITDA margi | H26: Net profit margin | I26: ROCE (post-tax) | J26: Return on total shareh | K26: Net block
A27: Current ratio | B27: =CORREL(Panel!$F$2:$F$64,Panel!$F$2:$F$64) -> 1 | C27: =CORREL(Panel!$F$2:$F$64,Panel!$T$2:$T$64) -> -0.22485167 | D27: =CORREL(Panel!$F$2:$F$64,Panel!$H$2:$H$64) -> 0.080291347 | E27: =CORREL(Panel!$F$2:$F$64,Panel!$I$2:$I$64) -> 0.37172608 | F27: =CORREL(Panel!$F$2:$F$64,Panel!$R$2:$R$64) -> -0.12844468 | G27: =CORREL(Panel!$F$2:$F$64,Panel!$S$2:$S$64) -> -0.15873841 | H27: =CORREL(Panel!$F$2:$F$64,Panel!$K$2:$K$64) -> 0.07048714 | I27: =CORREL(Panel!$F$2:$F$64,Panel!$Q$2:$Q$64) -> -0.084995625 | J27: =CORREL(Panel!$F$2:$F$64,Panel!$M$2:$M$64) -> -0.082784283 | K27: =CORREL(Panel!$F$2:$F$64,Panel!$E$2:$E$64) -> -0.3946427
A28: Debt-equity (Khan & Jain) | B28: =CORREL(Panel!$T$2:$T$64,Panel!$F$2:$F$64) -> -0.22485167 | C28: =CORREL(Panel!$T$2:$T$64,Panel!$T$2:$T$64) -> 1 | D28: =CORREL(Panel!$T$2:$T$64,Panel!$H$2:$H$64) -> -0.63024213 | E28: =CORREL(Panel!$T$2:$T$64,Panel!$I$2:$I$64) -> 0.20230971 | F28: =CORREL(Panel!$T$2:$T$64,Panel!$R$2:$R$64) -> 0.16550781 | G28: =CORREL(Panel!$T$2:$T$64,Panel!$S$2:$S$64) -> -0.1632458 | H28: =CORREL(Panel!$T$2:$T$64,Panel!$K$2:$K$64) -> -0.49373224 | I28: =CORREL(Panel!$T$2:$T$64,Panel!$Q$2:$Q$64) -> -0.27830573 | J28: =CORREL(Panel!$T$2:$T$64,Panel!$M$2:$M$64) -> -0.23273743 | K28: =CORREL(Panel!$T$2:$T$64,Panel!$E$2:$E$64) -> 0.091410862
A29: Interest coverage | B29: =CORREL(Panel!$H$2:$H$64,Panel!$F$2:$F$64) -> 0.080291347 | C29: =CORREL(Panel!$H$2:$H$64,Panel!$T$2:$T$64) -> -0.63024213 | D29: =CORREL(Panel!$H$2:$H$64,Panel!$H$2:$H$64) -> 1 | E29: =CORREL(Panel!$H$2:$H$64,Panel!$I$2:$I$64) -> -0.40402919 | F29: =CORREL(Panel!$H$2:$H$64,Panel!$R$2:$R$64) -> -0.064544926 | G29: =CORREL(Panel!$H$2:$H$64,Panel!$S$2:$S$64) -> 0.44527481 | H29: =CORREL(Panel!$H$2:$H$64,Panel!$K$2:$K$64) -> 0.7634351 | I29: =CORREL(Panel!$H$2:$H$64,Panel!$Q$2:$Q$64) -> 0.58296463 | J29: =CORREL(Panel!$H$2:$H$64,Panel!$M$2:$M$64) -> 0.44836396 | K29: =CORREL(Panel!$H$2:$H$64,Panel!$E$2:$E$64) -> 0.072798319
A30: Average collection period (days) | B30: =CORREL(Panel!$I$2:$I$64,Panel!$F$2:$F$64) -> 0.37172608 | C30: =CORREL(Panel!$I$2:$I$64,Panel!$T$2:$T$64) -> 0.20230971 | D30: =CORREL(Panel!$I$2:$I$64,Panel!$H$2:$H$64) -> -0.40402919 | E30: =CORREL(Panel!$I$2:$I$64,Panel!$I$2:$I$64) -> 1 | F30: =CORREL(Panel!$I$2:$I$64,Panel!$R$2:$R$64) -> -0.094035133 | G30: =CORREL(Panel!$I$2:$I$64,Panel!$S$2:$S$64) -> -0.46811685 | H30: =CORREL(Panel!$I$2:$I$64,Panel!$K$2:$K$64) -> -0.4506101 | I30: =CORREL(Panel!$I$2:$I$64,Panel!$Q$2:$Q$64) -> -0.27359237 | J30: =CORREL(Panel!$I$2:$I$64,Panel!$M$2:$M$64) -> -0.21656331 | K30: =CORREL(Panel!$I$2:$I$64,Panel!$E$2:$E$64) -> -0.26743376
A31: Total assets turnover | B31: =CORREL(Panel!$R$2:$R$64,Panel!$F$2:$F$64) -> -0.12844468 | C31: =CORREL(Panel!$R$2:$R$64,Panel!$T$2:$T$64) -> 0.16550781 | D31: =CORREL(Panel!$R$2:$R$64,Panel!$H$2:$H$64) -> -0.064544926 | E31: =CORREL(Panel!$R$2:$R$64,Panel!$I$2:$I$64) -> -0.094035133 | F31: =CORREL(Panel!$R$2:$R$64,Panel!$R$2:$R$64) -> 1 | G31: =CORREL(Panel!$R$2:$R$64,Panel!$S$2:$S$64) -> -0.56644284 | H31: =CORREL(Panel!$R$2:$R$64,Panel!$K$2:$K$64) -> -0.38098129 | I31: =CORREL(Panel!$R$2:$R$64,Panel!$Q$2:$Q$64) -> 0.35285226 | J31: =CORREL(Panel!$R$2:$R$64,Panel!$M$2:$M$64) -> 0.1707124 | K31: =CORREL(Panel!$R$2:$R$64,Panel!$E$2:$E$64) -> -0.61546802
A32: Operating EBITDA margin (core) | B32: =CORREL(Panel!$S$2:$S$64,Panel!$F$2:$F$64) -> -0.15873841 | C32: =CORREL(Panel!$S$2:$S$64,Panel!$T$2:$T$64) -> -0.1632458 | D32: =CORREL(Panel!$S$2:$S$64,Panel!$H$2:$H$64) -> 0.44527481 | E32: =CORREL(Panel!$S$2:$S$64,Panel!$I$2:$I$64) -> -0.46811685 | F32: =CORREL(Panel!$S$2:$S$64,Panel!$R$2:$R$64) -> -0.56644284 | G32: =CORREL(Panel!$S$2:$S$64,Panel!$S$2:$S$64) -> 1 | H32: =CORREL(Panel!$S$2:$S$64,Panel!$K$2:$K$64) -> 0.78821557 | I32: =CORREL(Panel!$S$2:$S$64,Panel!$Q$2:$Q$64) -> 0.32336156 | J32: =CORREL(Panel!$S$2:$S$64,Panel!$M$2:$M$64) -> 0.41242051 | K32: =CORREL(Panel!$S$2:$S$64,Panel!$E$2:$E$64) -> 0.70201305
A33: Net profit margin | B33: =CORREL(Panel!$K$2:$K$64,Panel!$F$2:$F$64) -> 0.07048714 | C33: =CORREL(Panel!$K$2:$K$64,Panel!$T$2:$T$64) -> -0.49373224 | D33: =CORREL(Panel!$K$2:$K$64,Panel!$H$2:$H$64) -> 0.7634351 | E33: =CORREL(Panel!$K$2:$K$64,Panel!$I$2:$I$64) -> -0.4506101 | F33: =CORREL(Panel!$K$2:$K$64,Panel!$R$2:$R$64) -> -0.38098129 | G33: =CORREL(Panel!$K$2:$K$64,Panel!$S$2:$S$64) -> 0.78821557 | H33: =CORREL(Panel!$K$2:$K$64,Panel!$K$2:$K$64) -> 1 | I33: =CORREL(Panel!$K$2:$K$64,Panel!$Q$2:$Q$64) -> 0.54176202 | J33: =CORREL(Panel!$K$2:$K$64,Panel!$M$2:$M$64) -> 0.57271281 | K33: =CORREL(Panel!$K$2:$K$64,Panel!$E$2:$E$64) -> 0.37741255
A34: ROCE (post-tax) | B34: =CORREL(Panel!$Q$2:$Q$64,Panel!$F$2:$F$64) -> -0.084995625 | C34: =CORREL(Panel!$Q$2:$Q$64,Panel!$T$2:$T$64) -> -0.27830573 | D34: =CORREL(Panel!$Q$2:$Q$64,Panel!$H$2:$H$64) -> 0.58296463 | E34: =CORREL(Panel!$Q$2:$Q$64,Panel!$I$2:$I$64) -> -0.27359237 | F34: =CORREL(Panel!$Q$2:$Q$64,Panel!$R$2:$R$64) -> 0.35285226 | G34: =CORREL(Panel!$Q$2:$Q$64,Panel!$S$2:$S$64) -> 0.32336156 | H34: =CORREL(Panel!$Q$2:$Q$64,Panel!$K$2:$K$64) -> 0.54176202 | I34: =CORREL(Panel!$Q$2:$Q$64,Panel!$Q$2:$Q$64) -> 1 | J34: =CORREL(Panel!$Q$2:$Q$64,Panel!$M$2:$M$64) -> 0.89871063 | K34: =CORREL(Panel!$Q$2:$Q$64,Panel!$E$2:$E$64) -> -0.006095554
A35: Return on total shareholders' equity | B35: =CORREL(Panel!$M$2:$M$64,Panel!$F$2:$F$64) -> -0.082784283 | C35: =CORREL(Panel!$M$2:$M$64,Panel!$T$2:$T$64) -> -0.23273743 | D35: =CORREL(Panel!$M$2:$M$64,Panel!$H$2:$H$64) -> 0.44836396 | E35: =CORREL(Panel!$M$2:$M$64,Panel!$I$2:$I$64) -> -0.21656331 | F35: =CORREL(Panel!$M$2:$M$64,Panel!$R$2:$R$64) -> 0.1707124 | G35: =CORREL(Panel!$M$2:$M$64,Panel!$S$2:$S$64) -> 0.41242051 | H35: =CORREL(Panel!$M$2:$M$64,Panel!$K$2:$K$64) -> 0.57271281 | I35: =CORREL(Panel!$M$2:$M$64,Panel!$Q$2:$Q$64) -> 0.89871063 | J35: =CORREL(Panel!$M$2:$M$64,Panel!$M$2:$M$64) -> 1 | K35: =CORREL(Panel!$M$2:$M$64,Panel!$E$2:$E$64) -> 0.10723358
A36: Net block | B36: =CORREL(Panel!$E$2:$E$64,Panel!$F$2:$F$64) -> -0.3946427 | C36: =CORREL(Panel!$E$2:$E$64,Panel!$T$2:$T$64) -> 0.091410862 | D36: =CORREL(Panel!$E$2:$E$64,Panel!$H$2:$H$64) -> 0.072798319 | E36: =CORREL(Panel!$E$2:$E$64,Panel!$I$2:$I$64) -> -0.26743376 | F36: =CORREL(Panel!$E$2:$E$64,Panel!$R$2:$R$64) -> -0.61546802 | G36: =CORREL(Panel!$E$2:$E$64,Panel!$S$2:$S$64) -> 0.70201305 | H36: =CORREL(Panel!$E$2:$E$64,Panel!$K$2:$K$64) -> 0.37741255 | I36: =CORREL(Panel!$E$2:$E$64,Panel!$Q$2:$Q$64) -> -0.006095554 | J36: =CORREL(Panel!$E$2:$E$64,Panel!$M$2:$M$64) -> 0.10723358 | K36: =CORREL(Panel!$E$2:$E$64,Panel!$E$2:$E$64) -> 1
A37: Green: r >= +0.5 (strong positive); red: r <= -0.5 (strong negative). With n = 63, |r| > 0.25 is significant at 5% (two-tailed).
A39: C. MULTIPLE REGRESSION (OLS, LINEST): ROCE = b0 + b1 Total-assets turnover + b2 Operating EBITDA margin + b3 Debt-equity + b4 ln(Sales)
A40: Variable | B40: Coefficient | C40: Std. error | D40: t-stat | E40: p-value | F40: Significant at 5%?
A41: Intercept | B41: =INDEX(LINEST(Panel!$Q$2:$Q$64,Panel!$R$2:$U$64,TRUE(),TRUE()),1,5) -> -0.084120691 | C41: =INDEX(LINEST(Panel!$Q$2:$Q$64,Panel!$R$2:$U$64,TRUE(),TRUE()),2,5) -> 0.048018803 | D41: =B41/C41 -> -1.7518282 | E41: =TDIST(ABS(D41),$B$51,2) -> 0.085089257 | F41: =IF(E41<0.05,"Yes","No") -> No
A42: Total assets turnover (x) | B42: =INDEX(LINEST(Panel!$Q$2:$Q$64,Panel!$R$2:$U$64,TRUE(),TRUE()),1,4) -> 0.079898148 | C42: =INDEX(LINEST(Panel!$Q$2:$Q$64,Panel!$R$2:$U$64,TRUE(),TRUE()),2,4) -> 0.0096843193 | D42: =B42/C42 -> 8.2502595 | E42: =TDIST(ABS(D42),$B$51,2) -> 2.3345843e-11 | F42: =IF(E42<0.05,"Yes","No") -> Yes
A43: Operating EBITDA margin | B43: =INDEX(LINEST(Panel!$Q$2:$Q$64,Panel!$R$2:$U$64,TRUE(),TRUE()),1,3) -> 1.0107039 | C43: =INDEX(LINEST(Panel!$Q$2:$Q$64,Panel!$R$2:$U$64,TRUE(),TRUE()),2,3) -> 0.14975144 | D43: =B43/C43 -> 6.7492098 | E43: =TDIST(ABS(D43),$B$51,2) -> 7.7219935e-09 | F43: =IF(E43<0.05,"Yes","No") -> Yes
A44: Debt-equity (x) | B44: =INDEX(LINEST(Panel!$Q$2:$Q$64,Panel!$R$2:$U$64,TRUE(),TRUE()),1,2) -> -0.044186349 | C44: =INDEX(LINEST(Panel!$Q$2:$Q$64,Panel!$R$2:$U$64,TRUE(),TRUE()),2,2) -> 0.012374764 | D44: =B44/C44 -> -3.5706821 | E44: =TDIST(ABS(D44),$B$51,2) -> 0.00072357698 | F44: =IF(E44<0.05,"Yes","No") -> Yes
A45: ln(Sales) | B45: =INDEX(LINEST(Panel!$Q$2:$Q$64,Panel!$R$2:$U$64,TRUE(),TRUE()),1,1) -> -0.0034645 | C45: =INDEX(LINEST(Panel!$Q$2:$Q$64,Panel!$R$2:$U$64,TRUE(),TRUE()),2,1) -> 0.0060235222 | D45: =B45/C45 -> -0.57516182 | E45: =TDIST(ABS(D45),$B$51,2) -> 0.56740651 | F45: =IF(E45<0.05,"Yes","No") -> No
A47: R-squared | B47: =INDEX(LINEST(Panel!$Q$2:$Q$64,Panel!$R$2:$U$64,TRUE(),TRUE()),3,1) -> 0.61287441
A48: Adjusted R-squared | B48: =1-(1-B47)*(B51+4)/B51 -> 0.58617609
A49: Std. error of estimate | B49: =INDEX(LINEST(Panel!$Q$2:$Q$64,Panel!$R$2:$U$64,TRUE(),TRUE()),3,2) -> 0.059528559
A50: F-statistic | B50: =INDEX(LINEST(Panel!$Q$2:$Q$64,Panel!$R$2:$U$64,TRUE(),TRUE()),4,1) -> 22.955545
A51: Residual df | B51: =INDEX(LINEST(Panel!$Q$2:$Q$64,Panel!$R$2:$U$64,TRUE(),TRUE()),4,2) -> 58
A52: p-value (F) | B52: =FDIST(B50,4,B51) -> 2.0953017e-11
A53: Observations | B53: =B51+5 -> 63
A55: D. PAIRED t-TESTS: has the typical firm changed between FY2020 and FY2026? (H0: mean difference = 0; n = 9 firms)
A56: Ratio | B56: Mean FY2020 | C56: Mean FY2026 | D56: Mean difference | E56: SD of differences | F56: n | G56: t-stat | H56: df | I56: p-value (2-tailed) | J56: Conclusion
A57: Operating EBITDA margin (core) | B57: =AVERAGE(B68:B76) -> 0.075506198 | C57: =AVERAGE(C68:C76) -> 0.087797989 | D57: =AVERAGE(D68:D76) -> 0.012291792 | E57: =STDEV(D68:D76) -> 0.040959639 | F57: =COUNT(D68:D76) -> 9 | G57: =D57/(E57/SQRT(F57)) -> 0.90028564 | H57: =F57-1 -> 8 | I57: =TDIST(ABS(G57),H57,2) -> 0.39426109 | J57: =IF(I57<0.05,"Significant at 5%",IF(I57<0.1,"Significant at 10%","Not significant")) -> Not significant
A58: Net profit margin | B58: =AVERAGE(E68:E76) -> 0.013553624 | C58: =AVERAGE(F68:F76) -> 0.040813482 | D58: =AVERAGE(G68:G76) -> 0.027259859 | E58: =STDEV(G68:G76) -> 0.039489649 | F58: =COUNT(G68:G76) -> 9 | G58: =D58/(E58/SQRT(F58)) -> 2.0709117 | H58: =F58-1 -> 8 | I58: =TDIST(ABS(G58),H58,2) -> 0.072126823 | J58: =IF(I58<0.05,"Significant at 5%",IF(I58<0.1,"Significant at 10%","Not significant")) -> Significant at 10%
A59: ROCE (post-tax) | B59: =AVERAGE(H68:H76) -> 0.048161174 | C59: =AVERAGE(I68:I76) -> 0.091147829 | D59: =AVERAGE(J68:J76) -> 0.042986655 | E59: =STDEV(J68:J76) -> 0.091531525 | F59: =COUNT(J68:J76) -> 9 | G59: =D59/(E59/SQRT(F59)) -> 1.4089131 | H59: =F59-1 -> 8 | I59: =TDIST(ABS(G59),H59,2) -> 0.19652243 | J59: =IF(I59<0.05,"Significant at 5%",IF(I59<0.1,"Significant at 10%","Not significant")) -> Not significant
A60: Total assets turnover | B60: =AVERAGE(K68:K76) -> 1.8705595 | C60: =AVERAGE(L68:L76) -> 1.8200179 | D60: =AVERAGE(M68:M76) -> -0.050541589 | E60: =STDEV(M68:M76) -> 0.46363291 | F60: =COUNT(M68:M76) -> 9 | G60: =D60/(E60/SQRT(F60)) -> -0.32703625 | H60: =F60-1 -> 8 | I60: =TDIST(ABS(G60),H60,2) -> 0.75203334 | J60: =IF(I60<0.05,"Significant at 5%",IF(I60<0.1,"Significant at 10%","Not significant")) -> Not significant
A61: Average collection period (days) | B61: =AVERAGE(N68:N76) -> 67.273306 | C61: =AVERAGE(O68:O76) -> 62.699936 | D61: =AVERAGE(P68:P76) -> -4.5733698 | E61: =STDEV(P68:P76) -> 16.065595 | F61: =COUNT(P68:P76) -> 9 | G61: =D61/(E61/SQRT(F61)) -> -0.85400568 | H61: =F61-1 -> 8 | I61: =TDIST(ABS(G61),H61,2) -> 0.41793874 | J61: =IF(I61<0.05,"Significant at 5%",IF(I61<0.1,"Significant at 10%","Not significant")) -> Not significant
A62: Debt-equity (Khan & Jain) | B62: =AVERAGE(Q68:Q76) -> 0.86498085 | C62: =AVERAGE(R68:R76) -> 0.51679178 | D62: =AVERAGE(S68:S76) -> -0.34818907 | E62: =STDEV(S68:S76) -> 0.5460735 | F62: =COUNT(S68:S76) -> 9 | G62: =D62/(E62/SQRT(F62)) -> -1.9128693 | H62: =F62-1 -> 8 | I62: =TDIST(ABS(G62),H62,2) -> 0.092122863 | J62: =IF(I62<0.05,"Significant at 5%",IF(I62<0.1,"Significant at 10%","Not significant")) -> Significant at 10%
A63: Interest coverage | B63: =AVERAGE(T68:T76) -> 3.4937393 | C63: =AVERAGE(U68:U76) -> 10.419496 | D63: =AVERAGE(V68:V76) -> 6.9257567 | E63: =STDEV(V68:V76) -> 10.333706 | F63: =COUNT(V68:V76) -> 9 | G63: =D63/(E63/SQRT(F63)) -> 2.010631 | H63: =F63-1 -> 8 | I63: =TDIST(ABS(G63),H63,2) -> 0.079200687 | J63: =IF(I63<0.05,"Significant at 5%",IF(I63<0.1,"Significant at 10%","Not significant")) -> Significant at 10%
A64: Current ratio | B64: =AVERAGE(W68:W76) -> 3.2865311 | C64: =AVERAGE(X68:X76) -> 3.1463133 | D64: =AVERAGE(Y68:Y76) -> -0.14021777 | E64: =STDEV(Y68:Y76) -> 1.4356317 | F64: =COUNT(Y68:Y76) -> 9 | G64: =D64/(E64/SQRT(F64)) -> -0.2930092 | H64: =F64-1 -> 8 | I64: =TDIST(ABS(G64),H64,2) -> 0.77697166 | J64: =IF(I64<0.05,"Significant at 5%",IF(I64<0.1,"Significant at 10%","Not significant")) -> Not significant
A66: Paired-test data (FY2020, FY2026, difference) - linked to company sheets
A67: Firm | B67: P2b FY20 | C67: P2b FY26 | D67: P2b diff | E67: P5 FY20 | F67: P5 FY26 | G67: P5 diff | H67: R4 FY20 | I67: R4 FY26 | J67: R4 diff | K67: T9 FY20 | L67: T9 FY26 | M67: T9 diff | N67: T4 FY20 | O67: T4 FY26 | P67: T4 diff | Q67: V1 FY20 | R67: V1 FY26 | S67: V1 diff | T67: C1 FY20 | U67: C1 FY26 | V67: C1 diff | W67: L2 FY20 | X67: L2 FY26 | Y67: L2 diff
A68: Tiger | B68: =Tiger!D121 -> -0.027829375 | C68: =Tiger!J121 -> 0.047152683 | D68: =C68-B68 -> 0.074982058 | E68: =Tiger!D124 -> -0.040931405 | F68: =Tiger!J124 -> 0.037568521 | G68: =F68-E68 -> 0.078499926 | H68: =Tiger!D138 -> -0.080745342 | I68: =Tiger!J138 -> 0.13263629 | J68: =I68-H68 -> 0.21338163 | K68: =Tiger!D113 -> 2.6200843 | L68: =Tiger!J113 -> 2.4997054 | M68: =L68-K68 -> -0.12037886 | N68: =Tiger!D108 -> 101.00214 | O68: =Tiger!J108 -> 84.017798 | P68: =O68-N68 -> -16.984342 | Q68: =Tiger!D87 -> 0.69582543 | R68: =Tiger!J87 -> 0.31691461 | S68: =R68-Q68 -> -0.37891081 | T68: =Tiger!D96 -> -1.7274775 | U68: =Tiger!J96 -> 6.5294118 | V68: =U68-T68 -> 8.2568892 | W68: =Tiger!D80 -> 6.047014 | X68: =Tiger!J80 -> 4.6170581 | Y68: =X68-W68 -> -1.4299558
A69: Allcargo | B69: =Allcargo!D121 -> 0.070124308 | C69: =Allcargo!J121 -> 0.11418853 | D69: =C69-B69 -> 0.044064224 | E69: =Allcargo!D124 -> 0.030355665 | F69: =Allcargo!J124 -> 0.0038872692 | G69: =F69-E69 -> -0.026468396 | H69: =Allcargo!D138 -> 0.091913326 | I69: =Allcargo!J138 -> 0.050574713 | J69: =I69-H69 -> -0.041338613 | K69: =Allcargo!D113 -> 1.5943555 | L69: =Allcargo!J113 -> 1.1837791 | M69: =L69-K69 -> -0.41057636 | N69: =Allcargo!D108 -> 51.976766 | O69: =Allcargo!J108 -> 71.297376 | P69: =O69-N69 -> 19.32061 | Q69: =Allcargo!D87 -> 0.747234 | R69: =Allcargo!J87 -> 1.2073171 | S69: =R69-Q69 -> 0.46008307 | T69: =Allcargo!D96 -> 5.0894363 | U69: =Allcargo!J96 -> 1.0645161 | V69: =U69-T69 -> -4.0249202 | W69: =Allcargo!D80 -> 1.6456859 | X69: =Allcargo!J80 -> 2.0255864 | Y69: =X69-W69 -> 0.37990042
A70: Blue Dart | B70: =BlueDart!D121 -> 0.14947734 | C70: =BlueDart!J121 -> 0.15480843 | D70: =C70-B70 -> 0.0053310871 | E70: =BlueDart!D124 -> -0.013183712 | F70: =BlueDart!J124 -> 0.040285757 | G70: =F70-E70 -> 0.053469469 | H70: =BlueDart!D138 -> 0.072088171 | I70: =BlueDart!J138 -> 0.11385367 | J70: =I70-H70 -> 0.041765499 | K70: =BlueDart!D113 -> 1.4263676 | L70: =BlueDart!J113 -> 1.5766848 | M70: =L70-K70 -> 0.15031721 | N70: =BlueDart!D108 -> 58.584412 | O70: =BlueDart!J108 -> 50.651055 | P70: =O70-N70 -> -7.9333574 | Q70: =BlueDart!D87 -> 1.0798036 | R70: =BlueDart!J87 -> 0.64266137 | S70: =R70-Q70 -> -0.43714223 | T70: =BlueDart!D96 -> 0.66672346 | U70: =BlueDart!J96 -> 4.81539 | V70: =U70-T70 -> 4.1486665 | W70: =BlueDart!D80 -> 0.59123682 | X70: =BlueDart!J80 -> 1.3674138 | Y70: =X70-W70 -> 0.77617701
A71: CONCOR | B71: =CONCOR!D121 -> 0.25944103 | C71: =CONCOR!J121 -> 0.21492746 | D71: =C71-B71 -> -0.04451357 | E71: =CONCOR!D124 -> 0.061792238 | F71: =CONCOR!J124 -> 0.13677763 | G71: =F71-E71 -> 0.074985392 | H71: =CONCOR!D138 -> 0.041514444 | I71: =CONCOR!J138 -> 0.096133312 | J71: =I71-H71 -> 0.054618868 | K71: =CONCOR!D113 -> 0.53121037 | L71: =CONCOR!J113 -> 0.61234666 | M71: =L71-K71 -> 0.081136291 | N71: =CONCOR!D108 -> 7.2692362 | O71: =CONCOR!J108 -> 17.788934 | P71: =O71-N71 -> 10.519698 | Q71: =CONCOR!D87 -> 0.0069678781 | R71: =CONCOR!J87 -> 0.074528196 | S71: =R71-Q71 -> 0.067560318 | T71: =CONCOR!D96 -> 12.709518 | U71: =CONCOR!J96 -> 22.020884 | V71: =U71-T71 -> 9.3113661 | W71: =CONCOR!D80 -> 2.5701338 | X71: =CONCOR!J80 -> 4.7511388 | Y71: =X71-W71 -> 2.181005
A72: Jet Freight | B72: =JetFreight!D121 -> -0.011708586 | C72: =JetFreight!J121 -> 0.037313097 | D72: =C72-B72 -> 0.049021683 | E72: =JetFreight!D124 -> -0.028587631 | F72: =JetFreight!J124 -> 0.015312556 | G72: =F72-E72 -> 0.043900187 | H72: =JetFreight!D138 -> -0.066294769 | I72: =JetFreight!J138 -> 0.078789833 | J72: =I72-H72 -> 0.1450846 | K72: =JetFreight!D113 -> 3.3051819 | L72: =JetFreight!J113 -> 2.3588654 | M72: =L72-K72 -> -0.94631652 | N72: =JetFreight!D108 -> 70.728034 | O72: =JetFreight!J108 -> 71.984102 | P72: =O72-N72 -> 1.2560681 | Q72: =JetFreight!D87 -> 2.1599073 | R72: =JetFreight!J87 -> 1.0175848 | S72: =R72-Q72 -> -1.1423225 | T72: =JetFreight!D96 -> -0.89519651 | U72: =JetFreight!J96 -> 2.6557143 | V72: =U72-T72 -> 3.5509108 | W72: =JetFreight!D80 -> 2.1770364 | X72: =JetFreight!J80 -> 3.5881855 | Y72: =X72-W72 -> 1.4111491
A73: Patel | B73: =Patel!D121 -> 0.023286607 | C73: =Patel!J121 -> 0.029036232 | D73: =C73-B73 -> 0.0057496257 | E73: =Patel!D124 -> 0.030914481 | F73: =Patel!J124 -> 0.026880215 | G73: =F73-E73 -> -0.0040342664 | H73: =Patel!D138 -> 0.088036094 | I73: =Patel!J138 -> 0.074973027 | J73: =I73-H73 -> -0.013063067 | K73: =Patel!D113 -> 1.6068546 | L73: =Patel!J113 -> 2.1550809 | M73: =L73-K73 -> 0.54822625 | N73: =Patel!D108 -> 98.827682 | O73: =Patel!J108 -> 71.627443 | P73: =O73-N73 -> -27.200239 | Q73: =Patel!D87 -> 0.5101235 | R73: =Patel!J87 -> 0.050680052 | S73: =R73-Q73 -> -0.45944345 | T73: =Patel!D96 -> 2.7361299 | U73: =Patel!J96 -> 30.457143 | V73: =U73-T73 -> 27.721013 | W73: =Patel!D80 -> 5.5191108 | X73: =Patel!J80 -> 3.3649374 | Y73: =X73-W73 -> -2.1541734
A74: TCI | B74: =TCI!D121 -> 0.088835252 | C74: =TCI!J121 -> 0.1055571 | D74: =C74-B74 -> 0.016721852 | E74: =TCI!D124 -> 0.052379831 | F74: =TCI!J124 -> 0.09279466 | G74: =F74-E74 -> 0.040414829 | H74: =TCI!D138 -> 0.12397741 | I74: =TCI!J138 -> 0.18230729 | J74: =I74-H74 -> 0.058329886 | K74: =TCI!D113 -> 1.6475402 | L74: =TCI!J113 -> 1.5326853 | M74: =L74-K74 -> -0.11485496 | N74: =TCI!D108 -> 67.308727 | O74: =TCI!J108 -> 57.098039 | P74: =O74-N74 -> -10.210688 | Q74: =TCI!D87 -> 0.41220248 | R74: =TCI!J87 -> 0.12174638 | S74: =R74-Q74 -> -0.2904561 | T74: =TCI!D96 -> 5.6360723 | U74: =TCI!J96 -> 22.93462 | V74: =U74-T74 -> 17.298548 | W74: =TCI!D80 -> 3.1791642 | X74: =TCI!J80 -> 2.4182809 | Y74: =X74-W74 -> -0.76088327
A75: Shreeji | B75: =Shreeji!D121 -> 0.082272727 | C75: =Shreeji!J121 -> 0.033078663 | D75: =C75-B75 -> -0.049194064 | E75: =Shreeji!D124 -> 0.013363636 | F75: =Shreeji!J124 -> 0.013487558 | G75: =F75-E75 -> 0.00012392179 | H75: =Shreeji!D138 -> 0.057660871 | I75: =Shreeji!J138 -> 0.069036714 | J75: =I75-H75 -> 0.011375844 | K75: =Shreeji!D113 -> 1.4607264 | L75: =Shreeji!J113 -> 1.9981237 | M75: =L75-K75 -> 0.53739737 | N75: =Shreeji!D108 -> 94.3525 | O75: =Shreeji!J108 -> 105.5554 | P75: =O75-N75 -> 11.202901 | Q75: =Shreeji!D87 -> 1.8031683 | R75: =Shreeji!J87 -> 0.66661121 | S75: =R75-Q75 -> -1.1365571 | T75: =Shreeji!D96 -> 1.6232295 | U75: =Shreeji!J96 -> 1.8557692 | V75: =U75-T75 -> 0.23253977 | W75: =Shreeji!D80 -> 6.1143524 | X75: =Shreeji!J80 -> 4.7719752 | Y75: =X75-W75 -> -1.3423772
A76: Mahindra Log. | B76: =MahindraLog!D121 -> 0.04565647 | C76: =MahindraLog!J121 -> 0.054119698 | D76: =C76-B76 -> 0.0084632275 | E76: =MahindraLog!D124 -> 0.015879509 | F76: =MahindraLog!J124 -> 0.00032717557 | G76: =F76-E76 -> -0.015552334 | H76: =MahindraLog!D138 -> 0.10530036 | I76: =MahindraLog!J138 -> 0.022025614 | J76: =I76-H76 -> -0.08327475 | K76: =MahindraLog!D113 -> 2.6427149 | L76: =MahindraLog!J113 -> 2.4628902 | M76: =L76-K76 -> -0.17982473 | N76: =MahindraLog!D108 -> 55.410254 | O76: =MahindraLog!J108 -> 34.279274 | P76: =O76-N76 -> -21.13098 | Q76: =MahindraLog!D87 -> 0.36959515 | R76: =MahindraLog!J87 -> 0.55308228 | S76: =R76-Q76 -> 0.18348713 | T76: =MahindraLog!D96 -> 5.6052184 | U76: =MahindraLog!J96 -> 1.4420155 | V76: =U76-T76 -> -4.1632029 | W76: =MahindraLog!D80 -> 1.7350456 | X76: =MahindraLog!J80 -> 1.4122438 | Y76: =X76-W76 -> -0.3228018
A78: E. BUSINESS-MODEL TEST: asset-light vs asset-heavy firms (Welch two-sample t-test on 7-year averages; H0: equal means)
A79: Firm | B79: Net block / TA (7-yr avg) | C79: Group (vs median) | D79: In test? (1/0) | E79: Total assets turno 7-yr | F79: light | G79: heavy | H79: Fixed assets turno 7-yr | I79: light | J79: heavy | K79: Operating EBITDA m 7-yr | L79: light | M79: heavy | N79: Net profit margin 7-yr | O79: light | P79: heavy | Q79: ROCE (post-tax) 7-yr | R79: light | S79: heavy | T79: Debt-equity (Khan 7-yr | U79: light | V79: heavy
A80: Tiger | B80: =Tiger!K195 -> 0.066850107 | C80: =IF(B80>=MEDIAN($B$80:$B$89),"Asset-heavy","Asset-light") -> Asset-light | D80: 1 | E80: =Tiger!K113 -> 3.0689379 | F80: =IF(AND($C80="Asset-light",$D80=1),E80,"") -> 3.0689379 | G80: =IF(AND($C80="Asset-heavy",$D80=1),E80,"") | H80: =Tiger!K112 -> 47.069011 | I80: =IF(AND($C80="Asset-light",$D80=1),H80,"") -> 47.069011 | J80: =IF(AND($C80="Asset-heavy",$D80=1),H80,"") | K80: =Tiger!K121 -> 0.029629489 | L80: =IF(AND($C80="Asset-light",$D80=1),K80,"") -> 0.029629489 | M80: =IF(AND($C80="Asset-heavy",$D80=1),K80,"") | N80: =Tiger!K124 -> 0.019312592 | O80: =IF(AND($C80="Asset-light",$D80=1),N80,"") -> 0.019312592 | P80: =IF(AND($C80="Asset-heavy",$D80=1),N80,"") | Q80: =Tiger!K138 -> 0.14951229 | R80: =IF(AND($C80="Asset-light",$D80=1),Q80,"") -> 0.14951229 | S80: =IF(AND($C80="Asset-heavy",$D80=1),Q80,"") | T80: =Tiger!K87 -> 0.24661787 | U80: =IF(AND($C80="Asset-light",$D80=1),T80,"") -> 0.24661787 | V80: =IF(AND($C80="Asset-heavy",$D80=1),T80,"")
A81: Allcargo | B81: =Allcargo!K195 -> 0.39214748 | C81: =IF(B81>=MEDIAN($B$80:$B$89),"Asset-heavy","Asset-light") -> Asset-heavy | D81: 1 | E81: =Allcargo!K113 -> 1.5832864 | F81: =IF(AND($C81="Asset-light",$D81=1),E81,"") | G81: =IF(AND($C81="Asset-heavy",$D81=1),E81,"") -> 1.5832864 | H81: =Allcargo!K112 -> 4.1918699 | I81: =IF(AND($C81="Asset-light",$D81=1),H81,"") | J81: =IF(AND($C81="Asset-heavy",$D81=1),H81,"") -> 4.1918699 | K81: =Allcargo!K121 -> 0.073607981 | L81: =IF(AND($C81="Asset-light",$D81=1),K81,"") | M81: =IF(AND($C81="Asset-heavy",$D81=1),K81,"") -> 0.073607981 | N81: =Allcargo!K124 -> 0.025549208 | O81: =IF(AND($C81="Asset-light",$D81=1),N81,"") | P81: =IF(AND($C81="Asset-heavy",$D81=1),N81,"") -> 0.025549208 | Q81: =Allcargo!K138 -> 0.091915108 | R81: =IF(AND($C81="Asset-light",$D81=1),Q81,"") | S81: =IF(AND($C81="Asset-heavy",$D81=1),Q81,"") -> 0.091915108 | T81: =Allcargo!K87 -> 0.87612163 | U81: =IF(AND($C81="Asset-light",$D81=1),T81,"") | V81: =IF(AND($C81="Asset-heavy",$D81=1),T81,"") -> 0.87612163
A82: Blue Dart | B82: =BlueDart!K195 -> 0.52080847 | C82: =IF(B82>=MEDIAN($B$80:$B$89),"Asset-heavy","Asset-light") -> Asset-heavy | D82: 1 | E82: =BlueDart!K113 -> 1.5174992 | F82: =IF(AND($C82="Asset-light",$D82=1),E82,"") | G82: =IF(AND($C82="Asset-heavy",$D82=1),E82,"") -> 1.5174992 | H82: =BlueDart!K112 -> 2.9788976 | I82: =IF(AND($C82="Asset-light",$D82=1),H82,"") | J82: =IF(AND($C82="Asset-heavy",$D82=1),H82,"") -> 2.9788976 | K82: =BlueDart!K121 -> 0.17658992 | L82: =IF(AND($C82="Asset-light",$D82=1),K82,"") | M82: =IF(AND($C82="Asset-heavy",$D82=1),K82,"") -> 0.17658992 | N82: =BlueDart!K124 -> 0.045375983 | O82: =IF(AND($C82="Asset-light",$D82=1),N82,"") | P82: =IF(AND($C82="Asset-heavy",$D82=1),N82,"") -> 0.045375983 | Q82: =BlueDart!K138 -> 0.14257551 | R82: =IF(AND($C82="Asset-light",$D82=1),Q82,"") | S82: =IF(AND($C82="Asset-heavy",$D82=1),Q82,"") -> 0.14257551 | T82: =BlueDart!K87 -> 1.1280755 | U82: =IF(AND($C82="Asset-light",$D82=1),T82,"") | V82: =IF(AND($C82="Asset-heavy",$D82=1),T82,"") -> 1.1280755
A83: CONCOR | B83: =CONCOR!K195 -> 0.44613792 | C83: =IF(B83>=MEDIAN($B$80:$B$89),"Asset-heavy","Asset-light") -> Asset-heavy | D83: 1 | E83: =CONCOR!K113 -> 0.59241299 | F83: =IF(AND($C83="Asset-light",$D83=1),E83,"") | G83: =IF(AND($C83="Asset-heavy",$D83=1),E83,"") -> 0.59241299 | H83: =CONCOR!K112 -> 1.355579 | I83: =IF(AND($C83="Asset-light",$D83=1),H83,"") | J83: =IF(AND($C83="Asset-heavy",$D83=1),H83,"") -> 1.355579 | K83: =CONCOR!K121 -> 0.21971019 | L83: =IF(AND($C83="Asset-light",$D83=1),K83,"") | M83: =IF(AND($C83="Asset-heavy",$D83=1),K83,"") -> 0.21971019 | N83: =CONCOR!K124 -> 0.12136961 | O83: =IF(AND($C83="Asset-light",$D83=1),N83,"") | P83: =IF(AND($C83="Asset-heavy",$D83=1),N83,"") -> 0.12136961 | Q83: =CONCOR!K138 -> 0.085792284 | R83: =IF(AND($C83="Asset-light",$D83=1),Q83,"") | S83: =IF(AND($C83="Asset-heavy",$D83=1),Q83,"") -> 0.085792284 | T83: =CONCOR!K87 -> 0.062736366 | U83: =IF(AND($C83="Asset-light",$D83=1),T83,"") | V83: =IF(AND($C83="Asset-heavy",$D83=1),T83,"") -> 0.062736366
A84: Jet Freight | B84: =JetFreight!K195 -> 0.19504924 | C84: =IF(B84>=MEDIAN($B$80:$B$89),"Asset-heavy","Asset-light") -> Asset-light | D84: 1 | E84: =JetFreight!K113 -> 3.1148906 | F84: =IF(AND($C84="Asset-light",$D84=1),E84,"") -> 3.1148906 | G84: =IF(AND($C84="Asset-heavy",$D84=1),E84,"") | H84: =JetFreight!K112 -> 16.059752 | I84: =IF(AND($C84="Asset-light",$D84=1),H84,"") -> 16.059752 | J84: =IF(AND($C84="Asset-heavy",$D84=1),H84,"") | K84: =JetFreight!K121 -> 0.020453399 | L84: =IF(AND($C84="Asset-light",$D84=1),K84,"") -> 0.020453399 | M84: =IF(AND($C84="Asset-heavy",$D84=1),K84,"") | N84: =JetFreight!K124 -> 0.0013562643 | O84: =IF(AND($C84="Asset-light",$D84=1),N84,"") -> 0.0013562643 | P84: =IF(AND($C84="Asset-heavy",$D84=1),N84,"") | Q84: =JetFreight!K138 -> 0.044213263 | R84: =IF(AND($C84="Asset-light",$D84=1),Q84,"") -> 0.044213263 | S84: =IF(AND($C84="Asset-heavy",$D84=1),Q84,"") | T84: =JetFreight!K87 -> 1.3550845 | U84: =IF(AND($C84="Asset-light",$D84=1),T84,"") -> 1.3550845 | V84: =IF(AND($C84="Asset-heavy",$D84=1),T84,"")
A85: Patel | B85: =Patel!K195 -> 0.28277252 | C85: =IF(B85>=MEDIAN($B$80:$B$89),"Asset-heavy","Asset-light") -> Asset-light | D85: 1 | E85: =Patel!K113 -> 1.5981271 | F85: =IF(AND($C85="Asset-light",$D85=1),E85,"") -> 1.5981271 | G85: =IF(AND($C85="Asset-heavy",$D85=1),E85,"") | H85: =Patel!K112 -> 5.7184543 | I85: =IF(AND($C85="Asset-light",$D85=1),H85,"") -> 5.7184543 | J85: =IF(AND($C85="Asset-heavy",$D85=1),H85,"") | K85: =Patel!K121 -> 0.0290875 | L85: =IF(AND($C85="Asset-light",$D85=1),K85,"") -> 0.0290875 | M85: =IF(AND($C85="Asset-heavy",$D85=1),K85,"") | N85: =Patel!K124 -> 0.018081543 | O85: =IF(AND($C85="Asset-light",$D85=1),N85,"") -> 0.018081543 | P85: =IF(AND($C85="Asset-heavy",$D85=1),N85,"") | Q85: =Patel!K138 -> 0.056385123 | R85: =IF(AND($C85="Asset-light",$D85=1),Q85,"") -> 0.056385123 | S85: =IF(AND($C85="Asset-heavy",$D85=1),Q85,"") | T85: =Patel!K87 -> 0.29634174 | U85: =IF(AND($C85="Asset-light",$D85=1),T85,"") -> 0.29634174 | V85: =IF(AND($C85="Asset-heavy",$D85=1),T85,"")
A86: Sical | B86: =Sical!K195 -> 0.58793765 | C86: =IF(B86>=MEDIAN($B$80:$B$89),"Asset-heavy","Asset-light") -> Asset-heavy | D86: 0 | E86: =Sical!K113 -> 0.30368275 | F86: =IF(AND($C86="Asset-light",$D86=1),E86,"") | G86: =IF(AND($C86="Asset-heavy",$D86=1),E86,"") | H86: =Sical!K112 -> 0.58461596 | I86: =IF(AND($C86="Asset-light",$D86=1),H86,"") | J86: =IF(AND($C86="Asset-heavy",$D86=1),H86,"") | K86: =Sical!K121 -> 0.041720612 | L86: =IF(AND($C86="Asset-light",$D86=1),K86,"") | M86: =IF(AND($C86="Asset-heavy",$D86=1),K86,"") | N86: =Sical!K124 -> -0.77125135 | O86: =IF(AND($C86="Asset-light",$D86=1),N86,"") | P86: =IF(AND($C86="Asset-heavy",$D86=1),N86,"") | Q86: =Sical!K138 -> -0.31089339 | R86: =IF(AND($C86="Asset-light",$D86=1),Q86,"") | S86: =IF(AND($C86="Asset-heavy",$D86=1),Q86,"") | T86: =Sical!K87 -> 8.2478837 | U86: =IF(AND($C86="Asset-light",$D86=1),T86,"") | V86: =IF(AND($C86="Asset-heavy",$D86=1),T86,"")
A87: TCI | B87: =TCI!K195 -> 0.39313615 | C87: =IF(B87>=MEDIAN($B$80:$B$89),"Asset-heavy","Asset-light") -> Asset-heavy | D87: 1 | E87: =TCI!K113 -> 1.7104834 | F87: =IF(AND($C87="Asset-light",$D87=1),E87,"") | G87: =IF(AND($C87="Asset-heavy",$D87=1),E87,"") -> 1.7104834 | H87: =TCI!K112 -> 4.3345309 | I87: =IF(AND($C87="Asset-light",$D87=1),H87,"") | J87: =IF(AND($C87="Asset-heavy",$D87=1),H87,"") -> 4.3345309 | K87: =TCI!K121 -> 0.10460636 | L87: =IF(AND($C87="Asset-light",$D87=1),K87,"") | M87: =IF(AND($C87="Asset-heavy",$D87=1),K87,"") -> 0.10460636 | N87: =TCI!K124 -> 0.078488617 | O87: =IF(AND($C87="Asset-light",$D87=1),N87,"") | P87: =IF(AND($C87="Asset-heavy",$D87=1),N87,"") -> 0.078488617 | Q87: =TCI!K138 -> 0.17138129 | R87: =IF(AND($C87="Asset-light",$D87=1),Q87,"") | S87: =IF(AND($C87="Asset-heavy",$D87=1),Q87,"") -> 0.17138129 | T87: =TCI!K87 -> 0.15977623 | U87: =IF(AND($C87="Asset-light",$D87=1),T87,"") | V87: =IF(AND($C87="Asset-heavy",$D87=1),T87,"") -> 0.15977623
A88: Shreeji | B88: =Shreeji!K195 -> 0.25601414 | C88: =IF(B88>=MEDIAN($B$80:$B$89),"Asset-heavy","Asset-light") -> Asset-light | D88: 1 | E88: =Shreeji!K113 -> 1.8179609 | F88: =IF(AND($C88="Asset-light",$D88=1),E88,"") -> 1.8179609 | G88: =IF(AND($C88="Asset-heavy",$D88=1),E88,"") | H88: =Shreeji!K112 -> 7.2256921 | I88: =IF(AND($C88="Asset-light",$D88=1),H88,"") -> 7.2256921 | J88: =IF(AND($C88="Asset-heavy",$D88=1),H88,"") | K88: =Shreeji!K121 -> 0.072103023 | L88: =IF(AND($C88="Asset-light",$D88=1),K88,"") -> 0.072103023 | M88: =IF(AND($C88="Asset-heavy",$D88=1),K88,"") | N88: =Shreeji!K124 -> 0.027812603 | O88: =IF(AND($C88="Asset-light",$D88=1),N88,"") -> 0.027812603 | P88: =IF(AND($C88="Asset-heavy",$D88=1),N88,"") | Q88: =Shreeji!K138 -> 0.10576238 | R88: =IF(AND($C88="Asset-light",$D88=1),Q88,"") -> 0.10576238 | S88: =IF(AND($C88="Asset-heavy",$D88=1),Q88,"") | T88: =Shreeji!K87 -> 1.2179689 | U88: =IF(AND($C88="Asset-light",$D88=1),T88,"") -> 1.2179689 | V88: =IF(AND($C88="Asset-heavy",$D88=1),T88,"")
A89: Mahindra Log. | B89: =MahindraLog!K195 -> 0.28888773 | C89: =IF(B89>=MEDIAN($B$80:$B$89),"Asset-heavy","Asset-light") -> Asset-light | D89: 1 | E89: =MahindraLog!K113 -> 2.3336528 | F89: =IF(AND($C89="Asset-light",$D89=1),E89,"") -> 2.3336528 | G89: =IF(AND($C89="Asset-heavy",$D89=1),E89,"") | H89: =MahindraLog!K112 -> 10.22712 | I89: =IF(AND($C89="Asset-light",$D89=1),H89,"") -> 10.22712 | J89: =IF(AND($C89="Asset-heavy",$D89=1),H89,"") | K89: =MahindraLog!K121 -> 0.046407247 | L89: =IF(AND($C89="Asset-light",$D89=1),K89,"") -> 0.046407247 | M89: =IF(AND($C89="Asset-heavy",$D89=1),K89,"") | N89: =MahindraLog!K124 -> 0.0027070853 | O89: =IF(AND($C89="Asset-light",$D89=1),N89,"") -> 0.0027070853 | P89: =IF(AND($C89="Asset-heavy",$D89=1),N89,"") | Q89: =MahindraLog!K138 -> 0.052441099 | R89: =IF(AND($C89="Asset-light",$D89=1),Q89,"") -> 0.052441099 | S89: =IF(AND($C89="Asset-heavy",$D89=1),Q89,"") | T89: =MahindraLog!K87 -> 1.0148062 | U89: =IF(AND($C89="Asset-light",$D89=1),T89,"") -> 1.0148062 | V89: =IF(AND($C89="Asset-heavy",$D89=1),T89,"")
A90: Median net block / TA | B90: =MEDIAN(B80:B89) -> 0.3405176
A92: Ratio (7-yr avg) | B92: Mean asset-light | C92: Mean asset-heavy | D92: SD light | E92: SD heavy | F92: n light | G92: n heavy | H92: t-stat (Welch) | I92: Welch df | J92: p-value (2-tailed) | K92: Conclusion
A93: Total assets turnover | B93: =AVERAGE(F80:F89) -> 2.3867139 | C93: =AVERAGE(G80:G89) -> 1.3509205 | D93: =STDEV(F80:F89) -> 0.6971075 | E93: =STDEV(G80:G89) -> 0.51197705 | F93: =COUNT(F80:F89) -> 5 | G93: =COUNT(G80:G89) -> 4 | H93: =(B93-C93)/SQRT(D93^2/F93+E93^2/G93) -> 2.5677346 | I93: =(D93^2/F93+E93^2/G93)^2/((D93^2/F93)^2/(F93-1)+(E93^2/G93)^2/(G93-1)) -> 6.9809387 | J93: =TDIST(ABS(H93),I93,2) -> 0.042464253 | K93: =IF(J93<0.05,"Significant at 5%",IF(J93<0.1,"Significant at 10%","Not significant")) -> Significant at 5%
A94: Fixed assets turnover | B94: =AVERAGE(I80:I89) -> 17.260006 | C94: =AVERAGE(J80:J89) -> 3.2152193 | D94: =STDEV(I80:I89) -> 17.127272 | E94: =STDEV(J80:J89) -> 1.3809194 | F94: =COUNT(I80:I89) -> 5 | G94: =COUNT(J80:J89) -> 4 | H94: =(B94-C94)/SQRT(D94^2/F94+E94^2/G94) -> 1.8262262 | I94: =(D94^2/F94+E94^2/G94)^2/((D94^2/F94)^2/(F94-1)+(E94^2/G94)^2/(G94-1)) -> 4.0649133 | J94: =TDIST(ABS(H94),I94,2) -> 0.14184765 | K94: =IF(J94<0.05,"Significant at 5%",IF(J94<0.1,"Significant at 10%","Not significant")) -> Not significant
A95: Operating EBITDA margin (core) | B95: =AVERAGE(L80:L89) -> 0.039536132 | C95: =AVERAGE(M80:M89) -> 0.14362861 | D95: =STDEV(L80:L89) -> 0.020489514 | E95: =STDEV(M80:M89) -> 0.066584481 | F95: =COUNT(L80:L89) -> 5 | G95: =COUNT(M80:M89) -> 4 | H95: =(B95-C95)/SQRT(D95^2/F95+E95^2/G95) -> -3.0145313 | I95: =(D95^2/F95+E95^2/G95)^2/((D95^2/F95)^2/(F95-1)+(E95^2/G95)^2/(G95-1)) -> 3.4568635 | J95: =TDIST(ABS(H95),I95,2) -> 0.057006081 | K95: =IF(J95<0.05,"Significant at 5%",IF(J95<0.1,"Significant at 10%","Not significant")) -> Significant at 10%
A96: Net profit margin | B96: =AVERAGE(O80:O89) -> 0.013854018 | C96: =AVERAGE(P80:P89) -> 0.067695854 | D96: =STDEV(O80:O89) -> 0.011434138 | E96: =STDEV(P80:P89) -> 0.041920052 | F96: =COUNT(O80:O89) -> 5 | G96: =COUNT(P80:P89) -> 4 | H96: =(B96-C96)/SQRT(D96^2/F96+E96^2/G96) -> -2.4955929 | I96: =(D96^2/F96+E96^2/G96)^2/((D96^2/F96)^2/(F96-1)+(E96^2/G96)^2/(G96-1)) -> 3.3588156 | J96: =TDIST(ABS(H96),I96,2) -> 0.088048229 | K96: =IF(J96<0.05,"Significant at 5%",IF(J96<0.1,"Significant at 10%","Not significant")) -> Significant at 10%
A97: ROCE (post-tax) | B97: =AVERAGE(R80:R89) -> 0.081662831 | C97: =AVERAGE(S80:S89) -> 0.12291605 | D97: =STDEV(R80:R89) -> 0.044943519 | E97: =STDEV(S80:S89) -> 0.04112828 | F97: =COUNT(R80:R89) -> 5 | G97: =COUNT(S80:S89) -> 4 | H97: =(B97-C97)/SQRT(D97^2/F97+E97^2/G97) -> -1.4346296 | I97: =(D97^2/F97+E97^2/G97)^2/((D97^2/F97)^2/(F97-1)+(E97^2/G97)^2/(G97-1)) -> 6.8091176 | J97: =TDIST(ABS(H97),I97,2) -> 0.20139327 | K97: =IF(J97<0.05,"Significant at 5%",IF(J97<0.1,"Significant at 10%","Not significant")) -> Not significant
A98: Debt-equity (Khan & Jain) | B98: =AVERAGE(U80:U89) -> 0.82616385 | C98: =AVERAGE(V80:V89) -> 0.55667743 | D98: =STDEV(U80:U89) -> 0.52092207 | E98: =STDEV(V80:V89) -> 0.52600655 | F98: =COUNT(U80:U89) -> 5 | G98: =COUNT(V80:V89) -> 4 | H98: =(B98-C98)/SQRT(D98^2/F98+E98^2/G98) -> 0.76701563 | I98: =(D98^2/F98+E98^2/G98)^2/((D98^2/F98)^2/(F98-1)+(E98^2/G98)^2/(G98-1)) -> 6.5365205 | J98: =TDIST(ABS(H98),I98,2) -> 0.47216438 | K98: =IF(J98<0.05,"Significant at 5%",IF(J98<0.1,"Significant at 10%","Not significant")) -> Not significant
A99: Groups split at the median asset intensity of all 10 firms; Sical (asset-heavy) excluded from the test. Excel TDIST truncates the Welch df to an integer.
A101: F. TWO-WAY ANOVA without replication: Operating EBITDA margin (core) - firm effect vs year effect (9 firms x 7 years)
A102: Firm | B102: FY2020 | C102: FY2021 | D102: FY2022 | E102: FY2023 | F102: FY2024 | G102: FY2025 | H102: FY2026 | I102: Firm mean
A103: Tiger | B103: =Tiger!D121 -> -0.027829375 | C103: =Tiger!E121 -> -0.05653184 | D103: =Tiger!F121 -> 0.061127278 | E103: =Tiger!G121 -> 0.061013038 | F103: =Tiger!H121 -> 0.06388912 | G103: =Tiger!I121 -> 0.05858552 | H103: =Tiger!J121 -> 0.047152683 | I103: =AVERAGE(B103:H103) -> 0.029629489
A104: Allcargo | B104: =Allcargo!D121 -> 0.070124308 | C104: =Allcargo!E121 -> 0.061257751 | D104: =Allcargo!F121 -> 0.067215191 | E104: =Allcargo!G121 -> 0.06316628 | F104: =Allcargo!H121 -> 0.036295136 | G104: =Allcargo!I121 -> 0.10300867 | H104: =Allcargo!J121 -> 0.11418853 | I104: =AVERAGE(B104:H104) -> 0.073607981
A105: Blue Dart | B105: =BlueDart!D121 -> 0.14947734 | C105: =BlueDart!E121 -> 0.20871742 | D105: =BlueDart!F121 -> 0.22673444 | E105: =BlueDart!G121 -> 0.18127806 | F105: =BlueDart!H121 -> 0.16192626 | G105: =BlueDart!I121 -> 0.15318749 | H105: =BlueDart!J121 -> 0.15480843 | I105: =AVERAGE(B105:H105) -> 0.17658992
A106: CONCOR | B106: =CONCOR!D121 -> 0.25944103 | C106: =CONCOR!E121 -> 0.16296514 | D106: =CONCOR!F121 -> 0.22847664 | E106: =CONCOR!G121 -> 0.22864152 | F106: =CONCOR!H121 -> 0.22634776 | G106: =CONCOR!I121 -> 0.21717179 | H106: =CONCOR!J121 -> 0.21492746 | I106: =AVERAGE(B106:H106) -> 0.21971019
A107: Jet Freight | B107: =JetFreight!D121 -> -0.011708586 | C107: =JetFreight!E121 -> 0.026846218 | D107: =JetFreight!F121 -> 0.023601016 | E107: =JetFreight!G121 -> 0.019198925 | F107: =JetFreight!H121 -> 0.015240993 | G107: =JetFreight!I121 -> 0.032682134 | H107: =JetFreight!J121 -> 0.037313097 | I107: =AVERAGE(B107:H107) -> 0.020453399
A108: Patel | B108: =Patel!D121 -> 0.023286607 | C108: =Patel!E121 -> 0.024358068 | D108: =Patel!F121 -> 0.032818368 | E108: =Patel!G121 -> 0.03708495 | F108: =Patel!H121 -> 0.031319911 | G108: =Patel!I121 -> 0.025708366 | H108: =Patel!J121 -> 0.029036232 | I108: =AVERAGE(B108:H108) -> 0.0290875
A109: TCI | B109: =TCI!D121 -> 0.088835252 | C109: =TCI!E121 -> 0.093855602 | D109: =TCI!F121 -> 0.12637435 | E109: =TCI!G121 -> 0.11245529 | F109: =TCI!H121 -> 0.10218773 | G109: =TCI!I121 -> 0.10297922 | H109: =TCI!J121 -> 0.1055571 | I109: =AVERAGE(B109:H109) -> 0.10460636
...

Sheet Panel
A1: Firm | B1: FY | C1: Sales (Rs cr) | D1: Total assets (Rs cr) | E1: Asset intensity (Net block / TA) | F1: Current ratio | G1: Quick ratio | H1: Interest coverage | I1: Collection period (days) | J1: Fixed assets turnover | K1: Net profit margin | L1: ROA | M1: ROE | N1: P/E | O1: P/B | P1: EV/EBITDA | Q1: ROCE (Y) | R1: Total assets turnover (X1) | S1: Operating EBITDA margin (X2) | T1: Debt-equity (X3) | U1: ln(Sales) (X4)
A2: Tiger | B2: 2020 | C2: =Tiger!D9 -> 301.48 | D2: =Tiger!D35 -> 105.11 | E2: =Tiger!D195 -> 0.091713443 | F2: =Tiger!D80 -> 6.047014 | G2: =Tiger!D81 -> 4.5463787 | H2: =Tiger!D96 -> -1.7274775 | I2: =Tiger!D108 -> 101.00214 | J2: =Tiger!D112 -> 29.938431 | K2: =Tiger!D124 -> -0.040931405 | L2: =Tiger!D135 -> -0.10724373 | M2: =Tiger!D139 -> -0.2093477 | N2: =Tiger!D152 -> N/M | O2: =Tiger!D146 -> 0.59970209 | P2: =Tiger!D154 -> N/M | Q2: =Tiger!D138 -> -0.080745342 | R2: =Tiger!D113 -> 2.6200843 | S2: =Tiger!D121 -> -0.027829375 | T2: =Tiger!D87 -> 0.69582543 | U2: =LN(C2) -> 5.7087037
A3: Tiger | B3: 2021 | C3: =Tiger!E9 -> 167.87 | D3: =Tiger!E35 -> 83.85 | E3: =Tiger!E195 -> 0.10280262 | F3: =Tiger!E80 -> 2.7896693 | G3: =Tiger!E81 -> 1.8784838 | H3: =Tiger!E96 -> -5.1836735 | I3: =Tiger!E108 -> 118.16242 | J3: =Tiger!E112 -> 18.386637 | K3: =Tiger!E124 -> -0.073985822 | L3: =Tiger!E135 -> -0.13145639 | M3: =Tiger!E139 -> -0.26235741 | N3: =Tiger!E152 -> N/M | O3: =Tiger!E146 -> 1.067575 | P3: =Tiger!E154 -> N/M | Q3: =Tiger!E138 -> -0.13888319 | R3: =Tiger!E113 -> 1.7767782 | S3: =Tiger!E121 -> -0.05653184 | T3: =Tiger!E87 -> 0.35636017 | U3: =LN(C3) -> 5.1231899
A4: Tiger | B4: 2022 | C4: =Tiger!F9 -> 615.11 | D4: =Tiger!F35 -> 121.25 | E4: =Tiger!F195 -> 0.064742268 | F4: =Tiger!F80 -> 2.310551 | G4: =Tiger!F81 -> 2.1405382 | H4: =Tiger!F96 -> 25.754967 | I4: =Tiger!F108 -> 33.179391 | J4: =Tiger!F112 -> 74.694596 | K4: =Tiger!F124 -> 0.054673148 | L4: =Tiger!F135 -> 0.32793759 | M4: =Tiger!F139 -> 0.57778541 | N4: =Tiger!F152 -> 6.6380731 | O4: =Tiger!F146 -> 2.9993067 | P4: =Tiger!F154 -> 4.8293878 | Q4: =Tiger!F138 -> 0.53267131 | R4: =Tiger!F113 -> 5.9981472 | S4: =Tiger!F121 -> 0.061127278 | T4: =Tiger!F87 -> 0 | U4: =LN(C4) -> 6.4218011
A5: Tiger | B5: 2023 | C5: =Tiger!G9 -> 433.35 | D5: =Tiger!G35 -> 119.51 | E5: =Tiger!G195 -> 0.06283993 | F5: =Tiger!G80 -> 4.8683729 | G5: =Tiger!G81 -> 4.6480804 | H5: =Tiger!G96 -> 31.427184 | I5: =Tiger!G108 -> 49.677397 | J5: =Tiger!G112 -> 56.425781 | K5: =Tiger!G124 -> 0.053559478 | L5: =Tiger!G135 -> 0.19280611 | M5: =Tiger!G139 -> 0.26978961 | N5: =Tiger!G152 -> 16.544942 | O5: =Tiger!G146 -> 3.9333002 | P5: =Tiger!G154 -> 10.003261 | Q5: =Tiger!G138 -> 0.27865634 | R5: =Tiger!G113 -> 3.5998505 | S5: =Tiger!G121 -> 0.061013038 | T5: =Tiger!G87 -> 0 | U5: =LN(C5) -> 6.0715457
A6: Tiger | B6: 2024 | C6: =Tiger!H9 -> 240.26 | D6: =Tiger!H35 -> 143.58 | E6: =Tiger!H195 -> 0.063031063 | F6: =Tiger!H80 -> 5.9541284 | G6: =Tiger!H81 -> 5.385804 | H6: =Tiger!H96 -> 24.276316 | I6: =Tiger!H108 -> 90.460022 | J6: =Tiger!H112 -> 29.016908 | K6: =Tiger!H124 -> 0.053941563 | L6: =Tiger!H135 -> 0.098521419 | M6: =Tiger!H139 -> 0.1243404 | N6: =Tiger!H152 -> 37.516975 | O6: =Tiger!H146 -> 4.3870793 | P6: =Tiger!H154 -> 23.73947 | Q6: =Tiger!H138 -> 0.12250666 | R6: =Tiger!H113 -> 1.8264472 | S6: =Tiger!H121 -> 0.06388912 | T6: =Tiger!H87 -> 0.10863485 | U6: =LN(C6) -> 5.4817217
A7: Tiger | B7: 2025 | C7: =Tiger!I9 -> 536.31 | D7: =Tiger!I35 -> 195.69 | E7: =Tiger!I195 -> 0.045428995 | F7: =Tiger!I80 -> 7.5958279 | G7: =Tiger!I81 -> 6.6857888 | H7: =Tiger!I96 -> 11.773134 | I7: =Tiger!I108 -> 58.689517 | J7: =Tiger!I112 -> 59.789298 | K7: =Tiger!I124 -> 0.050362663 | L7: =Tiger!I135 -> 0.15922422 | M7: =Tiger!I139 -> 0.21683458 | N7: =Tiger!I152 -> 18.588486 | O7: =Tiger!I146 -> 3.6303326 | P7: =Tiger!I154 -> 12.045048 | Q7: =Tiger!I138 -> 0.19974395 | R7: =Tiger!I113 -> 3.1615527 | S7: =Tiger!I121 -> 0.05858552 | T7: =Tiger!I87 -> 0.24859002 | U7: =LN(C7) -> 6.2847124
A8: Tiger | B8: 2026 | C8: =Tiger!J9 -> 572.82 | D8: =Tiger!J35 -> 262.62 | E8: =Tiger!J195 -> 0.03739243 | F8: =Tiger!J80 -> 4.6170581 | G8: =Tiger!J81 -> 3.8983442 | H8: =Tiger!J96 -> 6.5294118 | I8: =Tiger!J108 -> 84.017798 | J8: =Tiger!J112 -> 61.231427 | K8: =Tiger!J124 -> 0.037568521 | L8: =Tiger!J135 -> 0.093910235 | M8: =Tiger!J139 -> 0.14429395 | N8: =Tiger!J152 -> 11.738987 | O8: =Tiger!J146 -> 1.5790911 | P8: =Tiger!J154 -> 7.4038168 | Q8: =Tiger!J138 -> 0.13263629 | R8: =Tiger!J113 -> 2.4997054 | S8: =Tiger!J121 -> 0.047152683 | T8: =Tiger!J87 -> 0.31691461 | U8: =LN(C8) -> 6.3505715
A9: Allcargo | B9: 2020 | C9: =Allcargo!D9 -> 7346.24 | D9: =Allcargo!D35 -> 5300.94 | E9: =Allcargo!D195 -> 0.37125302 | F9: =Allcargo!D80 -> 1.6456859 | G9: =Allcargo!D81 -> 1.1198466 | H9: =Allcargo!D96 -> 5.0894363 | I9: =Allcargo!D108 -> 51.976766 | J9: =Allcargo!D112 -> 4.1217174 | K9: =Allcargo!D124 -> 0.030355665 | L9: =Allcargo!D135 -> 0.048397721 | M9: =Allcargo!D139 -> 0.10761302 | N9: =Allcargo!D152 -> N/C | O9: =Allcargo!D146 -> N/C | P9: =Allcargo!D154 -> N/C | Q9: =Allcargo!D138 -> 0.091913326 | R9: =Allcargo!D113 -> 1.5943555 | S9: =Allcargo!D121 -> 0.070124308 | T9: =Allcargo!D87 -> 0.747234 | U9: =LN(C9) -> 8.9019439
A10: Allcargo | B10: 2021 | C10: =Allcargo!E9 -> 10498.1 | D10: =Allcargo!E35 -> 7313.27 | E10: =Allcargo!E195 -> 0.43271478 | F10: =Allcargo!E80 -> 1.2893373 | G10: =Allcargo!E81 -> 0.86255381 | H10: =Allcargo!E96 -> 2.1105061 | I10: =Allcargo!E108 -> 57.81586 | J10: =Allcargo!E112 -> 4.0907931 | K10: =Allcargo!E124 -> 0.016469647 | L10: =Allcargo!E135 -> 0.027413528 | M10: =Allcargo!E139 -> 0.078072085 | N10: =Allcargo!E152 -> N/C | O10: =Allcargo!E146 -> N/C | P10: =Allcargo!E154 -> N/C | Q10: =Allcargo!E138 -> 0.044642319 | R10: =Allcargo!E113 -> 1.6644879 | S10: =Allcargo!E121 -> 0.061257751 | T10: =Allcargo!E87 -> 0.90445974 | U10: =LN(C10) -> 9.2589496
A11: Allcargo | B11: 2022 | C11: =Allcargo!F9 -> 19062.06 | D11: =Allcargo!F35 -> 9604 | E11: =Allcargo!F195 -> 0.36357351 | F11: =Allcargo!F80 -> 1.3437125 | G11: =Allcargo!F81 -> 0.90198137 | H11: =Allcargo!F96 -> 13.697329 | I11: =Allcargo!F108 -> 50.28222 | J11: =Allcargo!F112 -> 5.7275071 | K11: =Allcargo!F124 -> 0.048563482 | L11: =Allcargo!F135 -> 0.10944083 | M11: =Allcargo!F139 -> 0.34000698 | N11: =Allcargo!F152 -> N/C | O11: =Allcargo!F146 -> N/C | P11: =Allcargo!F154 -> N/C | Q11: =Allcargo!F138 -> 0.21175418 | R11: =Allcargo!F113 -> 2.2535622 | S11: =Allcargo!F121 -> 0.067215191 | T11: =Allcargo!F87 -> 0.73291774 | U11: =LN(C11) -> 9.8554553
A12: Allcargo | B12: 2023 | C12: =Allcargo!G9 -> 18050.77 | D12: =Allcargo!G35 -> 7230.85 | E12: =Allcargo!G195 -> 0.29483117 | F12: =Allcargo!G80 -> 1.3908215 | G12: =Allcargo!G81 -> 1.0338819 | H12: =Allcargo!G96 -> 11.463246 | I12: =Allcargo!G108 -> 51.707577 | J12: =Allcargo!G112 -> 6.4196037 | K12: =Allcargo!G124 -> 0.034878845 | L12: =Allcargo!G135 -> 0.074796033 | M12: =Allcargo!G139 -> 0.21070686 | N12: =Allcargo!G152 -> N/C | O12: =Allcargo!G146 -> N/C | P12: =Allcargo!G154 -> N/C | Q12: =Allcargo!G138 -> 0.15109361 | R12: =Allcargo!G113 -> 2.1444527 | S12: =Allcargo!G121 -> 0.06316628 | T12: =Allcargo!G87 -> 0.41912146 | U12: =LN(C12) -> 9.8009436
A13: Allcargo | B13: 2024 | C13: =Allcargo!H9 -> 12968.68 | D13: =Allcargo!H35 -> 7163.48 | E13: =Allcargo!H195 -> 0.39566663 | F13: =Allcargo!H80 -> 1.4445132 | G13: =Allcargo!H81 -> 0.99669494 | H13: =Allcargo!H96 -> 2.1782285 | I13: =Allcargo!H108 -> 60.02891 | J13: =Allcargo!H112 -> 5.2227464 | K13: =Allcargo!H124 -> 0.011543195 | L13: =Allcargo!H135 -> 0.020799857 | M13: =Allcargo!H139 -> 0.056111023 | N13: =Allcargo!H152 -> N/C | O13: =Allcargo!H146 -> N/C | P13: =Allcargo!H154 -> N/C | Q13: =Allcargo!H138 -> 0.061908214 | R13: =Allcargo!H113 -> 1.8019151 | S13: =Allcargo!H121 -> 0.036295136 | T13: =Allcargo!H87 -> 0.73212168 | U13: =LN(C13) -> 9.4702925
A14: Allcargo | B14: 2025 | C14: =Allcargo!I9 -> 1961 | D14: =Allcargo!I35 -> 1741 | E14: =Allcargo!I195 -> 0.43595635 | F14: =Allcargo!I80 -> 2.4522613 | G14: =Allcargo!I81 -> 1.3366834 | H14: =Allcargo!I96 -> 1.2 | I14: =Allcargo!I108 -> 242.2178 | J14: =Allcargo!I112 -> 1.0914606 | K14: =Allcargo!I124 -> 0.033146354 | L14: =Allcargo!I135 -> 0.014599393 | M14: =Allcargo!I139 -> 0.042158106 | N14: =Allcargo!I152 -> N/C | O14: =Allcargo!I146 -> N/C | P14: =Allcargo!I154 -> N/C | Q14: =Allcargo!I138 -> 0.031519392 | R14: =Allcargo!I113 -> 0.44045245 | S14: =Allcargo!I121 -> 0.10300867 | T14: =Allcargo!I87 -> 1.3896797 | U14: =LN(C14) -> 7.5812098
A15: Allcargo | B15: 2026 | C15: =Allcargo!J9 -> 2058 | D15: =Allcargo!J35 -> 1736 | E15: =Allcargo!J195 -> 0.45103687 | F15: =Allcargo!J80 -> 2.0255864 | G15: =Allcargo!J81 -> 1.1940299 | H15: =Allcargo!J96 -> 1.0645161 | I15: =Allcargo!J108 -> 71.297376 | J15: =Allcargo!J112 -> 2.6692607 | K15: =Allcargo!J124 -> 0.0038872692 | L15: =Allcargo!J135 -> 0.0046016681 | M15: =Allcargo!J139 -> 0.014084507 | N15: =Allcargo!J152 -> 134.42755 | O15: =Allcargo!J146 -> 1.8735547 | P15: =Allcargo!J154 -> 6.06452 | Q15: =Allcargo!J138 -> 0.050574713 | R15: =Allcargo!J113 -> 1.1837791 | S15: =Allcargo!J121 -> 0.11418853 | T15: =Allcargo!J87 -> 1.2073171 | U15: =LN(C15) -> 7.6294899
A16: Blue Dart | B16: 2020 | C16: =BlueDart!D9 -> 3175.13 | D16: =BlueDart!D35 -> 2640.79 | E16: =BlueDart!D195 -> 0.63048557 | F16: =BlueDart!D80 -> 0.59123682 | G16: =BlueDart!D81 -> 0.38780587 | H16: =BlueDart!D96 -> 0.66672346 | I16: =BlueDart!D108 -> 58.584412 | J16: =BlueDart!D112 -> 2.7379599 | K16: =BlueDart!D124 -> -0.013183712 | L16: =BlueDart!D135 -> -0.01880482 | M16: =BlueDart!D139 -> -0.078349165 | N16: =BlueDart!D152 -> N/M | O16: =BlueDart!D146 -> 10.618235 | P16: =BlueDart!D154 -> 13.256299 | Q16: =BlueDart!D138 -> 0.072088171 | R16: =BlueDart!D113 -> 1.4263676 | S16: =BlueDart!D121 -> 0.14947734 | T16: =BlueDart!D87 -> 1.0798036 | U16: =LN(C16) -> 8.0631039
A17: Blue Dart | B17: 2021 | C17: =BlueDart!E9 -> 3288.13 | D17: =BlueDart!E35 -> 2897.43 | E17: =BlueDart!E195 -> 0.54640837 | F17: =BlueDart!E80 -> 1.4776847 | G17: =BlueDart!E81 -> 1.057601 | H17: =BlueDart!E96 -> 2.2599369 | I17: =BlueDart!E108 -> 58.06412 | J17: =BlueDart!E112 -> 2.0246109 | K17: =BlueDart!E124 -> 0.030962888 | L17: =BlueDart!E135 -> 0.036766326 | M17: =BlueDart!E139 -> 0.18805124 | N17: =BlueDart!E152 -> 129.76338 | O17: =BlueDart!E146 -> 22.31774 | P17: =BlueDart!E154 -> 21.187002 | Q17: =BlueDart!E138 -> 0.11650343 | R17: =BlueDart!E113 -> 1.1874321 | S17: =BlueDart!E121 -> 0.20871742 | T17: =BlueDart!E87 -> 2.5713731 | U17: =LN(C17) -> 8.0980743
A18: Blue Dart | B18: 2022 | C18: =BlueDart!F9 -> 4410.49 | D18: =BlueDart!F35 -> 2828.76 | E18: =BlueDart!F195 -> 0.50795048 | F18: =BlueDart!F80 -> 1.2520571 | G18: =BlueDart!F81 -> 0.85800882 | H18: =BlueDart!F96 -> 6.890422 | I18: =BlueDart!F108 -> 45.430831 | J18: =BlueDart!F112 -> 2.9208059 | K18: =BlueDart!F124 -> 0.086659305 | L18: =BlueDart!F135 -> 0.1334954 | M18: =BlueDart!F139 -> 0.52216264 | N18: =BlueDart!F152 -> 42.5513 | O18: =BlueDart!F146 -> 18.651054 | P18: =BlueDart!F154 -> 17.237709 | Q18: =BlueDart!F138 -> 0.22067733 | R18: =BlueDart!F113 -> 1.5404623 | S18: =BlueDart!F121 -> 0.22673444 | T18: =BlueDart!F87 -> 1.2224223 | U18: =LN(C18) -> 8.3917411
A19: Blue Dart | B19: 2023 | C19: =BlueDart!G9 -> 5172.22 | D19: =BlueDart!G35 -> 3223.04 | E19: =BlueDart!G195 -> 0.44586167 | F19: =BlueDart!G80 -> 1.2738644 | G19: =BlueDart!G81 -> 0.792969 | H19: =BlueDart!G96 -> 8.6020942 | I19: =BlueDart!G108 -> 42.929782 | J19: =BlueDart!G112 -> 3.5994433 | K19: =BlueDart!G124 -> 0.071638484 | L19: =BlueDart!G135 -> 0.12245282 | M19: =BlueDart!G139 -> 0.36121957 | N19: =BlueDart!G152 -> 39.739539 | O19: =BlueDart!G146 -> 12.483207 | P19: =BlueDart!G154 -> 16.244275 | Q19: =BlueDart!G138 -> 0.19787972 | R19: =BlueDart!G113 -> 1.7093162 | S19: =BlueDart!G121 -> 0.18127806 | T19: =BlueDart!G87 -> 0.94962528 | U19: =LN(C19) -> 8.5510573
A20: Blue Dart | B20: 2024 | C20: =BlueDart!H9 -> 5267.83 | D20: =BlueDart!H35 -> 3460.9 | E20: =BlueDart!H195 -> 0.52660869 | F20: =BlueDart!H80 -> 1.2317475 | G20: =BlueDart!H81 -> 0.81971823 | H20: =BlueDart!H96 -> 6.0307456 | I20: =BlueDart!H108 -> 45.283148 | J20: =BlueDart!H112 -> 3.2322239 | K20: =BlueDart!H124 -> 0.057141176 | L20: =BlueDart!H135 -> 0.09006963 | M20: =BlueDart!H139 -> 0.23638013 | N20: =BlueDart!H152 -> 48.689284 | O20: =BlueDart!H146 -> 10.719142 | P20: =BlueDart!H154 -> 17.222584 | Q20: =BlueDart!H138 -> 0.15225745 | R20: =BlueDart!H113 -> 1.5762649 | S20: =BlueDart!H121 -> 0.16192626 | T20: =BlueDart!H87 -> 0.78473893 | U20: =LN(C20) -> 8.5693738
A21: Blue Dart | B21: 2025 | C21: =BlueDart!I9 -> 5720.18 | D21: =BlueDart!I35 -> 3662.76 | E21: =BlueDart!I195 -> 0.49514028 | F21: =BlueDart!I80 -> 1.2641671 | G21: =BlueDart!I81 -> 0.8693115 | H21: =BlueDart!I96 -> 5.2145891 | I21: =BlueDart!I108 -> 46.469674 | J21: =BlueDart!I112 -> 3.1463098 | K21: =BlueDart!I124 -> 0.044127982 | L21: =BlueDart!I135 -> 0.070868065 | M21: =BlueDart!I139 -> 0.17251761 | N21: =BlueDart!I152 -> 57.616294 | O21: =BlueDart!I146 -> 9.3285002 | P21: =BlueDart!I154 -> 16.820129 | Q21: =BlueDart!I138 -> 0.12476882 | R21: =BlueDart!I113 -> 1.6059666 | S21: =BlueDart!I121 -> 0.15318749 | T21: =BlueDart!I87 -> 0.64590389 | U21: =LN(C21) -> 8.6517556
A22: Blue Dart | B22: 2026 | C22: =BlueDart!J9 -> 6140.88 | D22: =BlueDart!J35 -> 4126.85 | E22: =BlueDart!J195 -> 0.49320426 | F22: =BlueDart!J80 -> 1.3674138 | G22: =BlueDart!J81 -> 0.9578767 | H22: =BlueDart!J96 -> 4.81539 | I22: =BlueDart!J108 -> 50.651055 | J22: =BlueDart!J112 -> 3.1909295 | K22: =BlueDart!J124 -> 0.040285757 | L22: =BlueDart!J135 -> 0.063517942 | M22: =BlueDart!J139 -> 0.14832113 | N22: =BlueDart!J152 -> 45.476333 | O22: =BlueDart!J146 -> 6.33172 | P22: =BlueDart!J154 -> 12.81373 | Q22: =BlueDart!J138 -> 0.11385367 | R22: =BlueDart!J113 -> 1.5766848 | S22: =BlueDart!J121 -> 0.15480843 | T22: =BlueDart!J87 -> 0.64266137 | U22: =LN(C22) -> 8.7227233
A23: CONCOR | B23: 2020 | C23: =CONCOR!D9 -> 6530.27 | D23: =CONCOR!D35 -> 11788.76 | E23: =CONCOR!D195 -> 0.45363635 | F23: =CONCOR!D80 -> 2.5701338 | G23: =CONCOR!D81 -> 1.4086844 | H23: =CONCOR!D96 -> 12.709518 | I23: =CONCOR!D108 -> 7.2692362 | J23: =CONCOR!D112 -> 1.3176666 | K23: =CONCOR!D124 -> 0.061792238 | L23: =CONCOR!D135 -> 0.032824678 | M23: =CONCOR!D139 -> 0.039612222 | N23: =CONCOR!D152 -> 50.076257 | O23: =CONCOR!D146 -> 2.0114045 | P23: =CONCOR!D154 -> 15.939109 | Q23: =CONCOR!D138 -> 0.041514444 | R23: =CONCOR!D113 -> 0.53121037 | S23: =CONCOR!D121 -> 0.25944103 | T23: =CONCOR!D87 -> 0.0069678781 | U23: =LN(C23) -> 8.7842036
A24: CONCOR | B24: 2021 | C24: =CONCOR!E9 -> 6427.08 | D24: =CONCOR!E35 -> 12410.45 | E24: =CONCOR!E195 -> 0.45628321 | F24: =CONCOR!E80 -> 3.042066 | G24: =CONCOR!E81 -> 1.7689134 | H24: =CONCOR!E96 -> 16.519005 | I24: =CONCOR!E108 -> 9.2472709 | J24: =CONCOR!E112 -> 1.1674467 | K24: =CONCOR!E124 -> 0.078614239 | L24: =CONCOR!E135 -> 0.041758388 | M24: =CONCOR!E139 -> 0.049943262 | N24: =CONCOR!E152 -> 72.111277 | O24: =CONCOR!E146 -> 3.5765205 | P24: =CONCOR!E154 -> 27.285236 | Q24: =CONCOR!E138 -> 0.050694979 | R24: =CONCOR!E113 -> 0.53118098 | S24: =CONCOR!E121 -> 0.16296514 | T24: =CONCOR!E87 -> 0.070964126 | U24: =LN(C24) -> 8.7682756
A25: CONCOR | B25: 2022 | C25: =CONCOR!F9 -> 7652.73 | D25: =CONCOR!F35 -> 13002.26 | E25: =CONCOR!F195 -> 0.44013195 | F25: =CONCOR!F80 -> 3.5179069 | G25: =CONCOR!F81 -> 2.0507466 | H25: =CONCOR!F96 -> 23.190802 | I25: =CONCOR!F108 -> 8.1737988 | J25: =CONCOR!F112 -> 1.344307 | K25: =CONCOR!F124 -> 0.13787498 | L25: =CONCOR!F135 -> 0.083038763 | M25: =CONCOR!F139 -> 0.10076203 | N25: =CONCOR!F152 -> 38.813363 | O25: =CONCOR!F146 -> 3.8075928 | P25: =CONCOR!F154 -> 19.205241 | Q25: =CONCOR!F138 -> 0.098182065 | R25: =CONCOR!F113 -> 0.60227579 | S25: =CONCOR!F121 -> 0.22847664 | T25: =CONCOR!F87 -> 0.068362845 | U25: =LN(C25) -> 8.9428177
A26: CONCOR | B26: 2023 | C26: =CONCOR!G9 -> 8169.12 | D26: =CONCOR!G35 -> 13465.06 | E26: =CONCOR!G195 -> 0.41742777 | F26: =CONCOR!G80 -> 3.9676867 | G26: =CONCOR!G81 -> 2.272078 | H26: =CONCOR!G96 -> 25.168058 | I26: =CONCOR!G108 -> 8.8851553 | J26: =CONCOR!G112 -> 1.4403301 | K26: =CONCOR!G124 -> 0.14369602 | L26: =CONCOR!G135 -> 0.088703352 | M26: =CONCOR!G139 -> 0.10680488 | N26: =CONCOR!G152 -> 30.117025 | O26: =CONCOR!G146 -> 3.1492408 | P26: =CONCOR!G154 -> 15.00763 | Q26: =CONCOR!G138 -> 0.10402201 | R26: =CONCOR!G113 -> 0.61729862 | S26: =CONCOR!G121 -> 0.22864152 | T26: =CONCOR!G87 -> 0.069360228 | U26: =LN(C26) -> 9.0081165
A27: CONCOR | B27: 2024 | C27: =CONCOR!H9 -> 8653.41 | D27: =CONCOR!H35 -> 14038.16 | E27: =CONCOR!H195 -> 0.42845786 | F27: =CONCOR!H80 -> 4.7198355 | G27: =CONCOR!H81 -> 2.8440509 | H27: =CONCOR!H96 -> 24.261397 | I27: =CONCOR!H108 -> 11.59167 | J27: =CONCOR!H112 -> 1.4874216 | K27: =CONCOR!H124 -> 0.14567552 | L27: =CONCOR!H135 -> 0.091668539 | M27: =CONCOR!H139 -> 0.10938235 | N27: =CONCOR!H152 -> 42.634472 | O27: =CONCOR!H146 -> 4.545685 | P27: =CONCOR!H154 -> 21.784575 | Q27: =CONCOR!H138 -> 0.10630025 | R27: =CONCOR!H113 -> 0.62926523 | S27: =CONCOR!H121 -> 0.22634776 | T27: =CONCOR!H87 -> 0.079394682 | U27: =LN(C27) -> 9.0657087
A28: CONCOR | B28: 2025 | C28: =CONCOR!I9 -> 8887.02 | D28: =CONCOR!I35 -> 14477.26 | E28: =CONCOR!I195 -> 0.45440021 | F28: =CONCOR!I80 -> 4.7991234 | G28: =CONCOR!I81 -> 3.2917024 | H28: =CONCOR!I96 -> 24.410277 | I28: =CONCOR!I108 -> 15.065098 | J28: =CONCOR!I112 -> 1.4113964 | K28: =CONCOR!I124 -> 0.14515664 | L28: =CONCOR!I135 -> 0.090478064 | M28: =CONCOR!I139 -> 0.10659183 | N28: =CONCOR!I152 -> 32.664712 | O28: =CONCOR!I146 -> 3.4032985 | P28: =CONCOR!I154 -> 16.549635 | Q28: =CONCOR!I138 -> 0.10369892 | R28: =CONCOR!I113 -> 0.62331328 | S28: =CONCOR!I121 -> 0.21717179 | T28: =CONCOR!I87 -> 0.069576609 | U28: =LN(C28) -> 9.0923471
A29: CONCOR | B29: 2026 | C29: =CONCOR!J9 -> 9078.97 | D29: =CONCOR!J35 -> 15175.78 | E29: =CONCOR!J195 -> 0.4726281 | F29: =CONCOR!J80 -> 4.7511388 | G29: =CONCOR!J81 -> 3.1306054 | H29: =CONCOR!J96 -> 22.020884 | I29: =CONCOR!J108 -> 17.788934 | J29: =CONCOR!J112 -> 1.3204843 | K29: =CONCOR!J124 -> 0.13677763 | L29: =CONCOR!J135 -> 0.083755325 | M29: =CONCOR!J139 -> 0.09807371 | N29: =CONCOR!J152 -> 26.083788 | O29: =CONCOR!J146 -> 2.5027022 | P29: =CONCOR!J154 -> 12.737852 | Q29: =CONCOR!J138 -> 0.096133312 | R29: =CONCOR!J113 -> 0.61234666 | S29: =CONCOR!J121 -> 0.21492746 | T29: =CONCOR!J87 -> 0.074528196 | U29: =LN(C29) -> 9.113716
A30: Jet Freight | B30: 2020 | C30: =JetFreight!D9 -> 299.78 | D30: =JetFreight!D35 -> 87.81 | E30: =JetFreight!D195 -> 0.16342102 | F30: =JetFreight!D80 -> 2.1770364 | G30: =JetFreight!D81 -> 1.6537421 | H30: =JetFreight!D96 -> -0.89519651 | I30: =JetFreight!D108 -> 70.728034 | J30: =JetFreight!D112 -> 20.187205 | K30: =JetFreight!D124 -> -0.028587631 | L30: =JetFreight!D135 -> -0.094487321 | M30: =JetFreight!D139 -> -0.3977721 | N30: =JetFreight!D152 -> N/M | O30: =JetFreight!D146 -> 1.5269525 | P30: =JetFreight!D154 -> N/M | Q30: =JetFreight!D138 -> -0.066294769 | R30: =JetFreight!D113 -> 3.3051819 | S30: =JetFreight!D121 -> -0.011708586 | T30: =JetFreight!D87 -> 2.1599073 | U30: =LN(C30) -> 5.7030489
A31: Jet Freight | B31: 2021 | C31: =JetFreight!E9 -> 346.79 | D31: =JetFreight!E35 -> 98.17 | E31: =JetFreight!E195 -> 0.29082204 | F31: =JetFreight!E80 -> 1.5218345 | G31: =JetFreight!E81 -> 0.93877551 | H31: =JetFreight!E96 -> 1.9974227 | I31: =JetFreight!E108 -> 47.978676 | J31: =JetFreight!E112 -> 16.167366 | K31: =JetFreight!E124 -> 0.0072378096 | L31: =JetFreight!E135 -> 0.02699215 | M31: =JetFreight!E139 -> 0.1294148 | N31: =JetFreight!E152 -> 13.291474 | O31: =JetFreight!E146 -> 1.5495402 | P31: =JetFreight!E154 -> 6.179778 | Q31: =JetFreight!E138 -> 0.093456411 | R31: =JetFreight!E113 -> 3.7293257 | S31: =JetFreight!E121 -> 0.026846218 | T31: =JetFreight!E87 -> 1.4431026 | U31: =LN(C31) -> 5.8487194
A32: Jet Freight | B32: 2022 | C32: =JetFreight!F9 -> 456.76 | D32: =JetFreight!F35 -> 110.01 | E32: =JetFreight!F195 -> 0.28324698 | F32: =JetFreight!F80 -> 2.1581983 | G32: =JetFreight!F81 -> 1.331777 | H32: =JetFreight!F96 -> 2.1138614 | I32: =JetFreight!F108 -> 32.559605 | J32: =JetFreight!F112 -> 15.29928 | K32: =JetFreight!F124 -> 0.0061739207 | L32: =JetFreight!F135 -> 0.02709194 | M32: =JetFreight!F139 -> 0.12287582 | N32: =JetFreight!F152 -> 47.847943 | O32: =JetFreight!F146 -> 5.5367747 | P32: =JetFreight!F154 -> 15.742128 | Q32: =JetFreight!F138 -> 0.084813524 | R32: =JetFreight!F113 -> 4.3881257 | S32: =JetFreight!F121 -> 0.023601016 | T32: =JetFreight!F87 -> 2.0201067 | U32: =LN(C32) -> 6.1241581
A33: Jet Freight | B33: 2023 | C33: =JetFreight!G9 -> 416.69 | D33: =JetFreight!G35 -> 153.86 | E33: =JetFreight!G195 -> 0.19855713 | F33: =JetFreight!G80 -> 4.0013008 | G33: =JetFreight!G81 -> 1.739187 | H33: =JetFreight!G96 -> 1.170297 | I33: =JetFreight!G108 -> 38.055689 | J33: =JetFreight!G112 -> 13.50478 | K33: =JetFreight!G124 -> 0.00014399194 | L33: =JetFreight!G135 -> 0.00045476939 | M33: =JetFreight!G139 -> 0.0013855213 | N33: =JetFreight!G152 -> 912.53333 | O33: =JetFreight!G146 -> 0.87969152 | P33: =JetFreight!G154 -> 12.28578 | Q33: =JetFreight!G138 -> 0.0048909208 | R33: =JetFreight!G113 -> 3.1582976 | S33: =JetFreight!G121 -> 0.019198925 | T33: =JetFreight!G87 -> 0.97798843 | U33: =LN(C33) -> 6.0323425
A34: Jet Freight | B34: 2024 | C34: =JetFreight!H9 -> 387.77 | D34: =JetFreight!H35 -> 170.56 | E34: =JetFreight!H195 -> 0.15924015 | F34: =JetFreight!H80 -> 2.7379495 | G34: =JetFreight!H81 -> 1.5774675 | H34: =JetFreight!H96 -> 1.037037 | I34: =JetFreight!H108 -> 53.728241 | J34: =JetFreight!H112 -> 13.438572 | K34: =JetFreight!H124 -> 0.00067050055 | L34: =JetFreight!H135 -> 0.0016028605 | M34: =JetFreight!H139 -> 0.0041693393 | N34: =JetFreight!H152 -> 222.18462 | O34: =JetFreight!H146 -> 0.92458387 | P34: =JetFreight!H154 -> 11.97945 | Q34: =JetFreight!H138 -> 0.05103774 | R34: =JetFreight!H113 -> 2.3905431 | S34: =JetFreight!H121 -> 0.015240993 | T34: =JetFreight!H87 -> 0.89308579 | U34: =LN(C34) -> 5.9604124
A35: Jet Freight | B35: 2025 | C35: =JetFreight!I9 -> 436.63 | D35: =JetFreight!I35 -> 182.43 | E35: =JetFreight!I195 -> 0.14454859 | F35: =JetFreight!I80 -> 2.9950019 | G35: =JetFreight!I81 -> 1.739331 | H35: =JetFreight!I96 -> 1.9144928 | I35: =JetFreight!I108 -> 61.534136 | J35: =JetFreight!I112 -> 16.313469 | K35: =JetFreight!I124 -> 0.0085427021 | L35: =JetFreight!I135 -> 0.021133743 | M35: =JetFreight!I139 -> 0.058031894 | N35: =JetFreight!I152 -> 14.330509 | O35: =JetFreight!I146 -> 0.80903284 | P35: =JetFreight!I154 -> 6.8909614 | Q35: =JetFreight!I138 -> 0.062799179 | R35: =JetFreight!I113 -> 2.4738944 | S35: =JetFreight!I121 -> 0.032682134 | T35: =JetFreight!I87 -> 0.97381565 | U35: =LN(C35) -> 6.0790862
A36: Jet Freight | B36: 2026 | C36: =JetFreight!J9 -> 444.08 | D36: =JetFreight!J35 -> 194.09 | E36: =JetFreight!J195 -> 0.12550878 | F36: =JetFreight!J80 -> 3.5881855 | G36: =JetFreight!J81 -> 2.3645988 | H36: =JetFreight!J96 -> 2.6557143 | I36: =JetFreight!J108 -> 71.984102 | J36: =JetFreight!J112 -> 17.507589 | K36: =JetFreight!J124 -> 0.015312556 | L36: =JetFreight!J135 -> 0.036120259 | M36: =JetFreight!J139 -> 0.097940372 | N36: =JetFreight!J152 -> 11.640941 | O36: =JetFreight!J146 -> 1.08749 | P36: =JetFreight!J154 -> 6.7638244 | Q36: =JetFreight!J138 -> 0.078789833 | R36: =JetFreight!J113 -> 2.3588654 | S36: =JetFreight!J121 -> 0.037313097 | T36: =JetFreight!J87 -> 1.0175848 | U36: =LN(C36) -> 6.0960047
A37: Patel | B37: 2020 | C37: =Patel!D9 -> 347.41 | D37: =Patel!D35 -> 205.39 | E37: =Patel!D195 -> 0.24879498 | F37: =Patel!D80 -> 5.5191108 | G37: =Patel!D81 -> 3.9637285 | H37: =Patel!D96 -> 2.7361299 | I37: =Patel!D108 -> 98.827682 | J37: =Patel!D112 -> 6.2686756 | K37: =Patel!D124 -> 0.030914481 | L37: =Patel!D135 -> 0.049675077 | M37: =Patel!D139 -> 0.086924851 | N37: =Patel!D152 -> 3.1335196 | O37: =Patel!D146 -> 0.28273544 | P37: =Patel!D154 -> 3.3777041 | Q37: =Patel!D138 -> 0.088036094 | R37: =Patel!D113 -> 1.6068546 | S37: =Patel!D121 -> 0.023286607 | T37: =Patel!D87 -> 0.5101235 | U37: =LN(C37) -> 5.8505056
A38: Patel | B38: 2021 | C38: =Patel!E9 -> 212.25 | D38: =Patel!E35 -> 190.3 | E38: =Patel!E195 -> 0.27919075 | F38: =Patel!E80 -> 10.618729 | G38: =Patel!E81 -> 7.9423077 | H38: =Patel!E96 -> 1.0368906 | I38: =Patel!E108 -> 138.14971 | J38: =Patel!E112 -> 4.0727238 | K38: =Patel!E124 -> 0.00023557126 | L38: =Patel!E135 -> 0.00025272309 | M38: =Patel!E139 -> 0.00042435816 | N38: =Patel!E152 -> 1350.422 | O38: =Patel!E146 -> 0.57898388 | P38: =Patel!E154 -> 10.387583 | Q38: =Patel!E138 -> 0.0094190208 | R38: =Patel!E113 -> 1.0728095 | S38: =Patel!E121 -> 0.024358068 | T38: =Patel!E87 -> 0.52924027 | U38: =LN(C38) -> 5.3577648
A39: Patel | B39: 2022 | C39: =Patel!F9 -> 234.32 | D39: =Patel!F35 -> 179.05 | E39: =Patel!F195 -> 0.31784418 | F39: =Patel!F80 -> 8.4062274 | G39: =Patel!F81 -> 6.2280956 | H39: =Patel!F96 -> 1.417603 | I39: =Patel!F108 -> 106.11824 | J39: =Patel!F112 -> 4.258815 | K39: =Patel!F124 -> 0.0096876067 | L39: =Patel!F135 -> 0.012291864 | M39: =Patel!F139 -> 0.019411664 | N39: =Patel!F152 -> 39.796079 | O39: =Patel!F146 -> 0.77039997 | P39: =Patel!F154 -> 11.43599 | Q39: =Patel!F138 -> 0.044065429 | R39: =Patel!F113 -> 1.2688236 | S39: =Patel!F121 -> 0.032818368 | T39: =Patel!F87 -> 0.40917619 | U39: =LN(C39) -> 5.4566877
A40: Patel | B40: 2023 | C40: =Patel!G9 -> 278.28 | D40: =Patel!G35 -> 172.15 | E40: =Patel!G195 -> 0.31995353 | F40: =Patel!G80 -> 4.8155172 | G40: =Patel!G81 -> 4.225 | H40: =Patel!G96 -> 1.9727463 | I40: =Patel!G108 -> 90.633535 | J40: =Patel!G112 -> 4.9697294 | K40: =Patel!G124 -> 0.017608164 | L40: =Patel!G135 -> 0.027904328 | M40: =Patel!G139 -> 0.041711002 | N40: =Patel!G152 -> 15.340408 | O40: =Patel!G146 -> 0.63869488 | P40: =Patel!G154 -> 6.6721817 | Q40: =Patel!G138 -> 0.05990006 | R40: =Patel!G113 -> 1.584738 | S40: =Patel!G121 -> 0.03708495 | T40: =Patel!G87 -> 0.26561305 | U40: =LN(C40) -> 5.6286278
A41: Patel | B41: 2024 | C41: =Patel!H9 -> 290.55 | D41: =Patel!H35 -> 192.04 | E41: =Patel!H195 -> 0.25255155 | F41: =Patel!H80 -> 2.8559374 | G41: =Patel!H81 -> 2.5336489 | H41: =Patel!H96 -> 3.1930502 | I41: =Patel!H108 -> 103.40096 | J41: =Patel!H112 -> 5.6101564 | K41: =Patel!H124 -> 0.019067286 | L41: =Patel!H135 -> 0.03042368 | M41: =Patel!H139 -> 0.04674711 | N41: =Patel!H152 -> 24.736895 | O41: =Patel!H146 -> 1.1484321 | P41: =Patel!H154 -> 11.63617 | Q41: =Patel!H138 -> 0.055172107 | R41: =Patel!H113 -> 1.5955957 | S41: =Patel!H121 -> 0.031319911 | T41: =Patel!H87 -> 0.20212855 | U41: =LN(C41) -> 5.6717757
A42: Patel | B42: 2025 | C42: =Patel!I9 -> 342.69 | D42: =Patel!I35 -> 168.12 | E42: =Patel!I195 -> 0.28033547 | F42: =Patel!I80 -> 3.4914645 | G42: =Patel!I81 -> 2.8772087 | H42: =Patel!I96 -> 7.5 | I42: =Patel!I108 -> 84.276241 | J42: =Patel!I112 -> 7.1669978 | K42: =Patel!I124 -> 0.022177478 | L42: =Patel!I135 -> 0.042203465 | M42: =Patel!I139 -> 0.063073157 | N42: =Patel!I152 -> 12.234947 | O42: =Patel!I146 -> 0.76430709 | P42: =Patel!I154 -> 6.7605236 | Q42: =Patel!I138 -> 0.063130126 | R42: =Patel!I113 -> 1.9029876 | S42: =Patel!I121 -> 0.025708366 | T42: =Patel!I87 -> 0.10743054 | U42: =LN(C42) -> 5.8368262
A43: Patel | B43: 2026 | C43: =Patel!J9 -> 357.14 | D43: =Patel!J35 -> 163.32 | E43: =Patel!J195 -> 0.2807372 | F43: =Patel!J80 -> 3.3649374 | G43: =Patel!J81 -> 2.9698867 | H43: =Patel!J96 -> 30.457143 | I43: =Patel!J108 -> 71.627443 | J43: =Patel!J112 -> 7.6820822 | K43: =Patel!J124 -> 0.026880215 | L43: =Patel!J135 -> 0.057929037 | M43: =Patel!J139 -> 0.078309813 | N43: =Patel!J152 -> 5.9885 | O43: =Patel!J146 -> 0.46542746 | P43: =Patel!J154 -> 2.7872521 | Q43: =Patel!J138 -> 0.074973027 | R43: =Patel!J113 -> 2.1550809 | S43: =Patel!J121 -> 0.029036232 | T43: =Patel!J87 -> 0.050680052 | U43: =LN(C43) -> 5.8781279
A44: TCI | B44: 2020 | C44: =TCI!D9 -> 2717.84 | D44: =TCI!D35 -> 1683.32 | E44: =TCI!D195 -> 0.45845116 | F44: =TCI!D80 -> 3.1791642 | G44: =TCI!D81 -> 2.1620187 | H44: =TCI!D96 -> 5.6360723 | I44: =TCI!D108 -> 67.308727 | J44: =TCI!D112 -> 3.6273657 | K44: =TCI!D124 -> 0.052379831 | L44: =TCI!D135 -> 0.086297878 | M44: =TCI!D139 -> 0.14861289 | N44: =TCI!D152 -> 10.144872 | O44: =TCI!D146 -> 1.4105265 | P44: =TCI!D154 -> 6.6698826 | Q44: =TCI!D138 -> 0.12397741 | R44: =TCI!D113 -> 1.6475402 | S44: =TCI!D121 -> 0.088835252 | T44: =TCI!D87 -> 0.41220248 | U44: =LN(C44) -> 7.9075927
A45: TCI | B45: 2021 | C45: =TCI!E9 -> 2802.39 | D45: =TCI!E35 -> 1738.81 | E45: =TCI!E195 -> 0.46274751 | F45: =TCI!E80 -> 2.8679037 | G45: =TCI!E81 -> 2.0269126 | H45: =TCI!E96 -> 7.5262172 | I45: =TCI!E108 -> 65.01488 | J45: =TCI!E112 -> 3.5555429 | K45: =TCI!E124 -> 0.052501615 | L45: =TCI!E135 -> 0.085987382 | M45: =TCI!E139 -> 0.13414478 | N45: =TCI!E152 -> 13.422935 | O45: =TCI!E146 -> 1.6883813 | P45: =TCI!E154 -> 7.601057 | Q45: =TCI!E138 -> 0.11909429 | R45: =TCI!E113 -> 1.6378045 | S45: =TCI!E121 -> 0.093855602 | T45: =TCI!E87 -> 0.25431945 | U45: =LN(C45) -> 7.9382279
A46: TCI | B46: 2022 | C46: =TCI!F9 -> 3258.81 | D46: =TCI!F35 -> 1827.03 | E46: =TCI!F195 -> 0.43860801 | F46: =TCI!F80 -> 2.7474711 | G46: =TCI!F81 -> 1.9389724 | H46: =TCI!F96 -> 26.757599 | I46: =TCI!F108 -> 57.082317 | J46: =TCI!F112 -> 4.0583444 | K46: =TCI!F124 -> 0.088869864 | L46: =TCI!F135 -> 0.16243578 | M46: =TCI!F139 -> 0.22277778 | N46: =TCI!F152 -> 15.990618 | O46: =TCI!F146 -> 3.2378576 | P46: =TCI!F154 -> 10.196404 | Q46: =TCI!F138 -> 0.20321896 | R46: =TCI!F113 -> 1.8277937 | S46: =TCI!F121 -> 0.12637435 | T46: =TCI!F87 -> 0.067280532 | U46: =LN(C46) -> 8.0891174
A47: TCI | B47: 2023 | C47: =TCI!G9 -> 3782.57 | D47: =TCI!G35 -> 2100.91 | E47: =TCI!G195 -> 0.37662727 | F47: =TCI!G80 -> 3.2474207 | G47: =TCI!G81 -> 2.4263303 | H47: =TCI!G96 -> 38.070265 | I47: =TCI!G108 -> 51.584425 | J47: =TCI!G112 -> 4.7501523 | K47: =TCI!G124 -> 0.083895341 | L47: =TCI!G135 -> 0.16158088 | M47: =TCI!G139 -> 0.20263915 | N47: =TCI!G152 -> 15.328531 | O47: =TCI!G146 -> 2.8583762 | P47: =TCI!G154 -> 9.6346283 | Q47: =TCI!G138 -> 0.19832609 | R47: =TCI!G113 -> 1.9259816 | S47: =TCI!G121 -> 0.11245529 | T47: =TCI!G87 -> 0.053984334 | U47: =LN(C47) -> 8.238159
A48: TCI | B48: 2024 | C48: =TCI!H9 -> 4024.26 | D48: =TCI!H35 -> 2501.4 | E48: =TCI!H195 -> 0.34451907 | F48: =TCI!H80 -> 3.2510365 | G48: =TCI!H81 -> 2.2909839 | H48: =TCI!H96 -> 30.245667 | I48: =TCI!H108 -> 52.675784 | J48: =TCI!H112 -> 4.8689203 | K48: =TCI!H124 -> 0.087171306 | L48: =TCI!H135 -> 0.15244519 | M48: =TCI!H139 -> 0.18933455 | N48: =TCI!H152 -> 17.976431 | O48: =TCI!H146 -> 3.1470551 | P48: =TCI!H154 -> 12.087752 | Q48: =TCI!H138 -> 0.18369601 | R48: =TCI!H113 -> 1.7488001 | S48: =TCI!H121 -> 0.10218773 | T48: =TCI!H87 -> 0.096655388 | U48: =LN(C48) -> 8.3000963
A49: TCI | B49: 2025 | C49: =TCI!I9 -> 4491.78 | D49: =TCI!I35 -> 2934.03 | E49: =TCI!I195 -> 0.32845608 | F49: =TCI!I80 -> 2.4267054 | G49: =TCI!I81 -> 1.5013025 | H49: =TCI!I96 -> 23.787202 | I49: =TCI!I108 -> 53.735312 | J49: =TCI!I112 -> 4.9212043 | K49: =TCI!I124 -> 0.091807702 | L49: =TCI!I135 -> 0.15173776 | M49: =TCI!I139 -> 0.19832779 | N49: =TCI!I152 -> 20.479048 | O49: =TCI!I146 -> 3.9193178 | P49: =TCI!I154 -> 14.399729 | Q49: =TCI!I138 -> 0.18904896 | R49: =TCI!I113 -> 1.6527782 | S49: =TCI!I121 -> 0.10297922 | T49: =TCI!I87 -> 0.11224504 | U49: =LN(C49) -> 8.4100043
A50: TCI | B50: 2026 | C50: =TCI!J9 -> 4916.77 | D50: =TCI!J35 -> 3481.86 | E50: =TCI!J195 -> 0.34254393 | F50: =TCI!J80 -> 2.4182809 | G50: =TCI!J81 -> 1.5404411 | H50: =TCI!J96 -> 22.93462 | I50: =TCI!J108 -> 57.098039 | J50: =TCI!J112 -> 4.5601862 | K50: =TCI!J124 -> 0.09279466 | L50: =TCI!J135 -> 0.14222501 | M50: =TCI!J139 -> 0.19329597 | N50: =TCI!J152 -> 15.516515 | O50: =TCI!J146 -> 2.758939 | P50: =TCI!J154 -> 11.198129 | Q50: =TCI!J138 -> 0.18230729 | R50: =TCI!J113 -> 1.5326853 | S50: =TCI!J121 -> 0.1055571 | T50: =TCI!J87 -> 0.12174638 | U50: =LN(C50) -> 8.5004071
A51: Shreeji | B51: 2020 | C51: =Shreeji!D9 -> 110 | D51: =Shreeji!D35 -> 79.35 | E51: =Shreeji!D195 -> 0.33484562 | F51: =Shreeji!D80 -> 6.1143524 | G51: =Shreeji!D81 -> 3.5227538 | H51: =Shreeji!D96 -> 1.6232295 | I51: =Shreeji!D108 -> 94.3525 | J51: =Shreeji!D112 -> 4.7149593 | K51: =Shreeji!D124 -> 0.013363636 | L51: =Shreeji!D135 -> 0.019520616 | M51: =Shreeji!D139 -> 0.059707555 | N51: =Shreeji!D152 -> 21.47619 | O51: =Shreeji!D146 -> 1.250297 | P51: =Shreeji!D154 -> 7.4636364 | Q51: =Shreeji!D138 -> 0.057660871 | R51: =Shreeji!D113 -> 1.4607264 | S51: =Shreeji!D121 -> 0.082272727 | T51: =Shreeji!D87 -> 1.8031683 | U51: =LN(C51) -> 4.7004804
A52: Shreeji | B52: 2021 | C52: =Shreeji!E9 -> 108.23 | D52: =Shreeji!E35 -> 81.98 | E52: =Shreeji!E195 -> 0.30141498 | F52: =Shreeji!E80 -> 5.4709865 | G52: =Shreeji!E81 -> 4.0522244 | H52: =Shreeji!E96 -> 0.7719715 | I52: =Shreeji!E108 -> 106.95717 | J52: =Shreeji!E112 -> 4.2211388 | K52: =Shreeji!E124 -> -0.010071145 | L52: =Shreeji!E135 -> -0.013512676 | M52: =Shreeji!E139 -> -0.044120623 | N52: =Shreeji!E152 -> N/M | O52: =Shreeji!E146 -> 2.3903146 | P52: =Shreeji!E154 -> 13.198413 | Q52: =Shreeji!E138 -> 0.045639657 | R52: =Shreeji!E113 -> 1.3417219 | S52: =Shreeji!E121 -> 0.065693431 | T52: =Shreeji!E87 -> 1.9652318 | U52: =LN(C52) -> 4.6842586
A53: Shreeji | B53: 2022 | C53: =Shreeji!F9 -> 163.74 | D53: =Shreeji!F35 -> 89.59 | E53: =Shreeji!F195 -> 0.22748075 | F53: =Shreeji!F80 -> 5.4686757 | G53: =Shreeji!F81 -> 3.8818398 | H53: =Shreeji!F96 -> 3.8571429 | I53: =Shreeji!F108 -> 90.402925 | J53: =Shreeji!F112 -> 7.2628077 | K53: =Shreeji!F124 -> 0.054049102 | L53: =Shreeji!F135 -> 0.10316489 | M53: =Shreeji!F139 -> 0.31449893 | N53: =Shreeji!F152 -> 24.061017 | O53: =Shreeji!F146 -> 6.6295143 | P53: =Shreeji!F154 -> 12.810005 | Q53: =Shreeji!F138 -> 0.1605975 | R53: =Shreeji!F113 -> 1.9087253 | S53: =Shreeji!F121 -> 0.10205203 | T53: =Shreeji!F87 -> 1.3966376 | U53: =LN(C53) -> 5.0982798
A54: Shreeji | B54: 2023 | C54: =Shreeji!G9 -> 186.44 | D54: =Shreeji!G35 -> 104.66 | E54: =Shreeji!G195 -> 0.19262373 | F54: =Shreeji!G80 -> 4.1375839 | G54: =Shreeji!G81 -> 3.4765101 | H54: =Shreeji!G96 -> 4.6037736 | I54: =Shreeji!G108 -> 97.974818 | J54: =Shreeji!G112 -> 9.1978293 | K54: =Shreeji!G124 -> 0.051920189 | L54: =Shreeji!G135 -> 0.09966538 | M54: =Shreeji!G139 -> 0.26546003 | N54: =Shreeji!G152 -> 35.997056 | O54: =Shreeji!G146 -> 8.5383852 | P54: =Shreeji!G154 -> 18.967295 | Q54: =Shreeji!G138 -> 0.15118281 | R54: =Shreeji!G113 -> 1.9195882 | S54: =Shreeji!G121 -> 0.10528856 | T54: =Shreeji!G87 -> 1.1264396 | U54: =LN(C54) -> 5.2281095
A55: Shreeji | B55: 2024 | C55: =Shreeji!H9 -> 250.5 | D55: =Shreeji!H35 -> 120.4 | E55: =Shreeji!H195 -> 0.27591362 | F55: =Shreeji!H80 -> 4.7823629 | G55: =Shreeji!H81 -> 3.924251 | H55: =Shreeji!H96 -> 5.3205645 | I55: =Shreeji!H108 -> 87.650998 | J55: =Shreeji!H112 -> 9.3855377 | K55: =Shreeji!H124 -> 0.06499002 | L55: =Shreeji!H135 -> 0.14467253 | M55: =Shreeji!H139 -> 0.33650269 | N55: =Shreeji!H152 -> 11.171978 | O55: =Shreeji!H146 -> 3.250756 | P55: =Shreeji!H154 -> 7.2759675 | Q55: =Shreeji!H138 -> 0.21146986 | R55: =Shreeji!H113 -> 2.226073 | S55: =Shreeji!H121 -> 0.075369261 | T55: =Shreeji!H87 -> 0.8357462 | U55: =LN(C55) -> 5.5234589
A56: Shreeji | B56: 2025 | C56: =Shreeji!I9 -> 220.18 | D56: =Shreeji!I35 -> 114.99 | E56: =Shreeji!I195 -> 0.25115227 | F56: =Shreeji!I80 -> 4.9369369 | G56: =Shreeji!I81 -> 4.1321321 | H56: =Shreeji!I96 -> 1.5205479 | I56: =Shreeji!I108 -> 104.42899 | J56: =Shreeji!I112 -> 7.0911433 | K56: =Shreeji!I124 -> 0.00694886 | L56: =Shreeji!I135 -> 0.012999703 | M56: =Shreeji!I139 -> 0.027144505 | N56: =Shreeji!I152 -> 40.432353 | O56: =Shreeji!I146 -> 1.0894945 | P56: =Shreeji!I154 -> 8.3317232 | Q56: =Shreeji!I138 -> 0.044749277 | R56: =Shreeji!I113 -> 1.8707677 | S56: =Shreeji!I121 -> 0.040966482 | T56: =Shreeji!I87 -> 0.73194787 | U56: =LN(C56) -> 5.3944454
A57: Shreeji | B57: 2026 | C57: =Shreeji!J9 -> 234.29 | D57: =Shreeji!J35 -> 119.52 | E57: =Shreeji!J195 -> 0.20866801 | F57: =Shreeji!J80 -> 4.7719752 | G57: =Shreeji!J81 -> 4.1773526 | H57: =Shreeji!J96 -> 1.8557692 | I57: =Shreeji!J108 -> 105.5554 | J57: =Shreeji!J112 -> 8.7064288 | K57: =Shreeji!J124 -> 0.013487558 | L57: =Shreeji!J135 -> 0.02694981 | M57: =Shreeji!J139 -> 0.054067927 | N57: =Shreeji!J152 -> 13.006709 | O57: =Shreeji!J146 -> 0.68376643 | P57: =Shreeji!J154 -> 6.3806485 | Q57: =Shreeji!J138 -> 0.069036714 | R57: =Shreeji!J113 -> 1.9981237 | S57: =Shreeji!J121 -> 0.033078663 | T57: =Shreeji!J87 -> 0.66661121 | U57: =LN(C57) -> 5.4565597
A58: Mahindra Log. | B58: 2020 | C58: =MahindraLog!D9 -> 3471.14 | D58: =MahindraLog!D35 -> 1421.84 | E58: =MahindraLog!D195 -> 0.16243741 | F58: =MahindraLog!D80 -> 1.7350456 | G58: =MahindraLog!D81 -> 0.93973871 | H58: =MahindraLog!D96 -> 5.6052184 | I58: =MahindraLog!D108 -> 55.410254 | J58: =MahindraLog!D112 -> 22.967149 | K58: =MahindraLog!D124 -> 0.015879509 | L58: =MahindraLog!D135 -> 0.041965016 | M58: =MahindraLog!D139 -> 0.10570829 | N58: =MahindraLog!D152 -> 36.924993 | O58: =MahindraLog!D146 -> 3.7369055 | P58: =MahindraLog!D154 -> 12.406825 | Q58: =MahindraLog!D138 -> 0.10530036 | R58: =MahindraLog!D113 -> 2.6427149 | S58: =MahindraLog!D121 -> 0.04565647 | T58: =MahindraLog!D87 -> 0.36959515 | U58: =LN(C58) -> 8.1522383
A59: Mahindra Log. | B59: 2021 | C59: =MahindraLog!E9 -> 3263.72 | D59: =MahindraLog!E35 -> 1686.93 | E59: =MahindraLog!E195 -> 0.21383223 | F59: =MahindraLog!E80 -> 1.4929302 | G59: =MahindraLog!E81 -> 0.80454208 | H59: =MahindraLog!E96 -> 2.9512195 | I59: =MahindraLog!E108 -> 57.104922 | J59: =MahindraLog!E112 -> 11.032044 | K59: =MahindraLog!E124 -> 0.009191965 | L59: =MahindraLog!E135 -> 0.019300238 | M59: =MahindraLog!E139 -> 0.053922406 | N59: =MahindraLog!E152 -> 173.7146 | O59: =MahindraLog!E146 -> 9.1740978 | P59: =MahindraLog!E154 -> 35.471653 | Q59: =MahindraLog!E138 -> 0.055743642 | R59: =MahindraLog!E113 -> 2.0996857 | S59: =MahindraLog!E121 -> 0.041265795 | T59: =MahindraLog!E87 -> 0.47438651 | U59: =LN(C59) -> 8.0906229
A60: Mahindra Log. | B60: 2022 | C60: =MahindraLog!F9 -> 4140.76 | D60: =MahindraLog!F35 -> 1975.44 | E60: =MahindraLog!F195 -> 0.25338659 | F60: =MahindraLog!F80 -> 1.30859 | G60: =MahindraLog!F81 -> 0.60711711 | H60: =MahindraLog!F96 -> 1.8822938 | I60: =MahindraLog!F108 -> 42.950147 | J60: =MahindraLog!F112 -> 9.6154748 | K60: =MahindraLog!F124 -> 0.0042407674 | L60: =MahindraLog!F135 -> 0.0095894189 | M60: =MahindraLog!F139 -> 0.031510758 | N60: =MahindraLog!F152 -> 259.09681 | O60: =MahindraLog!F146 -> 8.325538 | P60: =MahindraLog!F154 -> 24.350922 | Q60: =MahindraLog!F138 -> 0.035970024 | R60: =MahindraLog!F113 -> 2.2612461 | S60: =MahindraLog!F121 -> 0.044523228 | T60: =MahindraLog!F87 -> 0.7363856 | U60: =LN(C60) -> 8.3286346
A61: Mahindra Log. | B61: 2023 | C61: =MahindraLog!G9 -> 5128.29 | D61: =MahindraLog!G35 -> 2552.94 | E61: =MahindraLog!G195 -> 0.32499001 | F61: =MahindraLog!G80 -> 1.3995697 | G61: =MahindraLog!G81 -> 0.67292304 | H61: =MahindraLog!G96 -> 1.6697692 | I61: =MahindraLog!G108 -> 40.618544 | J61: =MahindraLog!G112 -> 7.7103809 | K61: =MahindraLog!G124 -> 0.0051245152 | L61: =MahindraLog!G135 -> 0.0116068 | M61: =MahindraLog!G139 -> 0.047430402 | N61: =MahindraLog!G152 -> 121.8024 | O61: =MahindraLog!G146 -> 5.6990172 | P61: =MahindraLog!G154 -> 14.182312 | Q61: =MahindraLog!G138 -> 0.058311772 | R61: =MahindraLog!G113 -> 2.2649557 | S61: =MahindraLog!G121 -> 0.050703061 | T61: =MahindraLog!G87 -> 1.4849467 | U61: =LN(C61) -> 8.5425275
A62: Mahindra Log. | B62: 2024 | C62: =MahindraLog!H9 -> 5505.97 | D62: =MahindraLog!H35 -> 2477.2 | E62: =MahindraLog!H195 -> 0.3375545 | F62: =MahindraLog!H80 -> 1.2998699 | G62: =MahindraLog!H81 -> 0.6206401 | H62: =MahindraLog!H96 -> 0.61282277 | I62: =MahindraLog!H108 -> 44.892394 | J62: =MahindraLog!H112 -> 6.6103237 | K62: =MahindraLog!H124 -> -0.0099419358 | L62: =MahindraLog!H135 -> -0.021764802 | M62: =MahindraLog!H139 -> -0.10385717 | N62: =MahindraLog!H152 -> N/M | O62: =MahindraLog!H146 -> 7.5007371 | P62: =MahindraLog!H154 -> 17.39555 | Q62: =MahindraLog!H138 -> 0.031794723 | R62: =MahindraLog!H113 -> 2.1891916 | S62: =MahindraLog!H121 -> 0.041998049 | T62: =MahindraLog!H87 -> 1.5011879 | U62: =LN(C62) -> 8.6135882
A63: Mahindra Log. | B63: 2025 | C63: =MahindraLog!I9 -> 6104.83 | D63: =MahindraLog!I35 -> 2578.8 | E63: =MahindraLog!I195 -> 0.36046223 | F63: =MahindraLog!I80 -> 1.2426698 | G63: =MahindraLog!I81 -> 0.55109501 | H63: =MahindraLog!I96 -> 0.9055535 | I63: =MahindraLog!I108 -> 39.669819 | J63: =MahindraLog!I112 -> 6.9147161 | K63: =MahindraLog!I124 -> -0.0058723994 | L63: =MahindraLog!I135 -> -0.014181171 | M63: =MahindraLog!I139 -> -0.07706777 | N63: =MahindraLog!I152 -> N/M | O63: =MahindraLog!I146 -> 5.4085612 | P63: =MahindraLog!I154 -> 10.541956 | Q63: =MahindraLog!I138 -> 0.057941554 | R63: =MahindraLog!I113 -> 2.4148853 | S63: =MahindraLog!I121 -> 0.046584426 | T63: =MahindraLog!I87 -> 1.9840596 | U63: =LN(C63) -> 8.7168355
A64: Mahindra Log. | B64: 2026 | C64: =MahindraLog!J9 -> 6999.3 | D64: =MahindraLog!J35 -> 3105.01 | E64: =MahindraLog!J195 -> 0.36955114 | F64: =MahindraLog!J80 -> 1.4122438 | G64: =MahindraLog!J81 -> 0.69438023 | H64: =MahindraLog!J96 -> 1.4420155 | I64: =MahindraLog!J108 -> 34.279274 | J64: =MahindraLog!J112 -> 6.7397521 | K64: =MahindraLog!J124 -> 0.00032717557 | L64: =MahindraLog!J135 -> 0.00080579752 | M64: =MahindraLog!J139 -> 0.0028400283 | N64: =MahindraLog!J152 -> 1441.6489 | O64: =MahindraLog!J146 -> 2.8102079 | P64: =MahindraLog!J154 -> 9.71785 | Q64: =MahindraLog!J138 -> 0.022025614 | R64: =MahindraLog!J113 -> 2.4628902 | S64: =MahindraLog!J121 -> 0.054119698 | T64: =MahindraLog!J87 -> 0.55308228 | U64: =LN(C64) -> 8.8535654
A65: Sical | B65: 2020 | C65: =Sical!D9 -> 1005.84 | D65: =Sical!D35 -> 2766.94 | E65: =Sical!D195 -> 0.33971824 | F65: =Sical!D80 -> 0.53880059 | G65: =Sical!D81 -> 0.29196076 | H65: =Sical!D96 -> -1.4166515 | I65: =Sical!D108 -> 115.64829 | J65: =Sical!D112 -> 1.0889721 | K65: =Sical!D124 -> -0.10641852 | L65: =Sical!D135 -> -0.038811858 | M65: =Sical!D139 -> -0.19565337 | N65: =Sical!D152 -> N/M | O65: =Sical!D146 -> 0.062998015 | P65: =Sical!D154 -> 193.24634 | Q65: =Sical!D138 -> -0.041155067 | R65: =Sical!D113 -> 0.36470964 | S65: =Sical!D121 -> -0.022339537 | T65: =Sical!D87 -> 2.601688 | U65: =LN(C65) -> 6.9135783
A66: Sical | B66: 2021 | C66: =Sical!E9 -> 503.63 | D66: =Sical!E35 -> 1731.06 | E66: =Sical!E195 -> 0.48494564 | F66: =Sical!E80 -> 0.43040965 | G66: =Sical!E81 -> 0.24450927 | H66: =Sical!E96 -> -7.3820677 | I66: =Sical!E108 -> 164.27645 | J66: =Sical!E112 -> 0.56605131 | K66: =Sical!E124 -> -2.3024443 | L66: =Sical!E135 -> -0.51559804 | M66: =Sical!E139 -> N/M | N66: =Sical!E152 -> N/M | O66: =Sical!E146 -> N/M | P66: =Sical!E154 -> N/M | Q66: =Sical!E138 -> -0.86806034 | R66: =Sical!E113 -> 0.22393508 | S66: =Sical!E121 -> -0.018763775 | T66: =Sical!E87 -> N/M | U66: =LN(C66) -> 6.2218419
A67: Sical | B67: 2022 | C67: =Sical!F9 -> 348.87 | D67: =Sical!F35 -> 1565.58 | E67: =Sical!F195 -> 0.48799806 | F67: =Sical!F80 -> 0.53771673 | G67: =Sical!F81 -> 0.31262155 | H67: =Sical!F96 -> -10.814433 | I67: =Sical!F108 -> 185.47654 | J67: =Sical!F112 -> 0.43514378 | K67: =Sical!F124 -> -0.74646717 | L67: =Sical!F135 -> -0.15799117 | M67: =Sical!F139 -> N/M | N67: =Sical!F152 -> N/M | O67: =Sical!F146 -> N/M | P67: =Sical!F154 -> N/M | Q67: =Sical!F138 -> -0.32235896 | R67: =Sical!F113 -> 0.21165186 | S67: =Sical!F121 -> -0.11224812 | T67: =Sical!F87 -> N/M | U67: =LN(C67) -> 5.8546994
A68: Sical | B68: 2023 | C68: =Sical!G9 -> 392.11 | D68: =Sical!G35 -> 793.01 | E68: =Sical!G195 -> 0.76336994 | F68: =Sical!G80 -> 0.73076322 | G68: =Sical!G81 -> 0.53558316 | H68: =Sical!G96 -> -41.722767 | I68: =Sical!G108 -> 91.415228 | J68: =Sical!G112 -> 0.57269089 | K68: =Sical!G124 -> -2.1268012 | L68: =Sical!G135 -> -0.70715131 | M68: =Sical!G139 -> N/M | N68: =Sical!G152 -> N/M | O68: =Sical!G146 -> 0.7826954 | P68: =Sical!G154 -> N/M | Q68: =Sical!G138 -> -1.1777556 | R68: =Sical!G113 -> 0.33249526 | S68: =Sical!G121 -> 0.070362908 | T68: =Sical!G87 -> 9.0334454 | U68: =LN(C68) -> 5.9715424
A69: Sical | B69: 2024 | C69: =Sical!H9 -> 221.09 | D69: =Sical!H35 -> 767.54 | E69: =Sical!H195 -> 0.72605988 | F69: =Sical!H80 -> 0.86142419 | G69: =Sical!H81 -> 0.70548862 | H69: =Sical!H96 -> 0.39331291 | I69: =Sical!H108 -> 81.488986 | J69: =Sical!H112 -> 0.38032409 | K69: =Sical!H124 -> -0.12795694 | L69: =Sical!H135 -> -0.036256448 | M69: =Sical!H139 -> -0.68798638 | N69: =Sical!H152 -> N/M | O69: =Sical!H146 -> 33.431025 | P69: =Sical!H154 -> 21.152974 | Q69: =Sical!H138 -> 0.028724277 | R69: =Sical!H113 -> 0.28334882 | S69: =Sical!H121 -> 0.075082546 | T69: =Sical!H87 -> 17.661908 | U69: =LN(C69) -> 5.3985699
A70: Sical | B70: 2025 | C70: =Sical!I9 -> 221.82 | D70: =Sical!I35 -> 858.91 | E70: =Sical!I195 -> 0.70084176 | F70: =Sical!I80 -> 0.79756136 | G70: =Sical!I81 -> 0.61997811 | H70: =Sical!I96 -> 0.28971098 | I70: =Sical!I108 -> 95.594063 | J70: =Sical!I112 -> 0.38269901 | K70: =Sical!I124 -> -0.11644577 | L70: =Sical!I135 -> -0.031762427 | M70: =Sical!I139 -> -2.1569937 | N70: =Sical!I152 -> N/M | O70: =Sical!I146 -> N/M | P70: =Sical!I154 -> 19.255649 | Q70: =Sical!I138 -> 0.022001756 | R70: =Sical!I113 -> 0.27276584 | S70: =Sical!I121 -> 0.096880353 | T70: =Sical!I87 -> N/M | U70: =LN(C70) -> 5.4018662
A71: Sical | B71: 2026 | C71: =Sical!J9 -> 385.68 | D71: =Sical!J35 -> 906.73 | E71: =Sical!J195 -> 0.61263 | F71: =Sical!J80 -> 1.1402597 | G71: =Sical!J81 -> 0.55759496 | H71: =Sical!J96 -> 1.7926965 | I71: =Sical!J108 -> 79.53381 | J71: =Sical!J112 -> 0.66643052 | K71: =Sical!J124 -> 0.12777432 | L71: =Sical!J135 -> 0.055821119 | M71: =Sical!J139 -> 0.77900727 | N71: =Sical!J152 -> 10.200767 | O71: =Sical!J146 -> 3.828881 | P71: =Sical!J154 -> 5.396802 | Q71: =Sical!J138 -> 0.18235018 | R71: =Sical!J113 -> 0.43687275 | S71: =Sical!J121 -> 0.2030699 | T71: =Sical!J87 -> 3.6944931 | U71: =LN(C71) -> 5.955008
A73: Rows 2-64 = 9 firms x 7 years used for inferential statistics; rows 65-71 = Sical Logistics (negative / near-zero net worth in 5 of 7 years under IBC resolution) - included in descriptive statistics and industry ratios, excluded from correlation, regression, t-tests and ANOVA as a statistical outlier.

Sheet Industry
A1: INDUSTRY AGGREGATE (the 10 firms treated as the entire industry)
A2: Inputs = SUM of the 10 company sheets (green links). Ratios use the same formulas on the aggregate figures, i.e. size-weighted industry ratios. Valuation multiples use valuation-comparable firm-years only. Per-share items not meaningful (n.a.).
A3: Year (numeric helper for SLOPE) | C3: 2019 | D3: 2020 | E3: 2021 | F3: 2022 | G3: 2023 | H3: 2024 | I3: 2025 | J3: 2026
A5: Line item / Ratio | B5: Formula / definition | C5: FY2019 | D5: FY2020 | E5: FY2021 | F5: FY2022 | G5: FY2023 | H5: FY2024 | I5: FY2025 | J5: FY2026 | K5: 7-yr avg FY20-26 | L5: Change FY26 vs FY20 | M5: Trend slope / yr
A8: PROFIT & LOSS (Rs crore)
A9: Sales / Revenue from operations | B9: Screener export: "Sales" | C9: =SUM(Tiger!C9,Allcargo!C9,BlueDart!C9,CONCOR!C9,JetFreight!C9,Patel!C9,Sical!C9,TCI!C9,Shreeji!C9,MahindraLog!C9) -> 26602.39 | D9: =SUM(Tiger!D9,Allcargo!D9,BlueDart!D9,CONCOR!D9,JetFreight!D9,Patel!D9,Sical!D9,TCI!D9,Shreeji!D9,MahindraLog!D9) -> 25305.13 | E9: =SUM(Tiger!E9,Allcargo!E9,BlueDart!E9,CONCOR!E9,JetFreight!E9,Patel!E9,Sical!E9,TCI!E9,Shreeji!E9,MahindraLog!E9) -> 27618.19 | F9: =SUM(Tiger!F9,Allcargo!F9,BlueDart!F9,CONCOR!F9,JetFreight!F9,Patel!F9,Sical!F9,TCI!F9,Shreeji!F9,MahindraLog!F9) -> 40343.65 | G9: =SUM(Tiger!G9,Allcargo!G9,BlueDart!G9,CONCOR!G9,JetFreight!G9,Patel!G9,Sical!G9,TCI!G9,Shreeji!G9,MahindraLog!G9) -> 42009.84 | H9: =SUM(Tiger!H9,Allcargo!H9,BlueDart!H9,CONCOR!H9,JetFreight!H9,Patel!H9,Sical!H9,TCI!H9,Shreeji!H9,MahindraLog!H9) -> 37810.32 | I9: =SUM(Tiger!I9,Allcargo!I9,BlueDart!I9,CONCOR!I9,JetFreight!I9,Patel!I9,Sical!I9,TCI!I9,Shreeji!I9,MahindraLog!I9) -> 28922.44 | J9: =SUM(Tiger!J9,Allcargo!J9,BlueDart!J9,CONCOR!J9,JetFreight!J9,Patel!J9,Sical!J9,TCI!J9,Shreeji!J9,MahindraLog!J9) -> 31187.93
